Workbook

Sheet Index
B2: Bill Of Material (BOM)
B3: 1 | C3: Pregnancy Powder
B4: 2 | C4: Lactation Powder
B5: 3 | C5: Infant Formula Milk
B6: 4 | C6: Child Nutrition
B8: Profit & Loss Statement
B10: 22Cr Summary Sheet
B12: Year 1
B13: 1 | C13: 22Cr Capital Raised Working
B14: 2 | C14: Working Capital
B16: Year 2
B17: 1 | C17: 60Cr Capital Raised Working
B18: 2 | C18: Working Capital
B20: Year 3
B21: 1 | C21: Plant works @ 100% Efficiency
B22: 2 | C22: Working Capital

Sheet Infant Complementary BOM
B2: RAW MATERIAL COST
B4: Item No. | C4: Ingredient Name | D4: In Grams | F4: In Rupees
D5: Quantity Per 100 g | E5: Quantity per 400 gm | F5: Rate / Kg | G5: Rate / Gram | H5: Rate Per 400 g
B6: 1 | C6: Milk Solids | D6: 35 | E6: =D6*4 | F6: 240 | G6: =F6/1000 | H6: =E6*G6
B7: 2 | C7: Maltodextrin | D7: 20 | E7: =D7*4 | F7: 50 | G7: =F7/1000 | H7: =E7*G7
B8: 3 | C8: Sprouted Ragi Powder | D8: 13 | E8: =D8*4 | F8: 50 | G8: =F8/1000 | H8: =E8*G8
B9: 4 | C9: Rice Powder | D9: 10 | E9: =D9*4 | F9: 50 | G9: =F9/1000 | H9: =E9*G9
B10: 5 | C10: Apple Powder | D10: 8 | E10: =D10*4 | F10: 170 | G10: =F10/1000 | H10: =E10*G10
B11: 6 | C11: Enzyme(Alpha Amylase) | D11: 0.5 | E11: =D11*4 | F11: 1000 | G11: =F11/1000 | H11: =E11*G11
B12: 7 | C12: Fructooligosaccharides | D12: 7 | E12: =D12*4 | F12: 170 | G12: =F12/1000 | H12: =E12*G12
B13: 8 | C13: Mineral premix(Calcium, Phosphorous, Sodium, Potassium, Chloride, Magnesium, Iron, Zinc, Copper, Manganese, Iodine, Selenium) | D13: 1.88 | E13: =D13*4 | F13: 400 | G13: =F13/1000 | H13: =E13*G13
B14: 9 | C14: Vitamin premix(Vitamin A, D, E, K, C, B1, B2, B6, B12, B7,B5, B3) | D14: 0.05 | E14: =D14*4 | F14: 500 | G14: =F14/1000 | H14: =E14*G14
B15: 10 | C15: Jaggery Powder | D15: 5 | E15: =D15*4 | F15: 60 | G15: =F15/1000 | H15: =E15*G15
B16: RAW MATERIAL TOTAL COST | D16: =SUM(D6:D15) | E16: =D16*4 | H16: =SUM(H6:H14)
B18: OTHER COSTS
C20: Packaging | H20: 12
C21: Conversion | H21: 30
F23: TOTAL COST / BOX | H23: =H16+H20+H21
F25: PRODUCTION COST / BATCH | H25: 20000000
F27: BOXES / BATCH | H27: =H25/H23
F29: BOXES / VARIANT | H29: =H27/3
F31: AS PER PROJETIONS SHEET
F32: Total Cost (Excl. GST) | H32: 111 | I32: VS | J32: =H23
F33: GST 18% | H33: 16
F34: Total Cost (Incl. GST) | H34: 127

Sheet Total Production
A1: VALENCIA NUTRACARE LIFESCIENCES (Consumer Validation)
B3: EARLY STAGE FUND | C3: Natal Care | D3: Infant & Child Nutrition | E3: Total
B4: Funding (₹ Cr) | C4: 11 | D4: 11 | E4: =C4+D4
B5: Production (₹ Cr) | C5: 8 | D5: 8 | E5: =C5+D5 | F5: * 2 cycles of production
B6: Admin & Marketing Exp (₹ Cr) | C6: 3 | D6: 3 | E6: =C6+D6
C8: Pregnancy Powder (Garbhika) | D8: Lactation Powder (Matrusneha) | E8: Infant Formula Milk Powder (Poshit) | F8: Child Nutrition Powder
B9: Cost/Box | C9: ='PP BOM'!H25 | D9: ='LP BOM'!H28 | E9: ='IFM BOM'!H30 | F9: ='CNP BOM'!H24
B10: Production Cost/Batch | C10: ='PP BOM'!H27 | D10: ='LP BOM'!H30 | E10: ='IFM BOM'!H32 | F10: ='CNP BOM'!H26
B11: Boxes/Batch | C11: =Round(C10/C9,0) | D11: =Round(D10/D9,0) | E11: =Round(E10/E9,0) | F11: =Round(F10/F9,0)
B13: TOTAL BOXES | C13: =C11+D11+E11+F11
B15: AVERAGE BOXES/VARIANT | C15: =average(C11:F11)
B17: AVERAGE COST/BOX | C17: =average(C9:F9)
B19: Products | C19: Selling Price (in ₹) | D19: Boxes/Batch | E19: Revenue / Batch (in ₹) | F19: COGS / Batch (in ₹) | G19: Gross Profit/ Batch (in ₹)
B20: Pregnancy Powder | C20: 280 | D20: =C11 | E20: =C20*D20 | F20: =D20*C9 | G20: =E20-F20
B21: Lactation Powder | C21: 286 | D21: =D11 | E21: =C21*D21 | F21: =D21*D9 | G21: =E21-F21
B22: Infant Formula Milk Powder | C22: 242 | D22: =E11 | E22: =C22*E11 | F22: =D22*E9 | G22: =E22-F22
B23: Child Nutrition Powder | C23: 212 | D23: =F11 | E23: =C23*F11 | F23: =D23*F9 | G23: =E23-F23
D24: TOTAL (in ₹) | E24: =SUM(E20:E23) | F24: =SUM(F20:F23) | G24: =SUM(G20:G23)
D25: TOTAL (₹ in Cr) | E25: =E24/10^7 | F25: =F24/10^7 | G25: =G24/10^7
B28: Amount in ₹ Cr
B29: Gross Profit | C29: =G25
B30: Marketing Expense | C30: =E6/2
B31: EBITDA | C31: =C29-C30
B33: Remaining Funds | C33: =(E5+E6)/2 | D33: * 8cr for Production, 3cr for Marketing Expense
B34: Production Funds for Batch 2 | C34: =C31+(E5/2)
B36: Maketing Funds for Batch 2 | C36: =E6/2
B38: TRIO FIT WORKING CAPACITY
C39: 1 day | D39: Working Efficiency | F39: Bulk density | G39: Manufacturing | H39: 1 day
B40: Blender | C40: 500l | D40: 0.7 | E40: =1200 | F40: 0.4 | G40: 400kg/5 hrs | H40: 800kg
B41: Blender 1 | C41: 1500 | D41: 0.7
B42: Blender 2 | C42: =300 | D42: 0.7 | G42: 100kg/5hrs | H42: 200kg
C44: PP | D44: LP | E44: IFP | F44: CNP
B45: Kgs to be Manufactured | C45: =C11*0.5 | D45: =D11*0.5 | E45: =(E11*400)/1000 | F45: =(F11*400)/1000 | G45: * 1 batch capacity
B46: Tons to be Manufactured | C46: =C45/1000 | D46: =D45/1000 | E46: =E45/1000 | F46: =F45/1000
C48: Total Production Capacity | D48: Days | E48: Months (25 days working)
C49: =2*300*1000 | D49: 300 | E49: =D49/25
C50: =sum(C45:F45) | D50: =(C50*D49)/C49 | E50: =D50/25
C52: 1 DAY PRODUCTION CAPACITY (Rohan sir's factory)
C53: PP | D53: LP | E53: IFP | F53: CNP
B54: Boxes | C54: =C55*2 | D54: =D55*2 | E54: =(E55*1000)/400 | F54: =(F55*1000)/400 | G54: =SUM(C54:F54)
B55: Kgs | C55: =C56*$G$55 | D55: =D56*$G$55 | E55: =E56*$G$55 | F55: =F56*$G$55 | G55: =2*1000 | H55: * 300 kg per batch
B56: Percentage % | C56: =C11/sum($C$11:$F$11) | D56: =D11/sum($C$11:$F$11) | E56: =E11/sum($C$11:$F$11) | F56: =F11/sum($C$11:$F$11)
B57: Days taken for 1 Batch | C57: =C11/C54 | D57: =D11/D54 | E57: =E11/E54 | F57: =F11/F54 | G57: =average(C57:F57) | H57: * Average Days Taken
B59: APPLICATION & SOURCES OF FUND
B60: Sources of Fund | C60: =C63
B61: A. VNL | C61: =C60-C62
B62: B. Capital Raise | C62: =E4
B63: Application of Fund | C63: =sum(C64:C65)
B64: A. Production | C64: ='WC (Year 1)'!H9/10^7
B65: B. Indirect Expense | C65: ='WC (Year 1)'!I9/10^7
B89: Phase 1
B90: Phase 2

Sheet Year 2
B2: YEAR 2 FUNDING (in Cr) | C2: 60
C4: Pregnancy Powder (Garbhika) | D4: Lactation Powder (Matrusneha) | E4: Infant Formula Milk Powder (Poshit) | F4: Child Nutrition Powder
B5: Cost/Box | C5: ='PP BOM'!H32 | D5: ='LP BOM'!H35 | E5: ='IFM BOM'!H39 | F5: ='CNP BOM'!H31
B6: Selling Price/Box | C6: ='Total Production'!C20 | D6: ='Total Production'!C21 | E6: ='Total Production'!C22 | F6: ='Total Production'!C23
B7: Profit/Box | C7: =C6-C5 | D7: =D6-D5 | E7: =E6-E5 | F7: =F6-F5
B9: Taking into consideration the following information:
B10: Tons Manufactured / Day | C10: 40 | D10: * 2 tons a day at Rohan Sir's Factory (Natal Care only). Assuming another factory will have 2 tons too
B11: Kgs Manufactured / Day | C11: =C10*1000
B12: Boxes Manufactured / Day | C12: =((C11*1000*0.5)/500)+((C11*1000*0.5)/400)
B14: Natal Care Boxes/Day | C14: =((C11*1000*0.5)/500)*C76 | D14: * Natal Care Products are 500gms each
B15: Infant & Child Care Boxes/Day | C15: =((C11*1000*0.5)/400)*C76 | D15: * Infant and Child Care Products are 400gms each
B17: Working Days/Month | C17: 25
B18: Working Months/Year | C18: 12
B19: Working Days/Year | C19: =C17*C18
B21: PRODUCTION
B22: Products | C22: Boxes/Year | D22: Revenue/Year | E22: Revenue (in Cr) | F22: COGS (in Cr) | G22: Gross Profit (in Cr)
B23: Infant Formula Milk | C23: =($C$19*$C$15)/2 | D23: =C23*E6 | E23: =D23/10^7 | F23: =(C23*E5)/10^7 | G23: =E23-F23
B24: Child Nutrition Powder | C24: =($C$19*$C$15)/2 | D24: =C24*F6 | E24: =D24/10^7 | F24: =(C24*F5)/10^7 | G24: =E24-F24
B25: Pregnancy Powder | C25: =($C$19*$C$14)/2 | D25: =C25*C6 | E25: =D25/10^7 | F25: =(C25*C5)/10^7 | G25: =E25-F25
B26: Lactation Powder | C26: =($C$19*$C$14)/2 | D26: =C26*D6 | E26: =D26/10^7 | F26: =(C26*D5)/10^7 | G26: =E26-F26
C27: =sum(C23:C26) | E27: =sum(E23:E26) | F27: =sum(F23:F26) | G27: =sum(G23:G26)
B29: WORKING CAPITAL
C30: Year 1 | D30: Year 2 | E30: Fresh Capital Needed
B31: Working Capital (in Cr) | C31: ='Contract (1 yr)'!C30 | D31: ='WC (Year 3-5)'!D17/10^7 | E31: =D31-C31
B32: Pregnancy Powder (in Cr) | C32: ='Contract (1 yr)'!C31 | D32: ='WC (Year 3-5)'!D5/10^7 | E32: =D32-C32
B33: Lactation Powder (in Cr) | C33: ='Contract (1 yr)'!C32 | D33: ='WC (Year 3-5)'!D8/10^7 | E33: =D33-C33
B34: Infant Formula Milk (in Cr) | C34: ='Contract (1 yr)'!C33 | D34: ='WC (Year 3-5)'!D11/10^7 | E34: =D34-C34
B35: Child Nutrition Powder (in Cr) | C35: ='Contract (1 yr)'!C34 | D35: ='WC (Year 3-5)'!D14/10^7 | E35: =D35-C35
B37: APPLICATION & SOURCES OF FUND
B38: Sources of Fund | C38: =C42
B39: A. VNL | C39: =C38-C40-C41
B40: B. Capital Raise | C40: =C2
B41: C. Existing Working Capital | C41: =C31
B42: Application of Fund | C42: =sum(C43:C45)
B43: A. Production | C43: ='WC (Year 3-5)'!H17/10^7
B44: B. Indirect Expense | C44: ='WC (Year 3-5)'!I17/10^7
B45: C. Plant CAPEX | C45: =C64
B47: CAPEX TABLE
B48: Cost of Project | C48: Cost (in Cr)
B49: Land and Plant Building | C49: ='Capex & Depreciation'!C26
B50: Utilities (Power, Tanks etc.)
B51: FBD (Fluid Bed Dryer)
B52: Precision Octagonal Blending
B53: Compressor Unit
B54: HVAC
B55: Vibro Sifter
B56: Multi-mill Crusher
B57: Vertical Form Filling Sachets
B58: Packaging Conveyor Unit
B59: Sanitization Machine
B60: Laboratories and Accessories
B61: Tray Dryer
... B63: Contingency Expenses
B64: Total | C64: =sum(C49:C63)
B66: WORKING EFFICIENCY
B67: Months | C67: Year 1
C68: Capacity/Month | D68: Capacity/Quarter
B69: April to June | C69: 0.8
B70: January to March
B71: July to September
B72: October to December
B73: Average Working Capacity %
B75: Capacity Breakup | C75: Year 1 Plant | D75: * Divided in the ratio 3:1
B76: Our brand manufacturing | C76: =D73
B77: Contract manufacturing | C77: =D73-C76
B79: INDIRECT EXPENSES
B80: Expense Bifurcation | D80: Expense % | E80: Total Expense
B81: Training & Community Engagement | D81: ='Contract (1 yr)'!D63 | E81: =(D81*$E$27)*10^7
B82: Monitoring & Evaluation | D82: 0.005 | E82: =(D82*$E$27)*10^7
B83: Technology & Reporting | D83: 0.003 | E83: =(D83*$E$27)*10^7
B84: Administrative Cost | D84: 0.017 | E84: =(D84*$E$27)*10^7
B85: Logistics & Distribution Cost | D85: Rs. 8.5/ Box | E85: =8.5*C27
B86: Communication & Impact Documentation | D86: ='Contract (1 yr)'!D68 | E86: =(D86*$E$27)*10^7
B87: Contingency | D87: ='Contract (1 yr)'!D69 | E87: =sum(E81:E86)*D87
D88: TOTAL (in ₹) | E88: =sum(E81:E87)
D89: TOTAL (₹ in Cr) | E89: =E88/10^7

Sheet Year 3
B2: YEAR 3 FUNDING (in Cr) | C2: 0
C4: Pregnancy Powder (Garbhika) | D4: Lactation Powder (Matrusneha) | E4: Infant Formula Milk Powder (Poshit) | F4: Child Nutrition Powder
B5: Cost/Box | C5: ='PP BOM'!H32 | D5: ='LP BOM'!H35 | E5: ='IFM BOM'!H39 | F5: ='CNP BOM'!H31
B6: Selling Price/Box | C6: ='Total Production'!C20 | D6: ='Total Production'!C21 | E6: ='Total Production'!C22 | F6: ='Total Production'!C23
B7: Profit/Box | C7: =C6-C5 | D7: =D6-D5 | E7: =E6-E5 | F7: =F6-F5
B9: Taking into consideration the following information:
B10: Tons Manufactured / Day | C10: 40 | D10: * 2 tons a day at Rohan Sir's Factory (Natal Care only). Assuming another factory will have 2 tons too
B11: Kgs Manufactured / Day | C11: =C10*1000
B12: Boxes Manufactured / Day | C12: =((C11*1000*0.5)/500)+((C11*1000*0.5)/400)
B14: Natal Care Boxes/Day | C14: =((C11*1000*0.5)/500)*C75 | D14: * Natal Care Products are 500gms each
B15: Infant & Child Care Boxes/Day | C15: =((C11*1000*0.5)/400)*C75 | D15: * Infant and Child Care Products are 400gms each
B17: Working Days/Month | C17: 25
B18: Working Months/Year | C18: 12
B19: Working Days/Year | C19: =C17*C18
B21: PRODUCTION
B22: Products | C22: Boxes/Year | D22: Revenue/Year | E22: Revenue (in Cr) | F22: COGS (in Cr) | G22: Gross Profit (in Cr)
B23: Infant Formula Milk | C23: =($C$19*$C$15)/2 | D23: =C23*E6 | E23: =D23/10^7 | F23: =(C23*E5)/10^7 | G23: =E23-F23
B24: Child Nutrition Powder | C24: =($C$19*$C$15)/2 | D24: =C24*F6 | E24: =D24/10^7 | F24: =(C24*F5)/10^7 | G24: =E24-F24
B25: Pregnancy Powder | C25: =($C$19*$C$14)/2 | D25: =C25*C6 | E25: =D25/10^7 | F25: =(C25*C5)/10^7 | G25: =E25-F25
B26: Lactation Powder | C26: =($C$19*$C$14)/2 | D26: =C26*D6 | E26: =D26/10^7 | F26: =(C26*D5)/10^7 | G26: =E26-F26
C27: =sum(C23:C26) | E27: =sum(E23:E26) | F27: =sum(F23:F26) | G27: =sum(G23:G26)
B29: WORKING CAPITAL
C30: Year 3 | D30: Year 2 | E30: Fresh Capital Needed
B31: Working Capital (in Cr) | C31: ='WC (Year 3)'!D9/10^7 | D31: ='Year 2'!D31 | E31: =C31-D31
B32: Pregnancy Powder (in Cr) | C32: ='WC (Year 3)'!D5/10^7 | D32: ='WC (Year 3-5)'!D5/10^7 | E32: =C32-D32
B33: Lactation Powder (in Cr) | C33: ='WC (Year 3)'!D6/10^7 | D33: ='WC (Year 3-5)'!D8/10^7 | E33: =C33-D33
B34: Infant Formula Milk (in Cr) | C34: ='WC (Year 3)'!D7/10^7 | D34: ='WC (Year 3-5)'!D11/10^7 | E34: =C34-D34
B35: Child Nutrition Powder (in Cr) | C35: ='WC (Year 3)'!D8/10^7 | D35: ='WC (Year 3-5)'!D14/10^7 | E35: =C35-D35
B37: APPLICATION & SOURCES OF FUND
B38: Sources of Fund | C38: =C42
B39: A. VNL Retained Earnings | C39: =C38-C40-C41 | D39: * 7.58% of Retained Earnings
B40: B. Capital Raise | C40: =C2
B41: C. Existing Working Capital | C41: =D31
B42: Application of Fund | C42: =sum(C43:C44)
B43: A. Production | C43: ='WC (Year 3)'!H9/10^7
B44: B. Indirect Expense | C44: ='WC (Year 3)'!I9/10^7
B46: CAPEX TABLE
B47: Cost of Project | C47: Cost (in Cr)
B48: Land and Plant Building | C48: ='Capex & Depreciation'!C26
B49: Utilities (Power, Tanks etc.)
B50: FBD (Fluid Bed Dryer)
B51: Precision Octagonal Blending
B52: Compressor Unit
B53: HVAC
B54: Vibro Sifter
B55: Multi-mill Crusher
B56: Vertical Form Filling Sachets
B57: Packaging Conveyor Unit
B58: Sanitization Machine
B59: Laboratories and Accessories
B60: Tray Dryer
... B62: Contingency Expenses
B63: Total | C63: =sum(C48:C62)
B65: WORKING EFFICIENCY
B66: Months | C66: Year 1 | E66: Year 2
C67: Capacity/Month | D67: Capacity/Quarter | E67: Capacity/Month | F67: Capacity/Quarter
B68: April to June | C68: 0.8 | E68: 0.8
B69: January to March
B70: July to September
B71: October to December
B72: Average Working Capacity %
B74: Capacity Breakup | C74: Year 2 Plant
B75: Our brand manufacturing | C75: =F72
B76: Contract manufacturing | C76: =F72-C75
B78: INDIRECT EXPENSES
B79: Expense Bifurcation | D79: Expense % | E79: Total Expense
B80: Training & Community Engagement | D80: 0.008 | E80: =(D80*$E$27)*10^7
B81: Monitoring & Evaluation | D81: 0.003 | E81: =(D81*$E$27)*10^7
B82: Technology & Reporting | D82: 0.0015 | E82: =(D82*$E$27)*10^7
B83: Administrative Cost | D83: 0.015 | E83: =(D83*$E$27)*10^7
B84: Logistics & Distribution Cost | D84: Rs. 7/ Box | E84: =7*C27
B85: Communication & Impact Documentation | D85: ='Year 2'!D86 | E85: =(D85*$E$27)*10^7
B86: Contingency | D86: 0.05 | E86: =(D86*$E$27)*10^7
D87: TOTAL (in ₹) | E87: =sum(E80:E86)
D88: TOTAL (₹ in Cr) | E88: =E87/10^7

Sheet WC (Year 3)
B2: TOTAL WORKING CAPITAL | G2: APPLICATION OF FUNDS
C4: Revenue | D4: Initial Working Capital | E4: W.C.Rotation | H4: Production | I4: Indirect Expense
B5: PP | C5: =D35 | D5: =D36 | E5: =IFERROR(C5/D5,0) | G5: PP | H5: =(D13*D14)*2.5 | I5: =D16*2.5
B6: LP | C6: =D64 | D6: =D65 | E6: =IFERROR(C6/D6,0) | G6: LP | H6: =(D42*D43)*2.5 | I6: =D45*2.5
B7: IFP | C7: =D93 | D7: =D94 | E7: =IFERROR(C7/D7,0) | G7: IFP | H7: =(D71*D72)*2.5 | I7: =D74*2.5
B8: CNP | C8: =D122 | D8: =D123 | E8: =IFERROR(C8/D8,0) | G8: CNP | H8: =(D100*D101)*2.5 | I8: =D103*2.5
D9: =sum(D5:D8) | H9: =sum(H5:H8) | I9: =sum(I5:I8)
H10: =H9+I9
B11: PREGNANCY POWDER
B13: Monthly Boxes Produced (in Units) | D13: ='Year 3'!C25/12
B14: Cost/Box (in ₹) | D14: ='Year 2'!C5
B15: Revenue/Box (in ₹) | D15: ='Year 2'!C6
B16: Monthly Indirect Expense (in ₹) | D16: =('Year 2'!$E$88/12)/4
G17: * The working capital that we are investing in the first month is derived from the cash outflow that is required in the first month
B18: Month | C18: Cash Outflow | D18: Cash Inflow | E18: Difference (CO-CI) | G18: Opening W.C. | H18: Net Cash Flow | I18: Closing W.C.
B19: April | C19: =($D$13*$D$14)+$D$16 | D19: =$D$13*$D$15 | E19: =D19-C19 | G19: =C19+D33 | H19: =E19 | I19: =G19+H19
B20: May | C20: =($D$13*$D$14)+$D$16 | D20: =$D$13*$D$15 | E20: =D20-C20 | G20: =I19 | H20: =E20 | I20: =G20+H20
B21: June | C21: =($D$13*$D$14)+$D$16 | D21: =$D$13*$D$15 | E21: =D21-C21 | G21: =I20 | H21: =E21 | I21: =G21+H21
B22: July | C22: =($D$13*$D$14)+$D$16 | D22: =$D$13*$D$15 | E22: =D22-C22 | G22: =I21 | H22: =E22 | I22: =G22+H22
B23: August | C23: =($D$13*$D$14)+$D$16 | D23: =$D$13*$D$15 | E23: =D23-C23 | G23: =I22 | H23: =E23 | I23: =G23+H23
B24: September | C24: =($D$13*$D$14)+$D$16 | D24: =$D$13*$D$15 | E24: =D24-C24 | G24: =I23 | H24: =E24 | I24: =G24+H24
B25: October | C25: =($D$13*$D$14)+$D$16 | D25: =$D$13*$D$15 | E25: =D25-C25 | G25: =I24 | H25: =E25 | I25: =G25+H25
B26: November | C26: =($D$13*$D$14)+$D$16 | D26: =$D$13*$D$15 | E26: =D26-C26 | G26: =I25 | H26: =E26 | I26: =G26+H26
B27: December | C27: =($D$13*$D$14)+$D$16 | D27: =$D$13*$D$15 | E27: =D27-C27 | G27: =I26 | H27: =E27 | I27: =G27+H27
B28: January | C28: =($D$13*$D$14)+$D$16 | D28: =$D$13*$D$15 | E28: =D28-C28 | G28: =I27 | H28: =E28 | I28: =G28+H28
B29: February | C29: =($D$13*$D$14)+$D$16 | D29: =$D$13*$D$15 | E29: =D29-C29 | G29: =I28 | H29: =E29 | I29: =G29+H29
B30: March | C30: =($D$13*$D$14)+$D$16 | D30: =$D$13*$D$15 | E30: =D30-C30 | G30: =I29 | H30: =E30 | I30: =G30+H30
C31: =SUM(C19:C30) | D31: =SUM(D19:D30) | E31: =D31-C31
B33: Buffer Capital (Production Cost of 1.5 Months) | D33: =C19*1.5
B35: Total Yearly Turnover | D35: =D31
B36: Initial Working Capital | D36: =C19+D33 | E36: * Working Capital Required=Cash outflow for the first month + Contingency fund
B37: Working Capital Rotation | D37: =IFERROR(D35/D36,0)
B40: LACTATION POWDER
B42: Monthly Boxes Produced (in Units) | D42: ='Year 3'!C26/12
B43: Cost/Box (in ₹) | D43: ='Year 2'!D5
B44: Revenue/Box (in ₹) | D44: ='Year 2'!D6
B45: Monthly Indirect Expense (in ₹) | D45: =('Year 2'!$E$88/12)/4
G46: * The working capital that we are investing in the first month is derived from the cash outflow that is required in the first month
B47: Month | C47: Cash Outflow | D47: Cash Inflow | E47: Difference (CO-CI) | G47: Opening W.C. | H47: Net Cash Flow | I47: Closing W.C.
B48: April | C48: =($D$42*$D$43)+$D$45 | D48: =$D$42*$D$44 | E48: =D48-C48 | G48: =C48+D62 | H48: =E48 | I48: =G48+H48
B49: May | C49: =($D$42*$D$43)+$D$45 | D49: =$D$42*$D$44 | E49: =D49-C49 | G49: =I48 | H49: =E49 | I49: =G49+H49
B50: June | C50: =($D$42*$D$43)+$D$45 | D50: =$D$42*$D$44 | E50: =D50-C50 | G50: =I49 | H50: =E50 | I50: =G50+H50
B51: July | C51: =($D$42*$D$43)+$D$45 | D51: =$D$42*$D$44 | E51: =D51-C51 | G51: =I50 | H51: =E51 | I51: =G51+H51
B52: August | C52: =($D$42*$D$43)+$D$45 | D52: =$D$42*$D$44 | E52: =D52-C52 | G52: =I51 | H52: =E52 | I52: =G52+H52
B53: September | C53: =($D$42*$D$43)+$D$45 | D53: =$D$42*$D$44 | E53: =D53-C53 | G53: =I52 | H53: =E53 | I53: =G53+H53
B54: October | C54: =($D$42*$D$43)+$D$45 | D54: =$D$42*$D$44 | E54: =D54-C54 | G54: =I53 | H54: =E54 | I54: =G54+H54
B55: November | C55: =($D$42*$D$43)+$D$45 | D55: =$D$42*$D$44 | E55: =D55-C55 | G55: =I54 | H55: =E55 | I55: =G55+H55
B56: December | C56: =($D$42*$D$43)+$D$45 | D56: =$D$42*$D$44 | E56: =D56-C56 | G56: =I55 | H56: =E56 | I56: =G56+H56
B57: January | C57: =($D$42*$D$43)+$D$45 | D57: =$D$42*$D$44 | E57: =D57-C57 | G57: =I56 | H57: =E57 | I57: =G57+H57
B58: February | C58: =($D$42*$D$43)+$D$45 | D58: =$D$42*$D$44 | E58: =D58-C58 | G58: =I57 | H58: =E58 | I58: =G58+H58
B59: March | C59: =($D$42*$D$43)+$D$45 | D59: =$D$42*$D$44 | E59: =D59-C59 | G59: =I58 | H59: =E59 | I59: =G59+H59
C60: =SUM(C48:C59) | D60: =SUM(D48:D59) | E60: =D60-C60
B62: Buffer Capital (Production Cost of 1.5 Months) | D62: =C48*1.5
B64: Total Yearly Turnover | D64: =D60
B65: Initial Working Capital | D65: =C48+D62 | E65: * Working Capital Required=Cash outflow for the first month + Contingency fund
B66: Working Capital Rotation | D66: =IFERROR(D64/D65,0)
B69: INFANT POWDER
B71: Monthly Boxes Produced (in Units) | D71: ='Year 3'!C23/12
B72: Cost/Box (in ₹) | D72: ='Year 2'!E5
B73: Revenue/Box (in ₹) | D73: ='Year 2'!E6
B74: Monthly Indirect Expense (in ₹) | D74: =('Year 2'!$E$88/12)/4
G75: * The working capital that we are investing in the first month is derived from the cash outflow that is required in the first month
B76: Month | C76: Cash Outflow | D76: Cash Inflow | E76: Difference (CO-CI) | G76: Opening W.C. | H76: Net Cash Flow | I76: Closing W.C.
B77: April | C77: =($D$71*$D$72)+$D$74 | D77: =$D$71*$D$73 | E77: =D77-C77 | G77: =C77+D91 | H77: =E77 | I77: =G77+H77
B78: May | C78: =($D$71*$D$72)+$D$74 | D78: =$D$71*$D$73 | E78: =D78-C78 | G78: =I77 | H78: =E78 | I78: =G78+H78
B79: June | C79: =($D$71*$D$72)+$D$74 | D79: =$D$71*$D$73 | E79: =D79-C79 | G79: =I78 | H79: =E79 | I79: =G79+H79
B80: July | C80: =($D$71*$D$72)+$D$74 | D80: =$D$71*$D$73 | E80: =D80-C80 | G80: =I79 | H80: =E80 | I80: =G80+H80
B81: August | C81: =($D$71*$D$72)+$D$74 | D81: =$D$71*$D$73 | E81: =D81-C81 | G81: =I80 | H81: =E81 | I81: =G81+H81
B82: September | C82: =($D$71*$D$72)+$D$74 | D82: =$D$71*$D$73 | E82: =D82-C82 | G82: =I81 | H82: =E82 | I82: =G82+H82
B83: October | C83: =($D$71*$D$72)+$D$74 | D83: =$D$71*$D$73 | E83: =D83-C83 | G83: =I82 | H83: =E83 | I83: =G83+H83
B84: November | C84: =($D$71*$D$72)+$D$74 | D84: =$D$71*$D$73 | E84: =D84-C84 | G84: =I83 | H84: =E84 | I84: =G84+H84
B85: December | C85: =($D$71*$D$72)+$D$74 | D85: =$D$71*$D$73 | E85: =D85-C85 | G85: =I84 | H85: =E85 | I85: =G85+H85
B86: January | C86: =($D$71*$D$72)+$D$74 | D86: =$D$71*$D$73 | E86: =D86-C86 | G86: =I85 | H86: =E86 | I86: =G86+H86
B87: February | C87: =($D$71*$D$72)+$D$74 | D87: =$D$71*$D$73 | E87: =D87-C87 | G87: =I86 | H87: =E87 | I87: =G87+H87
B88: March | C88: =($D$71*$D$72)+$D$74 | D88: =$D$71*$D$73 | E88: =D88-C88 | G88: =I87 | H88: =E88 | I88: =G88+H88
C89: =SUM(C77:C88) | D89: =SUM(D77:D88) | E89: =D89-C89
B91: Buffer Capital (Production Cost of 1.5 Months) | D91: =C77*1.5
B93: Total Yearly Turnover | D93: =D89
B94: Initial Working Capital | D94: =C77+D91 | E94: * Working Capital Required=Cash outflow for the first month + Contingency fund
B95: Working Capital Rotation | D95: =IFERROR(D93/D94,0)
B98: CHILDREN POWDER
B100: Monthly Boxes Produced (in Units) | D100: ='Year 3'!C24/12
B101: Cost/Box (in ₹) | D101: ='Year 2'!F5
B102: Revenue/Box (in ₹) | D102: ='Year 2'!F6
B103: Monthly Indirect Expense (in ₹) | D103: =('Year 2'!$E$88/12)/4
G104: * The working capital that we are investing in the first month is derived from the cash outflow that is required in the first month
B105: Month | C105: Cash Outflow | D105: Cash Inflow | E105: Difference (CO-CI) | G105: Opening W.C. | H105: Net Cash Flow | I105: Closing W.C.
B106: April | C106: =($D$100*$D$101)+$D$103 | D106: =$D$100*$D$102 | E106: =D106-C106 | G106: =C106+D120 | H106: =E106 | I106: =G106+H106
B107: May | C107: =($D$100*$D$101)+$D$103 | D107: =$D$100*$D$102 | E107: =D107-C107 | G107: =I106 | H107: =E107 | I107: =G107+H107
B108: June | C108: =($D$100*$D$101)+$D$103 | D108: =$D$100*$D$102 | E108: =D108-C108 | G108: =I107 | H108: =E108 | I108: =G108+H108
B109: July | C109: =($D$100*$D$101)+$D$103 | D109: =$D$100*$D$102 | E109: =D109-C109 | G109: =I108 | H109: =E109 | I109: =G109+H109
B110: August | C110: =($D$100*$D$101)+$D$103 | D110: =$D$100*$D$102 | E110: =D110-C110 | G110: =I109 | H110: =E110 | I110: =G110+H110
B111: September | C111: =($D$100*$D$101)+$D$103 | D111: =$D$100*$D$102 | E111: =D111-C111 | G111: =I110 | H111: =E111 | I111: =G111+H111
B112: October | C112: =($D$100*$D$101)+$D$103 | D112: =$D$100*$D$102 | E112: =D112-C112 | G112: =I111 | H112: =E112 | I112: =G112+H112
B113: November | C113: =($D$100*$D$101)+$D$103 | D113: =$D$100*$D$102 | E113: =D113-C113 | G113: =I112 | H113: =E113 | I113: =G113+H113
B114: December | C114: =($D$100*$D$101)+$D$103 | D114: =$D$100*$D$102 | E114: =D114-C114 | G114: =I113 | H114: =E114 | I114: =G114+H114
B115: January | C115: =($D$100*$D$101)+$D$103 | D115: =$D$100*$D$102 | E115: =D115-C115 | G115: =I114 | H115: =E115 | I115: =G115+H115
B116: February | C116: =($D$100*$D$101)+$D$103 | D116: =$D$100*$D$102 | E116: =D116-C116 | G116: =I115 | H116: =E116 | I116: =G116+H116
B117: March | C117: =($D$100*$D$101)+$D$103 | D117: =$D$100*$D$102 | E117: =D117-C117 | G117: =I116 | H117: =E117 | I117: =G117+H117
C118: =SUM(C106:C117) | D118: =SUM(D106:D117) | E118: =D118-C118
...

Sheet PP BOM
B2: RAW MATERIAL COST
B4: Item No. | C4: Ingredient Name | D4: In Grams | F4: In Rupees
D5: Quantity Per 100 g | E5: Quantity per 500 gm | F5: Rate / Kg | G5: Rate / Gram | H5: Rate Per 500 g
B6: 1 | C6: Skimmed Milk Powder | D6: 35 | E6: =D6*5 | F6: 320 | G6: =F6/1000 | H6: =E6*G6
B7: 2 | C7: Maltodextrin | D7: 23.84 | E7: =D7*5 | F7: 70 | G7: =F7/1000 | H7: =E7*G7
B8: 3 | C8: Fructooligosaccharides | D8: 5 | E8: =D8*5 | F8: 170 | G8: =F8/1000 | H8: =E8*G8
B9: 4 | C9: Rice Protein | D9: 7 | E9: =D9*5 | F9: 270 | G9: =F9/1000 | H9: =E9*G9
B10: 5 | C10: Soy Protein | D10: 13 | E10: =D10*5 | F10: 290 | G10: =F10/1000 | H10: =E10*G10
B11: 6 | C11: Shingada Flour | D11: 2 | E11: =D11*5 | F11: 190 | G11: =F11/1000 | H11: =E11*G11
B12: 7 | C12: Cocoa Powder | D12: 8 | E12: =D12*5 | F12: 600 | G12: =F12/1000 | H12: =E12*G12 | I12: 1 | J12: KESAR PISTA
B13: 8 | C13: Vitamin and Mineral Premix | D13: 3.5 | E13: =D13*5 | F13: 850 | G13: =F13/1000 | H13: =E13*G13 | I13: 2 | J13: CHOCOLATE
B14: 9 | C14: Culture | D14: 0.1 | E14: =D14*5 | F14: 480 | G14: =F14/1000 | H14: =E14*G14
B15: 10 | C15: Sucralose | D15: 0.06 | E15: =D15*5 | F15: 1450 | G15: =F15/1000 | H15: =E15*G15
B16: 11 | C16: Nature Identical Flavour | D16: 2 | E16: =D16*5 | F16: 700 | G16: =F16/1000 | H16: =E16*G16 | J16: KG | K16: BOXES | L16: COST
B17: 12 | C17: Multisense | D17: 0.5 | E17: =D17*5 | F17: 2500 | G17: =F17/1000 | H17: =E17*G17 | J17: =(K17*500)/1000 | K17: 800 | L17: =K17*H25 | M17: COGS_ Preg
D18: =SUM(D6:D17) | E18: =SUM(E6:E17) | H18: =SUM(H6:H17) | J18: =(K18*500)/1000 | K18: 800 | L18: =K18*'LP BOM'!H28 | M18: COGS_Lact
J19: =J17+J18 | K19: =K17+K18 | L19: =L17+L18 | M19: TOTAL
B20: OTHER COSTS
C22: Packaging cost | H22: 20
C23: Conversion cost | H23: ='Contract (1 yr)'!C43
F25: TOTAL COST / BOX | H25: =SUM(H18:H23)
F27: COST / BATCH | H27: 20000000
F29: BOXES / BATCH | H29: =H27/H25
F31: AS PER PROJETIONS SHEET
F32: Total Cost (Excl. GST) | H32: =H25 | I32: VS | J32: =H25
F33: GST 18%
F34: Total Cost (Incl. GST)
B37: Mawa Kulfi
B38: Item No. | C38: Ingredient Name | D38: In Grams | F38: In Rupees
D39: Quantity Per 100 g | E39: Quantity per 500 gm | F39: Rate / Kg | G39: Rate / Gram | H39: Rate Per 500 g
B40: 1 | C40: Skimmed Milk Powder | D40: 36 | E40: =D40*5 | F40: 240 | G40: =F40/1000 | H40: =E40*G40
B41: 2 | C41: Maltodextrin | D41: 27.84 | E41: =D41*5 | F41: 70 | G41: =F41/1000 | H41: =E41*G41
B42: 3 | C42: Fructooligosaccharides | D42: 5 | E42: =D42*5 | F42: 170 | G42: =F42/1000 | H42: =E42*G42
B43: 4 | C43: Rice Protein | D43: 8 | E43: =D43*5 | F43: 270 | G43: =F43/1000 | H43: =E43*G43
B44: 5 | C44: Soy Protein | D44: 15 | E44: =D44*5 | F44: 290 | G44: =F44/1000 | H44: =E44*G44
B45: 6 | C45: Shingada Flour | D45: 2 | E45: =D45*5 | F45: 190 | G45: =F45/1000 | H45: =E45*G45
B46: 7 | D46: 0 | E46: =D46*5 | F46: 600 | G46: =F46/1000 | H46: =E46*G46
B47: 8 | C47: Vitamin and Mineral Premix | D47: 3.5 | E47: =D47*5 | F47: 850 | G47: =F47/1000 | H47: =E47*G47
B48: 9 | C48: Culture | D48: 0.1 | E48: =D48*5 | F48: 480 | G48: =F48/1000 | H48: =E48*G48
B49: 10 | C49: Sucralose | D49: 0.06 | E49: =D49*5 | F49: 1300 | G49: =F49/1000 | H49: =E49*G49
B50: 11 | C50: Nature Identical Flavour | D50: 2 | E50: =D50*5 | F50: 700 | G50: =F50/1000 | H50: =E50*G50
B51: 12 | C51: Multisense | D51: 0.5 | E51: =D51*5 | G51: =F51/1000 | H51: =E51*G51
D52: =SUM(D40:D51) | E52: =SUM(E40:E51) | H52: =SUM(H40:H51)

Sheet LP BOM
B2: RAW MATERIAL COST
B4: Item No. | C4: Ingredient Name | D4: In Grams | F4: In Rupees
D5: Quantity Per 100 g | E5: Quantity per 500 gm | F5: Rate / Kg | G5: Rate / Gram | H5: Rate Per 500 g
B6: 1 | C6: Skimmed Milk Powder | D6: 35.5 | E6: =D6*5 | F6: 320 | G6: =F6/1000 | H6: =E6*G6
B7: 2 | C7: Maltodextrin | D7: 24.85 | E7: =D7*5 | F7: 70 | G7: =F7/1000 | H7: =E7*G7
B8: 3 | C8: Fructooligosaccharides | D8: 5 | E8: =D8*5 | F8: 170 | G8: =F8/1000 | H8: =E8*G8
B9: 4 | C9: Rice Protein | D9: 8 | E9: =D9*5 | F9: 270 | G9: =F9/1000 | H9: =E9*G9 | I9: 1 | J9: MAWA KULFI
B10: 5 | C10: Soy Protein | D10: 15 | E10: =D10*5 | F10: 290 | G10: =F10/1000 | H10: =E10*G10 | I10: 2 | J10: VANILA
B11: 6 | C11: Shingada Flour | D11: 2 | E11: =D11*5 | F11: 180 | G11: =F11/1000 | H11: =E11*G11
B12: 7 | C12: Vitamin and Mineral premix | D12: 3.5 | E12: =D12*5 | F12: 800 | G12: =F12/1000 | H12: =E12*G12
B13: 8 | C13: Culture | D13: 0.1 | E13: =D13*5 | F13: 450 | G13: =F13/1000 | H13: =E13*G13
B14: 9 | C14: Sucralose | D14: 0.05 | E14: =D14*5 | F14: 1450 | G14: =F14/1000 | H14: =E14*G14
B15: 10 | C15: Nature Identical Flavour Cardamom | D15: 1.5 | E15: =D15*5 | F15: 700 | G15: =F15/1000 | H15: =E15*G15
B16: 11 | C16: Shatavari | D16: 2 | E16: =D16*5 | F16: 350 | G16: =F16/1000 | H16: =E16*G16
B17: 12 | C17: Ashwagandha | D17: 1 | E17: =D17*5 | F17: 650 | G17: =F17/1000 | H17: =E17*G17
B18: 13 | C18: Moringa | D18: 0.5 | E18: =D18*5 | F18: 180 | G18: =F18/1000 | H18: =E18*G18
B19: 14 | C19: Funnel | D19: 0.5 | E19: =D19*5 | F19: 180 | G19: =F19/1000 | H19: =E19*G19
B20: 15 | C20: Cinnamon | D20: 0.5 | E20: =D20*5 | F20: 100 | G20: =F20/1000 | H20: =E20*G20
D21: =SUM(D6:D20) | E21: =SUM(E6:E20) | H21: =SUM(H6:H20)
B23: OTHER COSTS
C25: Packaging cost | H25: 20
C26: Conversion cost | H26: ='Contract (1 yr)'!C43
F28: TOTAL COST / BOX | H28: =sum(H21:H26) | K28: =H28*800 | L28: - COST OF 400 Boxes
F30: PRODUCTION COST / BATCH | H30: 20000000
F32: BOXES / BATCH | H32: =H30/H28
F34: AS PER PROJETIONS SHEET
F35: Total Cost (Excl. GST) | H35: =H28 | I35: VS | J35: =H28
F36: GST 18%
F37: Total Cost (Incl. GST)
C39: Kesar
B40: Item No. | C40: Ingredient Name | D40: In Grams | F40: In Rupees
D41: Quantity Per 100 g | E41: Quantity per 500 gm | F41: Rate / Kg | G41: Rate / Gram | H41: Rate Per 500 g
B42: 1 | C42: Skimmed Milk Powder | D42: 35 | E42: =D42*5 | F42: 240 | G42: =F42/1000 | H42: =E42*G42
B43: 2 | C43: Maltodextrin | D43: 25 | E43: =D43*5 | F43: 50 | G43: =F43/1000 | H43: =E43*G43
B44: 3 | C44: Fructooligosaccharides | D44: 5 | E44: =D44*5 | F44: 170 | G44: =F44/1000 | H44: =E44*G44
B45: 4 | C45: Rice Protein | D45: 8.35 | E45: =D45*5 | F45: 270 | G45: =F45/1000 | H45: =E45*G45
B46: 5 | C46: Soy Protein | D46: 15 | E46: =D46*5 | F46: 290 | G46: =F46/1000 | H46: =E46*G46
B47: 6 | C47: Shingada Flour | D47: 2 | E47: =D47*5 | F47: 180 | G47: =F47/1000 | H47: =E47*G47
B48: 7 | C48: Vitamin and Mineral premix | D48: 3.5 | E48: =D48*5 | F48: 800 | G48: =F48/1000 | H48: =E48*G48
B49: 8 | C49: Culture | D49: 0.1 | E49: =D49*5 | F49: 450 | G49: =F49/1000 | H49: =E49*G49
B50: 9 | C50: Sucralose | D50: 0.05 | E50: =D50*5 | F50: 1300 | G50: =F50/1000 | H50: =E50*G50
B51: 10 | C51: Nature Identical Flavour kesar | D51: 2 | E51: =D51*5 | F51: 700 | G51: =F51/1000 | H51: =E51*G51
B52: 11 | C52: Shatavari | D52: 2 | E52: =D52*5 | F52: 350 | G52: =F52/1000 | H52: =E52*G52
B53: 12 | C53: Ashwagandha | D53: 1 | E53: =D53*5 | F53: 190 | G53: =F53/1000 | H53: =E53*G53
... B55: 14 | C55: Cinnamon Powder | D55: 0.5 | E55: =D55*5 | F55: 180 | G55: =F55/1000 | H55: =E55*G55
D56: 0 | E56: =D56*5 | G56: =F56/1000 | H56: =E56*G56
D57: =SUM(D42:D56) | E57: =SUM(E42:E56) | H57: =SUM(H42:H56)

Sheet IFM BOM
B2: RAW MATERIAL COST
B4: Item No. | C4: Ingredient Name | D4: In Grams | F4: In Rupees
D5: Quantity Per 100 g | E5: Quantity per 400 gm | F5: Rate / Kg | G5: Rate / Gram | H5: Rate Per 400 g
B6: 1 | C6: Skim Milk Powder | D6: 35 | E6: =D6*4 | F6: 320 | G6: =F6/1000 | H6: =E6*G6
B7: 2 | C7: Demineralised Whey Powder | D7: 22 | E7: =D7*4 | F7: 150 | G7: =F7/1000 | H7: =E7*G7
B8: 3 | C8: Lactose | D8: 13 | E8: =D8*4 | F8: 200 | G8: =F8/1000 | H8: =E8*G8
B9: 4 | C9: Maltodextrin | D9: 8.05 | E9: =D9*4 | F9: 70 | G9: =F9/1000 | H9: =E9*G9
B10: 5 | C10: High Oleic Sunflower Oil | D10: 6 | E10: =D10*4 | F10: 350 | G10: =F10/1000 | H10: =E10*G10
B11: 6 | C11: Soya oil Powder | D11: 4 | E11: =D11*4 | F11: 100 | G11: =F11/1000 | H11: =E11*G11
B12: 7 | C12: Coconut oil Powder | D12: 2 | E12: =D12*4 | F12: 250 | G12: =F12/1000 | H12: =E12*G12
B13: 8 | C13: Milk fat powder | D13: 4 | E13: =D13*4 | F13: 230 | G13: =F13/1000 | H13: =E13*G13
B14: 9 | C14: DHA oil Powder | D14: 0.2 | E14: =D14*4 | F14: 400 | G14: =F14/1000 | H14: =E14*G14
B15: 10 | C15: ARA oil Powder | D15: 0.2 | E15: =D15*4 | F15: 150 | G15: =F15/1000 | H15: =E15*G15
B16: 11 | C16: Fructooligosaccharides | D16: 2 | E16: =D16*4 | F16: 170 | G16: =F16/1000 | H16: =E16*G16
B17: 12 | C17: Galactooligosaccharides | D17: 1.5 | E17: =D17*4 | F17: 200 | G17: =F17/1000 | H17: =E17*G17
... B22: 17 | C22: L-Carnitine | D22: 0.05 | E22: =D22*4 | F22: 2000 | G22: =F22/1000 | H22: =E22*G22
B23: RAW MATERIAL TOTAL COST | D23: =SUM(D6:D22) | E23: =D23*5 | H23: =SUM(H6:H22)
B25: OTHER COSTS
C27: Packaging | H27: 20
C28: Conversion | H28: ='Contract (1 yr)'!C51
F30: TOTAL COST / BOX | H30: =H23+H27+H28
F32: PRODUCTION COST / BATCH | H32: 20000000
F34: BOXES / BATCH | H34: =H32/H30
F36: BOXES / VARIANT | H36: =H34/3
F38: AS PER PROJETIONS SHEET
F39: Total Cost (Excl. GST) | H39: =H30 | I39: VS | J39: =H30
F40: GST 18%
F41: Total Cost (Incl. GST)

Sheet CNP BOM
B2: RAW MATERIAL COST
B4: Item No. | C4: Ingredient Name | D4: In Grams | F4: In Rupees
D5: Quantity Per 100 g | E5: Quantity per 400 gm | F5: Rate / Kg | G5: Rate / Gram | H5: Rate Per 400 g
B6: 1 | C6: Skimmed Milk Powder | D6: 35 | E6: =D6*4 | F6: 320 | G6: =F6/1000 | H6: =E6*G6
B7: 2 | C7: Maltodextrin | D7: 14 | E7: =D7*4 | F7: 70 | G7: =F7/1000 | H7: =E7*G7
B8: 3 | C8: Nuts blend(Almond, Cashew, Walnut, Pista, Dates) | D8: 6 | E8: =D8*4 | F8: 180 | G8: =F8/1000 | H8: =E8*G8
B9: 4 | C9: Cocoa powder | D9: 6 | E9: =D9*4 | F9: 600 | G9: =F9/1000 | H9: =E9*G9 | I9: 1 | J9: VANILLA
B10: 5 | C10: Palmyra Jaggery | D10: 13 | E10: =D10*4 | F10: 50 | G10: =F10/1000 | H10: =E10*G10 | I10: 2 | J10: CHOCOLATE
B11: 6 | C11: Fructooligosaccharides | D11: 2 | E11: =D11*4 | F11: 170 | G11: =F11/1000 | H11: =E11*G11
B12: 7 | C12: Nature Identical Flavours | D12: 2 | E12: =D12*4 | F12: 600 | G12: =F12/1000 | H12: =E12*G12
B13: 8 | C13: Vitamins | D13: 1 | E13: =D13*4 | F13: 500 | G13: =F13/1000 | H13: =E13*G13
B14: 9 | C14: Minerals | D14: 1 | E14: =D14*4 | F14: 400 | G14: =F14/1000 | H14: =E14*G14
B15: 10 | C15: Fruit Powder | D15: 12 | E15: =D15*4 | F15: 200 | G15: =F15/1000 | H15: =E15*G15
B16: 11 | C16: Ragi Powder | D16: 8 | E16: =D16*4 | F16: 40 | G16: =F16/1000 | H16: =E16*G16
D17: =SUM(D6:D16) | E17: =D17*4 | H17: =SUM(H6:H16)
B19: OTHER COSTS
C21: Packaging Cost | H21: 20
C22: Conversion cost | H22: ='Contract (1 yr)'!C51
F24: TOTAL COST / BOX | H24: =sum(H17:H22)
F26: PRODUCTION COST / BATCH | H26: 20000000
F28: BOXES / BATCH | H28: =H26/H24
F30: AS PER PROJETIONS SHEET
F31: Total Cost (Excl. GST) | H31: =H24 | I31: VS | J31: =H24
F32: GST 18%
F33: Total Cost (Incl. GST)

Sheet Product Line
B2: * SKUs may vary from year to year due to addition of new flavours (Currently 1-2 flavours of each Variant)
B3: Years | C3: All Products | D3: Tier
B4: Year 1 | C4: 4
C5: Pregnancy Powder | D5: 3
C6: Lactation Powder | D6: 3
C7: Infant Powder | D7: 3
C8: Children Powder | D8: 3
B10: Year 2 | C10: =COUNTA(C11:C24)
C11: Pregnancy Powder- Trimester 1 | D11: 1
C12: Pregnancy Powder- Trimester 2 | D12: 1
C13: Pregnancy Powder- Trimester 3 | D13: 1
C14: Lactation Powder | D14: 1
C15: Infant Formula Powder- 0 to 6m | D15: 1
C16: Infant Formula Powder- 6 to 12m | D16: 1
C17: Infant Formula Powder- 12 to 24m | D17: 1
C18: Infant Complementary Food- 6 to 12m | D18: 1
C19: Infant Complementary Food- 12 to 24m | D19: 1
C20: Children Powder | D20: 1
C21: Pregnancy Powder | D21: 3
C22: Lactation Powder | D22: 3
... C24: Children Powder | D24: 3
B26: Year 3 | C26: =counta(C27:C50)
C27: Pregnancy Powder- Trimester 1 | D27: 1
C28: Pregnancy Powder- Trimester 2 | D28: 1
C29: Pregnancy Powder- Trimester 3 | D29: 1
C30: Lactation Powder | D30: 1
C31: Infant Formula Powder- 0 to 6m | D31: 1
C32: Infant Formula Powder- 6 to 12m | D32: 1
C33: Infant Formula Powder- 12 to 24m | D33: 1
C34: Infant Complementary Food- 6 to 12m | D34: 1
C35: Infant Complementary Food- 12 to 24m | D35: 1
C36: Children Powder | D36: 1
C37: Pregnancy Powder- Trimester 1 | D37: 2
C38: Pregnancy Powder- Trimester 2 | D38: 2
... C50: Children Powder | D50: 3
B52: Year 4 | C52: =counta(C53:C76)
C53: Pregnancy Powder- Trimester 1 | D53: 1
C54: Pregnancy Powder- Trimester 2 | D54: 1
C55: Pregnancy Powder- Trimester 3 | D55: 1
C56: Lactation Powder | D56: 1
C57: Infant Formula Powder- 0 to 6m | D57: 1
C58: Infant Formula Powder- 6 to 12m | D58: 1
C59: Infant Formula Powder- 12 to 24m | D59: 1
C60: Infant Complementary Food- 6 to 12m | D60: 1
C61: Infant Complementary Food- 12 to 24m | D61: 1
C62: Children Powder | D62: 1
C63: Pregnancy Powder- Trimester 1 | D63: 2
C64: Pregnancy Powder- Trimester 2 | D64: 2
... C76: Children Powder | D76: 3
B78: Year 5 | C78: =counta(C79:C102)
C79: Pregnancy Powder- Trimester 1 | D79: 1
C80: Pregnancy Powder- Trimester 2 | D80: 1
C81: Pregnancy Powder- Trimester 3 | D81: 1
C82: Lactation Powder | D82: 1
C83: Infant Formula Powder- 0 to 6m | D83: 1
C84: Infant Formula Powder- 6 to 12m | D84: 1
C85: Infant Formula Powder- 12 to 24m | D85: 1
C86: Infant Complementary Food- 6 to 12m | D86: 1
C87: Infant Complementary Food- 12 to 24m | D87: 1
C88: Children Powder | D88: 1
C89: Pregnancy Powder- Trimester 1 | D89: 2
C90: Pregnancy Powder- Trimester 2 | D90: 2
... C102: Children Powder | D102: 3
B105: Pregnancy Powder (GREESHMA)
B106: Tier 1 | C106: Wonder Womb
B107: Tier 2 | C107: Matrunayana
B108: Tier 3 | C108: Garbhika
B110: Lactation Powder
B111: Tier 1 | C111: Lacto Love
B112: Tier 2 | C112: Milknest
B113: Tier 3 | C113: Matrusneha
B115: Infant Nutrition
B116: Tier 1 | C116: Alpha Baby
B117: Tier 2 | C117: Healthy Cubs
B118: Tier 3 | C118: Poshit
B120: Child Nutrition
B121: Tier 1 | C121: Little Vita GOLD
B122: Tier 2 | C122: Little Vita PRO
B123: Tier 3 | C123: Little Vita CHINDI

Sheet Strategy
H5: Years | I5: 1 | J5: 2 | K5: 3 | L5: 4 | M5: 5
H6: Tiers Targetted | I6: Tier 3 | J6: Tier 1 & 3 | K6: All Tiers | L6: All Tiers | M6: All Tiers
H7: Investor Capital Deployed (in Cr) | I7: 22 | J7: 60 | K7: 220 | L7: 0 | M7: 0
H8: Products (SKUs) | I8: ='Product Line'!C4 | J8: ='Product Line'!C10 | K8: ='Product Line'!C26 | L8: =K8 | M8: =L8
H9: Manufacturing | I9: Contract Manufacturing | J9: In-house & Third Party Manufacturing | K9: In-house & Third Party Manufacturing | L9: In-house & Third Party Manufacturing | M9: In-house & Third Party Manufacturing
H10: Plants Set up | I10: ='In-house (2-5yrs)'!C3 | J10: ='In-house (2-5yrs)'!C4 | K10: ='In-house (2-5yrs)'!C5 | L10: ='In-house (2-5yrs)'!C6 | M10: ='In-house (2-5yrs)'!C7
H11: Total Plants | I11: =I10 | J11: =J10+I11 | K11: =K10+J11 | L11: =L10+K11 | M11: =M10+L11

Sheet P&L
G2: Rs. in cr
B3: YEARS | C3: 1 | D3: 2 | E3: 3 | F3: 4 | G3: 5
B5: REVENUE
B6: Revenue from Operation | C6: ='Contract (1 yr)'!E27 | D6: ='In-house (2-5yrs)'!F4+'Third Party (2-5yrs)'!R4 | E6: ='In-house (2-5yrs)'!F5+'Third Party (2-5yrs)'!R5 | F6: ='In-house (2-5yrs)'!F6+'Third Party (2-5yrs)'!R6 | G6: ='In-house (2-5yrs)'!F7+'Third Party (2-5yrs)'!R7
B7: Pregnancy Powder- Trimester 1- Tier 1 | D7: =('In-house (2-5yrs)'!$C$20/3)/10^7 | E7: =('In-house (2-5yrs)'!$C$21/10^7)/3 | F7: =('In-house (2-5yrs)'!$C$22/10^7)/3 | G7: ='In-house (2-5yrs)'!$C$23/10^7/3
B8: Pregnancy Powder- Trimester 2- Tier 1 | D8: =('In-house (2-5yrs)'!$C$20/3)/10^7 | E8: =('In-house (2-5yrs)'!$C$21/10^7)/3 | F8: =('In-house (2-5yrs)'!$C$22/10^7)/3 | G8: ='In-house (2-5yrs)'!$C$23/10^7/3
B9: Pregnancy Powder- Trimester 3- Tier 1 | D9: =('In-house (2-5yrs)'!$C$20/3)/10^7 | E9: =('In-house (2-5yrs)'!$C$21/10^7)/3 | F9: =('In-house (2-5yrs)'!$C$22/10^7)/3 | G9: ='In-house (2-5yrs)'!$C$23/10^7/3
B10: Lactation Powder- Tier 1 | D10: ='In-house (2-5yrs)'!F20/10^7 | E10: ='In-house (2-5yrs)'!F21/10^7 | F10: ='In-house (2-5yrs)'!F22/10^7 | G10: ='In-house (2-5yrs)'!F23/10^7
B11: Infant Formula Powder- 0 to 6m- Tier 1 | D11: =('In-house (2-5yrs)'!$D$97*'In-house (2-5yrs)'!$I$12)/10^7/5 | E11: =('In-house (2-5yrs)'!$I$21/10^7)/5 | F11: =('In-house (2-5yrs)'!$I$22/10^7)/5 | G11: ='In-house (2-5yrs)'!$I$23/10^7/5
B12: Infant Formula Powder- 6 to 12m- Tier 1 | D12: =('In-house (2-5yrs)'!$D$97*'In-house (2-5yrs)'!$I$12)/10^7/5 | E12: =('In-house (2-5yrs)'!$I$21/10^7)/5 | F12: =('In-house (2-5yrs)'!$I$22/10^7)/5 | G12: ='In-house (2-5yrs)'!$I$23/10^7/5
B13: Infant Formula Powder- 12 to 24m- Tier 1 | D13: =('In-house (2-5yrs)'!$D$97*'In-house (2-5yrs)'!$I$12)/10^7/5 | E13: =('In-house (2-5yrs)'!$I$21/10^7)/5 | F13: =('In-house (2-5yrs)'!$I$22/10^7)/5 | G13: ='In-house (2-5yrs)'!$I$23/10^7/5
B14: Infant Complementary Food- 6 to 12m- Tier 1 | D14: =('In-house (2-5yrs)'!$D$97*'In-house (2-5yrs)'!$I$12)/10^7/5 | E14: =('In-house (2-5yrs)'!$I$21/10^7)/5 | F14: =('In-house (2-5yrs)'!$I$22/10^7)/5 | G14: ='In-house (2-5yrs)'!$I$23/10^7/5
B15: Infant Complementary Food- 12 to 24m- Tier 1 | D15: =('In-house (2-5yrs)'!$D$97*'In-house (2-5yrs)'!$I$12)/10^7/5 | E15: =('In-house (2-5yrs)'!$I$21/10^7)/5 | F15: =('In-house (2-5yrs)'!$I$22/10^7)/5 | G15: ='In-house (2-5yrs)'!$I$23/10^7/5
B16: Children Powder- Tier 1 | D16: =('In-house (2-5yrs)'!L12*'In-house (2-5yrs)'!D100)/10^7 | E16: ='In-house (2-5yrs)'!L21/10^7 | F16: ='In-house (2-5yrs)'!L22/10^7 | G16: ='In-house (2-5yrs)'!L23/10^7
B17: Pregnancy Powder- Trimester 1- Tier 2 | E17: =('In-house (2-5yrs)'!$D$21/10^7)/3 | F17: ='In-house (2-5yrs)'!$D$22/10^7/3 | G17: ='In-house (2-5yrs)'!$D$23/10^7/3
B18: Pregnancy Powder- Trimester 2- Tier 2 | E18: =('In-house (2-5yrs)'!$D$21/10^7)/3 | F18: ='In-house (2-5yrs)'!$D$22/10^7/3 | G18: ='In-house (2-5yrs)'!$D$23/10^7/3
B19: Pregnancy Powder- Trimester 3- Tier 2 | E19: =('In-house (2-5yrs)'!$D$21/10^7)/3 | F19: ='In-house (2-5yrs)'!$D$22/10^7/3 | G19: ='In-house (2-5yrs)'!$D$23/10^7/3
B20: Lactation Powder- Tier 2 | E20: ='In-house (2-5yrs)'!G21/10^7 | F20: ='In-house (2-5yrs)'!G22/10^7 | G20: ='In-house (2-5yrs)'!G23/10^7
B21: Infant Formula Powder- 0 to 6m- Tier 2 | E21: =('In-house (2-5yrs)'!$J$21/10^7)/5 | F21: ='In-house (2-5yrs)'!$J$22/10^7/5 | G21: ='In-house (2-5yrs)'!$J$23/10^7/5
B22: Infant Formula Powder- 6 to 12m- Tier 2 | E22: =('In-house (2-5yrs)'!$J$21/10^7)/5 | F22: ='In-house (2-5yrs)'!$J$22/10^7/5 | G22: ='In-house (2-5yrs)'!$J$23/10^7/5
B23: Infant Formula Powder- 12 to 24m- Tier 2 | E23: =('In-house (2-5yrs)'!$J$21/10^7)/5 | F23: ='In-house (2-5yrs)'!$J$22/10^7/5 | G23: ='In-house (2-5yrs)'!$J$23/10^7/5
B24: Infant Complementary Food- 6 to 12m- Tier 2 | E24: =('In-house (2-5yrs)'!$J$21/10^7)/5 | F24: ='In-house (2-5yrs)'!$J$22/10^7/5 | G24: ='In-house (2-5yrs)'!$J$23/10^7/5
B25: Infant Complementary Food- 12 to 24m- Tier 2 | E25: =('In-house (2-5yrs)'!$J$21/10^7)/5 | F25: ='In-house (2-5yrs)'!$J$22/10^7/5 | G25: ='In-house (2-5yrs)'!$J$23/10^7/5
B26: Children Powder- Tier 2 | E26: ='In-house (2-5yrs)'!M21/10^7 | F26: ='In-house (2-5yrs)'!M22/10^7 | G26: ='In-house (2-5yrs)'!M23/10^7
B27: Pregnancy Powder- Tier 3 | C27: ='Contract (1 yr)'!E25 | D27: =('In-house (2-5yrs)'!E12*'In-house (2-5yrs)'!D93)/10^7 | E27: ='In-house (2-5yrs)'!E21/10^7 | F27: ='In-house (2-5yrs)'!E22/10^7 | G27: ='In-house (2-5yrs)'!E23/10^7
B28: Lactation Powder- Tier 3 | C28: ='Contract (1 yr)'!E26 | D28: =('In-house (2-5yrs)'!D96*'In-house (2-5yrs)'!H12)/10^7 | E28: ='In-house (2-5yrs)'!H21/10^7 | F28: ='In-house (2-5yrs)'!H22/10^7 | G28: ='In-house (2-5yrs)'!H23/10^7
B29: Infant Powder- Tier 3 | C29: ='Contract (1 yr)'!E23 | D29: =('In-house (2-5yrs)'!K12*'In-house (2-5yrs)'!D99)/10^7 | E29: ='In-house (2-5yrs)'!K21/10^7 | F29: ='In-house (2-5yrs)'!K22/10^7 | G29: ='In-house (2-5yrs)'!K23/10^7
B30: Children Powder- Tier 3 | C30: ='Contract (1 yr)'!E24 | D30: =('In-house (2-5yrs)'!D102*'In-house (2-5yrs)'!N12)/10^7 | E30: ='In-house (2-5yrs)'!N21/10^7 | F30: ='In-house (2-5yrs)'!N22/10^7 | G30: ='In-house (2-5yrs)'!N23/10^7
B31: Contract Manufacturing | D31: ='Third Party (2-5yrs)'!R4 | E31: ='Third Party (2-5yrs)'!R5 | F31: ='Third Party (2-5yrs)'!R6 | G31: ='Third Party (2-5yrs)'!R7
B32: Other income | C32: ='Project Financing'!U14 | D32: ='Project Financing'!U15 | E32: ='Project Financing'!U16 | F32: ='Project Financing'!U17 | G32: ='Project Financing'!U18
B33: Total Revenue | C33: =C6+C32 | D33: =D6+D32 | E33: =E6+E32 | F33: =F6+F32 | G33: =G6+G32
B34: Revenue Growth % | D34: =(D33-C33)/C33 | E34: =(E33-D33)/D33 | F34: =(F33-E33)/E33 | G34: =(G33-F33)/F33
B36: COGS | C36: ='Contract (1 yr)'!F27 | D36: ='In-house (2-5yrs)'!G4 | E36: ='In-house (2-5yrs)'!G5 | F36: ='In-house (2-5yrs)'!G6 | G36: ='In-house (2-5yrs)'!G7
B37: Gross Profit Margin % | C37: =C36/C33 | D37: =D36/D33 | E37: =E36/E33 | F37: =F36/F33 | G37: =G36/G33
B39: INDIRECT EXPENSES
B40: Marketing & Advertising | C40: =sum('Indirect Expenses'!C56:E56) | D40: =sum('Indirect Expenses'!F56:H56) | E40: =sum('Indirect Expenses'!I56:K56) | F40: =sum('Indirect Expenses'!L56:N56) | G40: =sum('Indirect Expenses'!O56:Q56) | H40: * Includes Consumer digital ads, Influencer & KOL marketing, Sampling & trial programs, GTM marketing, Branding, Events, etc
B41: Tier 1 | C41: ='Indirect Expenses'!C56 | D41: ='Indirect Expenses'!F56 | E41: ='Indirect Expenses'!I56 | F41: ='Indirect Expenses'!L56 | G41: ='Indirect Expenses'!O56
B42: Tier 2 | C42: ='Indirect Expenses'!D56 | D42: ='Indirect Expenses'!G56 | E42: ='Indirect Expenses'!J56 | F42: ='Indirect Expenses'!M56 | G42: ='Indirect Expenses'!P56
B43: Tier 3 | C43: ='Indirect Expenses'!E56 | D43: ='Indirect Expenses'!H56 | E43: ='Indirect Expenses'!K56 | F43: ='Indirect Expenses'!N56 | G43: ='Indirect Expenses'!Q56
B44: HCP Detailing & Medical Engagement | C44: =sum('Indirect Expenses'!C57:E57) | D44: =sum('Indirect Expenses'!F57:H57) | E44: =sum('Indirect Expenses'!I57:K57) | F44: =sum('Indirect Expenses'!L57:N57) | G44: =sum('Indirect Expenses'!O57:Q57) | H44: * OBGYN, Gynecologist, Pediatrician detailing, Hospital & Nursing home tie-ups, Lactation Consultant & Dietitian programs, Medical conference sponsorships
B45: Tier 1 | C45: ='Indirect Expenses'!C57 | D45: ='Indirect Expenses'!F57 | E45: ='Indirect Expenses'!I57 | F45: ='Indirect Expenses'!L57 | G45: ='Indirect Expenses'!O57
B46: Tier 2 | C46: ='Indirect Expenses'!D57 | D46: ='Indirect Expenses'!G57 | E46: ='Indirect Expenses'!J57 | F46: ='Indirect Expenses'!M57 | G46: ='Indirect Expenses'!P57
B47: Tier 3 | C47: ='Indirect Expenses'!E57 | D47: ='Indirect Expenses'!H57 | E47: ='Indirect Expenses'!K57 | F47: ='Indirect Expenses'!N57 | G47: ='Indirect Expenses'!Q57
B48: Distribution & Logistics | C48: =sum('Indirect Expenses'!C58:E58) | D48: =sum('Indirect Expenses'!F58:H58) | E48: =sum('Indirect Expenses'!I58:K58) | F48: =sum('Indirect Expenses'!L58:N58) | G48: =sum('Indirect Expenses'!O58:Q58) | H48: * Rs. 9 per box for Year 1 & 2. Rs. 8.5 from Year 3 to 5. Includes Outbound freight, Warehousing, Cold chain storage, Channel commission
B49: Tier 1 | C49: ='Indirect Expenses'!C58 | D49: ='Indirect Expenses'!F58 | E49: ='Indirect Expenses'!I58 | F49: ='Indirect Expenses'!L58 | G49: ='Indirect Expenses'!O58
B50: Tier 2 | C50: ='Indirect Expenses'!D58 | D50: ='Indirect Expenses'!G58 | E50: ='Indirect Expenses'!J58 | F50: ='Indirect Expenses'!M58 | G50: ='Indirect Expenses'!P58
B51: Tier 3 | C51: ='Indirect Expenses'!E58 | D51: ='Indirect Expenses'!H58 | E51: ='Indirect Expenses'!K58 | F51: ='Indirect Expenses'!N58 | G51: ='Indirect Expenses'!Q58
B52: R&D / Regulatory / Compliance | C52: =sum('Indirect Expenses'!C59:E59) | D52: =sum('Indirect Expenses'!F59:H59) | E52: =sum('Indirect Expenses'!I59:K59) | F52: =sum('Indirect Expenses'!L59:N59) | G52: =sum('Indirect Expenses'!O59:Q59) | H52: * Product development, Clinical & nutritional testing, FSSAI approval (per SKU), IMS Act compliance monitoring, Stability & shelf-life studies
B53: Tier 1 | C53: ='Indirect Expenses'!C59 | D53: ='Indirect Expenses'!F59 | E53: ='Indirect Expenses'!I59 | F53: ='Indirect Expenses'!L59 | G53: ='Indirect Expenses'!O59
B54: Tier 2 | C54: ='Indirect Expenses'!D59 | D54: ='Indirect Expenses'!G59 | E54: ='Indirect Expenses'!J59 | F54: ='Indirect Expenses'!M59 | G54: ='Indirect Expenses'!P59
B55: Tier 3 | C55: ='Indirect Expenses'!E59 | D55: ='Indirect Expenses'!H59 | E55: ='Indirect Expenses'!K59 | F55: ='Indirect Expenses'!N59 | G55: ='Indirect Expenses'!Q59
B56: G&A / Operations Overheads | C56: =sum('Indirect Expenses'!C60:E60) | D56: =sum('Indirect Expenses'!F60:H60) | E56: =sum('Indirect Expenses'!I60:K60) | F56: =sum('Indirect Expenses'!L60:N60) | G56: =sum('Indirect Expenses'!O60:Q60) | H56: * Rent & utilities, IT infrastructure, ERP & CRM, Legal, audit & insurance, Office supplies & misc admin
B57: Tier 1 | C57: ='Indirect Expenses'!C60 | D57: ='Indirect Expenses'!F60 | E57: ='Indirect Expenses'!I60 | F57: ='Indirect Expenses'!L60 | G57: ='Indirect Expenses'!O60
B58: Tier 2 | C58: ='Indirect Expenses'!D60 | D58: ='Indirect Expenses'!G60 | E58: ='Indirect Expenses'!J60 | F58: ='Indirect Expenses'!M60 | G58: ='Indirect Expenses'!P60
B59: Tier 3 | C59: ='Indirect Expenses'!E60 | D59: ='Indirect Expenses'!H60 | E59: ='Indirect Expenses'!K60 | F59: ='Indirect Expenses'!N60 | G59: ='Indirect Expenses'!Q60
B60: Employee Cost | C60: =sum('Indirect Expenses'!C61:E61) | D60: =sum('Indirect Expenses'!F61:H61) | E60: =sum('Indirect Expenses'!I61:K61) | F60: =sum('Indirect Expenses'!L61:N61) | G60: =sum('Indirect Expenses'!O61:Q61) | H60: * Core team salaries, PF / ESI / statutory, HCP field force, Recruitment, training & contract staff
B61: Tier 1 | C61: ='Indirect Expenses'!C61 | D61: ='Indirect Expenses'!F61 | E61: ='Indirect Expenses'!I61 | F61: ='Indirect Expenses'!L61 | G61: ='Indirect Expenses'!O61
B62: Tier 2 | C62: ='Indirect Expenses'!D61 | D62: ='Indirect Expenses'!G61 | E62: ='Indirect Expenses'!J61 | F62: ='Indirect Expenses'!M61 | G62: ='Indirect Expenses'!P61
B63: Tier 3 | C63: ='Indirect Expenses'!E61 | D63: ='Indirect Expenses'!H61 | E63: ='Indirect Expenses'!K61 | F63: ='Indirect Expenses'!N61 | G63: ='Indirect Expenses'!Q61
B64: Contingency Fund | C64: =sum(C40:C60)*5% | D64: =sum(D40:D60)*5% | E64: =sum(E40:E60)*5% | F64: =sum(F40:F60)*5% | G64: =sum(G40:G60)*5% | H64: * 5% Contingency Fund
B66: Total Expenses | C66: =sum(C40,C44,C48,C52,C56,C60,C64,C36) | D66: =sum(D40,D44,D48,D52,D56,D60,D64,D36) | E66: =sum(E40,E44,E48,E52,E56,E60,E64,E36) | F66: =sum(F40,F44,F48,F52,F56,F60,F64,F36) | G66: =sum(G40,G44,G48,G52,G56,G60,G64,G36)
B68: EBIDTA | C68: =C33-C66 | D68: =D33-D66 | E68: =E33-E66 | F68: =F33-F66 | G68: =G33-G66
B69: EBIDTA Margin% | C69: =C68/C33 | D69: =D68/D33 | E69: =E68/E33 | F69: =F68/F33 | G69: =G68/G33
B71: Depreciation and Amortisation | C71: ='Capex & Depreciation'!E39 | D71: ='Capex & Depreciation'!E40 | E71: ='Capex & Depreciation'!E41 | F71: ='Capex & Depreciation'!E42 | G71: ='Capex & Depreciation'!E43
B72: EBIT | C72: =C68-C71 | D72: =D68-D71 | E72: =E68-E71 | F72: =F68-F71 | G72: =G68-G71
B74: Financial Costs | C74: ='Debt Schedule'!G3 | D74: ='Debt Schedule'!G4 | E74: ='Debt Schedule'!G5 | F74: ='Debt Schedule'!G6 | G74: ='Debt Schedule'!G7
B75: EBT/PBT | C75: =C72-C74 | D75: =D72-D74 | E75: =E72-E74 | F75: =F72-F74 | G75: =G72-G74
B77: Tax | C77: =IF(C75>0, C75*0.25,0) | D77: =IF(D75>0, D75*0.25,0) | E77: =IF(E75>0, E75*0.25,0) | F77: =IF(F75>0, F75*0.25,0) | G77: =IF(G75>0, G75*0.25,0)
B79: PAT/EAT | C79: =C75-C77 | D79: =D75-D77 | E79: =E75-E77 | F79: =F75-F77 | G79: =G75-G77
B80: Net Profit Margin% | C80: =C79/C33 | D80: =D79/D33 | E80: =E79/E33 | F80: =F79/F33 | G80: =G79/G33

Sheet Competitor Brands
B2: Expense Head | C2: Remarks | D2: HealthKart | E2: Kapiva | F2: OZiva | G2: Wellbeing Nutrition | H2: Early Stage Guide
B4: Marketing & brand
B5: Advertising & Promotions | C5: Digital, influencer, trade mktg | D5: 0.2 | E5: 0.55 | F5: 0.47 | G5: ~38% | H5: 30 – 50%
B6: Brand building & design | C6: Identity, packaging, PR | D6: ~3% | E6: ~5% | F6: ~4% | G6: ~5% | H6: 5 – 10%
B7: Doctor detailing & KOL | C7: Esp. critical for pregnancy/infant | D7: N/A | E7: N/A | F7: N/A | G7: N/A | H7: 3 – 6%
B9: Human resources
B10: Employee benefits | C10: Salaries, PF, ESOP | D10: 0.088 | E10: 0.17 | F10: 0.089 | G10: ~15% | H10: 15 – 25%
B12: Sales & distribution
B13: Channel commissions | C13: Amazon, Flipkart, 1mg, pharmacy | D13: 0.062 | E13: ~8% | F13: ~10% | G13: ~10% | H13: 8 – 12%
B14: Logistics & fulfilment | C14: Freight, 3PL, returns | D14: ~4% | E14: ~6% | F14: ~6% | G14: ~7% | H14: 5 – 8%
B16: Overheads & compliance
B17: Legal, regulatory & FSSAI | D17: ~1% | E17: ~2% | F17: ~2% | G17: ~2% | H17: 2 – 4%
B18: IT, SaaS & tech infra | D18: ~1% | E18: ~2% | F18: ~2% | G18: ~2% | H18: 2 – 4%
B19: Rent, utilities & admin | D19: ~2% | E19: ~3% | F19: ~3% | G19: ~4% | H19: 3 – 6%
B21: R&D & product
B22: R&D, testing & FSSAI dossiers | C22: 1.5-2x higher for infant formula | D22: ~1% | E22: ~1% | F22: ~3% | G22: ~4% | H22: 2 – 5%
B24: Profitability summary
B25: Gross margin | D25: ~51% | E25: ~72% | F25: ~73% | G25: ~70% | H25: 45 – 65%
B26: EBITDA margin | D26: =+6% | E26: -0.21 | F26: -0.012 | G26: ~-5% | H26: -30 to -50%
B27: ₹ spent to earn ₹1 | D27: ₹0.97 | E27: ₹1.22 | F27: ₹1.04 | G27: ~₹1.10 | H27: ₹1.40–1.80

Sheet Revenue Breakup
C2: 1 | E2: 2 | G2: 3 | I2: 4 | K2: 5
B3: Revenue from Operation | C3: ='P&L'!C6 | D3: =C3/$C$3 | E3: ='P&L'!D6 | F3: =E3/$E$3 | G3: ='P&L'!E6 | H3: =G3/$G$3 | I3: ='P&L'!F6 | J3: =I3/$I$3 | K3: ='P&L'!G6 | L3: =K3/$K$3
B4: Pregnancy Powder- Trimester 1- Tier 1 | C4: ='P&L'!C7 | D4: =C4/$C$3 | E4: ='P&L'!D7 | F4: =E4/$E$3 | G4: ='P&L'!E7 | H4: =G4/$G$3 | I4: ='P&L'!F7 | J4: =I4/$I$3 | K4: ='P&L'!G7 | L4: =K4/$K$3
B5: Pregnancy Powder- Trimester 2- Tier 1 | C5: ='P&L'!C8 | D5: =C5/$C$3 | E5: ='P&L'!D8 | F5: =E5/$E$3 | G5: ='P&L'!E8 | H5: =G5/$G$3 | I5: ='P&L'!F8 | J5: =I5/$I$3 | K5: ='P&L'!G8 | L5: =K5/$K$3
B6: Pregnancy Powder- Trimester 3- Tier 1 | C6: ='P&L'!C9 | D6: =C6/$C$3 | E6: ='P&L'!D9 | F6: =E6/$E$3 | G6: ='P&L'!E9 | H6: =G6/$G$3 | I6: ='P&L'!F9 | J6: =I6/$I$3 | K6: ='P&L'!G9 | L6: =K6/$K$3
B7: Lactation Powder- Tier 1 | C7: ='P&L'!C10 | D7: =C7/$C$3 | E7: ='P&L'!D10 | F7: =E7/$E$3 | G7: ='P&L'!E10 | H7: =G7/$G$3 | I7: ='P&L'!F10 | J7: =I7/$I$3 | K7: ='P&L'!G10 | L7: =K7/$K$3
B8: Infant Formula Powder- 0 to 6m- Tier 1 | C8: ='P&L'!C11 | D8: =C8/$C$3 | E8: ='P&L'!D11 | F8: =E8/$E$3 | G8: ='P&L'!E11 | H8: =G8/$G$3 | I8: ='P&L'!F11 | J8: =I8/$I$3 | K8: ='P&L'!G11 | L8: =K8/$K$3
B9: Infant Formula Powder- 6 to 12m- Tier 1 | C9: ='P&L'!C12 | D9: =C9/$C$3 | E9: ='P&L'!D12 | F9: =E9/$E$3 | G9: ='P&L'!E12 | H9: =G9/$G$3 | I9: ='P&L'!F12 | J9: =I9/$I$3 | K9: ='P&L'!G12 | L9: =K9/$K$3
B10: Infant Formula Powder- 12 to 24m- Tier 1 | C10: ='P&L'!C13 | D10: =C10/$C$3 | E10: ='P&L'!D13 | F10: =E10/$E$3 | G10: ='P&L'!E13 | H10: =G10/$G$3 | I10: ='P&L'!F13 | J10: =I10/$I$3 | K10: ='P&L'!G13 | L10: =K10/$K$3
B11: Infant Complementary Food- 6 to 12m- Tier 1 | C11: ='P&L'!C14 | D11: =C11/$C$3 | E11: ='P&L'!D14 | F11: =E11/$E$3 | G11: ='P&L'!E14 | H11: =G11/$G$3 | I11: ='P&L'!F14 | J11: =I11/$I$3 | K11: ='P&L'!G14 | L11: =K11/$K$3
B12: Infant Complementary Food- 12 to 24m- Tier 1 | C12: ='P&L'!C15 | D12: =C12/$C$3 | E12: ='P&L'!D15 | F12: =E12/$E$3 | G12: ='P&L'!E15 | H12: =G12/$G$3 | I12: ='P&L'!F15 | J12: =I12/$I$3 | K12: ='P&L'!G15 | L12: =K12/$K$3
B13: Children Powder- Tier 1 | C13: ='P&L'!C16 | D13: =C13/$C$3 | E13: ='P&L'!D16 | F13: =E13/$E$3 | G13: ='P&L'!E16 | H13: =G13/$G$3 | I13: ='P&L'!F16 | J13: =I13/$I$3 | K13: ='P&L'!G16 | L13: =K13/$K$3
B14: Pregnancy Powder- Trimester 1- Tier 2 | C14: ='P&L'!C17 | D14: =C14/$C$3 | E14: ='P&L'!D17 | F14: =E14/$E$3 | G14: ='P&L'!E17 | H14: =G14/$G$3 | I14: ='P&L'!F17 | J14: =I14/$I$3 | K14: ='P&L'!G17 | L14: =K14/$K$3
... B28: Contract Manufacturing | C28: ='P&L'!C31 | D28: =C28/$C$3 | E28: ='P&L'!D31 | F28: =E28/$E$3 | G28: ='P&L'!E31 | H28: =G28/$G$3 | I28: ='P&L'!F31 | J28: =I28/$I$3 | K28: ='P&L'!G31 | L28: =K28/$K$3
C30: 1 | E30: 2 | G30: 3 | I30: 4 | K30: 5
B31: Tier 1 | C31: =sum(C4:C13) | D31: =sum(D4:D13) | E31: =sum(E4:E13) | F31: =sum(F4:F13) | G31: =sum(G4:G13) | H31: =sum(H4:H13) | I31: =sum(I4:I13) | J31: =sum(J4:J13) | ... L31: =sum(L4:L13)
B32: Tier 2 | C32: =sum(C14:C23) | D32: =sum(D14:D23) | E32: =sum(E14:E23) | F32: =sum(F14:F23) | G32: =sum(G14:G23) | H32: =sum(H14:H23) | I32: =sum(I14:I23) | J32: =sum(J14:J23) | ... L32: =sum(L14:L23)
B33: Tier 3 | C33: =sum(C24:C27) | D33: =sum(D24:D27) | E33: =sum(E24:E27) | F33: =sum(F24:F27) | G33: =sum(G24:G27) | H33: =sum(H24:H27) | I33: =sum(I24:I27) | J33: =sum(J24:J27) | ... L33: =sum(L24:L27)
C35: 1 | D35: 2 | E35: 3 | F35: 4 | G35: 5
B36: Pregnancy Powder | C36: =sum($D$4:$D$6,$D$14:$D$16,$D$24) | D36: =sum(F4:F6,F14:F16,F24) | E36: =sum(H4:H6,H14:H16,H24) | F36: =sum(J4:J6,J14:J16,J24) | G36: =sum(L4:L6,L14:L16,L24)
B37: Lactation Powder | C37: =sum($D$7,$D$17,$D$25) | D37: =sum(F7,F17,F25) | E37: =sum(H7,H17,H25) | F37: =sum(J7,J17,J25) | G37: =sum(L7,L17,L25)
B38: Infant Powder | C38: =sum($D$8:$D$12,$D$18:$D$22,$D$26) | D38: =sum(F8:F12,F18:F22,F26) | E38: =sum(H8:H12,H18:H22,H26) | F38: =sum(J8:J12,J18:J22,J26) | G38: =sum(L8:L12,L18:L22,L26)
B39: Children Powder | C39: =$D$13+$D$23+$D$27 | D39: =F13+F23+F27 | E39: =H13+H23+H27 | F39: =J13+J23+J27 | G39: =L13+L23+L27
B40: Total | C40: =sum(C36:C39) | D40: =sum(D36:D39) | E40: =sum(E36:E39) | F40: =sum(F36:F39) | G40: =sum(G36:G39)
B41: Average | C41: =average(C36:C39) | D41: =average(D36:D39) | E41: =average(E36:E39) | F41: =average(F36:F39) | G41: =average(G36:G39)
C43: 1 | D43: 2 | E43: 3 | F43: 4 | G43: 5
B44: Pregnancy Powder | C44: =VALUE(SUBSTITUTE(C36, "%", "")) | D44: =VALUE(SUBSTITUTE(D36, "%", "")) | E44: =VALUE(SUBSTITUTE(E36, "%", "")) | F44: =VALUE(SUBSTITUTE(F36, "%", "")) | G44: =VALUE(SUBSTITUTE(G36, "%", ""))
B45: Lactation Powder | C45: =VALUE(SUBSTITUTE(C37, "%", "")) | D45: =VALUE(SUBSTITUTE(D37, "%", "")) | E45: =VALUE(SUBSTITUTE(E37, "%", "")) | F45: =VALUE(SUBSTITUTE(F37, "%", "")) | G45: =VALUE(SUBSTITUTE(G37, "%", ""))
B46: Infant Powder | C46: =VALUE(SUBSTITUTE(C38, "%", "")) | D46: =VALUE(SUBSTITUTE(D38, "%", "")) | E46: =VALUE(SUBSTITUTE(E38, "%", "")) | F46: =VALUE(SUBSTITUTE(F38, "%", "")) | G46: =VALUE(SUBSTITUTE(G38, "%", ""))
B47: Children Powder | C47: =VALUE(SUBSTITUTE(C39, "%", "")) | D47: =VALUE(SUBSTITUTE(D39, "%", "")) | E47: =VALUE(SUBSTITUTE(E39, "%", "")) | F47: =VALUE(SUBSTITUTE(F39, "%", "")) | G47: =VALUE(SUBSTITUTE(G39, "%", ""))
C48: =sum(C44:C47) | D48: =sum(D44:D47) | E48: =sum(E44:E47) | F48: =sum(F44:F47) | G48: =sum(G44:G47)

Sheet Indirect Expenses
B2: INDIRECT EXPENSE % BREAKUP TIER WISE & PRODUCT WISE
B3: Cost Head | C3: Remark | D3: Year 1 | G3: Year 2 | J3: Year 3 | M3: Year 4 | P3: Year 5
D4: Tier 1 (Metro) | E4: Tier 2 (Mid Cities) | F4: Tier 3 (Small Towns) | G4: Tier 1 (Metro) | H4: Tier 2 (Mid Cities) | I4: Tier 3 (Small Towns) | J4: Tier 1 (Metro) | K4: Tier 2 (Mid Cities) | L4: Tier 3 (Small Towns) | M4: Tier 1 (Metro) | N4: Tier 2 (Mid Cities) | O4: Tier 3 (Small Towns) | P4: Tier 1 (Metro) | Q4: Tier 2 (Mid Cities) | R4: Tier 3 (Small Towns)
B5: Marketing & Advertising (in %) | C5: * IMS Act prohibits infant formula consumer ads. Tier 1 budget shifts entirely to HCP detailing. 3 brand budgets from Y3. | D5: =VALUE(SUBSTITUTE('IE Biffurcation'!N13, "%", "")) | E5: =VALUE(SUBSTITUTE('IE Biffurcation'!I13, "%", "")) | F5: =VALUE(SUBSTITUTE('IE Biffurcation'!D13, "%", "")) | G5: =VALUE(SUBSTITUTE('IE Biffurcation'!O13, "%", "")) | H5: =VALUE(SUBSTITUTE('IE Biffurcation'!J13, "%", "")) | I5: =VALUE(SUBSTITUTE('IE Biffurcation'!E13, "%", "")) | J5: =VALUE(SUBSTITUTE('IE Biffurcation'!P13, "%", "")) | K5: =VALUE(SUBSTITUTE('IE Biffurcation'!K13, "%", "")) | L5: =VALUE(SUBSTITUTE('IE Biffurcation'!F13, "%", "")) | M5: =VALUE(SUBSTITUTE('IE Biffurcation'!Q13, "%", "")) | N5: =VALUE(SUBSTITUTE('IE Biffurcation'!L13, "%", "")) | O5: =VALUE(SUBSTITUTE('IE Biffurcation'!G13, "%", "")) | P5: =VALUE(SUBSTITUTE('IE Biffurcation'!R13, "%", "")) | Q5: =VALUE(SUBSTITUTE('IE Biffurcation'!M13, "%", "")) | R5: =VALUE(SUBSTITUTE('IE Biffurcation'!H13, "%", ""))
B6: Pregnancy Powder | D6: =D5 | E6: =E5 | F6: =$F$5*'Revenue Breakup'!C36 | G6: =$G$5*('Revenue Breakup'!D36/'Revenue Breakup'!$D$40) | H6: =H5 | I6: =$I$5*('Revenue Breakup'!D36/'Revenue Breakup'!$D$40) | J6: =$J$5*('Revenue Breakup'!E36/'Revenue Breakup'!$E$40) | K6: =$K$5*('Revenue Breakup'!E36/'Revenue Breakup'!$E$40) | L6: =$L$5*('Revenue Breakup'!E36/'Revenue Breakup'!$E$40) | M6: =$M$5*('Revenue Breakup'!F36/'Revenue Breakup'!$F$40) | N6: =$N$5*('Revenue Breakup'!F36/'Revenue Breakup'!$F$40) | O6: =$O$5*('Revenue Breakup'!F36/'Revenue Breakup'!$F$40) | P6: =$P$5*('Revenue Breakup'!G36/'Revenue Breakup'!$G$40) | Q6: =$Q$5*('Revenue Breakup'!G36/'Revenue Breakup'!$G$40) | R6: =$R$5*('Revenue Breakup'!G36/'Revenue Breakup'!$G$40)
B7: Lactation Powder | D7: =D6 | E7: =E6 | F7: =$F$5*'Revenue Breakup'!C37 | G7: =$G$5*('Revenue Breakup'!D37/'Revenue Breakup'!$D$40) | H7: =H6 | I7: =$I$5*('Revenue Breakup'!D37/'Revenue Breakup'!$D$40) | J7: =$J$5*('Revenue Breakup'!E37/'Revenue Breakup'!$E$40) | K7: =$K$5*('Revenue Breakup'!E37/'Revenue Breakup'!$E$40) | L7: =$L$5*('Revenue Breakup'!E37/'Revenue Breakup'!$E$40) | M7: =$M$5*('Revenue Breakup'!F37/'Revenue Breakup'!$F$40) | N7: =$N$5*('Revenue Breakup'!F37/'Revenue Breakup'!$F$40) | O7: =$O$5*('Revenue Breakup'!F37/'Revenue Breakup'!$F$40) | P7: =$P$5*('Revenue Breakup'!G37/'Revenue Breakup'!$G$40) | Q7: =$Q$5*('Revenue Breakup'!G37/'Revenue Breakup'!$G$40) | R7: =$R$5*('Revenue Breakup'!G37/'Revenue Breakup'!$G$40)
B8: Infant Powder | D8: =D7 | E8: =E7 | F8: =$F$5*'Revenue Breakup'!C38 | G8: =$G$5*('Revenue Breakup'!D38/'Revenue Breakup'!$D$40) | H8: =H7 | I8: =$I$5*('Revenue Breakup'!D38/'Revenue Breakup'!$D$40) | J8: =$J$5*('Revenue Breakup'!E38/'Revenue Breakup'!$E$40) | K8: =$K$5*('Revenue Breakup'!E38/'Revenue Breakup'!$E$40) | L8: =$L$5*('Revenue Breakup'!E38/'Revenue Breakup'!$E$40) | M8: =$M$5*('Revenue Breakup'!F38/'Revenue Breakup'!$F$40) | N8: =$N$5*('Revenue Breakup'!F38/'Revenue Breakup'!$F$40) | O8: =$O$5*('Revenue Breakup'!F38/'Revenue Breakup'!$F$40) | P8: =$P$5*('Revenue Breakup'!G38/'Revenue Breakup'!$G$40) | Q8: =$Q$5*('Revenue Breakup'!G38/'Revenue Breakup'!$G$40) | R8: =$R$5*('Revenue Breakup'!G38/'Revenue Breakup'!$G$40)
B9: Children Powder | D9: =D8 | E9: =E8 | F9: =$F$5*'Revenue Breakup'!C39 | G9: =$G$5*('Revenue Breakup'!D39/'Revenue Breakup'!$D$40) | H9: =H8 | I9: =$I$5*('Revenue Breakup'!D39/'Revenue Breakup'!$D$40) | J9: =$J$5*('Revenue Breakup'!E39/'Revenue Breakup'!$E$40) | K9: =$K$5*('Revenue Breakup'!E39/'Revenue Breakup'!$E$40) | L9: =$L$5*('Revenue Breakup'!E39/'Revenue Breakup'!$E$40) | M9: =$M$5*('Revenue Breakup'!F39/'Revenue Breakup'!$F$40) | N9: =$N$5*('Revenue Breakup'!F39/'Revenue Breakup'!$F$40) | O9: =$O$5*('Revenue Breakup'!F39/'Revenue Breakup'!$F$40) | P9: =$P$5*('Revenue Breakup'!G39/'Revenue Breakup'!$G$40) | Q9: =$Q$5*('Revenue Breakup'!G39/'Revenue Breakup'!$G$40) | R9: =$R$5*('Revenue Breakup'!G39/'Revenue Breakup'!$G$40)
B10: HCP Detailing & Medical Engagement (in %) | C10: * OBGYNs, pediatricians, hospitals drive prescription/recommendation. Mandatory for infant formula category growth. | D10: =VALUE(SUBSTITUTE('IE Biffurcation'!N20, "%", "")) | E10: =VALUE(SUBSTITUTE('IE Biffurcation'!I20, "%", "")) | F10: =VALUE(SUBSTITUTE('IE Biffurcation'!D20, "%", "")) | G10: =VALUE(SUBSTITUTE('IE Biffurcation'!O20, "%", "")) | H10: =VALUE(SUBSTITUTE('IE Biffurcation'!J20, "%", "")) | I10: =VALUE(SUBSTITUTE('IE Biffurcation'!E20, "%", "")) | J10: =VALUE(SUBSTITUTE('IE Biffurcation'!P20, "%", "")) | K10: =VALUE(SUBSTITUTE('IE Biffurcation'!K20, "%", "")) | L10: =VALUE(SUBSTITUTE('IE Biffurcation'!F20, "%", "")) | M10: =VALUE(SUBSTITUTE('IE Biffurcation'!Q20, "%", "")) | N10: =VALUE(SUBSTITUTE('IE Biffurcation'!L20, "%", "")) | O10: =VALUE(SUBSTITUTE('IE Biffurcation'!G20, "%", "")) | P10: =VALUE(SUBSTITUTE('IE Biffurcation'!R20, "%", "")) | Q10: =VALUE(SUBSTITUTE('IE Biffurcation'!M20, "%", "")) | R10: =VALUE(SUBSTITUTE('IE Biffurcation'!H20, "%", ""))
B11: Pregnancy Powder | D11: =D10 | E11: =E10 | F11: =$F$10*'Revenue Breakup'!C36 | G11: =$G$10*('Revenue Breakup'!D36/'Revenue Breakup'!$D$40) | H11: =H10 | I11: =$I$10*('Revenue Breakup'!D36/'Revenue Breakup'!$D$40) | J11: =$J$10*('Revenue Breakup'!E36/'Revenue Breakup'!$E$40) | K11: =$K$10*('Revenue Breakup'!E36/'Revenue Breakup'!$E$40) | L11: =$L$10*('Revenue Breakup'!E36/'Revenue Breakup'!$E$40) | M11: =$M$10*('Revenue Breakup'!F36/'Revenue Breakup'!$F$40) | N11: =$N$10*('Revenue Breakup'!F36/'Revenue Breakup'!$F$40) | O11: =$O$10*('Revenue Breakup'!F36/'Revenue Breakup'!$F$40) | P11: =$P$10*('Revenue Breakup'!G36/'Revenue Breakup'!$G$40) | Q11: =$Q$10*('Revenue Breakup'!G36/'Revenue Breakup'!$G$40) | R11: =$R$10*('Revenue Breakup'!G36/'Revenue Breakup'!$G$40)
B12: Lactation Powder | D12: =D11 | E12: =E11 | F12: =$F$10*'Revenue Breakup'!C37 | G12: =$G$10*('Revenue Breakup'!D37/'Revenue Breakup'!$D$40) | H12: =H11 | I12: =$I$10*('Revenue Breakup'!D37/'Revenue Breakup'!$D$40) | J12: =$J$10*('Revenue Breakup'!E37/'Revenue Breakup'!$E$40) | K12: =$K$10*('Revenue Breakup'!E37/'Revenue Breakup'!$E$40) | L12: =$L$10*('Revenue Breakup'!E37/'Revenue Breakup'!$E$40) | M12: =$M$10*('Revenue Breakup'!F37/'Revenue Breakup'!$F$40) | N12: =$N$10*('Revenue Breakup'!F37/'Revenue Breakup'!$F$40) | O12: =$O$10*('Revenue Breakup'!F37/'Revenue Breakup'!$F$40) | P12: =$P$10*('Revenue Breakup'!G37/'Revenue Breakup'!$G$40) | Q12: =$Q$10*('Revenue Breakup'!G37/'Revenue Breakup'!$G$40) | R12: =$R$10*('Revenue Breakup'!G37/'Revenue Breakup'!$G$40)
B13: Infant Powder | D13: =D12 | E13: =E12 | F13: =$F$10*'Revenue Breakup'!C38 | G13: =$G$10*('Revenue Breakup'!D38/'Revenue Breakup'!$D$40) | H13: =H12 | I13: =$I$10*('Revenue Breakup'!D38/'Revenue Breakup'!$D$40) | J13: =$J$10*('Revenue Breakup'!E38/'Revenue Breakup'!$E$40) | K13: =$K$10*('Revenue Breakup'!E38/'Revenue Breakup'!$E$40) | L13: =$L$10*('Revenue Breakup'!E38/'Revenue Breakup'!$E$40) | M13: =$M$10*('Revenue Breakup'!F38/'Revenue Breakup'!$F$40) | N13: =$N$10*('Revenue Breakup'!F38/'Revenue Breakup'!$F$40) | O13: =$O$10*('Revenue Breakup'!F38/'Revenue Breakup'!$F$40) | P13: =$P$10*('Revenue Breakup'!G38/'Revenue Breakup'!$G$40) | Q13: =$Q$10*('Revenue Breakup'!G38/'Revenue Breakup'!$G$40) | R13: =$R$10*('Revenue Breakup'!G38/'Revenue Breakup'!$G$40)
B14: Children Powder | D14: =D13 | E14: =E13 | F14: =$F$10*'Revenue Breakup'!C39 | G14: =$G$10*('Revenue Breakup'!D39/'Revenue Breakup'!$D$40) | H14: =H13 | I14: =$I$10*('Revenue Breakup'!D39/'Revenue Breakup'!$D$40) | J14: =$J$10*('Revenue Breakup'!E39/'Revenue Breakup'!$E$40) | K14: =$K$10*('Revenue Breakup'!E39/'Revenue Breakup'!$E$40) | L14: =$L$10*('Revenue Breakup'!E39/'Revenue Breakup'!$E$40) | M14: =$M$10*('Revenue Breakup'!F39/'Revenue Breakup'!$F$40) | N14: =$N$10*('Revenue Breakup'!F39/'Revenue Breakup'!$F$40) | O14: =$O$10*('Revenue Breakup'!F39/'Revenue Breakup'!$F$40) | P14: =$P$10*('Revenue Breakup'!G39/'Revenue Breakup'!$G$40) | Q14: =$Q$10*('Revenue Breakup'!G39/'Revenue Breakup'!$G$40) | R14: =$R$10*('Revenue Breakup'!G39/'Revenue Breakup'!$G$40)
B15: Distribution & Logistics (in Cr) | C15: * Rs. 9 per box in Year 1 and Year 2. Rs. 8.5 per box Year 3 onwards | D15: =sum(D17:D20) | E15: =sum(E17:E20) | F15: =sum(F17:F20) | G15: =sum(G17:G20) | H15: =sum(H17:H20) | I15: =sum(I17:I20) | J15: =sum(J17:J20) | K15: =sum(K17:K20) | ... R15: =sum(R17:R20)
B16: Cost per Box (in ₹) | D16: 9 | E16: =D16 | F16: =E16 | G16: 9 | H16: =G16 | I16: =H16 | J16: 9 | K16: 9 | L16: 9 | M16: 8 | N16: 8 | O16: 8 | P16: 8 | Q16: 8 | R16: 8
B17: Pregnancy Powder | D17: =D16*'In-house (2-5yrs)'!C11 | E17: =E16*'In-house (2-5yrs)'!D11 | F17: =($F$16*'Contract (1 yr)'!C25)/10^7 | G17: =($G$16*'In-house (2-5yrs)'!C12)/10^7 | H17: =($H$16*'In-house (2-5yrs)'!D12)/10^7 | I17: =($I$16*'In-house (2-5yrs)'!E12)/10^7 | J17: =($J$16*'In-house (2-5yrs)'!C13)/10^7 | K17: =($K$16*'In-house (2-5yrs)'!D13)/10^7 | L17: =($L$16*'In-house (2-5yrs)'!E13)/10^7 | M17: =($M$16*'In-house (2-5yrs)'!C14)/10^7 | N17: =($N$16*'In-house (2-5yrs)'!D14)/10^7 | O17: =($O$16*'In-house (2-5yrs)'!E14)/10^7 | P17: =($P$16*'In-house (2-5yrs)'!C15)/10^7 | Q17: =($Q$16*'In-house (2-5yrs)'!D15)/10^7 | R17: =($R$16*'In-house (2-5yrs)'!E15)/10^7
B18: Lactation Powder | D18: ='In-house (2-5yrs)'!F11*D16 | E18: =E16*'In-house (2-5yrs)'!D11 | F18: =($F$16*'Contract (1 yr)'!C26)/10^7 | G18: =($G$16*'In-house (2-5yrs)'!F12)/10^7 | H18: =($H$16*'In-house (2-5yrs)'!G12)/10^7 | I18: =($I$16*'In-house (2-5yrs)'!H12)/10^7 | J18: =($J$16*'In-house (2-5yrs)'!F13)/10^7 | K18: =($K$16*'In-house (2-5yrs)'!G13)/10^7 | L18: =($L$16*'In-house (2-5yrs)'!H13)/10^7 | M18: =($M$16*'In-house (2-5yrs)'!F14)/10^7 | N18: =($N$16*'In-house (2-5yrs)'!G14)/10^7 | O18: =($O$16*'In-house (2-5yrs)'!H14)/10^7 | P18: =($P$16*'In-house (2-5yrs)'!F15)/10^7 | Q18: =($Q$16*'In-house (2-5yrs)'!G15)/10^7 | R18: =($R$16*'In-house (2-5yrs)'!H15)/10^7
B19: Infant Powder | D19: ='In-house (2-5yrs)'!I11*D16 | E19: ='In-house (2-5yrs)'!J11*E16 | F19: =($F$16*'Contract (1 yr)'!C23)/10^7 | G19: =($G$16*'In-house (2-5yrs)'!I12)/10^7 | H19: =($H$16*'In-house (2-5yrs)'!J12)/10^7 | I19: =($I$16*'In-house (2-5yrs)'!K12)/10^7 | J19: =($J$16*'In-house (2-5yrs)'!I13)/10^7 | K19: =($K$16*'In-house (2-5yrs)'!J13)/10^7 | L19: =($L$16*'In-house (2-5yrs)'!K13)/10^7 | M19: =($M$16*'In-house (2-5yrs)'!I14)/10^7 | N19: =($N$16*'In-house (2-5yrs)'!J14)/10^7 | O19: =($O$16*'In-house (2-5yrs)'!K14)/10^7 | P19: =($P$16*'In-house (2-5yrs)'!I15)/10^7 | Q19: =($Q$16*'In-house (2-5yrs)'!J15)/10^7 | R19: =($R$16*'In-house (2-5yrs)'!K15)/10^7
B20: Children Powder | D20: =D16*'In-house (2-5yrs)'!L11 | E20: =E16*'In-house (2-5yrs)'!M11 | F20: =($F$16*'Contract (1 yr)'!C24)/10^7 | G20: =($G$16*'In-house (2-5yrs)'!L12)/10^7 | H20: =($H$16*'In-house (2-5yrs)'!M12)/10^7 | I20: =($I$16*'In-house (2-5yrs)'!N12)/10^7 | J20: =($J$16*'In-house (2-5yrs)'!L13)/10^7 | K20: =($K$16*'In-house (2-5yrs)'!M13)/10^7 | L20: =($L$16*'In-house (2-5yrs)'!N13)/10^7 | M20: =($M$16*'In-house (2-5yrs)'!L14)/10^7 | N20: =($N$16*'In-house (2-5yrs)'!M14)/10^7 | O20: =($O$16*'In-house (2-5yrs)'!N14)/10^7 | P20: =($P$16*'In-house (2-5yrs)'!L15)/10^7 | Q20: =($Q$16*'In-house (2-5yrs)'!M15)/10^7 | R20: =($R$16*'In-house (2-5yrs)'!N15)/10^7
B21: R&D / Regulatory / Compliance (in %) | C21: * Infant formula under FSS Act strictest category. Each stage/ trimester/ flavour variant = separate FSSAI testing + label approval. | D21: ='IE Biffurcation'!N27 | E21: ='IE Biffurcation'!I27 | F21: =VALUE(SUBSTITUTE('IE Biffurcation'!D27, "%", "")) | G21: =VALUE(SUBSTITUTE('IE Biffurcation'!E27, "%", "")) | H21: ='IE Biffurcation'!J27 | I21: =VALUE(SUBSTITUTE('IE Biffurcation'!O27, "%", "")) | J21: =VALUE(SUBSTITUTE('IE Biffurcation'!F27, "%", "")) | K21: =VALUE(SUBSTITUTE('IE Biffurcation'!K27, "%", "")) | L21: =VALUE(SUBSTITUTE('IE Biffurcation'!P27, "%", "")) | M21: =VALUE(SUBSTITUTE('IE Biffurcation'!G27, "%", "")) | N21: =VALUE(SUBSTITUTE('IE Biffurcation'!L27, "%", "")) | O21: =VALUE(SUBSTITUTE('IE Biffurcation'!Q27, "%", "")) | P21: =VALUE(SUBSTITUTE('IE Biffurcation'!H27, "%", "")) | Q21: =VALUE(SUBSTITUTE('IE Biffurcation'!M27, "%", "")) | R21: =VALUE(SUBSTITUTE('IE Biffurcation'!R27, "%", ""))
B22: Pregnancy Powder | D22: =D21 | E22: =E21 | F22: =$F$21*'Revenue Breakup'!C36 | G22: =$G$21*('Revenue Breakup'!D36/'Revenue Breakup'!$D$40) | H22: =H21 | I22: =$I$21*('Revenue Breakup'!D36/'Revenue Breakup'!$D$40) | J22: =$J$21*('Revenue Breakup'!E36/'Revenue Breakup'!$E$40) | K22: =$K$21*('Revenue Breakup'!E36/'Revenue Breakup'!$E$40) | L22: =$L$21*('Revenue Breakup'!E36/'Revenue Breakup'!$E$40) | M22: =$M$21*('Revenue Breakup'!F36/'Revenue Breakup'!$F$40) | N22: =$N$21*('Revenue Breakup'!F36/'Revenue Breakup'!$F$40) | O22: =$O$21*('Revenue Breakup'!F36/'Revenue Breakup'!$F$40) | P22: =$P$21*('Revenue Breakup'!G36/'Revenue Breakup'!$G$40) | Q22: =$Q$21*('Revenue Breakup'!G36/'Revenue Breakup'!$G$40) | R22: =$R$21*('Revenue Breakup'!G36/'Revenue Breakup'!$G$40)
B23: Lactation Powder | D23: =D22 | E23: =E22 | F23: =$F$21*'Revenue Breakup'!C37 | G23: =$G$21*('Revenue Breakup'!D37/'Revenue Breakup'!$D$40) | H23: =H22 | I23: =$I$21*('Revenue Breakup'!D37/'Revenue Breakup'!$D$40) | J23: =$J$21*('Revenue Breakup'!E37/'Revenue Breakup'!$E$40) | K23: =$K$21*('Revenue Breakup'!E37/'Revenue Breakup'!$E$40) | L23: =$L$21*('Revenue Breakup'!E37/'Revenue Breakup'!$E$40) | M23: =$M$21*('Revenue Breakup'!F37/'Revenue Breakup'!$F$40) | N23: =$N$21*('Revenue Breakup'!F37/'Revenue Breakup'!$F$40) | O23: =$O$21*('Revenue Breakup'!F37/'Revenue Breakup'!$F$40) | P23: =$P$21*('Revenue Breakup'!G37/'Revenue Breakup'!$G$40) | Q23: =$Q$21*('Revenue Breakup'!G37/'Revenue Breakup'!$G$40) | R23: =$R$21*('Revenue Breakup'!G37/'Revenue Breakup'!$G$40)
B24: Infant Powder | D24: =D23 | E24: =E23 | F24: =$F$21*'Revenue Breakup'!C38 | G24: =$G$21*('Revenue Breakup'!D38/'Revenue Breakup'!$D$40) | H24: =H23 | I24: =$I$21*('Revenue Breakup'!D38/'Revenue Breakup'!$D$40) | J24: =$J$21*('Revenue Breakup'!E38/'Revenue Breakup'!$E$40) | K24: =$K$21*('Revenue Breakup'!E38/'Revenue Breakup'!$E$40) | L24: =$L$21*('Revenue Breakup'!E38/'Revenue Breakup'!$E$40) | M24: =$M$21*('Revenue Breakup'!F38/'Revenue Breakup'!$F$40) | N24: =$N$21*('Revenue Breakup'!F38/'Revenue Breakup'!$F$40) | O24: =$O$21*('Revenue Breakup'!F38/'Revenue Breakup'!$F$40) | P24: =$P$21*('Revenue Breakup'!G38/'Revenue Breakup'!$G$40) | Q24: =$Q$21*('Revenue Breakup'!G38/'Revenue Breakup'!$G$40) | R24: =$R$21*('Revenue Breakup'!G38/'Revenue Breakup'!$G$40)
B25: Children Powder | D25: =D24 | E25: =E24 | F25: =$F$21*'Revenue Breakup'!C39 | G25: =$G$21*('Revenue Breakup'!D39/'Revenue Breakup'!$D$40) | H25: =H24 | I25: =$I$21*('Revenue Breakup'!D39/'Revenue Breakup'!$D$40) | J25: =$J$21*('Revenue Breakup'!E39/'Revenue Breakup'!$E$40) | K25: =$K$21*('Revenue Breakup'!E39/'Revenue Breakup'!$E$40) | L25: =$L$21*('Revenue Breakup'!E39/'Revenue Breakup'!$E$40) | M25: =$M$21*('Revenue Breakup'!F39/'Revenue Breakup'!$F$40) | N25: =$N$21*('Revenue Breakup'!F39/'Revenue Breakup'!$F$40) | O25: =$O$21*('Revenue Breakup'!F39/'Revenue Breakup'!$F$40) | P25: =$P$21*('Revenue Breakup'!G39/'Revenue Breakup'!$G$40) | Q25: =$Q$21*('Revenue Breakup'!G39/'Revenue Breakup'!$G$40) | R25: =$R$21*('Revenue Breakup'!G39/'Revenue Breakup'!$G$40)
B26: G&A / Operations Overheads (in %) | D26: ='IE Biffurcation'!N33 | E26: ='IE Biffurcation'!I33 | F26: =VALUE(SUBSTITUTE('IE Biffurcation'!D33, "%", "")) | G26: =VALUE(SUBSTITUTE('IE Biffurcation'!E33, "%", "")) | H26: ='IE Biffurcation'!J33 | I26: =VALUE(SUBSTITUTE('IE Biffurcation'!O33, "%", "")) | J26: =VALUE(SUBSTITUTE('IE Biffurcation'!F33, "%", "")) | K26: =VALUE(SUBSTITUTE('IE Biffurcation'!K33, "%", "")) | L26: =VALUE(SUBSTITUTE('IE Biffurcation'!P33, "%", "")) | M26: =VALUE(SUBSTITUTE('IE Biffurcation'!G33, "%", "")) | N26: =VALUE(SUBSTITUTE('IE Biffurcation'!L33, "%", "")) | O26: =VALUE(SUBSTITUTE('IE Biffurcation'!Q33, "%", "")) | P26: =VALUE(SUBSTITUTE('IE Biffurcation'!H33, "%", "")) | Q26: =VALUE(SUBSTITUTE('IE Biffurcation'!M33, "%", "")) | R26: =VALUE(SUBSTITUTE('IE Biffurcation'!R33, "%", ""))
B27: Pregnancy Powder | D27: =D26 | E27: =E26 | F27: =$F$26*('Revenue Breakup'!C36) | G27: =$G$26*('Revenue Breakup'!D36/'Revenue Breakup'!$D$40) | H27: =H26 | I27: =$I$26*('Revenue Breakup'!D36/'Revenue Breakup'!$D$40) | J27: =$J$26*('Revenue Breakup'!E36/'Revenue Breakup'!$E$40) | K27: =$K$26*('Revenue Breakup'!E36/'Revenue Breakup'!$E$40) | L27: =$K$26*('Revenue Breakup'!E36/'Revenue Breakup'!$E$40) | M27: =$M$26*('Revenue Breakup'!F36/'Revenue Breakup'!$F$40) | N27: =$N$26*('Revenue Breakup'!F36/'Revenue Breakup'!$F$40) | O27: =$O$26*('Revenue Breakup'!F36/'Revenue Breakup'!$F$40) | P27: =$P$26*('Revenue Breakup'!G36/'Revenue Breakup'!$G$40) | Q27: =$Q$26*('Revenue Breakup'!G36/'Revenue Breakup'!$G$40) | R27: =$R$26*('Revenue Breakup'!G36/'Revenue Breakup'!$G$40)
B28: Lactation Powder | D28: =D27 | E28: =E27 | F28: =$F$26*('Revenue Breakup'!C37) | G28: =$G$26*('Revenue Breakup'!D37/'Revenue Breakup'!$D$40) | H28: =H27 | I28: =$I$26*('Revenue Breakup'!D37/'Revenue Breakup'!$D$40) | J28: =$J$26*('Revenue Breakup'!E37/'Revenue Breakup'!$E$40) | K28: =$K$26*('Revenue Breakup'!E37/'Revenue Breakup'!$E$40) | L28: =$K$26*('Revenue Breakup'!E37/'Revenue Breakup'!$E$40) | M28: =$M$26*('Revenue Breakup'!F37/'Revenue Breakup'!$F$40) | N28: =$N$26*('Revenue Breakup'!F37/'Revenue Breakup'!$F$40) | O28: =$O$26*('Revenue Breakup'!F37/'Revenue Breakup'!$F$40) | P28: =$P$26*('Revenue Breakup'!G37/'Revenue Breakup'!$G$40) | Q28: =$Q$26*('Revenue Breakup'!G37/'Revenue Breakup'!$G$40) | R28: =$R$26*('Revenue Breakup'!G37/'Revenue Breakup'!$G$40)
B29: Infant Powder | D29: =D28 | E29: =E28 | F29: =$F$26*('Revenue Breakup'!C38) | G29: =$G$26*('Revenue Breakup'!D38/'Revenue Breakup'!$D$40) | H29: =H28 | I29: =$I$26*('Revenue Breakup'!D38/'Revenue Breakup'!$D$40) | J29: =$J$26*('Revenue Breakup'!E38/'Revenue Breakup'!$E$40) | K29: =$K$26*('Revenue Breakup'!E38/'Revenue Breakup'!$E$40) | L29: =$K$26*('Revenue Breakup'!E38/'Revenue Breakup'!$E$40) | M29: =$M$26*('Revenue Breakup'!F38/'Revenue Breakup'!$F$40) | N29: =$N$26*('Revenue Breakup'!F38/'Revenue Breakup'!$F$40) | O29: =$O$26*('Revenue Breakup'!F38/'Revenue Breakup'!$F$40) | P29: =$P$26*('Revenue Breakup'!G38/'Revenue Breakup'!$G$40) | Q29: =$Q$26*('Revenue Breakup'!G38/'Revenue Breakup'!$G$40) | R29: =$R$26*('Revenue Breakup'!G38/'Revenue Breakup'!$G$40)
B30: Children Powder | D30: =D29 | E30: =E29 | F30: =$F$26*('Revenue Breakup'!C39) | G30: =$G$26*('Revenue Breakup'!D39/'Revenue Breakup'!$D$40) | H30: =H29 | I30: =$I$26*('Revenue Breakup'!D39/'Revenue Breakup'!$D$40) | J30: =$J$26*('Revenue Breakup'!E39/'Revenue Breakup'!$E$40) | K30: =$K$26*('Revenue Breakup'!E39/'Revenue Breakup'!$E$40) | L30: =$K$26*('Revenue Breakup'!E39/'Revenue Breakup'!$E$40) | M30: =$M$26*('Revenue Breakup'!F39/'Revenue Breakup'!$F$40) | N30: =$N$26*('Revenue Breakup'!F39/'Revenue Breakup'!$F$40) | O30: =$O$26*('Revenue Breakup'!F39/'Revenue Breakup'!$F$40) | P30: =$P$26*('Revenue Breakup'!G39/'Revenue Breakup'!$G$40) | Q30: =$Q$26*('Revenue Breakup'!G39/'Revenue Breakup'!$G$40) | R30: =$R$26*('Revenue Breakup'!G39/'Revenue Breakup'!$G$40)
B31: Employee Cost (in %) | C31: * QA/QC teams per plant, regulatory staff per brand, HCP field force are unavoidable. Costs higher in early years. | D31: ='IE Biffurcation'!N40 | E31: ='IE Biffurcation'!I40 | F31: =VALUE(SUBSTITUTE('IE Biffurcation'!D40, "%", "")) | G31: =VALUE(SUBSTITUTE('IE Biffurcation'!O40, "%", "")) | H31: ='IE Biffurcation'!J40 | I31: =VALUE(SUBSTITUTE('IE Biffurcation'!E40, "%", "")) | J31: =VALUE(SUBSTITUTE('IE Biffurcation'!P40, "%", "")) | K31: =VALUE(SUBSTITUTE('IE Biffurcation'!K40, "%", "")) | L31: =VALUE(SUBSTITUTE('IE Biffurcation'!P40, "%", "")) | M31: =VALUE(SUBSTITUTE('IE Biffurcation'!G40, "%", "")) | N31: =VALUE(SUBSTITUTE('IE Biffurcation'!L40, "%", "")) | O31: =VALUE(SUBSTITUTE('IE Biffurcation'!Q40, "%", "")) | P31: =VALUE(SUBSTITUTE('IE Biffurcation'!R40, "%", "")) | Q31: =VALUE(SUBSTITUTE('IE Biffurcation'!M40, "%", "")) | R31: =VALUE(SUBSTITUTE('IE Biffurcation'!H40, "%", ""))
B32: Pregnancy Powder | D32: =D31 | E32: =E31 | F32: =$F$31*('Revenue Breakup'!C36) | G32: =$G$31*('Revenue Breakup'!D36/'Revenue Breakup'!$D$40) | H32: =H31 | I32: =$I$31*('Revenue Breakup'!D36/'Revenue Breakup'!$D$40) | J32: =$J$31*('Revenue Breakup'!E36/'Revenue Breakup'!$E$40) | K32: =$K$31*('Revenue Breakup'!E36/'Revenue Breakup'!$E$40) | L32: =$K$31*('Revenue Breakup'!E36/'Revenue Breakup'!$E$40) | M32: =$M$31*('Revenue Breakup'!F36/'Revenue Breakup'!$F$40) | N32: =$N$31*('Revenue Breakup'!F36/'Revenue Breakup'!$F$40) | O32: =$O$31*('Revenue Breakup'!F36/'Revenue Breakup'!$F$40) | P32: =$P$31*('Revenue Breakup'!G36/'Revenue Breakup'!$G$40) | Q32: =$Q$31*('Revenue Breakup'!G36/'Revenue Breakup'!$G$40) | R32: =$R$31*('Revenue Breakup'!G36/'Revenue Breakup'!$G$40)
B33: Lactation Powder | D33: =D32 | E33: =E32 | F33: =$F$31*('Revenue Breakup'!C37) | G33: =$G$31*('Revenue Breakup'!D37/'Revenue Breakup'!$D$40) | H33: =H32 | I33: =$I$31*('Revenue Breakup'!D37/'Revenue Breakup'!$D$40) | J33: =$J$31*('Revenue Breakup'!E37/'Revenue Breakup'!$E$40) | K33: =$K$31*('Revenue Breakup'!E37/'Revenue Breakup'!$E$40) | L33: =$K$31*('Revenue Breakup'!E37/'Revenue Breakup'!$E$40) | M33: =$M$31*('Revenue Breakup'!F37/'Revenue Breakup'!$F$40) | N33: =$N$31*('Revenue Breakup'!F37/'Revenue Breakup'!$F$40) | O33: =$O$31*('Revenue Breakup'!F37/'Revenue Breakup'!$F$40) | P33: =$P$31*('Revenue Breakup'!G37/'Revenue Breakup'!$G$40) | Q33: =$Q$31*('Revenue Breakup'!G37/'Revenue Breakup'!$G$40) | R33: =$R$31*('Revenue Breakup'!G37/'Revenue Breakup'!$G$40)
B34: Infant Powder | D34: =D33 | E34: =E33 | F34: =$F$31*('Revenue Breakup'!C38) | G34: =$G$31*('Revenue Breakup'!D38/'Revenue Breakup'!$D$40) | H34: =H33 | I34: =$I$31*('Revenue Breakup'!D38/'Revenue Breakup'!$D$40) | J34: =$J$31*('Revenue Breakup'!E38/'Revenue Breakup'!$E$40) | K34: =$K$31*('Revenue Breakup'!E38/'Revenue Breakup'!$E$40) | L34: =$K$31*('Revenue Breakup'!E38/'Revenue Breakup'!$E$40) | M34: =$M$31*('Revenue Breakup'!F38/'Revenue Breakup'!$F$40) | N34: =$N$31*('Revenue Breakup'!F38/'Revenue Breakup'!$F$40) | O34: =$O$31*('Revenue Breakup'!F38/'Revenue Breakup'!$F$40) | P34: =$P$31*('Revenue Breakup'!G38/'Revenue Breakup'!$G$40) | Q34: =$Q$31*('Revenue Breakup'!G38/'Revenue Breakup'!$G$40) | R34: =$R$31*('Revenue Breakup'!G38/'Revenue Breakup'!$G$40)
B35: Children Powder | D35: =D34 | E35: =E34 | F35: =$F$31*('Revenue Breakup'!C39) | G35: =$G$31*('Revenue Breakup'!D39/'Revenue Breakup'!$D$40) | H35: =H34 | I35: =$I$31*('Revenue Breakup'!D39/'Revenue Breakup'!$D$40) | J35: =$J$31*('Revenue Breakup'!E39/'Revenue Breakup'!$E$40) | K35: =$K$31*('Revenue Breakup'!E39/'Revenue Breakup'!$E$40) | L35: =$K$31*('Revenue Breakup'!E39/'Revenue Breakup'!$E$40) | M35: =$M$31*('Revenue Breakup'!F39/'Revenue Breakup'!$F$40) | N35: =$N$31*('Revenue Breakup'!F39/'Revenue Breakup'!$F$40) | O35: =$O$31*('Revenue Breakup'!F39/'Revenue Breakup'!$F$40) | P35: =$P$31*('Revenue Breakup'!G39/'Revenue Breakup'!$G$40) | Q35: =$Q$31*('Revenue Breakup'!G39/'Revenue Breakup'!$G$40) | R35: =$R$31*('Revenue Breakup'!G39/'Revenue Breakup'!$G$40)
B37: INDIRECT EXPENSE % BREAKUP TIER WISE
B38: Cost Head | C38: Year 1 | F38: Year 2 | I38: Year 3 | L38: Year 4 | O38: Year 5
C39: Tier 1 (Metro) | D39: Tier 2 (Mid Cities) | E39: Tier 3 (Small Towns) | F39: Tier 1 (Metro) | G39: Tier 2 (Mid Cities) | H39: Tier 3 (Small Towns) | I39: Tier 1 (Metro) | J39: Tier 2 (Mid Cities) | K39: Tier 3 (Small Towns) | L39: Tier 1 (Metro) | M39: Tier 2 (Mid Cities) | N39: Tier 3 (Small Towns) | O39: Tier 1 (Metro) | P39: Tier 2 (Mid Cities) | Q39: Tier 3 (Small Towns)
B40: Marketing & Advertising | C40: =D5 | D40: =E5 | E40: =F5 | F40: =G5 | G40: =H5 | H40: =I5 | I40: =J5 | J40: =K5 | ... Q40: =R5 | X40: 5
B41: HCP Detailing & Medical Engagement | C41: =D10 | D41: =E10 | E41: =F10 | F41: =G10 | G41: =H10 | H41: =I10 | I41: =J10 | J41: =K10 | ... Q41: =R10
B42: R&D / Regulatory / Compliance | C42: =D12 | D42: =E12 | E42: =F21 | F42: =G21 | G42: =H21 | H42: =I21 | I42: =J21 | J42: =K21 | K42: =L21 | L42: =M21 | ... Q42: =R21
B43: G&A / Operations Overheads | C43: =D13 | D43: =E13 | E43: =F26 | F43: =G26 | G43: =H26 | H43: =I26 | I43: =J26 | J43: =K26 | K43: =L26 | L43: =M26 | ... Q43: =R26
B44: Employee Cost | C44: =D14 | D44: =E14 | E44: =F31 | F44: =G31 | G44: =H31 | H44: =I31 | I44: =J31 | J44: =K31 | K44: =L31 | L44: =M31 | ... Q44: =R31
B46: REVENUE BREAKUP TIER WISE
B47: REVENUE BREAKUP | C47: 1 | D47: 2 | E47: 3 | F47: 4 | G47: 5
B48: Tier 1 | C48: ='Revenue Breakup'!C31 | D48: ='Revenue Breakup'!E31 | E48: ='Revenue Breakup'!G31 | F48: ='Revenue Breakup'!I31 | G48: ='Revenue Breakup'!K31
B49: Tier 2 | C49: ='Revenue Breakup'!C32 | D49: ='Revenue Breakup'!E32 | E49: ='Revenue Breakup'!G32 | F49: ='Revenue Breakup'!I32 | G49: ='Revenue Breakup'!K32
B50: Tier 3 | C50: ='Revenue Breakup'!C33 | D50: ='Revenue Breakup'!E33 | E50: ='Revenue Breakup'!G33 | F50: ='Revenue Breakup'!I33 | G50: ='Revenue Breakup'!K33
B52: INDIRECT EXPENSE BREAKUP TIER WISE
B53: Cost Head | C53: Year 1 | F53: Year 2 | I53: Year 3 | L53: Year 4 | O53: Year 5
C54: Tier 1 (Metro) | D54: Tier 2 (Mid Cities) | E54: Tier 3 (Small Towns) | F54: Tier 1 (Metro) | G54: Tier 2 (Mid Cities) | H54: Tier 3 (Small Towns) | I54: Tier 1 (Metro) | J54: Tier 2 (Mid Cities) | K54: Tier 3 (Small Towns) | L54: Tier 1 (Metro) | M54: Tier 2 (Mid Cities) | N54: Tier 3 (Small Towns) | O54: Tier 1 (Metro) | P54: Tier 2 (Mid Cities) | Q54: Tier 3 (Small Towns)
B55: Revenue | C55: =C48 | D55: =C49 | E55: =C50 | F55: =D48 | G55: =D49 | H55: =D50 | I55: =E48 | J55: =E49 | K55: =E50 | L55: =F48 | M55: =F49 | N55: =F50 | O55: =G48 | P55: =G49 | Q55: =G50
B56: Marketing & Advertising | C56: 0 | D56: 0 | E56: =$E$55*(E40/100) | F56: =$F$55*(F40/100) | G56: 0 | H56: =$H$55*(H40/100) | I56: =$I$55*(I40/100) | J56: =$J$55*(J40/100) | K56: =$K$55*(K40/100) | L56: =$L$55*(L40/100) | M56: =$M$55*(M40/100) | N56: =$N$55*(N40/100) | O56: =$O$55*(O40/100) | P56: =$P$55*(P40/100) | Q56: =$Q$55*(Q40/100)
B57: HCP Detailing & Medical Engagement | C57: 0 | D57: 0 | E57: =$E$55*(E41/100) | F57: =$F$55*(F41/100) | G57: 0 | H57: =$H$55*(H41/100) | I57: =$I$55*(I41/100) | J57: =$J$55*(J41/100) | K57: =$K$55*(K41/100) | L57: =$L$55*(L41/100) | M57: =$M$55*(M41/100) | N57: =$N$55*(N41/100) | O57: =$O$55*(O41/100) | P57: =$P$55*(P41/100) | Q57: =$Q$55*(Q41/100)
B58: Distribution & Logistics | C58: 0 | D58: 0 | E58: =sum(F17:F20) | F58: =sum(G17:G20) | G58: 0 | H58: =sum(I17:I20) | I58: =sum(J17:J20) | J58: =sum(K17:K20) | K58: =sum(L17:L20) | L58: =sum(M17:M20) | M58: =sum(N17:N20) | N58: =sum(O17:O20) | O58: =sum(P16:P20) | P58: =sum(Q16:Q20) | Q58: =sum(R16:R20)
B59: R&D / Regulatory / Compliance | C59: 0 | D59: 0 | E59: =$E$55*(E42/100) | F59: =$F$55*(F42/100) | G59: 0 | H59: =$H$55*(H42/100) | I59: =$I$55*(I42/100) | J59: =$J$55*(J42/100) | K59: =$K$55*(K42/100) | L59: =$L$55*(L42/100) | M59: =$M$55*(M42/100) | N59: =$N$55*(N42/100) | O59: =$O$55*(O42/100) | P59: =$P$55*(P42/100) | Q59: =$Q$55*(Q42/100)
B60: G&A / Operations Overheads | C60: 0 | D60: 0 | E60: =$E$55*(E43/100) | F60: =$F$55*(F43/100) | G60: 0 | H60: =$H$55*(H43/100) | I60: =$I$55*(I43/100) | J60: =$J$55*(J43/100) | K60: =$K$55*(K43/100) | L60: =$L$55*(L43/100) | M60: =$M$55*(M43/100) | N60: =$N$55*(N43/100) | O60: =$O$55*(O43/100) | P60: =$P$55*(P43/100) | Q60: =$Q$55*(Q43/100)
B61: Employee Cost | C61: 0 | D61: 0 | E61: =$E$55*(E44/100) | F61: =$F$55*(F44/100) | G61: 0 | H61: =$H$55*(H44/100) | I61: =$I$55*(I44/100) | J61: =$J$55*(J44/100) | K61: =$K$55*(K44/100) | L61: =$L$55*(L44/100) | M61: =$M$55*(M44/100) | N61: =$N$55*(N44/100) | O61: =$O$55*(O44/100) | P61: =$P$55*(P44/100) | Q61: =$Q$55*(Q44/100)
B62: Contingency Fund | C62: =sum(C56:C61)*5% | D62: =sum(D56:D61)*5% | E62: =sum(E56:E61)*5% | F62: =sum(F56:F61)*5% | G62: =sum(G56:G61)*5% | H62: =sum(H56:H61)*5% | I62: =sum(I56:I61)*5% | J62: =sum(J56:J61)*5% | ... Q62: =sum(Q56:Q61)*5%
B63: Sub-Total | C63: =sum(C56:C62) | D63: =sum(D56:D62) | E63: =sum(E56:E62) | F63: =sum(F56:F62) | G63: =sum(G56:G62) | H63: =sum(H56:H62) | I63: =sum(I56:I62) | J63: =sum(J56:J62) | ... Q63: =sum(Q56:Q62)
B64: Total | C64: =sum(C63:E63) | F64: =sum(F63:H63) | I64: =sum(I63:K63) | L64: =sum(L63:N63) | O64: =sum(O63:Q63)
B66: INDIRECT EXPENSE BREAKUP TIER WISE & PRODUCT WISE
B67: Cost Head | C67: Remark | D67: Year 1 | G67: Year 2 | J67: Year 3 | M67: Year 4 | P67: Year 5
D68: Tier 1 (Metro) | E68: Tier 2 (Mid Cities) | F68: Tier 3 (Small Towns) | G68: Tier 1 (Metro) | H68: Tier 2 (Mid Cities) | I68: Tier 3 (Small Towns) | J68: Tier 1 (Metro) | K68: Tier 2 (Mid Cities) | L68: Tier 3 (Small Towns) | M68: Tier 1 (Metro) | N68: Tier 2 (Mid Cities) | O68: Tier 3 (Small Towns) | P68: Tier 1 (Metro) | Q68: Tier 2 (Mid Cities) | R68: Tier 3 (Small Towns)
B69: Marketing & Advertising | C69: * IMS Act prohibits infant formula consumer ads. Tier 1 budget shifts entirely to HCP detailing. 3 brand budgets from Y3. | D69: =IFERROR(D5*$C$55,0) | E69: =IFERROr(0,$D$55*E5) | F69: =iferror($E$55*F5%,0) | G69: =iferror($F$55*G5%,0) | H69: =iferror($G$55*H5%,0) | I69: =iferror($H$55*I5%,0) | J69: =iferror($I$55*J5%,0) | K69: =iferror($J$55*K5%,0) | L69: =iferror($K$55*L5%,0) | M69: =iferror($L$55*M5%,0) | N69: =iferror($M$55*N5%,0) | O69: =iferror($N$55*O5%,0) | P69: =iferror($O$55*P5%,0) | Q69: =iferror($P$55*Q5%,0) | R69: =iferror($Q$55*R5%,0)
B70: Pregnancy Powder | D70: =IFERROR(D6*$C$55,0) | E70: =IFERROr(0,$D$55*E6) | F70: =iferror($E$55*F6%,0) | G70: =iferror($F$55*G6%,0) | H70: =iferror($G$55*H6%,0) | I70: =iferror($H$55*I6%,0) | J70: =iferror($I$55*J6%,0) | K70: =iferror($J$55*K6%,0) | L70: =iferror($K$55*L6%,0) | M70: =iferror($L$55*M6%,0) | N70: =iferror($M$55*N6%,0) | O70: =iferror($N$55*O6%,0) | P70: =iferror($O$55*P6%,0) | Q70: =iferror($P$55*Q6%,0) | R70: =iferror($Q$55*R6%,0)
B71: Lactation Powder | D71: =IFERROR(D7*$C$55,0) | E71: =IFERROr(0,$D$55*E7) | F71: =iferror($E$55*F7%,0) | G71: =iferror($F$55*G7%,0) | H71: =iferror($G$55*H7%,0) | I71: =iferror($H$55*I7%,0) | J71: =iferror($I$55*J7%,0) | K71: =iferror($J$55*K7%,0) | L71: =iferror($K$55*L7%,0) | M71: =iferror($L$55*M7%,0) | N71: =iferror($M$55*N7%,0) | O71: =iferror($N$55*O7%,0) | P71: =iferror($O$55*P7%,0) | Q71: =iferror($P$55*Q7%,0) | R71: =iferror($Q$55*R7%,0)
B72: Infant Powder | D72: =IFERROR(D8*$C$55,0) | E72: =IFERROr(0,$D$55*E8) | F72: =iferror($E$55*F8%,0) | G72: =iferror($F$55*G8%,0) | H72: =iferror($G$55*H8%,0) | I72: =iferror($H$55*I8%,0) | J72: =iferror($I$55*J8%,0) | K72: =iferror($J$55*K8%,0) | L72: =iferror($K$55*L8%,0) | M72: =iferror($L$55*M8%,0) | N72: =iferror($M$55*N8%,0) | O72: =iferror($N$55*O8%,0) | P72: =iferror($O$55*P8%,0) | Q72: =iferror($P$55*Q8%,0) | R72: =iferror($Q$55*R8%,0)
B73: Children Powder | D73: =IFERROR(D9*$C$55,0) | E73: =IFERROr(0,$D$55*E9) | F73: =iferror($E$55*F9%,0) | G73: =iferror($F$55*G9%,0) | H73: =iferror($G$55*H9%,0) | I73: =iferror($H$55*I9%,0) | J73: =iferror($I$55*J9%,0) | K73: =iferror($J$55*K9%,0) | L73: =iferror($K$55*L9%,0) | M73: =iferror($L$55*M9%,0) | N73: =iferror($M$55*N9%,0) | O73: =iferror($N$55*O9%,0) | P73: =iferror($O$55*P9%,0) | Q73: =iferror($P$55*Q9%,0) | R73: =iferror($Q$55*R9%,0)
B74: HCP Detailing & Medical Engagement | C74: * OBGYNs, pediatricians, hospitals drive prescription/recommendation. Mandatory for infant formula category growth. | D74: =IFERROR(0 ,D10*$C$55) | E74: =IFERROr($D$55*E10,0) | F74: =iferror($E$55*F10%,0) | G74: =iferror($F$55*G10%,0) | H74: =iferror($G$55*H10%,0) | I74: =iferror($H$55*I10%,0) | J74: =iferror($I$55*J10%,0) | K74: =iferror($J$55*K10%,0) | L74: =iferror($K$55*L10%,0) | M74: =iferror($L$55*M10%,0) | N74: =iferror($M$55*N10%,0) | O74: =iferror($N$55*O10%,0) | P74: =iferror($O$55*P10%,0) | Q74: =iferror($P$55*Q10%,0) | R74: =iferror($Q$55*R10%,0)
B75: Pregnancy Powder | D75: =IFERROR(0 ,D11*$C$55) | E75: =IFERROr($D$55*E11,0) | F75: =iferror($E$55*F11%,0) | G75: =iferror($F$55*G11%,0) | H75: =iferror($G$55*H11%,0) | I75: =iferror($H$55*I11%,0) | J75: =iferror($I$55*J11%,0) | K75: =iferror($J$55*K11%,0) | L75: =iferror($K$55*L11%,0) | M75: =iferror($L$55*M11%,0) | N75: =iferror($M$55*N11%,0) | O75: =iferror($N$55*O11%,0) | P75: =iferror($O$55*P11%,0) | Q75: =iferror($P$55*Q11%,0) | R75: =iferror($Q$55*R11%,0)
B76: Lactation Powder | D76: =IFERROR(0 ,D12*$C$55) | E76: =IFERROr($D$55*E12,0) | F76: =iferror($E$55*F12%,0) | G76: =iferror($F$55*G12%,0) | H76: =iferror($G$55*H12%,0) | I76: =iferror($H$55*I12%,0) | J76: =iferror($I$55*J12%,0) | K76: =iferror($J$55*K12%,0) | L76: =iferror($K$55*L12%,0) | M76: =iferror($L$55*M12%,0) | N76: =iferror($M$55*N12%,0) | O76: =iferror($N$55*O12%,0) | P76: =iferror($O$55*P12%,0) | Q76: =iferror($P$55*Q12%,0) | R76: =iferror($Q$55*R12%,0)
B77: Infant Powder | D77: =IFERROR(0 ,D13*$C$55) | E77: =IFERROr($D$55*E13,0) | F77: =iferror($E$55*F13%,0) | G77: =iferror($F$55*G13%,0) | H77: =iferror($G$55*H13%,0) | I77: =iferror($H$55*I13%,0) | J77: =iferror($I$55*J13%,0) | K77: =iferror($J$55*K13%,0) | L77: =iferror($K$55*L13%,0) | M77: =iferror($L$55*M13%,0) | N77: =iferror($M$55*N13%,0) | O77: =iferror($N$55*O13%,0) | P77: =iferror($O$55*P13%,0) | Q77: =iferror($P$55*Q13%,0) | R77: =iferror($Q$55*R13%,0)
B78: Children Powder | D78: =IFERROR(0 ,D14*$C$55) | E78: =IFERROr($D$55*E14,0) | F78: =iferror($E$55*F14%,0) | G78: =iferror($F$55*G14%,0) | H78: =iferror($G$55*H14%,0) | I78: =iferror($H$55*I14%,0) | J78: =iferror($I$55*J14%,0) | K78: =iferror($J$55*K14%,0) | L78: =iferror($K$55*L14%,0) | M78: =iferror($L$55*M14%,0) | N78: =iferror($M$55*N14%,0) | O78: =iferror($N$55*O14%,0) | P78: =iferror($O$55*P14%,0) | Q78: =iferror($P$55*Q14%,0) | R78: =iferror($Q$55*R14%,0)
B79: Distribution & Logistics (in Cr) | C79: * Rs. 9 per box in Year 1 and Year 2. Rs. 8.5 per box Year 3 onwards | D79: =IFERROR(0 ,D15*$C$55) | E79: =IFERROr(0,$D$55*E15) | F79: =sum(F80:F83) | G79: =sum(G80:G83) | H79: =sum(H80:H83) | I79: =sum(I80:I83) | J79: =sum(J80:J83) | K79: =sum(K80:K83) | L79: =sum(L80:L83) | M79: =sum(M80:M83) | ... R79: =sum(R80:R83)
B80: Pregnancy Powder | D80: =IFERROR(0 ,D17*$C$55) | E80: =IFERROr(0,$D$55*E17) | F80: =F17 | G80: =G17 | H80: =H17 | I80: =I17 | J80: =J17 | K80: =K17 | L80: =L17 | M80: =M17 | ... R80: =R17
B81: Lactation Powder | D81: =IFERROR(0 ,D18*$C$55) | E81: =IFERROr(0,$D$55*E18) | F81: =F18 | G81: =G18 | H81: =H18 | I81: =I18 | J81: =J18 | K81: =K18 | L81: =L18 | M81: =M18 | ... R81: =R18
B82: Infant Powder | D82: =IFERROR(0 ,D19*$C$55) | E82: =IFERROr(0,$D$55*E19) | F82: =F19 | G82: =G19 | H82: =H19 | I82: =I19 | J82: =J19 | K82: =K19 | L82: =L19 | M82: =M19 | ... R82: =R19
B83: Children Powder | D83: =IFERROR(0 ,D20*$C$55) | E83: =IFERROr(0,$D$55*E20) | F83: =F20 | G83: =G20 | H83: =H20 | I83: =I20 | J83: =J20 | K83: =K20 | L83: =L20 | M83: =M20 | ... R83: =R20
B84: R&D / Regulatory / Compliance | C84: * Infant formula under FSS Act strictest category. Each stage/ trimester/ flavour variant = separate FSSAI testing + label approval. | D84: =IFERROR(0 ,D21*$C$55) | E84: =IFERROr(0,$D$55*E21) | F84: =iferror($E$55*F21%,0) | G84: =iferror($F$55*G21%,0) | H84: =iferror($G$55*H21%,0) | I84: =iferror($H$55*I21%,0) | J84: =iferror($I$55*J21%,0) | K84: =iferror($J$55*K21%,0) | L84: =iferror($K$55*L21%,0) | M84: =iferror($L$55*M21%,0) | N84: =iferror($M$55*N21%,0) | O84: =iferror($N$55*O21%,0) | P84: =iferror($O$55*P21%,0) | Q84: =iferror($P$55*Q21%,0) | R84: =iferror($Q$55*R21%,0)
B85: Pregnancy Powder | D85: =IFERROR(0 ,D22*$C$55) | E85: =IFERROr(0,$D$55*E22) | F85: =iferror($E$55*F22%,0) | G85: =iferror($F$55*G22%,0) | H85: =iferror($G$55*H22%,0) | I85: =iferror($H$55*I22%,0) | J85: =iferror($I$55*J22%,0) | K85: =iferror($J$55*K22%,0) | L85: =iferror($K$55*L22%,0) | M85: =iferror($L$55*M22%,0) | N85: =iferror($M$55*N22%,0) | O85: =iferror($N$55*O22%,0) | P85: =iferror($O$55*P22%,0) | Q85: =iferror($P$55*Q22%,0) | R85: =iferror($Q$55*R22%,0)
B86: Lactation Powder | D86: =IFERROR(0 ,D23*$C$55) | E86: =IFERROr(0,$D$55*E23) | F86: =iferror($E$55*F23%,0) | G86: =iferror($F$55*G23%,0) | H86: =iferror($G$55*H23%,0) | I86: =iferror($H$55*I23%,0) | J86: =iferror($I$55*J23%,0) | K86: =iferror($J$55*K23%,0) | L86: =iferror($K$55*L23%,0) | M86: =iferror($L$55*M23%,0) | N86: =iferror($M$55*N23%,0) | O86: =iferror($N$55*O23%,0) | P86: =iferror($O$55*P23%,0) | Q86: =iferror($P$55*Q23%,0) | R86: =iferror($Q$55*R23%,0)
B87: Infant Powder | D87: =IFERROR(0 ,D24*$C$55) | E87: =IFERROr(0,$D$55*E24) | F87: =iferror($E$55*F24%,0) | G87: =iferror($F$55*G24%,0) | H87: =iferror($G$55*H24%,0) | I87: =iferror($H$55*I24%,0) | J87: =iferror($I$55*J24%,0) | K87: =iferror($J$55*K24%,0) | L87: =iferror($K$55*L24%,0) | M87: =iferror($L$55*M24%,0) | N87: =iferror($M$55*N24%,0) | O87: =iferror($N$55*O24%,0) | P87: =iferror($O$55*P24%,0) | Q87: =iferror($P$55*Q24%,0) | R87: =iferror($Q$55*R24%,0)
B88: Children Powder | D88: =IFERROR(0 ,D25*$C$55) | E88: =IFERROr(0,$D$55*E25) | F88: =iferror($E$55*F25%,0) | G88: =iferror($F$55*G25%,0) | H88: =iferror($G$55*H25%,0) | I88: =iferror($H$55*I25%,0) | J88: =iferror($I$55*J25%,0) | K88: =iferror($J$55*K25%,0) | L88: =iferror($K$55*L25%,0) | M88: =iferror($L$55*M25%,0) | N88: =iferror($M$55*N25%,0) | O88: =iferror($N$55*O25%,0) | P88: =iferror($O$55*P25%,0) | Q88: =iferror($P$55*Q25%,0) | R88: =iferror($Q$55*R25%,0)
B89: G&A / Operations Overheads | D89: =IFERROR(0 ,D26*$C$55) | E89: =IFERROr(0,$D$55*E26) | F89: =iferror($E$55*F26%,0) | G89: =iferror($F$55*G26%,0) | H89: =iferror($G$55*H26%,0) | I89: =iferror($H$55*I26%,0) | J89: =iferror($I$55*J26%,0) | K89: =iferror($J$55*K26%,0) | L89: =iferror($K$55*L26%,0) | M89: =iferror($L$55*M26%,0) | N89: =iferror($M$55*N26%,0) | O89: =iferror($N$55*O26%,0) | P89: =iferror($O$55*P26%,0) | Q89: =iferror($P$55*Q26%,0) | R89: =iferror($Q$55*R26%,0)
B90: Pregnancy Powder | D90: =IFERROR(0 ,D27*$C$55) | E90: =IFERROr(0,$D$55*E27) | F90: =iferror($E$55*F27%,0) | G90: =iferror($F$55*G27%,0) | H90: =iferror($G$55*H27%,0) | I90: =iferror($H$55*I27%,0) | J90: =iferror($I$55*J27%,0) | K90: =iferror($J$55*K27%,0) | L90: =iferror($K$55*L27%,0) | M90: =iferror($L$55*M27%,0) | N90: =iferror($M$55*N27%,0) | O90: =iferror($N$55*O27%,0) | P90: =iferror($O$55*P27%,0) | Q90: =iferror($P$55*Q27%,0) | R90: =iferror($Q$55*R27%,0)
B91: Lactation Powder | D91: =IFERROR(0 ,D28*$C$55) | E91: =IFERROr(0,$D$55*E28) | F91: =iferror($E$55*F28%,0) | G91: =iferror($F$55*G28%,0) | H91: =iferror($G$55*H28%,0) | I91: =iferror($H$55*I28%,0) | J91: =iferror($I$55*J28%,0) | K91: =iferror($J$55*K28%,0) | L91: =iferror($K$55*L28%,0) | M91: =iferror($L$55*M28%,0) | N91: =iferror($M$55*N28%,0) | O91: =iferror($N$55*O28%,0) | P91: =iferror($O$55*P28%,0) | Q91: =iferror($P$55*Q28%,0) | R91: =iferror($Q$55*R28%,0)
B92: Infant Powder | D92: =IFERROR(0 ,D29*$C$55) | E92: =IFERROr(0,$D$55*E29) | F92: =iferror($E$55*F29%,0) | G92: =iferror($F$55*G29%,0) | H92: =iferror($G$55*H29%,0) | I92: =iferror($H$55*I29%,0) | J92: =iferror($I$55*J29%,0) | K92: =iferror($J$55*K29%,0) | L92: =iferror($K$55*L29%,0) | M92: =iferror($L$55*M29%,0) | N92: =iferror($M$55*N29%,0) | O92: =iferror($N$55*O29%,0) | P92: =iferror($O$55*P29%,0) | Q92: =iferror($P$55*Q29%,0) | R92: =iferror($Q$55*R29%,0)
B93: Children Powder | D93: =IFERROR(0 ,D30*$C$55) | E93: =IFERROr(0,$D$55*E30) | F93: =iferror($E$55*F30%,0) | G93: =iferror($F$55*G30%,0) | H93: =iferror($G$55*H30%,0) | I93: =iferror($H$55*I30%,0) | J93: =iferror($I$55*J30%,0) | K93: =iferror($J$55*K30%,0) | L93: =iferror($K$55*L30%,0) | M93: =iferror($L$55*M30%,0) | N93: =iferror($M$55*N30%,0) | O93: =iferror($N$55*O30%,0) | P93: =iferror($O$55*P30%,0) | Q93: =iferror($P$55*Q30%,0) | R93: =iferror($Q$55*R30%,0)
B94: Employee Cost | C94: * QA/QC teams per plant, regulatory staff per brand, HCP field force are unavoidable. Costs higher in early years. | D94: =IFERROR(0 ,D31*$C$55) | E94: =IFERROr(0,$D$55*E31) | F94: =iferror($E$55*F31%,0) | G94: =iferror($F$55*G31%,0) | H94: =iferror($G$55*H31%,0) | I94: =iferror($H$55*I31%,0) | J94: =iferror($I$55*J31%,0) | K94: =iferror($J$55*K31%,0) | L94: =iferror($K$55*L31%,0) | M94: =iferror($L$55*M31%,0) | N94: =iferror($M$55*N31%,0) | O94: =iferror($N$55*O31%,0) | P94: =iferror($O$55*P31%,0) | Q94: =iferror($P$55*Q31%,0) | R94: =iferror($Q$55*R31%,0)
B95: Pregnancy Powder | D95: =IFERROR(0 ,D32*$C$55) | E95: =IFERROr(0,$D$55*E32) | F95: =iferror($E$55*F32%,0) | G95: =iferror($F$55*G32%,0) | H95: =iferror($G$55*H32%,0) | I95: =iferror($H$55*I32%,0) | J95: =iferror($I$55*J32%,0) | K95: =iferror($J$55*K32%,0) | L95: =iferror($K$55*L32%,0) | M95: =iferror($L$55*M32%,0) | N95: =iferror($M$55*N32%,0) | O95: =iferror($N$55*O32%,0) | P95: =iferror($O$55*P32%,0) | Q95: =iferror($P$55*Q32%,0) | R95: =iferror($Q$55*R32%,0)
B96: Lactation Powder | D96: =IFERROR(0 ,D33*$C$55) | E96: =IFERROr(0,$D$55*E33) | F96: =iferror($E$55*F33%,0) | G96: =iferror($F$55*G33%,0) | H96: =iferror($G$55*H33%,0) | I96: =iferror($H$55*I33%,0) | J96: =iferror($I$55*J33%,0) | K96: =iferror($J$55*K33%,0) | L96: =iferror($K$55*L33%,0) | M96: =iferror($L$55*M33%,0) | N96: =iferror($M$55*N33%,0) | O96: =iferror($N$55*O33%,0) | P96: =iferror($O$55*P33%,0) | Q96: =iferror($P$55*Q33%,0) | R96: =iferror($Q$55*R33%,0)
B97: Infant Powder | D97: =IFERROR(0 ,D34*$C$55) | E97: =IFERROr(0,$D$55*E34) | F97: =iferror($E$55*F34%,0) | G97: =iferror($F$55*G34%,0) | H97: =iferror($G$55*H34%,0) | I97: =iferror($H$55*I34%,0) | J97: =iferror($I$55*J34%,0) | K97: =iferror($J$55*K34%,0) | L97: =iferror($K$55*L34%,0) | M97: =iferror($L$55*M34%,0) | N97: =iferror($M$55*N34%,0) | O97: =iferror($N$55*O34%,0) | P97: =iferror($O$55*P34%,0) | Q97: =iferror($P$55*Q34%,0) | R97: =iferror($Q$55*R34%,0)
B98: Children Powder | D98: =IFERROR(0 ,D35*$C$55) | E98: =IFERROr(0,$D$55*E35) | F98: =iferror($E$55*F35%,0) | G98: =iferror($F$55*G35%,0) | H98: =iferror($G$55*H35%,0) | I98: =iferror($H$55*I35%,0) | J98: =iferror($I$55*J35%,0) | K98: =iferror($J$55*K35%,0) | L98: =iferror($K$55*L35%,0) | M98: =iferror($L$55*M35%,0) | N98: =iferror($M$55*N35%,0) | O98: =iferror($N$55*O35%,0) | P98: =iferror($O$55*P35%,0) | Q98: =iferror($P$55*Q35%,0) | R98: =iferror($Q$55*R35%,0)
B99: Employee Cost | D99: =sum(D100:D103) | E99: =sum(E100:E103) | F99: =sum(F100:F103) | G99: =sum(G100:G103) | H99: =sum(H100:H103) | I99: =sum(I100:I103) | J99: =sum(J100:J103) | K99: =sum(K100:K103) | ... R99: =sum(R100:R103)
B100: Pregnancy Powder | D100: =sum(D70,D75,D80,D85,D90,D95)*5% | E100: =sum(E70,E75,E80,E85,E90,E95)*5% | F100: =sum(F70,F75,F80,F85,F90,F95)*5% | G100: =sum(G70,G75,G80,G85,G90,G95)*5% | H100: =sum(H70,H75,H80,H85,H90,H95)*5% | I100: =sum(I70,I75,I80,I85,I90,I95)*5% | J100: =sum(J70,J75,J80,J85,J90,J95)*5% | K100: =sum(K70,K75,K80,K85,K90,K95)*5% | ... R100: =sum(R70,R75,R80,R85,R90,R95)*5%
B101: Lactation Powder | D101: =sum(D71,D76,D81,D86,D91,D96)*5% | E101: =sum(E71,E76,E81,E86,E91,E96)*5% | F101: =sum(F71,F76,F81,F86,F91,F96)*5% | G101: =sum(G71,G76,G81,G86,G91,G96)*5% | H101: =sum(H71,H76,H81,H86,H91,H96)*5% | I101: =sum(I71,I76,I81,I86,I91,I96)*5% | J101: =sum(J71,J76,J81,J86,J91,J96)*5% | K101: =sum(K71,K76,K81,K86,K91,K96)*5% | ... R101: =sum(R71,R76,R81,R86,R91,R96)*5%
B102: Infant Powder | D102: =sum(D72,D77,D82,D87,D92,D97)*5% | E102: =sum(E72,E77,E82,E87,E92,E97)*5% | F102: =sum(F72,F77,F82,F87,F92,F97)*5% | G102: =sum(G72,G77,G82,G87,G92,G97)*5% | H102: =sum(H72,H77,H82,H87,H92,H97)*5% | I102: =sum(I72,I77,I82,I87,I92,I97)*5% | J102: =sum(J72,J77,J82,J87,J92,J97)*5% | K102: =sum(K72,K77,K82,K87,K92,K97)*5% | ... R102: =sum(R72,R77,R82,R87,R92,R97)*5%
B103: Children Powder | D103: =sum(D73,D78,D83,D88,D93,D98)*5% | E103: =sum(E73,E78,E83,E88,E93,E98)*5% | F103: =sum(F73,F78,F83,F88,F93,F98)*5% | G103: =sum(G73,G78,G83,G88,G93,G98)*5% | H103: =sum(H73,H78,H83,H88,H93,H98)*5% | I103: =sum(I73,I78,I83,I88,I93,I98)*5% | J103: =sum(J73,J78,J83,J88,J93,J98)*5% | K103: =sum(K73,K78,K83,K88,K93,K98)*5% | ... R103: =sum(R73,R78,R83,R88,R93,R98)*5%
B105: INDIRECT EXPENSE PER PRODUCT
B106: Products | C106: Year 1 | F106: Year 2 | I106: Year 3 | L106: Year 4 | O106: Year 5
...

Sheet Contract (1 yr)
B2: YEAR 1 FUNDING (in Cr) | C2: ='Total Production'!E4
C4: Pregnancy Powder (Garbhika) | D4: Lactation Powder (Matrusneha) | E4: Infant Formula Milk Powder (Poshit) | F4: Child Nutrition Powder
B5: Cost/Box | C5: ='Total Production'!C9 | D5: ='Total Production'!D9 | E5: ='Total Production'!E9 | F5: ='Total Production'!F9
B6: Selling Price/Box | C6: ='Total Production'!C20 | D6: ='Total Production'!C21 | E6: ='Total Production'!C22 | F6: ='Total Production'!C23
B7: Profit/Box | C7: =C6-C5 | D7: =D6-D5 | E7: =E6-E5 | F7: =F6-F5
B9: Taking into consideration the following information:
B10: Tons Manufactured / Day | C10: 5 | D10: * 2 tons a day at Rohan Sir's Factory (Natal Care only). Assuming another factory will have 4 tons too
B11: Kgs Manufactured / Day | C11: =C10*1000
B12: Boxes Manufactured / Day | C12: =((C11*1000*0.5)/500)+((C11*1000*0.5)/400)
B14: Natal Care Boxes/Day | C14: =(C11*1000*0.5)/500 | D14: * Natal Care Products are 500gms each
B15: Infant & Child Care Boxes/Day | C15: =(C11*1000*0.5)/400 | D15: * Infant and Child Care Products are 400gms each
B17: Working Days/Month | C17: 26
B18: Working Months/Year | C18: 12
B19: Working Days/Year | C19: =C17*C18
B21: PRODUCTION
B22: Products | C22: Boxes/Year | D22: Revenue/Year | E22: Revenue (in Cr) | F22: COGS (in Cr) | G22: Gross Profit (in Cr)
B23: Infant Formula Milk | C23: =($C$19*$C$15)/2 | D23: =C23*E6 | E23: =D23/10^7 | F23: =(C23*E5)/10^7 | G23: =E23-F23
B24: Child Nutrition Powder | C24: =($C$19*$C$15)/2 | D24: =C24*F6 | E24: =D24/10^7 | F24: =(C24*F5)/10^7 | G24: =E24-F24
B25: Pregnancy Powder | C25: =($C$19*$C$14)/2 | D25: =C25*C6 | E25: =D25/10^7 | F25: =(C25*C5)/10^7 | G25: =E25-F25
B26: Lactation Powder | C26: =($C$19*$C$14)/2 | D26: =C26*D6 | E26: =D26/10^7 | F26: =(C26*D5)/10^7 | G26: =E26-F26
C27: =sum(C23:C26) | E27: =sum(E23:E26) | F27: =sum(F23:F26) | G27: =sum(G23:G26)
B29: WORKING CAPITAL
B30: Working Capital (in Cr) | C30: ='WC (Year 1)'!D9/10^7
B31: Pregnancy Powder (in Cr) | C31: ='WC (Year 1)'!D5/10^7
B32: Lactation Powder (in Cr) | C32: ='WC (Year 1)'!D6/10^7 | D32: =D94
B33: Infant Formula Milk (in Cr) | C33: ='WC (Year 1)'!D7/10^7 | D33: =D124
B34: Child Nutrition Powder (in Cr) | C34: ='WC (Year 1)'!D8/10^7 | D34: =D154
B36: CONVERSION CHARGES
B37: Rohan Sir's Factory
B39: Conversion Charges/Day | C39: 35000
B41: Natal Care Boxes/Day | C41: =C14
B43: Conversion Charge/Box | C43: =C39/C41
B45: Other Person's Factory
B47: Conversion Charges/Day | C47: =C39*2
B49: Infant & Child Care Boxes/Day | C49: =C15
B51: Conversion Charge/Box | C51: =C47/C49
B53: APPLICATION & SOURCES OF FUND
B54: Sources of Fund | C54: =C57
B55: A. VNL | C55: =C54-C56
B56: B. Capital Raise | C56: =C2
B57: Application of Fund | C57: =sum(C58:C59)
B58: A. Production | C58: ='WC (Year 1)'!H9/10^7
B59: B. Indirect Expense | C59: ='WC (Year 1)'!I9/10^7
B61: INDIRECT EXPENSE BREAKUP
B62: Expenses | D62: % of Revenue | E62: Total Expense
B63: Training & Community Engagement | D63: 0.01 | E63: =(D63*$E$27)*10^7
B64: Monitoring & Evaluation | D64: 0.008 | E64: =(D64*$E$27)*10^7
B65: Technology & Reporting | D65: 0.0065 | E65: =(D65*$E$27)*10^7
B66: Administrative Cost | D66: 0.015 | E66: =(D66*$E$27)*10^7
B67: Logistics & Distribution Cost | D67: Rs. 9/ Box | E67: =9*C27
B68: Communication & Impact Documentation | D68: 0.0065035685 | E68: =(D68*$E$27)*10^7
B69: Contingency | D69: 0.1 | E69: =sum(E63:E68)*D69
D70: TOTAL (in ₹) | E70: =sum(E63:E69)
D71: TOTAL (₹ in Cr) | E71: =E70/10^7

Sheet In-house (2-5yrs)
B2: Year | C2: New Plants Added | D2: Total Plants | E2: Working Capacity | F2: Gross Revenue (Rs. Cr) | G2: COGS | H2: Gross Profit
B3: 1 | C3: 0 | D3: =C3 | E3: =D121 | F3: =(($C11*$D$91)+($D$92*$D11)+($E11*$D$93)+($F11*$D$94)+($D$95*$G11)+($H11*$D$96)+($I11*$D$97)+($D$98*$J11)+($K11*$D$99)+($D$100*$L11)+($M11*$D$101)+($D$102*$N11))/10000000 | G3: =(($C11*$E$91)+($E$92*$D11)+($E11*$E$93)+($F11*$E$94)+($E$95*$G11)+($H11*$E$96)+($I11*$E$97)+($E$98*$J11)+($K11*$E$99)+($E$100*$L11)+($M11*$E$101)+($E$102*$N11))/10000000 | H3: =F3-G3
B4: 2 | C4: 1 | D4: =D3+C4 | E4: =D125 | F4: =(($C12*$D$91)+($D$92*$D12)+($E12*$D$93)+($F12*$D$94)+($D$95*$G12)+($H12*$D$96)+($I12*$D$97)+($D$98*$J12)+($K12*$D$99)+($D$100*$L12)+($M12*$D$101)+($D$102*$N12))/10000000 | G4: =(($C12*$E$91)+($E$92*$D12)+($E12*$E$93)+($F12*$E$94)+($E$95*$G12)+($H12*$E$96)+($I12*$E$97)+($E$98*$J12)+($K12*$E$99)+($E$100*$L12)+($M12*$E$101)+($E$102*$N12))/10000000 | H4: =F4-G4
B5: 3 | C5: 2 | D5: =D4+C5 | E5: =D129 | F5: =(($C13*$D$91)+($D$92*$D13)+($E13*$D$93)+($F13*$D$94)+($D$95*$G13)+($H13*$D$96)+($I13*$D$97)+($D$98*$J13)+($K13*$D$99)+($D$100*$L13)+($M13*$D$101)+($D$102*$N13))/10000000 | G5: =(($C13*$E$91)+($E$92*$D13)+($E13*$E$93)+($F13*$E$94)+($E$95*$G13)+($H13*$E$96)+($I13*$E$97)+($E$98*$J13)+($K13*$E$99)+($E$100*$L13)+($M13*$E$101)+($E$102*$N13))/10000000 | H5: =F5-G5
B6: 4 | C6: 3 | D6: =D5+C6 | E6: =D133 | F6: =(($C14*$D$91)+($D$92*$D14)+($E14*$D$93)+($F14*$D$94)+($D$95*$G14)+($H14*$D$96)+($I14*$D$97)+($D$98*$J14)+($K14*$D$99)+($D$100*$L14)+($M14*$D$101)+($D$102*$N14))/10000000 | G6: =(($C14*$E$91)+($E$92*$D14)+($E14*$E$93)+($F14*$E$94)+($E$95*$G14)+($H14*$E$96)+($I14*$E$97)+($E$98*$J14)+($K14*$E$99)+($E$100*$L14)+($M14*$E$101)+($E$102*$N14))/10000000 | H6: =F6-G6
B7: 5 | C7: 3 | D7: =D6+C7 | E7: =D137 | F7: =(($C15*$D$91)+($D$92*$D15)+($E15*$D$93)+($F15*$D$94)+($D$95*$G15)+($H15*$D$96)+($I15*$D$97)+($D$98*$J15)+($K15*$D$99)+($D$100*$L15)+($M15*$D$101)+($D$102*$N15))/10000000 | G7: =(($C15*$E$91)+($E$92*$D15)+($E15*$E$93)+($F15*$E$94)+($E$95*$G15)+($H15*$E$96)+($I15*$E$97)+($E$98*$J15)+($K15*$E$99)+($E$100*$L15)+($M15*$E$101)+($E$102*$N15))/10000000 | H7: =F7-G7
B9: BOXES MANUFACTURED
B10: Year | C10: Total PP - Tier 1 | D10: Total PP - Tier 2 | E10: Total PP - Tier 3 | F10: Total LP - Tier 1 | G10: Total LP - Tier 2 | H10: Total LP - Tier 3 | I10: Total IFP - Tier 1 | J10: Total IFP - Tier 2 | K10: Total IFP - Tier 3 | L10: Total CP - Tier 1 | M10: Total CP - Tier 2 | N10: Total CP - Tier 3
B11: 1 | C11: =sum(E121:E124) | D11: =sum(F121:F124) | E11: =sum(G121:G124) | F11: =sum(H121:H124) | G11: =sum(I121:I124) | H11: =sum(J121:J124) | I11: =sum(K121:K124) | J11: =sum(L121:L124) | ... N11: =sum(P121:P124)
B12: 2 | C12: =sum(E125:E128) | D12: =sum(F125:F128) | E12: =sum(G125:G128) | F12: =sum(H125:H128) | G12: =sum(I125:I128) | H12: =sum(J125:J128) | I12: =sum(K125:K128) | J12: =sum(L125:L128) | ... N12: =sum(P125:P128)
B13: 3 | C13: =sum(E129:E132) | D13: =sum(F129:F132) | E13: =sum(G129:G132) | F13: =sum(H129:H132) | G13: =sum(I129:I132) | H13: =sum(J129:J132) | I13: =sum(K129:K132) | J13: =sum(L129:L132) | ... N13: =sum(P129:P132)
B14: 4 | C14: =sum(E133:E136) | D14: =sum(F133:F136) | E14: =sum(G133:G136) | F14: =sum(H133:H136) | G14: =sum(I133:I136) | H14: =sum(J133:J136) | I14: =sum(K133:K136) | J14: =sum(L133:L136) | ... N14: =sum(P133:P136)
B15: 5 | C15: =sum(E137:E140) | D15: =sum(F137:F140) | E15: =sum(G137:G140) | F15: =sum(H137:H140) | G15: =sum(I137:I140) | H15: =sum(J137:J140) | I15: =sum(K137:K140) | J15: =sum(L137:L140) | ... N15: =sum(P137:P140)
B17: REVENUE TABLE
B18: Year | C18: Total PP - Tier 1 | D18: Total PP - Tier 2 | E18: Total PP - Tier 3 | F18: Total LP - Tier 1 | G18: Total LP - Tier 2 | H18: Total LP - Tier 3 | I18: Total IFP - Tier 1 | J18: Total IFP - Tier 2 | K18: Total IFP - Tier 3 | L18: Total CP - Tier 1 | M18: Total CP - Tier 2 | N18: Total CP - Tier 3
B19: 1 | C19: =C11*$D$91 | D19: =D11*$D$92 | E19: =$D$93*E11 | F19: =F11*$D$94 | G19: =G11*$D$95 | H19: =H11*$D$96 | I19: =I11*$D$97 | J19: =J11*$D$98 | K19: =K11*$D$99 | L19: =L11*$D$100 | M19: =M11*$D$101 | N19: =N11*$D$102
B20: 2 | C20: =C12*$D$91 | D20: =D12*$D$92 | E20: =$D$93*E12 | F20: =F12*$D$94 | G20: =G12*$D$95 | H20: =H12*$D$96 | I20: =I12*$D$97 | J20: =J12*$D$98 | K20: =K12*$D$99 | L20: =L12*$D$100 | M20: =M12*$D$101 | N20: =N12*$D$102
B21: 3 | C21: =C13*$D$91 | D21: =D13*$D$92 | E21: =$D$93*E13 | F21: =F13*$D$94 | G21: =G13*$D$95 | H21: =H13*$D$96 | I21: =I13*$D$97 | J21: =J13*$D$98 | K21: =K13*$D$99 | L21: =L13*$D$100 | M21: =M13*$D$101 | N21: =N13*$D$102
B22: 4 | C22: =C14*$D$91 | D22: =D14*$D$92 | E22: =$D$93*E14 | F22: =F14*$D$94 | G22: =G14*$D$95 | H22: =H14*$D$96 | I22: =I14*$D$97 | J22: =J14*$D$98 | K22: =K14*$D$99 | L22: =L14*$D$100 | M22: =M14*$D$101 | N22: =N14*$D$102
B23: 5 | C23: =C15*$D$91 | D23: =D15*$D$92 | E23: =$D$93*E15 | F23: =F15*$D$94 | G23: =G15*$D$95 | H23: =H15*$D$96 | I23: =I15*$D$97 | J23: =J15*$D$98 | K23: =K15*$D$99 | L23: =L15*$D$100 | M23: =M15*$D$101 | N23: =N15*$D$102
B25: Working Days/Month | C25: 25 | D25: * Taking the number of working months/day into consideration
B26: Working Months/Year | C26: 7
B27: Working Hours/Day | C27: 16
B28: Minutes/Year | C28: =C27*C26*C25
B30: Kgs/Day Manufactured | C30: 40000 | D30: * As per engineers' recommendations
B31: Natal Boxes/Day Manufactured | C31: =((C30*1000)/2)/500
B32: Infant Boxes/Day Manufactured | C32: =((C30*1000)/2)/400
B33: Natal Boxes/Hour Manufactured | C33: =C31/C27
B34: Infant Boxes/Hour Manufactured | C34: =C32/C27
B36: SAM of 3rd Year | C36: Tier 1 | D36: Tier 2 | E36: Tier 3
B37: Pregnancy Powder | C37: 0.0447 | D37: 0.058 | E37: 0.8973
B38: Lactation Powder | C38: 0.0518 | D38: 0.0667 | E38: 0.8815
B39: Infant Nutrition Powder | C39: 0.032 | D39: 0.05 | E39: 0.918
B40: Child Nutrition Powder | C40: 0.045 | D40: 0.058 | E40: 0.897
C42: Year 2 | D42: Year 3-5
B43: Pregnancy Powder- Tier 1 | C43: =Round($C$37*$D$46,0) | D43: =Round($C$37*$D$46,0)
B44: Pregnancy Powder- Tier 2 | C44: 0 | D44: =Round($D$37*$D$46,0)
B45: Pregnancy Powder- Tier 3 | C45: =Round($E$37*$D$46,0) | D45: =Round($E$37*$D$46,0)
B46: Total BPH for Pregnancy Powder | C46: =sum(C43:C45) | D46: =$C$33/2
B48: Lactation Powder- Tier 1 | C48: =Round($C$38*$D$51,0) | D48: =Round($C$38*$D$51,0)
B49: Lactation Powder- Tier 2 | C49: 0 | D49: =Round($D$38*$D$51,0)
B50: Lactation Powder- Tier 3 | C50: =Round($E$38*$D$51,0) | D50: =Round($E$38*$D$51,0)
B51: Total BPH for Lactation Powder | C51: =sum(C48:C50) | D51: =$C$33/2
B53: Infant Powder- Tier 1 | C53: =ROUND($D$56*$C$39,0) | D53: =ROUND($D$56*$C$39,0)
B54: Infant Powder- Tier 2 | C54: 0 | D54: =ROUND($D$56*$D$39,0)
B55: Infant Powder- Tier 3 | C55: =ROUND($D$56*$E$39,0) | D55: =ROUND($D$56*$E$39,0)
B56: Total BPH for Infant Powder | C56: =sum(C53:C55) | D56: =Round($C$34/2,0)
B58: Children Powder- Tier 1 | C58: =Round($D$61*$C$40,0) | D58: =Round($D$61*$C$40,0)
B59: Children Powder- Tier 2 | C59: 0 | D59: =Round($D$61*$D$40,0)
B60: Children Powder- Tier 3 | C60: =Round($D$61*$E$40,0) | D60: =Round($D$61*$E$40,0)
B61: Total BPH for Children Powder | C61: =sum(C58:C60) | D61: =$C$34-D56
B63: Total BPH per Plant | C63: =C46+C51+C56+C61 | D63: =$C$34+C33
B65: Boxes/Year/Plant
C66: Year 1 | D66: Year 2 | E66: Year 3 | F66: Year 4 | G66: Year 5
B67: Boxes/Year (@ Working Capacity) | C67: =($C$28*$D$63*$E3) | D67: =($C$28*$C$63*$E4) | E67: =($C$28*$D$63*$E5) | F67: =($C$28*$D$63*$E6) | G67: =($C$28*$D$63*$E7)
B69: Total Pregnancy Powder Boxes | C69: =SUM(C70:C72) | D69: =SUM(D70:D72) | E69: =SUM(E70:E72) | F69: =SUM(F70:F72) | G69: =SUM(G70:G72)
B70: Total PP (Tier 1) | C70: =($C$28*$D43*$E$3) | D70: =($C$28*$C43*$E$4) | E70: =($C$28*$D43*$E$5) | F70: =($C$28*$D43*$E$6) | G70: =($C$28*$D43*$E$7)
B71: Total PP (Tier 2) | C71: =($C$28*$D44*$E$3) | D71: =($C$28*$C44*$E$4) | E71: =($C$28*$D44*$E$5) | F71: =($C$28*$D44*$E$6) | G71: =($C$28*$D44*$E$7)
B72: Total PP (Tier 3) | C72: =($C$28*$D45*$E$3) | D72: =($C$28*$C45*$E$4) | E72: =($C$28*$D45*$E$5) | F72: =($C$28*$D45*$E$6) | G72: =($C$28*$D45*$E$7)
B74: Total Lactation Powder Boxes | C74: =SUM(C75:C77) | D74: =SUM(D75:D77) | E74: =SUM(E75:E77) | F74: =SUM(F75:F77) | G74: =SUM(G75:G77)
B75: Total LP (Tier 1) | C75: =($C$28*$D48*$E$3) | D75: =($C$28*$C48*$E$4) | E75: =($C$28*$D48*$E$5) | F75: =($C$28*$D48*$E$6) | G75: =($C$28*$D48*$E$7)
B76: Total LP (Tier 2) | C76: =($C$28*$D49*$E$3) | D76: =($C$28*$C49*$E$4) | E76: =($C$28*$D49*$E$5) | F76: =($C$28*$D49*$E$6) | G76: =($C$28*$D49*$E$7)
B77: Total LP (Tier 3) | C77: =($C$28*$D50*$E$3) | D77: =($C$28*$C50*$E$4) | E77: =($C$28*$D50*$E$5) | F77: =($C$28*$D50*$E$6) | G77: =($C$28*$D50*$E$7)
B79: Total Infant Powder Boxes | C79: =SUM(C80:C82) | D79: =SUM(D80:D82) | E79: =SUM(E80:E82) | F79: =SUM(F80:F82) | G79: =SUM(G80:G82)
B80: Total IFP (Tier 1) | C80: =($C$28*$D53*$E$3) | D80: =($C$28*$C53*$E$4) | E80: =($C$28*$D53*$E$5) | F80: =($C$28*$D53*$E$6) | G80: =($C$28*$D53*$E$7)
B81: Total IFP (Tier 2) | C81: =($C$28*$D54*$E$3) | D81: =($C$28*$C54*$E$4) | E81: =($C$28*$D54*$E$5) | F81: =($C$28*$D54*$E$6) | G81: =($C$28*$D54*$E$7)
B82: Total IFP (Tier 3) | C82: =($C$28*$D55*$E$3) | D82: =($C$28*$C55*$E$4) | E82: =($C$28*$D55*$E$5) | F82: =($C$28*$D55*$E$6) | G82: =($C$28*$D55*$E$7)
B84: Total Child Powder Boxes | C84: =SUM(C85:C87) | D84: =SUM(D85:D87) | E84: =SUM(E85:E87) | F84: =SUM(F85:F87) | G84: =SUM(G85:G87)
B85: Total CP (Tier 1) | C85: =($C$28*$D58*$E$3) | D85: =($C$28*$C58*$E$4) | E85: =($C$28*$D58*$E$5) | F85: =($C$28*$D58*$E$6) | G85: =($C$28*$D58*$E$7)
B86: Total CP (Tier 2) | C86: =($C$28*$D59*$E$3) | D86: =($C$28*$C59*$E$4) | E86: =($C$28*$D59*$E$5) | F86: =($C$28*$D59*$E$6) | G86: =($C$28*$D59*$E$7)
B87: Total CP (Tier 3) | C87: =($C$28*$D60*$E$3) | D87: =($C$28*$C60*$E$4) | E87: =($C$28*$D60*$E$5) | F87: =($C$28*$D60*$E$6) | G87: =($C$28*$D60*$E$7)
B89: Exclusive of GST
B90: Products | C90: MRP | D90: Sale Price/Box | E90: Cost/Box | F90: Profit/Box
B91: Pregnancy Powder- Tier 1 (18%) | C91: 1120 | D91: =C91*($D$93/$C$93) | E91: ='PP BOM'!H25 | F91: =D91-E91
B92: Pregnancy Powder- Tier 2 (18%) | C92: 750 | D92: =C92*($D$93/$C$93) | E92: ='PP BOM'!H25 | F92: =D92-E92
B93: Pregnancy Powder- Tier 3 (18%) | C93: 500 | D93: 280 | E93: ='PP BOM'!H25 | F93: =D93-E93
B94: Lactation Powder- Tier 1 (18%) | C94: 1300 | D94: =C94*($D$96/$C$96) | E94: ='LP BOM'!H28 | F94: =D94-E94
B95: Lactation Powder- Tier 2 (18%) | C95: 800 | D95: =C95*($D$96/$C$96) | E95: ='LP BOM'!H28 | F95: =D95-E95
B96: Lactation Powder- Tier 3 (18%) | C96: 650 | D96: 286 | E96: ='LP BOM'!H28 | F96: =D96-E96
B97: Infant Powder- Tier 1 (18%) | C97: 1200 | D97: =C97*($D$99/$C$99) | E97: ='IFM BOM'!H30 | F97: =D97-E97
B98: Infant Powder- Tier 2 (18%) | C98: 800 | D98: =C98*($D$99/$C$99) | E98: ='IFM BOM'!H30 | F98: =D98-E98
B99: Infant Powder- Tier 3 (18%) | C99: 550 | D99: 242 | E99: ='IFM BOM'!H30 | F99: =D99-E99
B100: Children Powder- Tier 1 (18%) | C100: 1050 | D100: =C100*($D$102/$C$102) | E100: ='CNP BOM'!H24 | F100: =D100-E100
B101: Children Powder- Tier 2 (18%) | C101: 700 | D101: =C101*($D$102/$C$102) | E101: ='CNP BOM'!H24 | F101: =D101-E101
B102: Children Powder- Tier 3 (18%) | C102: 480 | D102: 212 | E102: ='CNP BOM'!H24 | F102: =D102-E102
B104: Working Capacity Calculations for Boxes (Quarterly)
B105: Months | C105: Year 1 | E105: Year 2 | G105: Year 3 | I105: Year 4 | K105: Year 5
C106: Capacity/Month | D106: Capacity/Quarter | E106: Capacity/Month | F106: Capacity/Quarter | G106: Capacity/Month | H106: Capacity/Quarter | I106: Capacity/Month | J106: Capacity/Quarter | K106: Capacity/Month | L106: Capacity/Quarter
B107: April to June | C107: 0.8 | D107: =C107*3 | E107: 0.8 | F107: =E107*3 | G107: 1 | H107: =G107*3 | I107: 1 | J107: =I107*3 | K107: 1 | L107: =K107*3
B108: January to March | C108: 0.8 | D108: =C108*3 | E108: 0.8 | F108: =E108*3 | G108: 1 | H108: =G108*3 | I108: 1 | J108: =I108*3 | K108: 1 | L108: =K108*3
B109: July to September | C109: 0.8 | D109: =C109*3 | E109: 0.8 | F109: =E109*3 | G109: 1 | H109: =G109*3 | I109: 1 | J109: =I109*3 | K109: 1 | L109: =K109*3
B110: October to December | C110: 0.8 | D110: =C110*3 | E110: 0.8 | F110: =E110*3 | G110: 1 | H110: =G110*3 | I110: 1 | J110: =I110*3 | K110: 1 | L110: =K110*3
B111: Average Working Capacity % | D111: =SUM(D107:D110)/C26 | F111: =SUM(F107:F110)/C26 | H111: =SUM(H107:H110)/C26 | J111: =SUM(J107:J110)/C26 | L111: =SUM(L107:L110)/C26
B113: Capacity Breakup for Boxes
C114: Year 1 Capacity | D114: Year 2 Capacity | E114: Year 3 Capacity | F114: Year 4 Capacity | G114: Year 5 Capacity
B115: Our brand manufacturing | C115: =D111*75% | D115: =F111*75% | E115: =H111*75% | F115: =J111*75% | G115: =L111*75%
B116: Contract manufacturing | C116: =D111-C115 | D116: =F111-D115 | E116: =H111-E115 | F116: =J111-F115 | G116: =L111-G115
B119: Quaterly Revenue Table | E119: *Multiplying by 3 considering no. of months
B120: Years | C120: Months | D120: Working Capacity (Monthly) | E120: Total PP - Tier 1 | F120: Total PP - Tier 2 | G120: Total PP - Tier 3 | H120: Total LP - Tier 1 | I120: Total LP - Tier 2 | J120: Total LP - Tier 3 | K120: Total IFP - Tier 1 | L120: Total IFP - Tier 2 | M120: Total IFP - Tier 3 | N120: Total CP - Tier 1 | O120: Total CP - Tier 2 | P120: Total CP - Tier 3 | Q120: Gross Revenue
B121: 1 | C121: April to June | D121: =IFERROR(0,($C$115*$C$3)/$D$3) | E121: =(($C$25*$C$27)*$D$43*3*D121*$D$3) | F121: =(($C$25*$C$27)*$D$44*3*D121*$D$3) | G121: =(($C$25*$C$27)*$D$45*3*$D121*$D$3) | H121: =(($C$25*$C$27)*$D$48*3*$D121*$D$3) | I121: =(($C$25*$C$27)*$D$49*3*$D121*$D$3) | J121: =(($C$25*$C$27)*$D$50*3*$D121*$D$3) | K121: =(($C$25*$C$27)*$D$53*3*$D121*$D$3) | L121: =(($C$25*$C$27)*$D$54*3*$D121*$D$3) | M121: =(($C$25*$C$27)*$D$55*3*$D121*$D$3) | N121: =(($C$25*$C$27)*$D$58*3*$D121*$D$3) | O121: =(($C$25*$C$27)*$D$59*3*$D121*$D$3) | P121: =(($C$25*$C$27)*$D$60*3*$D121*$D$3) | Q121: =(E121*$D$91)+(F121*$D$92)+($D$93*G121)+(H121*$D$94)+(I121*$D$95)+(J121*$D$96)+(K121*$D$97)+($D$98*L121)+(M121*$D$99)+($D$100*N121)+(O121*$D$101)+($D$102*P121)
...

Sheet Third Party (2-5yrs)
B2: Year | C2: New Plants Added | D2: Total Plants | E2: Working Capacity | F2: Total PP - Tier 1 | G2: Total PP - Tier 2 | H2: Total PP - Tier 3 | I2: Total LP - Tier 1 | J2: Total LP - Tier 2 | K2: Total LP - Tier 3 | L2: Total IFP - Tier 1 | M2: Total IFP - Tier 2 | N2: Total IFP - Tier 3 | O2: Total CP - Tier 1 | P2: Total CP - Tier 2 | Q2: Total CP - Tier 3 | R2: Gross Revenue (Rs. in Cr)
B3: 1 | C3: ='In-house (2-5yrs)'!C3 | D3: =C3 | E3: =IFERROR(((C3*C87)/D3),0) | F3: =D3*$C$42 | G3: =$C$43*D3 | H3: =$C$44*D3 | I3: =D3*$C$47 | J3: =D3*$C$48 | K3: =D3*$C$49 | L3: =E3*$C$52 | M3: =D3*$C$53 | N3: =$D3*$C$54 | O3: =$D3*$C$57 | P3: =$D3*$C$58 | Q3: =$D3*$C$59 | R3: =((F3*$C$63)+(G3*$C$64)+($C$65*H3)+($C$66*I3)+(J3*$C$67)+($C$68*K3))/10000000
B4: 2 | C4: ='In-house (2-5yrs)'!C4 | D4: =D3+C4 | E4: =IFERROR((((C4*D87)+(C3*C87))/D4),0) | F4: =D4*D42 | G4: =D43*D4 | H4: =D44*D4 | I4: =D4*D47 | J4: =D4*D48 | K4: =D4*$D$49 | L4: =E4*$D$52 | M4: =D4*$D$53 | N4: =D4*$D$54 | O4: =$D4*$D$57 | P4: =$D4*$D$58 | Q4: =$D4*$D$59 | R4: =((F4*$C$63)+(G4*$C$64)+($C$65*H4)+($C$66*I4)+(J4*$C$67)+($C$68*K4)+($C$69*L4)+(M4*$C$70)+($C$71*N4)+(O4*$C$72)+($C$73*P4)+(Q4*$C$74))/10000000
B5: 3 | C5: ='In-house (2-5yrs)'!C5 | D5: =D4+C5 | E5: =IFERROR(((C5*C87)+(D87*C4)+(C3*E87))/D5,0) | F5: =D5*E42 | G5: =D5*E43 | H5: =E44*D5 | I5: =D5*E47 | J5: =D5*E48 | K5: =D5*$E$49 | L5: =E5*$E$52 | M5: =D5*$E$53 | N5: =D5*$E$54 | O5: =$D5*$E$57 | P5: =$D5*$E$58 | Q5: =$D5*$E$59 | R5: =((F5*$C$63)+(G5*$C$64)+($C$65*H5)+($C$66*I5)+(J5*$C$67)+($C$68*K5)+($C$69*L5)+(M5*$C$70)+($C$71*N5)+(O5*$C$72)+($C$73*P5)+(Q5*$C$74))/10000000
B6: 4 | C6: ='In-house (2-5yrs)'!C6 | D6: =D5+C6 | E6: =iferror(((C6*C87)+(C5*D87)+(C4*E87)+(C3*F87))/D6,0) | F6: =D6*F42 | G6: =F43*D6 | H6: =F44*D6 | I6: =D6*F47 | J6: =D6*F48 | K6: =D6*$F$49 | L6: =E6*$F$52 | M6: =D6*$F$53 | N6: =D6*$F$54 | O6: =$D6*$F$57 | P6: =$D6*$F$58 | Q6: =$D6*$F$59 | R6: =((F6*$C$63)+(G6*$C$64)+($C$65*H6)+($C$66*I6)+(J6*$C$67)+($C$68*K6)+($C$69*L6)+(M6*$C$70)+($C$71*N6)+(O6*$C$72)+($C$73*P6)+(Q6*$C$74))/10000000
B7: 5 | C7: ='In-house (2-5yrs)'!C7 | D7: =D6+C7 | E7: =iferror(((C7*C87)+(C6*D87)+(C5*E87)+(C4*F87)+(G87*C3))/D7,0) | F7: =D7*G42 | G7: =G43*D7 | H7: =G44*D7 | I7: =D7*G47 | J7: =D7*G48 | K7: =D7*$G$49 | L7: =E7*$G$52 | M7: =D7*$G$53 | N7: =D7*$G$54 | O7: =$D7*$G$57 | P7: =$D7*$G$58 | Q7: =$D7*$G$59 | R7: =((F7*$C$63)+(G7*$C$64)+($C$65*H7)+($C$66*I7)+(J7*$C$67)+($C$68*K7)+($C$69*L7)+(M7*$C$70)+($C$71*N7)+(O7*$C$72)+($C$73*P7)+(Q7*$C$74))/10000000
B9: Working Days/Month | C9: ='In-house (2-5yrs)'!C25
B10: Working Months/Year | C10: ='In-house (2-5yrs)'!C26
B11: Working Hours/Day | C11: ='In-house (2-5yrs)'!C27
B12: Minutes/Year | C12: =C11*C10*C9
C14: Year 2 | D14: Year 3-5
B15: Pregnancy Powder- Tier 1 | C15: ='In-house (2-5yrs)'!C43 | D15: ='In-house (2-5yrs)'!D43
B16: Pregnancy Powder- Tier 2 | C16: ='In-house (2-5yrs)'!C44 | D16: ='In-house (2-5yrs)'!D44
B17: Pregnancy Powder- Tier 3 | C17: ='In-house (2-5yrs)'!C45 | D17: ='In-house (2-5yrs)'!D45
B18: Total BPH for Pregnancy Powder | C18: ='In-house (2-5yrs)'!C46 | D18: ='In-house (2-5yrs)'!D46
C19: ='In-house (2-5yrs)'!C47 | D19: ='In-house (2-5yrs)'!D47
B20: Lactation Powder- Tier 1 | C20: ='In-house (2-5yrs)'!C48 | D20: ='In-house (2-5yrs)'!D48
B21: Lactation Powder- Tier 2 | C21: ='In-house (2-5yrs)'!C49 | D21: ='In-house (2-5yrs)'!D49
B22: Lactation Powder- Tier 3 | C22: ='In-house (2-5yrs)'!C50 | D22: ='In-house (2-5yrs)'!D50
B23: Total BPH for Lactation Powder | C23: ='In-house (2-5yrs)'!C51 | D23: ='In-house (2-5yrs)'!D51
B25: Infant Powder- Tier 1 | C25: ='In-house (2-5yrs)'!C53 | D25: ='In-house (2-5yrs)'!D53
B26: Infant Powder- Tier 2 | C26: ='In-house (2-5yrs)'!C54 | D26: ='In-house (2-5yrs)'!D54
B27: Infant Powder- Tier 3 | C27: ='In-house (2-5yrs)'!C55 | D27: ='In-house (2-5yrs)'!D55
B28: Total BPH for Infant Powder | C28: ='In-house (2-5yrs)'!C56 | D28: ='In-house (2-5yrs)'!D56
B30: Children Powder- Tier 1 | C30: ='In-house (2-5yrs)'!C58 | D30: ='In-house (2-5yrs)'!D58
B31: Children Powder- Tier 2 | C31: ='In-house (2-5yrs)'!C59 | D31: ='In-house (2-5yrs)'!D59
B32: Children Powder- Tier 3 | C32: ='In-house (2-5yrs)'!C60 | D32: ='In-house (2-5yrs)'!D60
B33: Total BPH for Children Powder | C33: ='In-house (2-5yrs)'!C61 | D33: ='In-house (2-5yrs)'!D61
B35: Total BPH per Plant | C35: =sum(C18,C23,C28,C33) | D35: =sum(D18,D23,D28,D33)
B37: Boxes/Year/Plant
C38: Year 1 | D38: Year 2 | E38: Year 3 | F38: Year 4 | G38: Year 5
B39: Boxes/Year (@ Working Capacity) | C39: =(C12*D35*E3) | D39: =$D$35*$C$12*E4 | E39: =$D$35*$C$12*E5 | F39: =$D$35*$C$12*E6 | G39: =$D$35*$C$12*E7
B41: Total Pregnancy Powder Boxes | C41: =C42+C43+C44 | D41: =D42+D43+D44 | E41: =E42+E43+E44 | F41: =F42+F43+F44 | G41: =G42+G43+G44
B42: Total PP (Tier 1) | C42: =($C$12*$D15*$E$3) | D42: =($C$12*$C15*$E$4) | E42: =($C$12*$D15*$E$5) | F42: =($C$12*$D15*$E$6) | G42: =($C$12*$D15*$E$7)
B43: Total PP (Tier 2) | C43: =($C$12*$D16*$E$3) | D43: =($C$12*$C16*$E$4) | E43: =($C$12*$D16*$E$5) | F43: =($C$12*$D16*$E$6) | G43: =($C$12*$D16*$E$7)
B44: Total PP (Tier 3) | C44: =($C$12*$D17*$E$3) | D44: =($C$12*$C17*$E$4) | E44: =($C$12*$D17*$E$5) | F44: =($C$12*$D17*$E$6) | G44: =($C$12*$D17*$E$7)
B46: Total Lactation Powder Boxes | C46: =C47+C48+C49 | D46: =D47+D48+D49 | E46: =E47+E48+E49 | F46: =F47+F48+F49 | G46: =G47+G48+G49
B47: Total LP (Tier 1) | C47: =($C$12*$D20*$E$3) | D47: =($C$12*$C20*$E$4) | E47: =($C$12*$D20*$E$5) | F47: =($C$12*$D20*$E$6) | G47: =($C$12*$D20*$E$7)
B48: Total LP (Tier 2) | C48: =($C$12*$D21*$E$3) | D48: =($C$12*$C21*$E$4) | E48: =($C$12*$D21*$E$5) | F48: =($C$12*$D21*$E$6) | G48: =($C$12*$D21*$E$7)
B49: Total LP (Tier 3) | C49: =($C$12*$D22*$E$3) | D49: =($C$12*$C22*$E$4) | E49: =($C$12*$D22*$E$5) | F49: =($C$12*$D22*$E$6) | G49: =($C$12*$D22*$E$7)
B51: Total Infant Powder Boxes | C51: =SUM(C52:C54) | D51: =SUM(D52:D54) | E51: =SUM(E52:E54) | F51: =SUM(F52:F54) | G51: =SUM(G52:G54)
B52: Total IFP (Tier 1) | C52: =($C$12*$D25*$E$3) | D52: =($C$12*$C25*$E$4) | E52: =($C$12*$D25*$E$5) | F52: =($C$12*$D25*$E$6) | G52: =($C$12*$D25*$E$7)
B53: Total IFP (Tier 2) | C53: =($C$12*$D26*$E$3) | D53: =($C$12*$C26*$E$4) | E53: =($C$12*$D26*$E$5) | F53: =($C$12*$D26*$E$6) | G53: =($C$12*$D26*$E$7)
B54: Total IFP (Tier 3) | C54: =($C$12*$D27*$E$3) | D54: =($C$12*$C27*$E$4) | E54: =($C$12*$D27*$E$5) | F54: =($C$12*$D27*$E$6) | G54: =($C$12*$D27*$E$7)
B56: Total Child Powder Boxes | C56: =SUM(C57:C59) | D56: =SUM(D57:D59) | E56: =SUM(E57:E59) | F56: =SUM(F57:F59) | G56: =SUM(G57:G59)
B57: Total CP (Tier 1) | C57: =($C$12*$D30*$E$3) | D57: =($C$12*$C30*$E$4) | E57: =($C$12*$D30*$E$5) | F57: =($C$12*$D30*$E$6) | G57: =($C$12*$D30*$E$7)
B58: Total CP (Tier 2) | C58: =($C$12*$D31*$E$3) | D58: =($C$12*$C31*$E$4) | E58: =($C$12*$D31*$E$5) | F58: =($C$12*$D31*$E$6) | G58: =($C$12*$D31*$E$7)
B59: Total CP (Tier 3) | C59: =($C$12*$D32*$E$3) | D59: =($C$12*$C32*$E$4) | E59: =($C$12*$D32*$E$5) | F59: =($C$12*$D32*$E$6) | G59: =($C$12*$D32*$E$7)
B61: Exclusive of GST
B62: Products | C62: Sale Price/Box | D62: Cost/Box | E62: Profit/Box
B63: Pregnancy Powder- Tier 1 (18%) | C63: ='In-house (2-5yrs)'!D91 | D63: ='In-house (2-5yrs)'!E91 | E63: =C63-D63 | F63: * Our only cost is processing charges
B64: Pregnancy Powder- Tier 2 (18%) | C64: ='In-house (2-5yrs)'!D92 | D64: ='In-house (2-5yrs)'!E92 | E64: =C64-D64
B65: Pregnancy Powder- Tier 3 (18%) | C65: ='In-house (2-5yrs)'!D93 | D65: ='In-house (2-5yrs)'!E93 | E65: =C65-D65
B66: Lactation Powder- Tier 1 (18%) | C66: ='In-house (2-5yrs)'!D94 | D66: ='In-house (2-5yrs)'!E94 | E66: =C66-D66
B67: Lactation Powder- Tier 2 (18%) | C67: ='In-house (2-5yrs)'!D95 | D67: ='In-house (2-5yrs)'!E95 | E67: =C67-D67
B68: Lactation Powder- Tier 3 (18%) | C68: ='In-house (2-5yrs)'!D96 | D68: ='In-house (2-5yrs)'!E96 | E68: =C68-D68
B69: Infant Powder- Tier 1 (18%) | C69: ='In-house (2-5yrs)'!D97 | D69: ='In-house (2-5yrs)'!E97 | E69: =C69-D69
B70: Infant Powder- Tier 2 (18%) | C70: ='In-house (2-5yrs)'!D98 | D70: ='In-house (2-5yrs)'!E98 | E70: =C70-D70
B71: Infant Powder- Tier 3 (18%) | C71: ='In-house (2-5yrs)'!D99 | D71: ='In-house (2-5yrs)'!E99 | E71: =C71-D71
B72: Children Powder- Tier 1 (18%) | C72: ='In-house (2-5yrs)'!D100 | D72: ='In-house (2-5yrs)'!E100 | E72: =C72-D72
B73: Children Powder- Tier 2 (18%) | C73: ='In-house (2-5yrs)'!D101 | D73: ='In-house (2-5yrs)'!E101 | E73: =C73-D73
B74: Children Powder- Tier 3 (18%) | C74: ='In-house (2-5yrs)'!D102 | D74: ='In-house (2-5yrs)'!E102 | E74: =C74-D74
B76: Working Capacity Calculations (Quarterly)
C77: Year 1 | E77: Year 2 | G77: Year 3 | I77: Year 4 | K77: Year 5
C78: Capacity/Month | D78: Capacity/Quarter | E78: Capacity/Month | F78: Capacity/Quarter | G78: Capacity/Month | H78: Capacity/Quarter | I78: Capacity/Month | J78: Capacity/Quarter | K78: Capacity/Month | L78: Capacity/Quarter
B79: April to June | C79: ='In-house (2-5yrs)'!C107 | D79: ='In-house (2-5yrs)'!D107 | E79: ='In-house (2-5yrs)'!E107 | F79: ='In-house (2-5yrs)'!F107 | G79: ='In-house (2-5yrs)'!G107 | H79: ='In-house (2-5yrs)'!H107 | I79: ='In-house (2-5yrs)'!I107 | J79: ='In-house (2-5yrs)'!J107 | ... L79: ='In-house (2-5yrs)'!L107
B80: January to March | C80: ='In-house (2-5yrs)'!C108 | D80: ='In-house (2-5yrs)'!D108 | E80: ='In-house (2-5yrs)'!E108 | F80: ='In-house (2-5yrs)'!F108 | G80: ='In-house (2-5yrs)'!G108 | H80: ='In-house (2-5yrs)'!H108 | I80: ='In-house (2-5yrs)'!I108 | J80: ='In-house (2-5yrs)'!J108 | ... L80: ='In-house (2-5yrs)'!L108
B81: July to September | C81: ='In-house (2-5yrs)'!C109 | D81: ='In-house (2-5yrs)'!D109 | E81: ='In-house (2-5yrs)'!E109 | F81: ='In-house (2-5yrs)'!F109 | G81: ='In-house (2-5yrs)'!G109 | H81: ='In-house (2-5yrs)'!H109 | I81: ='In-house (2-5yrs)'!I109 | J81: ='In-house (2-5yrs)'!J109 | ... L81: ='In-house (2-5yrs)'!L109
B82: October to December | C82: ='In-house (2-5yrs)'!C110 | D82: ='In-house (2-5yrs)'!D110 | E82: ='In-house (2-5yrs)'!E110 | F82: ='In-house (2-5yrs)'!F110 | G82: ='In-house (2-5yrs)'!G110 | H82: ='In-house (2-5yrs)'!H110 | I82: ='In-house (2-5yrs)'!I110 | J82: ='In-house (2-5yrs)'!J110 | ... L82: ='In-house (2-5yrs)'!L110
B83: Average Working Capacity % | D83: =SUM(D79:D82)/C10 | F83: =SUM(F79:F82)/C10 | H83: =SUM(H79:H82)/C10 | J83: =SUM(J79:J82)/C10 | L83: =SUM(L79:L82)/C10
B85: Capacity Breakup for Boxes | C85: Year 1 Capacity | D85: Year 2 Capacity | E85: Year 3 Capacity | F85: Year 4 Capacity | G85: Year 5 Capacity
B86: Our brand manufacturing | C86: ='In-house (2-5yrs)'!C115 | D86: ='In-house (2-5yrs)'!D115 | E86: ='In-house (2-5yrs)'!E115 | F86: ='In-house (2-5yrs)'!F115 | G86: ='In-house (2-5yrs)'!G115
B87: Contract manufacturing | C87: ='In-house (2-5yrs)'!C116 | D87: ='In-house (2-5yrs)'!D116 | E87: ='In-house (2-5yrs)'!E116 | F87: ='In-house (2-5yrs)'!F116 | G87: ='In-house (2-5yrs)'!G116

Sheet IE Biffurcation
B2: Expense Head / Line Item | C2: Notes | D2: TIER 3 — VALUE (Small Towns / Mass) | I2: TIER 2 — MID (Mid Cities) | N2: TIER 1 — PREMIUM (Metro / Institutional)
D3: Year 1 | E3: Year 2 | F3: Year 3 | G3: Year 4 | H3: Year 5 | I3: Year 1 | J3: Year 2 | K3: Year 3 | L3: Year 4 | M3: Year 5 | N3: Year 1 | O3: Year 2 | P3: Year 3 | Q3: Year 4 | R3: Year 5
B4: A. MARKETING & ADVERTISING (% of tier net revenue)
B5: Consumer digital ads (Meta/Google/Programmatic) | C5: T3 high – volume push. T1 ZERO for infant formula (IMS Act) | D5: 0.03 | E5: 0.02 | F5: 0.01 | G5: 0.01 | H5: 0.01 | I5: - | J5: - | K5: 0.02 | L5: 0.02 | M5: 0.01 | N5: - | O5: 0.01 | P5: - | Q5: 0.01 | R5: -
B6: Influencer & KOL marketing | C6: Mommy bloggers, nutritionists | D6: 0.01 | E6: - | F6: 0.01 | G6: 0.01 | H6: 0.01 | I6: - | J6: - | K6: 0.01 | L6: 0.01 | M6: 0.01 | N6: - | O6: - | P6: - | Q6: 0.01 | R6: -
B7: Sampling & trial programs | C7: Higher in Y1-Y2 for trial generation | D7: 0.01 | E7: - | F7: 0.01 | G7: - | H7: - | I7: - | J7: - | K7: 0.01 | L7: - | M7: - | N7: - | O7: - | P7: 0.01 | Q7: - | R7: -
B8: Trade marketing (shelf / pharmacy / MT visibility) | C8: Grows as offline scale builds | D8: 0.01 | E8: 0.01 | F8: 0.01 | G8: 0.01 | H8: 0.01 | I8: - | J8: - | K8: 0.01 | L8: 0.01 | M8: 0.01 | N8: - | O8: 0.01 | P8: 0.01 | Q8: 0.01 | R8: 0.01
B9: Brand identity & design (per tier brand) | C9: T1 higher – premium packaging investment | D9: 0.01 | E9: 0.01 | F9: 0.01 | G9: - | H9: - | I9: - | J9: - | K9: 0.01 | L9: - | M9: - | N9: - | O9: 0.02 | P9: - | Q9: 0.01 | R9: -
B10: Events, baby expos, hospital tie-ups | D10: - | E10: - | F10: 0.01 | G10: - | H10: - | I10: - | J10: - | K10: - | L10: - | M10: - | N10: - | O10: - | P10: 0.01 | Q10: - | R10: -
B11: Loyalty & referral programs | C11: Grows with repeat purchase base | D11: - | E11: - | F11: 0.01 | G11: 0.01 | H11: 0.01 | I11: - | J11: - | K11: 0.01 | L11: 0.01 | M11: 0.01 | N11: - | O11: - | P11: 0.01 | Q11: 0.01 | R11: 0.01
B12: PR & communications | D12: - | E12: - | F12: 0.01 | G12: 0.01 | H12: 0.01 | I12: - | J12: - | K12: - | L12: 0.01 | M12: 0.01 | N12: - | O12: 0.01 | P12: 0.01 | Q12: 0.01 | R12: 0.01
B13: TOTAL Marketing & Advertising | C13: Target: Lean digital + HCP-led growth. | D13: =sum(D5:D12) | E13: =sum(E5:E12) | F13: =sum(F5:F12) | G13: =sum(G5:G12) | H13: =sum(H5:H12) | I13: =sum(I5:I12) | J13: =sum(J5:J12) | K13: =sum(K5:K12) | ... R13: =sum(R5:R12)
B14: B. HCP DETAILING & MEDICAL ENGAGEMENT (critical for maternal+infant category)
B15: OBGYN / gynecologist detailing | C15: T1 highest – drives Tier 1 infant formula prescriptions | D15: 0.01 | E15: 0.01 | F15: 0.01 | G15: 0.01 | H15: 0.01 | I15: - | J15: - | K15: 0.01 | L15: 0.01 | M15: 0.01 | N15: - | O15: 0.01 | P15: 0.01 | Q15: 0.01 | R15: 0.02
B16: Pediatrician detailing | C16: IMS Act: mandatory for infant formula growth | D16: 0.01 | E16: 0.01 | F16: 0.01 | G16: 0.01 | H16: 0.01 | I16: - | J16: - | K16: 0.01 | L16: 0.01 | M16: 0.01 | N16: - | O16: 0.01 | P16: 0.01 | Q16: 0.01 | R16: 0.01
B17: Hospital & nursing home tie-ups | C17: Formulary listing in private hospitals – T1 focus | D17: - | E17: - | F17: - | G17: 0.01 | H17: 0.01 | I17: - | J17: - | K17: 0.01 | L17: 0.01 | M17: 0.01 | N17: - | O17: 0.01 | P17: 0.01 | Q17: 0.01 | R17: 0.01
B18: Lactation consultant & dietitian programs | D18: - | E18: - | F18: - | G18: 0.01 | H18: 0.01 | I18: - | J18: - | K18: - | L18: 0.01 | M18: 0.01 | N18: - | O18: - | P18: 0.01 | Q18: 0.01 | R18: 0.01
B19: CME / medical conference sponsorships | D19: - | E19: - | F19: - | G19: - | H19: - | I19: - | J19: - | K19: - | L19: - | M19: 0.01 | N19: - | O19: - | P19: 0.01 | Q19: 0.01 | R19: 0.01
B20: TOTAL HCP Detailing | C20: Benchmark: Infant formula has ZERO consumer advertising — budget shifts to HCP detailing | D20: =sum(D15:D19) | E20: =sum(E15:E19) | F20: =sum(F15:F19) | G20: =sum(G15:G19) | H20: =sum(H15:H19) | I20: =sum(I15:I19) | J20: =sum(J15:J19) | K20: =sum(K15:K19) | ... R20: =sum(R15:R19)
B21: C. R&D / REGULATORY / COMPLIANCE (% of tier net revenue)
B22: Flavour & variant development | C22: Each new flavour triggers fresh lab trials | D22: 0.01 | E22: 0.01 | F22: 0.01 | G22: - | H22: - | I22: - | J22: - | K22: 0.01 | L22: - | M22: - | N22: - | O22: 0.01 | P22: 0.01 | Q22: - | R22: -
B23: Clinical & nutritional testing (per formulation) | C23: Trimester & stage-specific = multiply by variant count | D23: 0.01 | E23: 0.01 | F23: 0.01 | G23: 0.01 | H23: 0.01 | I23: - | J23: - | K23: 0.01 | L23: 0.01 | M23: 0.01 | N23: - | O23: 0.01 | P23: - | Q23: 0.01 | R23: -
B24: FSSAI dossier prep & label approval (per SKU) | C24: Infant formula = strictest FSSAI category | D24: 0.01 | E24: 0.01 | F24: 0.01 | G24: 0.01 | H24: 0.01 | I24: - | J24: - | K24: 0.01 | L24: 0.01 | M24: 0.01 | N24: - | O24: 0.01 | P24: - | Q24: 0.01 | R24: -
B25: IMS Act compliance monitoring | C25: IMS Act: ongoing monitoring for infant formula labeling/ads | D25: - | E25: - | F25: 0.01 | G25: 0.01 | H25: 0.01 | I25: - | J25: - | K25: - | L25: 0.01 | M25: 0.01 | N25: - | O25: - | P25: 0.01 | Q25: 0.01 | R25: 0.01
B26: Stability & shelf-life studies | D26: 0.01 | E26: 0.01 | F26: - | G26: - | H26: - | I26: - | J26: - | K26: - | L26: - | M26: - | N26: - | O26: 0.01 | P26: - | Q26: - | R26: -
B27: TOTAL R&D / Regulatory / Compliance | C27: Target: 3-5% across all years. FSSAI & IMS Act key drivers. | D27: 0.04 | E27: 0.04 | F27: 0.04 | G27: 0.03 | H27: 0.03 | I27: - | J27: - | K27: 0.03 | L27: 0.03 | M27: 0.03 | N27: - | O27: 0.04 | P27: 0.02 | Q27: 0.03 | R27: 0.01
B28: D. G&A / OPERATIONS OVERHEADS (% of tier net revenue)
B29: Rent & utilities (office + warehouse) | C29: T1 metro higher rent base | D29: 0.01 | E29: 0.01 | F29: 0.01 | G29: 0.01 | H29: 0.01 | I29: - | J29: - | K29: 0.01 | L29: 0.01 | M29: 0.01 | N29: - | O29: 0.01 | P29: 0.01 | Q29: 0.01 | R29: 0.01
B30: IT infrastructure, ERP & CRM | D30: 0.01 | E30: 0.01 | F30: 0.01 | G30: 0.01 | H30: 0.01 | I30: - | J30: - | K30: 0.01 | L30: 0.01 | M30: 0.01 | N30: - | O30: 0.01 | P30: 0.01 | Q30: 0.01 | R30: 0.01
B31: Legal, audit & insurance | D31: 0.01 | E31: 0.01 | F31: 0.01 | G31: 0.01 | H31: 0.01 | I31: - | J31: - | K31: 0.01 | L31: 0.01 | M31: 0.01 | N31: - | O31: 0.01 | P31: 0.01 | Q31: 0.01 | R31: 0.01
B32: Office supplies & misc admin | D32: - | E32: - | F32: - | G32: - | H32: - | I32: - | J32: - | K32: - | L32: - | M32: - | N32: - | O32: - | P32: - | Q32: - | R32: -
B33: TOTAL G&A / Overheads | C33: Target: 3% lean ops. Scales with headcount. | D33: 0.03 | E33: 0.03 | F33: 0.03 | G33: 0.03 | H33: 0.03 | I33: - | J33: - | K33: 0.03 | L33: 0.03 | M33: 0.03 | N33: - | O33: 0.03 | P33: 0.03 | Q33: 0.03 | R33: 0.03
B34: E. HUMAN RESOURCES (% of tier net revenue)
B35: Core team salaries | C35: Fixed cost – high as % when revenue small | D35: 0.04 | E35: 0.03 | F35: 0.03 | G35: 0.03 | H35: 0.03 | I35: - | J35: - | K35: 0.03 | L35: 0.03 | M35: 0.03 | N35: - | O35: 0.05 | P35: 0.04 | Q35: 0.03 | R35: 0.03
B36: PF / ESI / statutory (13% of salaries) | D36: 0.01 | E36: 0.01 | F36: 0.01 | G36: - | H36: - | I36: - | J36: - | K36: 0.01 | L36: - | M36: - | N36: - | O36: 0.01 | P36: 0.01 | Q36: - | R36: -
B37: QA/QC plant staff (Own plant from Y2) | C37: Per plant headcount fixed cost | D37: - | E37: 0.01 | F37: 0.01 | G37: 0.01 | H37: 0.01 | I37: - | J37: - | K37: 0.01 | L37: 0.01 | M37: 0.01 | N37: - | O37: 0.01 | P37: - | Q37: 0.01 | R37: -
B38: HCP field force (detailing reps) | C38: T1 highest field force – hospital + clinic coverage | D38: - | E38: - | F38: 0.01 | G38: 0.01 | H38: 0.01 | I38: - | J38: - | K38: 0.01 | L38: 0.01 | M38: 0.01 | N38: - | O38: 0.01 | P38: 0.01 | Q38: 0.01 | R38: 0.01
B39: Recruitment, training & contract staff | D39: 0.01 | E39: 0.01 | F39: - | G39: - | H39: - | I39: - | J39: - | K39: - | L39: - | M39: - | N39: - | O39: 0.01 | P39: - | Q39: - | R39: -
B40: TOTAL Human Resources | C40: Target: 6-8% Y1-Y2 lean team; 6-8% Y3+ as % reduces with revenue scale. | D40: 0.06 | E40: 0.06 | F40: 0.06 | G40: 0.05 | H40: 0.05 | I40: - | J40: - | K40: 0.06 | L40: 0.05 | M40: 0.05 | N40: - | O40: 0.09 | P40: 0.06 | Q40: 0.05 | R40: 0.04

Sheet WC (Year 1)
B2: TOTAL WORKING CAPITAL | G2: APPLICATION OF FUNDS
C4: Revenue | D4: Initial Working Capital | E4: W.C.Rotation | H4: Production | I4: Indirect Expense
B5: PP | C5: =D35 | D5: =D36 | E5: =C5/D5 | G5: PP | H5: =(D13*D14)*3.5 | I5: =D16*3.5
B6: LP | C6: =D64 | D6: =D65 | E6: =C6/D6 | G6: LP | H6: =(D42*D43)*3.5 | I6: =D45*3.5
B7: IFP | C7: =D93 | D7: =D94 | E7: =C7/D7 | G7: IFP | H7: =(D71*D72)*3.5 | I7: =D74*3.5
B8: CNP | C8: =D122 | D8: =D123 | E8: =C8/D8 | G8: CNP | H8: =(D100*D101)*3.5 | I8: =D103*3.5
D9: =sum(D5:D8) | H9: =sum(H5:H8) | I9: =sum(I5:I8)
H10: =H9+I9
B11: PREGNANCY POWDER
B13: Monthly Boxes Produced (in Units) | D13: ='Contract (1 yr)'!C25/12
B14: Cost/Box (in ₹) | D14: ='Total Production'!C9
B15: Revenue/Box (in ₹) | D15: ='Total Production'!C20
B16: Monthly Indirect Expense (in ₹) | D16: =(('Indirect Expenses'!E63/12)/4)*10^7
G17: * The working capital that we are investing in the first month is derived from the cash outflow that is required in the first month
B18: Month | C18: Cash Outflow | D18: Cash Inflow | E18: Difference (CO-CI) | G18: Opening W.C. | H18: Net Cash Flow | I18: Closing W.C.
B19: April | C19: =($D$13*$D$14)+$D$16 | D19: =$D$13*$D$15 | E19: =D19-C19 | G19: =C19+D33 | H19: =E19 | I19: =G19+H19
B20: May | C20: =($D$13*$D$14)+$D$16 | D20: =$D$13*$D$15 | E20: =D20-C20 | G20: =I19 | H20: =E20 | I20: =G20+H20
B21: June | C21: =($D$13*$D$14)+$D$16 | D21: =$D$13*$D$15 | E21: =D21-C21 | G21: =I20 | H21: =E21 | I21: =G21+H21
B22: July | C22: =($D$13*$D$14)+$D$16 | D22: =$D$13*$D$15 | E22: =D22-C22 | G22: =I21 | H22: =E22 | I22: =G22+H22
B23: August | C23: =($D$13*$D$14)+$D$16 | D23: =$D$13*$D$15 | E23: =D23-C23 | G23: =I22 | H23: =E23 | I23: =G23+H23
B24: September | C24: =($D$13*$D$14)+$D$16 | D24: =$D$13*$D$15 | E24: =D24-C24 | G24: =I23 | H24: =E24 | I24: =G24+H24
B25: October | C25: =($D$13*$D$14)+$D$16 | D25: =$D$13*$D$15 | E25: =D25-C25 | G25: =I24 | H25: =E25 | I25: =G25+H25
B26: November | C26: =($D$13*$D$14)+$D$16 | D26: =$D$13*$D$15 | E26: =D26-C26 | G26: =I25 | H26: =E26 | I26: =G26+H26
B27: December | C27: =($D$13*$D$14)+$D$16 | D27: =$D$13*$D$15 | E27: =D27-C27 | G27: =I26 | H27: =E27 | I27: =G27+H27
B28: January | C28: =($D$13*$D$14)+$D$16 | D28: =$D$13*$D$15 | E28: =D28-C28 | G28: =I27 | H28: =E28 | I28: =G28+H28
B29: February | C29: =($D$13*$D$14)+$D$16 | D29: =$D$13*$D$15 | E29: =D29-C29 | G29: =I28 | H29: =E29 | I29: =G29+H29
B30: March | C30: =($D$13*$D$14)+$D$16 | D30: =$D$13*$D$15 | E30: =D30-C30 | G30: =I29 | H30: =E30 | I30: =G30+H30
C31: =SUM(C19:C30) | D31: =SUM(D19:D30) | E31: =D31-C31
B33: Buffer Capital (Production Cost of 2.5 Months) | D33: =C19*2.5
B35: Total Yearly Turnover | D35: =D31
B36: Initial Working Capital | D36: =C19+D33 | E36: * Working Capital Required=Cash outflow for the first month + Contingency fund
B37: Working Capital Rotation | D37: =D35/D36
B40: LACTATION POWDER
B42: Monthly Boxes Produced (in Units) | D42: ='Contract (1 yr)'!C26/12
B43: Cost/Box (in ₹) | D43: ='Total Production'!D9
B44: Revenue/Box (in ₹) | D44: ='Total Production'!C21
B45: Monthly Indirect Expense (in ₹) | D45: =D16
G46: * The working capital that we are investing in the first month is derived from the cash outflow that is required in the first month
B47: Month | C47: Cash Outflow | D47: Cash Inflow | E47: Difference (CO-CI) | G47: Opening W.C. | H47: Net Cash Flow | I47: Closing W.C.
B48: April | C48: =($D$42*$D$43)+$D$45 | D48: =$D$42*$D$44 | E48: =D48-C48 | G48: =C48+D62 | H48: =E48 | I48: =G48+H48
B49: May | C49: =($D$42*$D$43)+$D$45 | D49: =$D$42*$D$44 | E49: =D49-C49 | G49: =I48 | H49: =E49 | I49: =G49+H49
B50: June | C50: =($D$42*$D$43)+$D$45 | D50: =$D$42*$D$44 | E50: =D50-C50 | G50: =I49 | H50: =E50 | I50: =G50+H50
B51: July | C51: =($D$42*$D$43)+$D$45 | D51: =$D$42*$D$44 | E51: =D51-C51 | G51: =I50 | H51: =E51 | I51: =G51+H51
B52: August | C52: =($D$42*$D$43)+$D$45 | D52: =$D$42*$D$44 | E52: =D52-C52 | G52: =I51 | H52: =E52 | I52: =G52+H52
B53: September | C53: =($D$42*$D$43)+$D$45 | D53: =$D$42*$D$44 | E53: =D53-C53 | G53: =I52 | H53: =E53 | I53: =G53+H53
B54: October | C54: =($D$42*$D$43)+$D$45 | D54: =$D$42*$D$44 | E54: =D54-C54 | G54: =I53 | H54: =E54 | I54: =G54+H54
B55: November | C55: =($D$42*$D$43)+$D$45 | D55: =$D$42*$D$44 | E55: =D55-C55 | G55: =I54 | H55: =E55 | I55: =G55+H55
B56: December | C56: =($D$42*$D$43)+$D$45 | D56: =$D$42*$D$44 | E56: =D56-C56 | G56: =I55 | H56: =E56 | I56: =G56+H56
B57: January | C57: =($D$42*$D$43)+$D$45 | D57: =$D$42*$D$44 | E57: =D57-C57 | G57: =I56 | H57: =E57 | I57: =G57+H57
B58: February | C58: =($D$42*$D$43)+$D$45 | D58: =$D$42*$D$44 | E58: =D58-C58 | G58: =I57 | H58: =E58 | I58: =G58+H58
B59: March | C59: =($D$42*$D$43)+$D$45 | D59: =$D$42*$D$44 | E59: =D59-C59 | G59: =I58 | H59: =E59 | I59: =G59+H59
C60: =SUM(C48:C59) | D60: =SUM(D48:D59) | E60: =D60-C60
B62: Buffer Capital (Production Cost of 2.5 Months) | D62: =C48*2.5
B64: Total Yearly Turnover | D64: =D60
B65: Initial Working Capital | D65: =C48+D62 | E65: * Working Capital Required=Cash outflow for the first month + Contingency fund
B66: Working Capital Rotation | D66: =D64/D65
B69: INFANT POWDER
B71: Monthly Boxes Produced (in Units) | D71: ='Contract (1 yr)'!C23/12
B72: Cost/Box (in ₹) | D72: ='Total Production'!E9
B73: Revenue/Box (in ₹) | D73: ='Total Production'!C22
B74: Monthly Indirect Expense (in ₹) | D74: =D45
G75: * The working capital that we are investing in the first month is derived from the cash outflow that is required in the first month
B76: Month | C76: Cash Outflow | D76: Cash Inflow | E76: Difference (CO-CI) | G76: Opening W.C. | H76: Net Cash Flow | I76: Closing W.C.
B77: April | C77: =($D$71*$D$72)+$D$74 | D77: =$D$71*$D$73 | E77: =D77-C77 | G77: =C77+D91 | H77: =E77 | I77: =G77+H77
B78: May | C78: =($D$71*$D$72)+$D$74 | D78: =$D$71*$D$73 | E78: =D78-C78 | G78: =I77 | H78: =E78 | I78: =G78+H78
B79: June | C79: =($D$71*$D$72)+$D$74 | D79: =$D$71*$D$73 | E79: =D79-C79 | G79: =I78 | H79: =E79 | I79: =G79+H79
B80: July | C80: =($D$71*$D$72)+$D$74 | D80: =$D$71*$D$73 | E80: =D80-C80 | G80: =I79 | H80: =E80 | I80: =G80+H80
B81: August | C81: =($D$71*$D$72)+$D$74 | D81: =$D$71*$D$73 | E81: =D81-C81 | G81: =I80 | H81: =E81 | I81: =G81+H81
B82: September | C82: =($D$71*$D$72)+$D$74 | D82: =$D$71*$D$73 | E82: =D82-C82 | G82: =I81 | H82: =E82 | I82: =G82+H82
B83: October | C83: =($D$71*$D$72)+$D$74 | D83: =$D$71*$D$73 | E83: =D83-C83 | G83: =I82 | H83: =E83 | I83: =G83+H83
B84: November | C84: =($D$71*$D$72)+$D$74 | D84: =$D$71*$D$73 | E84: =D84-C84 | G84: =I83 | H84: =E84 | I84: =G84+H84
B85: December | C85: =($D$71*$D$72)+$D$74 | D85: =$D$71*$D$73 | E85: =D85-C85 | G85: =I84 | H85: =E85 | I85: =G85+H85
B86: January | C86: =($D$71*$D$72)+$D$74 | D86: =$D$71*$D$73 | E86: =D86-C86 | G86: =I85 | H86: =E86 | I86: =G86+H86
B87: February | C87: =($D$71*$D$72)+$D$74 | D87: =$D$71*$D$73 | E87: =D87-C87 | G87: =I86 | H87: =E87 | I87: =G87+H87
B88: March | C88: =($D$71*$D$72)+$D$74 | D88: =$D$71*$D$73 | E88: =D88-C88 | G88: =I87 | H88: =E88 | I88: =G88+H88
C89: =SUM(C77:C88) | D89: =SUM(D77:D88) | E89: =D89-C89
B91: Buffer Capital (Production Cost of 2.5 Months) | D91: =C77*2.5
B93: Total Yearly Turnover | D93: =D89
B94: Initial Working Capital | D94: =C77+D91 | E94: * Working Capital Required=Cash outflow for the first month + Contingency fund
B95: Working Capital Rotation | D95: =D93/D94
B98: CHILDREN POWDER
B100: Monthly Boxes Produced (in Units) | D100: ='Contract (1 yr)'!C24/12
B101: Cost/Box (in ₹) | D101: ='Total Production'!F9
B102: Revenue/Box (in ₹) | D102: ='Total Production'!C23
B103: Monthly Indirect Expense (in ₹) | D103: =D74
G104: * The working capital that we are investing in the first month is derived from the cash outflow that is required in the first month
B105: Month | C105: Cash Outflow | D105: Cash Inflow | E105: Difference (CO-CI) | G105: Opening W.C. | H105: Net Cash Flow | I105: Closing W.C.
B106: April | C106: =($D$100*$D$101)+$D$103 | D106: =$D$100*$D$102 | E106: =D106-C106 | G106: =C106+D120 | H106: =E106 | I106: =G106+H106
B107: May | C107: =($D$100*$D$101)+$D$103 | D107: =$D$100*$D$102 | E107: =D107-C107 | G107: =I106 | H107: =E107 | I107: =G107+H107
B108: June | C108: =($D$100*$D$101)+$D$103 | D108: =$D$100*$D$102 | E108: =D108-C108 | G108: =I107 | H108: =E108 | I108: =G108+H108
B109: July | C109: =($D$100*$D$101)+$D$103 | D109: =$D$100*$D$102 | E109: =D109-C109 | G109: =I108 | H109: =E109 | I109: =G109+H109
B110: August | C110: =($D$100*$D$101)+$D$103 | D110: =$D$100*$D$102 | E110: =D110-C110 | G110: =I109 | H110: =E110 | I110: =G110+H110
B111: September | C111: =($D$100*$D$101)+$D$103 | D111: =$D$100*$D$102 | E111: =D111-C111 | G111: =I110 | H111: =E111 | I111: =G111+H111
B112: October | C112: =($D$100*$D$101)+$D$103 | D112: =$D$100*$D$102 | E112: =D112-C112 | G112: =I111 | H112: =E112 | I112: =G112+H112
B113: November | C113: =($D$100*$D$101)+$D$103 | D113: =$D$100*$D$102 | E113: =D113-C113 | G113: =I112 | H113: =E113 | I113: =G113+H113
B114: December | C114: =($D$100*$D$101)+$D$103 | D114: =$D$100*$D$102 | E114: =D114-C114 | G114: =I113 | H114: =E114 | I114: =G114+H114
B115: January | C115: =($D$100*$D$101)+$D$103 | D115: =$D$100*$D$102 | E115: =D115-C115 | G115: =I114 | H115: =E115 | I115: =G115+H115
B116: February | C116: =($D$100*$D$101)+$D$103 | D116: =$D$100*$D$102 | E116: =D116-C116 | G116: =I115 | H116: =E116 | I116: =G116+H116
B117: March | C117: =($D$100*$D$101)+$D$103 | D117: =$D$100*$D$102 | E117: =D117-C117 | G117: =I116 | H117: =E117 | I117: =G117+H117
C118: =SUM(C106:C117) | D118: =SUM(D106:D117) | E118: =D118-C118
...

Sheet WC (Year 2)
B2: TOTAL WORKING CAPITAL
C4: Revenue | D4: Initial Working Capital | E4: W.C.Rotation
B5: PP (Tier 1) | C5: =D42 | D5: =D43 | E5: =C5/D5
B6: PP (Tier 3) | C6: =D73 | D6: =D74 | E6: =C6/D6
B7: LP (Tier 1) | C7: =D104 | D7: =D105 | E7: =C7/D7
B8: LP (Tier 3) | C8: =D135 | D8: =D136 | E8: =C8/D8
B9: INP (Tier 1) | C9: =D166 | D9: =D167 | E9: =C9/D9
B10: INP (Tier 3) | C10: =D197 | D10: =D198 | E10: =C10/D10
B11: CNP (Tier 1) | C11: =D228 | D11: =D229 | E11: =C11/D11
B12: CNP (Tier 3) | C12: =D259 | D12: =D260 | E12: =C12/D12
D13: =sum(D5:D12)
B15: PREGNANCY POWDER: TIER 1
B17: Monthly Inhouse Boxes Produced (in Units) | D17: ='In-house (2-5yrs)'!D70/12
B18: Monthly Contract Boxes Produced (in Units) | D18: ='Third Party (2-5yrs)'!D42/12
B19: Cost/Box for Inhouse Mfg (in ₹) | D19: ='In-house (2-5yrs)'!E91
B20: Cost/Box for Contractual Mfg (in ₹) | D20: ='Third Party (2-5yrs)'!D63
B21: Revenue/Box for Inhouse Mfg (in ₹) | D21: ='In-house (2-5yrs)'!D91
B22: Revenue/Box for Contractual Mfg (in ₹) | D22: ='Third Party (2-5yrs)'!C63
B23: Monthly Indirect Expense (in ₹) | D23: =((('Indirect Expenses'!$F$63/12)/4)*105%)*10^7
G24: * The working capital that we are investing in the first month is derived from the cash outflow that is required in the first month
B25: Month | C25: Cash Outflow | D25: Cash Inflow | E25: Difference (CO-CI) | G25: Opening W.C. | H25: Net Cash Flow | I25: Closing W.C.
B26: April | C26: =(D$17*D$19)+($D$18*$D$20)+D$23 | D26: =($D$17*$D$21)+($D$18*$D$22) | E26: =D26-C26 | G26: =C26+D40 | H26: =E26 | I26: =G26+H26
B27: May | C27: =(D$17*D$19)+($D$18*$D$20)+D$23 | D27: =($D$17*$D$21)+($D$18*$D$22) | E27: =D27-C27 | G27: =I26 | H27: =E27 | I27: =G27+H27
B28: June | C28: =(D$17*D$19)+($D$18*$D$20)+D$23 | D28: =($D$17*$D$21)+($D$18*$D$22) | E28: =D28-C28 | G28: =I27 | H28: =E28 | I28: =G28+H28
B29: July | C29: =(D$17*D$19)+($D$18*$D$20)+D$23 | D29: =($D$17*$D$21)+($D$18*$D$22) | E29: =D29-C29 | G29: =I28 | H29: =E29 | I29: =G29+H29
B30: August | C30: =(D$17*D$19)+($D$18*$D$20)+D$23 | D30: =($D$17*$D$21)+($D$18*$D$22) | E30: =D30-C30 | G30: =I29 | H30: =E30 | I30: =G30+H30
B31: September | C31: =(D$17*D$19)+($D$18*$D$20)+D$23 | D31: =($D$17*$D$21)+($D$18*$D$22) | E31: =D31-C31 | G31: =I30 | H31: =E31 | I31: =G31+H31
B32: October | C32: =(D$17*D$19)+($D$18*$D$20)+D$23 | D32: =($D$17*$D$21)+($D$18*$D$22) | E32: =D32-C32 | G32: =I31 | H32: =E32 | I32: =G32+H32
B33: November | C33: =(D$17*D$19)+($D$18*$D$20)+D$23 | D33: =($D$17*$D$21)+($D$18*$D$22) | E33: =D33-C33 | G33: =I32 | H33: =E33 | I33: =G33+H33
B34: December | C34: =(D$17*D$19)+($D$18*$D$20)+D$23 | D34: =($D$17*$D$21)+($D$18*$D$22) | E34: =D34-C34 | G34: =I33 | H34: =E34 | I34: =G34+H34
B35: January | C35: =(D$17*D$19)+($D$18*$D$20)+D$23 | D35: =($D$17*$D$21)+($D$18*$D$22) | E35: =D35-C35 | G35: =I34 | H35: =E35 | I35: =G35+H35
B36: February | C36: =(D$17*D$19)+($D$18*$D$20)+D$23 | D36: =($D$17*$D$21)+($D$18*$D$22) | E36: =D36-C36 | G36: =I35 | H36: =E36 | I36: =G36+H36
B37: March | C37: =(D$17*D$19)+($D$18*$D$20)+D$23 | D37: =($D$17*$D$21)+($D$18*$D$22) | E37: =D37-C37 | G37: =I36 | H37: =E37 | I37: =G37+H37
C38: =SUM(C26:C37) | D38: =SUM(D26:D37) | E38: =D38-C38
B40: Buffer Capital (Production Cost of 1.5 Month) | D40: =C26*1.5
B42: Total Yearly Turnover | D42: =D38
B43: Initial Working Capital | D43: =C26+D40 | E43: * Working Capital Required=Cash outflow for the first month + Contingency fund
B44: Working Capital Rotation | D44: =D42/D43
B46: PREGNANCY POWDER: TIER 3
B48: Monthly Inhouse Boxes Produced (in Units) | D48: ='In-house (2-5yrs)'!D72/12
B49: Monthly Contract Boxes Produced (in Units) | D49: ='Third Party (2-5yrs)'!D44/12
B50: Cost/Box for Inhouse Mfg (in ₹) | D50: ='In-house (2-5yrs)'!E93
B51: Cost/Box for Contractual Mfg (in ₹) | D51: ='Third Party (2-5yrs)'!D65
B52: Revenue/Box for Inhouse Mfg (in ₹) | D52: ='In-house (2-5yrs)'!D93
B53: Revenue/Box for Contractual Mfg (in ₹) | D53: ='Third Party (2-5yrs)'!C65
B54: Monthly Indirect Expense (in ₹) | D54: =((('Indirect Expenses'!H63/12)/4)*105%)*10^7
G55: * The working capital that we are investing in the first month is derived from the cash outflow that is required in the first month
B56: Month | C56: Cash Outflow | D56: Cash Inflow | E56: Difference (CO-CI) | G56: Opening W.C. | H56: Net Cash Flow | I56: Closing W.C.
B57: April | C57: =($D$48*$D$50)+$D$54+($D$49*$D$51) | D57: =($D$48*$D$52)+($D$49*$D$53) | E57: =D57-C57 | G57: =C57+D71 | H57: =E57 | I57: =G57+H57
B58: May | C58: =($D$48*$D$50)+$D$54+($D$49*$D$51) | D58: =($D$48*$D$52)+($D$49*$D$53) | E58: =D58-C58 | G58: =I57 | H58: =E58 | I58: =G58+H58
B59: June | C59: =($D$48*$D$50)+$D$54+($D$49*$D$51) | D59: =($D$48*$D$52)+($D$49*$D$53) | E59: =D59-C59 | G59: =I58 | H59: =E59 | I59: =G59+H59
B60: July | C60: =($D$48*$D$50)+$D$54+($D$49*$D$51) | D60: =($D$48*$D$52)+($D$49*$D$53) | E60: =D60-C60 | G60: =I59 | H60: =E60 | I60: =G60+H60
B61: August | C61: =($D$48*$D$50)+$D$54+($D$49*$D$51) | D61: =($D$48*$D$52)+($D$49*$D$53) | E61: =D61-C61 | G61: =I60 | H61: =E61 | I61: =G61+H61
B62: September | C62: =($D$48*$D$50)+$D$54+($D$49*$D$51) | D62: =($D$48*$D$52)+($D$49*$D$53) | E62: =D62-C62 | G62: =I61 | H62: =E62 | I62: =G62+H62
B63: October | C63: =($D$48*$D$50)+$D$54+($D$49*$D$51) | D63: =($D$48*$D$52)+($D$49*$D$53) | E63: =D63-C63 | G63: =I62 | H63: =E63 | I63: =G63+H63
B64: November | C64: =($D$48*$D$50)+$D$54+($D$49*$D$51) | D64: =($D$48*$D$52)+($D$49*$D$53) | E64: =D64-C64 | G64: =I63 | H64: =E64 | I64: =G64+H64
B65: December | C65: =($D$48*$D$50)+$D$54+($D$49*$D$51) | D65: =($D$48*$D$52)+($D$49*$D$53) | E65: =D65-C65 | G65: =I64 | H65: =E65 | I65: =G65+H65
B66: January | C66: =($D$48*$D$50)+$D$54+($D$49*$D$51) | D66: =($D$48*$D$52)+($D$49*$D$53) | E66: =D66-C66 | G66: =I65 | H66: =E66 | I66: =G66+H66
B67: February | C67: =($D$48*$D$50)+$D$54+($D$49*$D$51) | D67: =($D$48*$D$52)+($D$49*$D$53) | E67: =D67-C67 | G67: =I66 | H67: =E67 | I67: =G67+H67
B68: March | C68: =($D$48*$D$50)+$D$54+($D$49*$D$51) | D68: =($D$48*$D$52)+($D$49*$D$53) | E68: =D68-C68 | G68: =I67 | H68: =E68 | I68: =G68+H68
C69: =SUM(C57:C68) | D69: =SUM(D57:D68) | E69: =D69-C69
B71: Buffer Capital (Production Cost of 1.5 Month) | D71: =C57*1.5
B73: Total Yearly Turnover | D73: =D69
B74: Initial Working Capital | D74: =C57+D71 | E74: * Working Capital Required=Cash outflow for the first month + Contingency fund
B75: Working Capital Rotation | D75: =D73/D74
B77: LACTATION POWDER: TIER 1
B79: Monthly Inhouse Boxes Produced (in Units) | D79: ='In-house (2-5yrs)'!D75/12
B80: Monthly Contract Boxes Produced (in Units) | D80: ='Third Party (2-5yrs)'!D47/12
B81: Cost/Box for Inhouse Mfg (in ₹) | D81: ='In-house (2-5yrs)'!E94
B82: Cost/Box for Contractual Mfg (in ₹) | D82: ='Third Party (2-5yrs)'!D66
B83: Revenue/Box for Inhouse Mfg (in ₹) | D83: ='In-house (2-5yrs)'!D94
B84: Revenue/Box for Contractual Mfg (in ₹) | D84: ='Third Party (2-5yrs)'!C66
B85: Monthly Indirect Expense (in ₹) | D85: =D23
G86: * The working capital that we are investing in the first month is derived from the cash outflow that is required in the first month
B87: Month | C87: Cash Outflow | D87: Cash Inflow | E87: Difference (CO-CI) | G87: Opening W.C. | H87: Net Cash Flow | I87: Closing W.C.
B88: April | C88: =($D$79*$D$81)+$D$85+($D$80*$D$82) | D88: =($D$79*$D$83)+($D$80*$D$84) | E88: =D88-C88 | G88: =C88+D102 | H88: =E88 | I88: =G88+H88
B89: May | C89: =($D$79*$D$81)+$D$85+($D$80*$D$82) | D89: =($D$79*$D$83)+($D$80*$D$84) | E89: =D89-C89 | G89: =I88 | H89: =E89 | I89: =G89+H89
B90: June | C90: =($D$79*$D$81)+$D$85+($D$80*$D$82) | D90: =($D$79*$D$83)+($D$80*$D$84) | E90: =D90-C90 | G90: =I89 | H90: =E90 | I90: =G90+H90
B91: July | C91: =($D$79*$D$81)+$D$85+($D$80*$D$82) | D91: =($D$79*$D$83)+($D$80*$D$84) | E91: =D91-C91 | G91: =I90 | H91: =E91 | I91: =G91+H91
B92: August | C92: =($D$79*$D$81)+$D$85+($D$80*$D$82) | D92: =($D$79*$D$83)+($D$80*$D$84) | E92: =D92-C92 | G92: =I91 | H92: =E92 | I92: =G92+H92
B93: September | C93: =($D$79*$D$81)+$D$85+($D$80*$D$82) | D93: =($D$79*$D$83)+($D$80*$D$84) | E93: =D93-C93 | G93: =I92 | H93: =E93 | I93: =G93+H93
B94: October | C94: =($D$79*$D$81)+$D$85+($D$80*$D$82) | D94: =($D$79*$D$83)+($D$80*$D$84) | E94: =D94-C94 | G94: =I93 | H94: =E94 | I94: =G94+H94
B95: November | C95: =($D$79*$D$81)+$D$85+($D$80*$D$82) | D95: =($D$79*$D$83)+($D$80*$D$84) | E95: =D95-C95 | G95: =I94 | H95: =E95 | I95: =G95+H95
B96: December | C96: =($D$79*$D$81)+$D$85+($D$80*$D$82) | D96: =($D$79*$D$83)+($D$80*$D$84) | E96: =D96-C96 | G96: =I95 | H96: =E96 | I96: =G96+H96
B97: January | C97: =($D$79*$D$81)+$D$85+($D$80*$D$82) | D97: =($D$79*$D$83)+($D$80*$D$84) | E97: =D97-C97 | G97: =I96 | H97: =E97 | I97: =G97+H97
B98: February | C98: =($D$79*$D$81)+$D$85+($D$80*$D$82) | D98: =($D$79*$D$83)+($D$80*$D$84) | E98: =D98-C98 | G98: =I97 | H98: =E98 | I98: =G98+H98
B99: March | C99: =($D$79*$D$81)+$D$85+($D$80*$D$82) | D99: =($D$79*$D$83)+($D$80*$D$84) | E99: =D99-C99 | G99: =I98 | H99: =E99 | I99: =G99+H99
C100: =SUM(C88:C99) | D100: =SUM(D88:D99) | E100: =D100-C100
B102: Buffer Capital (Production Cost of 1.5 Month) | D102: =C88*1.5
B104: Total Yearly Turnover | D104: =D100
B105: Initial Working Capital | D105: =C88+D102 | E105: * Working Capital Required=Cash outflow for the first month + Contingency fund
B106: Working Capital Rotation | D106: =D104/D105
B108: LACTATION POWDER: TIER 3
B110: Monthly Inhouse Boxes Produced (in Units) | D110: ='In-house (2-5yrs)'!D77/12
B111: Monthly Contract Boxes Produced (in Units) | D111: ='Third Party (2-5yrs)'!D49/12
B112: Cost/Box for Inhouse Mfg (in ₹) | D112: ='In-house (2-5yrs)'!E99
B113: Cost/Box for Contractual Mfg (in ₹) | D113: ='Third Party (2-5yrs)'!D68
B114: Revenue/Box for Inhouse Mfg (in ₹) | D114: ='In-house (2-5yrs)'!D99
B115: Revenue/Box for Contractual Mfg (in ₹) | D115: ='Third Party (2-5yrs)'!C68
B116: Monthly Indirect Expense (in ₹) | D116: =D54
...

Sheet WC (Year 3-5)
B2: TOTAL WORKING CAPITAL
C4: Revenue | D4: Initial Working Capital | E4: W.C.Rotation
B5: PP (Tier 1) | C5: =D46 | D5: =D47 | E5: =C5/D5
B6: PP (Tier 2) | C6: =D77 | D6: =D78 | E6: =C6/D6
B7: PP (Tier 3) | C7: =D108 | D7: =D109 | E7: =C7/D7
B8: LP (Tier 1) | C8: =D139 | D8: =D140 | E8: =C8/D8
B9: LP (Tier 2) | C9: =D170 | D9: =D171 | E9: =C9/D9
B10: LP (Tier 3) | C10: =D201 | D10: =D202 | E10: =C10/D10
B11: INP (Tier 1) | C11: =D232 | D11: =D233 | E11: =C11/D11
B12: INP (Tier 2) | C12: =D263 | D12: =D264 | E12: =C12/D12
B13: INP (Tier 3) | C13: =D294 | D13: =D295 | E13: =C13/D13
B14: CNP (Tier 1) | C14: =D325 | D14: =D326 | E14: =C14/D14
B15: CNP (Tier 2) | C15: =D356 | D15: =D357 | E15: =C15/D15
B16: CNP (Tier 3) | C16: =D387 | D16: =D388 | E16: =C16/D16
D17: =sum(D5:D16)
B19: PREGNANCY POWDER: TIER 1
B21: Monthly Inhouse Boxes Produced (in Units) | D21: ='In-house (2-5yrs)'!E70/12
B22: Monthly Contract Boxes Produced (in Units) | D22: ='Third Party (2-5yrs)'!E42/12
B23: Cost/Box for Inhouse Mfg (in ₹) | D23: ='In-house (2-5yrs)'!E91
B24: Cost/Box for Contractual Mfg (in ₹) | D24: ='Third Party (2-5yrs)'!D63
B25: Revenue/Box for Inhouse Mfg (in ₹) | D25: ='In-house (2-5yrs)'!D91
B26: Revenue/Box for Contractual Mfg (in ₹) | D26: ='Third Party (2-5yrs)'!C63
B27: Monthly Indirect Expense (in ₹) | D27: =((('Indirect Expenses'!I63/4)/12/'In-house (2-5yrs)'!$D$5)*105%)*10^7
G28: * The working capital that we are investing in the first month is derived from the cash outflow that is required in the first month
B29: Month | C29: Cash Outflow | D29: Cash Inflow | E29: Difference (CO-CI) | G29: Opening W.C. | H29: Net Cash Flow | I29: Closing W.C.
B30: April | C30: =($D$21*$D$23)+$D$27+($D$22*$D$24) | D30: =($D$21*$D$25)+($D$22*$D$26) | E30: =D30-C30 | G30: =C30+D44 | H30: =E30 | I30: =G30+H30
B31: May | C31: =($D$21*$D$23)+$D$27+($D$22*$D$24) | D31: =($D$21*$D$25)+($D$22*$D$26) | E31: =D31-C31 | G31: =I30 | H31: =E31 | I31: =G31+H31
B32: June | C32: =($D$21*$D$23)+$D$27+($D$22*$D$24) | D32: =($D$21*$D$25)+($D$22*$D$26) | E32: =D32-C32 | G32: =I31 | H32: =E32 | I32: =G32+H32
B33: July | C33: =($D$21*$D$23)+$D$27+($D$22*$D$24) | D33: =($D$21*$D$25)+($D$22*$D$26) | E33: =D33-C33 | G33: =I32 | H33: =E33 | I33: =G33+H33
B34: August | C34: =($D$21*$D$23)+$D$27+($D$22*$D$24) | D34: =($D$21*$D$25)+($D$22*$D$26) | E34: =D34-C34 | G34: =I33 | H34: =E34 | I34: =G34+H34
B35: September | C35: =($D$21*$D$23)+$D$27+($D$22*$D$24) | D35: =($D$21*$D$25)+($D$22*$D$26) | E35: =D35-C35 | G35: =I34 | H35: =E35 | I35: =G35+H35
B36: October | C36: =($D$21*$D$23)+$D$27+($D$22*$D$24) | D36: =($D$21*$D$25)+($D$22*$D$26) | E36: =D36-C36 | G36: =I35 | H36: =E36 | I36: =G36+H36
B37: November | C37: =($D$21*$D$23)+$D$27+($D$22*$D$24) | D37: =($D$21*$D$25)+($D$22*$D$26) | E37: =D37-C37 | G37: =I36 | H37: =E37 | I37: =G37+H37
B38: December | C38: =($D$21*$D$23)+$D$27+($D$22*$D$24) | D38: =($D$21*$D$25)+($D$22*$D$26) | E38: =D38-C38 | G38: =I37 | H38: =E38 | I38: =G38+H38
B39: January | C39: =($D$21*$D$23)+$D$27+($D$22*$D$24) | D39: =($D$21*$D$25)+($D$22*$D$26) | E39: =D39-C39 | G39: =I38 | H39: =E39 | I39: =G39+H39
B40: February | C40: =($D$21*$D$23)+$D$27+($D$22*$D$24) | D40: =($D$21*$D$25)+($D$22*$D$26) | E40: =D40-C40 | G40: =I39 | H40: =E40 | I40: =G40+H40
B41: March | C41: =($D$21*$D$23)+$D$27+($D$22*$D$24) | D41: =($D$21*$D$25)+($D$22*$D$26) | E41: =D41-C41 | G41: =I40 | H41: =E41 | I41: =G41+H41
C42: =SUM(C30:C41) | D42: =SUM(D30:D41) | E42: =D42-C42
B44: Buffer Capital (Production Cost of 2 Month) | D44: =C30*2
B46: Total Yearly Turnover | D46: =D42
B47: Initial Working Capital | D47: =C30+D44 | E47: * Working Capital Required=Cash outflow for the first month + Contingency fund
B48: Working Capital Rotation | D48: =D46/D47
B50: PREGNANCY POWDER: TIER 2
B52: Monthly Inhouse Boxes Produced (in Units) | D52: ='In-house (2-5yrs)'!E71/12
B53: Monthly Contract Boxes Produced (in Units) | D53: ='Third Party (2-5yrs)'!E43/12
B54: Cost/Box for Inhouse Mfg (in ₹) | D54: ='In-house (2-5yrs)'!E92
B55: Cost/Box for Contractual Mfg (in ₹) | D55: ='Third Party (2-5yrs)'!D64
B56: Revenue/Box for Inhouse Mfg (in ₹) | D56: ='In-house (2-5yrs)'!D92
B57: Revenue/Box for Contractual Mfg (in ₹) | D57: ='Third Party (2-5yrs)'!C64
B58: Monthly Indirect Expense (in ₹) | D58: =((('Indirect Expenses'!J63/4)/12/'In-house (2-5yrs)'!$D$5)*105%)*10^7
G59: * The working capital that we are investing in the first month is derived from the cash outflow that is required in the first month
B60: Month | C60: Cash Outflow | D60: Cash Inflow | E60: Difference (CO-CI) | G60: Opening W.C. | H60: Net Cash Flow | I60: Closing W.C.
B61: April | C61: =($D$52*$D$54)+$D$58+($D$53*$D$55) | D61: =($D$52*$D$56)+($D$53*$D$57) | E61: =D61-C61 | G61: =C61+D75 | H61: =E61 | I61: =G61+H61
B62: May | C62: =($D$52*$D$54)+$D$58+($D$53*$D$55) | D62: =($D$52*$D$56)+($D$53*$D$57) | E62: =D62-C62 | G62: =I61 | H62: =E62 | I62: =G62+H62
B63: June | C63: =($D$52*$D$54)+$D$58+($D$53*$D$55) | D63: =($D$52*$D$56)+($D$53*$D$57) | E63: =D63-C63 | G63: =I62 | H63: =E63 | I63: =G63+H63
B64: July | C64: =($D$52*$D$54)+$D$58+($D$53*$D$55) | D64: =($D$52*$D$56)+($D$53*$D$57) | E64: =D64-C64 | G64: =I63 | H64: =E64 | I64: =G64+H64
B65: August | C65: =($D$52*$D$54)+$D$58+($D$53*$D$55) | D65: =($D$52*$D$56)+($D$53*$D$57) | E65: =D65-C65 | G65: =I64 | H65: =E65 | I65: =G65+H65
B66: September | C66: =($D$52*$D$54)+$D$58+($D$53*$D$55) | D66: =($D$52*$D$56)+($D$53*$D$57) | E66: =D66-C66 | G66: =I65 | H66: =E66 | I66: =G66+H66
B67: October | C67: =($D$52*$D$54)+$D$58+($D$53*$D$55) | D67: =($D$52*$D$56)+($D$53*$D$57) | E67: =D67-C67 | G67: =I66 | H67: =E67 | I67: =G67+H67
B68: November | C68: =($D$52*$D$54)+$D$58+($D$53*$D$55) | D68: =($D$52*$D$56)+($D$53*$D$57) | E68: =D68-C68 | G68: =I67 | H68: =E68 | I68: =G68+H68
B69: December | C69: =($D$52*$D$54)+$D$58+($D$53*$D$55) | D69: =($D$52*$D$56)+($D$53*$D$57) | E69: =D69-C69 | G69: =I68 | H69: =E69 | I69: =G69+H69
B70: January | C70: =($D$52*$D$54)+$D$58+($D$53*$D$55) | D70: =($D$52*$D$56)+($D$53*$D$57) | E70: =D70-C70 | G70: =I69 | H70: =E70 | I70: =G70+H70
B71: February | C71: =($D$52*$D$54)+$D$58+($D$53*$D$55) | D71: =($D$52*$D$56)+($D$53*$D$57) | E71: =D71-C71 | G71: =I70 | H71: =E71 | I71: =G71+H71
B72: March | C72: =($D$52*$D$54)+$D$58+($D$53*$D$55) | D72: =($D$52*$D$56)+($D$53*$D$57) | E72: =D72-C72 | G72: =I71 | H72: =E72 | I72: =G72+H72
C73: =SUM(C61:C72) | D73: =SUM(D61:D72) | E73: =D73-C73
B75: Buffer Capital (Production Cost of 2 Month) | D75: =C61*2
B77: Total Yearly Turnover | D77: =D73
B78: Initial Working Capital | D78: =C61+D75 | E78: * Working Capital Required=Cash outflow for the first month + Contingency fund
B79: Working Capital Rotation | D79: =D77/D78
B81: PREGNANCY POWDER: TIER 3
B83: Monthly Inhouse Boxes Produced (in Units) | D83: ='In-house (2-5yrs)'!E72/12
B84: Monthly Contract Boxes Produced (in Units) | D84: ='Third Party (2-5yrs)'!E44/12
B85: Cost/Box for Inhouse Mfg (in ₹) | D85: ='In-house (2-5yrs)'!E93
B86: Cost/Box for Contractual Mfg (in ₹) | D86: ='Third Party (2-5yrs)'!D65
B87: Revenue/Box for Inhouse Mfg (in ₹) | D87: ='In-house (2-5yrs)'!D93
B88: Revenue/Box for Contractual Mfg (in ₹) | D88: ='Third Party (2-5yrs)'!C65
B89: Monthly Indirect Expense (in ₹) | D89: =((('Indirect Expenses'!K63/4)/12/'In-house (2-5yrs)'!$D$5)*105%)*10^7
G90: * The working capital that we are investing in the first month is derived from the cash outflow that is required in the first month
B91: Month | C91: Cash Outflow | D91: Cash Inflow | E91: Difference (CO-CI) | G91: Opening W.C. | H91: Net Cash Flow | I91: Closing W.C.
B92: April | C92: =($D$83*$D$85)+$D$89+($D$84*$D$86) | D92: =($D$83*$D$87)+($D$84*$D$88) | E92: =D92-C92 | G92: =C92+D106 | H92: =E92 | I92: =G92+H92
B93: May | C93: =($D$83*$D$85)+$D$89+($D$84*$D$86) | D93: =($D$83*$D$87)+($D$84*$D$88) | E93: =D93-C93 | G93: =I92 | H93: =E93 | I93: =G93+H93
B94: June | C94: =($D$83*$D$85)+$D$89+($D$84*$D$86) | D94: =($D$83*$D$87)+($D$84*$D$88) | E94: =D94-C94 | G94: =I93 | H94: =E94 | I94: =G94+H94
B95: July | C95: =($D$83*$D$85)+$D$89+($D$84*$D$86) | D95: =($D$83*$D$87)+($D$84*$D$88) | E95: =D95-C95 | G95: =I94 | H95: =E95 | I95: =G95+H95
B96: August | C96: =($D$83*$D$85)+$D$89+($D$84*$D$86) | D96: =($D$83*$D$87)+($D$84*$D$88) | E96: =D96-C96 | G96: =I95 | H96: =E96 | I96: =G96+H96
B97: September | C97: =($D$83*$D$85)+$D$89+($D$84*$D$86) | D97: =($D$83*$D$87)+($D$84*$D$88) | E97: =D97-C97 | G97: =I96 | H97: =E97 | I97: =G97+H97
B98: October | C98: =($D$83*$D$85)+$D$89+($D$84*$D$86) | D98: =($D$83*$D$87)+($D$84*$D$88) | E98: =D98-C98 | G98: =I97 | H98: =E98 | I98: =G98+H98
B99: November | C99: =($D$83*$D$85)+$D$89+($D$84*$D$86) | D99: =($D$83*$D$87)+($D$84*$D$88) | E99: =D99-C99 | G99: =I98 | H99: =E99 | I99: =G99+H99
B100: December | C100: =($D$83*$D$85)+$D$89+($D$84*$D$86) | D100: =($D$83*$D$87)+($D$84*$D$88) | E100: =D100-C100 | G100: =I99 | H100: =E100 | I100: =G100+H100
B101: January | C101: =($D$83*$D$85)+$D$89+($D$84*$D$86) | D101: =($D$83*$D$87)+($D$84*$D$88) | E101: =D101-C101 | G101: =I100 | H101: =E101 | I101: =G101+H101
B102: February | C102: =($D$83*$D$85)+$D$89+($D$84*$D$86) | D102: =($D$83*$D$87)+($D$84*$D$88) | E102: =D102-C102 | G102: =I101 | H102: =E102 | I102: =G102+H102
B103: March | C103: =($D$83*$D$85)+$D$89+($D$84*$D$86) | D103: =($D$83*$D$87)+($D$84*$D$88) | E103: =D103-C103 | G103: =I102 | H103: =E103 | I103: =G103+H103
C104: =SUM(C92:C103) | D104: =SUM(D92:D103) | E104: =D104-C104
B106: Buffer Capital (Production Cost of 2 Month) | D106: =C92*2
B108: Total Yearly Turnover | D108: =D104
B109: Initial Working Capital | D109: =C92+D106 | E109: * Working Capital Required=Cash outflow for the first month + Contingency fund
B110: Working Capital Rotation | D110: =D108/D109
B112: LACTATION POWDER: TIER 1
B114: Monthly Inhouse Boxes Produced (in Units) | D114: ='In-house (2-5yrs)'!E75/12
B115: Monthly Contract Boxes Produced (in Units) | D115: ='Third Party (2-5yrs)'!E47/12
B116: Cost/Box for Inhouse Mfg (in ₹) | D116: ='In-house (2-5yrs)'!E94
...

Sheet Capex & Depreciation
B2: Year | C2: New Plants Set Up | D2: Land & Construction (in Cr) | E2: Machinery (in Cr) | F2: Miscellaneous & Contingency Fund (in Cr) | G2: Total CAPEX (in Cr)
B3: 1 | C3: ='In-house (2-5yrs)'!C3 | D3: =C3*$C$11 | E3: =($C$26-$C$11-$C$24-$C$25)*C3 | F3: =($C$24+$C$25)*C3 | G3: =sum(D3:F3)
B4: 2 | C4: ='In-house (2-5yrs)'!C4 | D4: =C4*$C$11 | E4: =($C$26-$C$11-$C$24-$C$25)*C4 | F4: =($C$24+$C$25)*C4 | G4: =sum(D4:F4)
B5: 3 | C5: ='In-house (2-5yrs)'!C5 | D5: =C5*$C$11 | E5: =($C$26-$C$11-$C$24-$C$25)*C5 | F5: =($C$24+$C$25)*C5 | G5: =sum(D5:F5)
B6: 4 | C6: ='In-house (2-5yrs)'!C6 | D6: =C6*$C$11 | E6: =($C$26-$C$11-$C$24-$C$25)*C6 | F6: =($C$24+$C$25)*C6 | G6: =sum(D6:F6)
B7: 5 | C7: ='In-house (2-5yrs)'!C7 | D7: =C7*$C$11 | E7: =($C$26-$C$11-$C$24-$C$25)*C7 | F7: =($C$24+$C$25)*C7 | G7: =sum(D7:F7)
B8: Total | C8: =SUM(C3:C7) | D8: =SUM(D3:D7) | E8: =SUM(E3:E7) | F8: =SUM(F3:F7) | G8: =sum(G3:G7)
B10: Cost of Project | C10: Cost (in Cr)
B11: Land and Plant Building | C11: =C35
B12: Utilities (Power, Tanks etc.) | C12: =0.13*2
B13: FBD (Fluid Bed Dryer) | C13: =0.5*118%
B14: Precision Octagonal Blending | C14: =0.25*118%
B15: Compressor Unit | C15: =0.05*2
B16: HVAC | C16: =0.5*2
B17: Vibro Sifter | C17: =0.15*118%
B18: Multi-mill Crusher | C18: =0.05*118%
B19: Vertical Form Filling Sachets | C19: =0.24*2
B20: Packaging Conveyor Unit | C20: =0.0108*2
B21: Sanitization Machine | C21: =0.03*2
B22: Laboratories and Accessories | C22: =0.25*2
B23: Tray Dryer | C23: =0.12*2
B24: Miscellaneous Expense | C24: =sum(C11:C23)*0.1
B25: Contingency Expenses | C25: 10
B26: Total | C26: =SUM(C11:C25) | D26: * Can go upto 16cr
B28: LAND REQUIRED
B29: Land Area (sq ft) | C29: =43560*3 | D29: *43560 sq ft = 1 acre
B30: Constructible (70%) | C30: =C29*0.7
B31: Rate per sq ft | C31: 120
B32: Land Aquisition Cost (in Cr) | C32: =(C29*C31)/10000000
B33: Shed Construction Cost (per sq ft) | C33: 800
B34: Total Shed Cost (in Cr) | C34: =(C33*C30)/10000000
B35: Final Land Cost (with shed) (in Cr) | C35: =C32+C34
B37: DEPRICIATION
B38: Year | C38: Machinery (in Cr) | D38: Cumulative Cost (in Cr) | E38: Depreciation p.a (in Cr) | F38: * Assuming life of machine as 7 years
B39: FY 27-28 | C39: =E3 | D39: =C39 | E39: =D39*15%
B40: FY 28-29 | C40: =E4 | D40: =D39+C40 | E40: =D40*15%
B41: FY 29-30 | C41: =E5 | D41: =D40+C41 | E41: =D41*15%
B42: FY 30-31 | C42: =E6 | D42: =D41+C42 | E42: =D42*15%
B43: FY 31-32 | C43: =E7 | D43: =D42+C43 | E43: =D43*15%

Sheet Project Financing
B2: Year | C2: In-house Plants Set Up | E2: W.C. | F2: Capital Requirement | N2: Amnt (in Cr)
C3: New Plants | D3: Total Plants | E3: In-house | F3: W.C. | G3: Capex | H3: Total | J3: Fixed Asset | N3: ='Capex & Depreciation'!$C$26
B4: 1 | C4: ='Capex & Depreciation'!C3 | D4: =C4 | E4: =N4 | F4: =E4 | G4: =$N$3*C4 | H4: =G4+F4 | J4: Working Capital (Year 1) | N4: ='WC (Year 1)'!D9/10^7
B5: 2 | C5: ='Capex & Depreciation'!C4 | D5: =D4+C5 | E5: =C5*(N5-E4) | F5: =E5 | G5: =$N$3*C5 | H5: =G5+F5 | J5: Working Capital (Year 2) | N5: ='WC (Year 2)'!D13/10^7 | O5: * Additional Capital Added Only
B6: 3 | C6: ='Capex & Depreciation'!C5 | D6: =D5+C6 | E6: =($N$6*C6)+(D5*(N6-N5)) | F6: =E6 | G6: =$N$3*C6 | H6: =G6+F6 | J6: Working Capital (Year 3-5) | N6: ='WC (Year 3-5)'!D17/10^7
B7: 4 | C7: ='Capex & Depreciation'!C6 | D7: =D6+C7 | E7: =$N$6*C7 | F7: =E7 | G7: =$N$3*C7 | H7: =G7+F7
B8: 5 | C8: ='Capex & Depreciation'!C7 | D8: =D7+C8 | E8: =$N$6*C8 | F8: =E8 | G8: =$N$3*C8 | H8: =G8+F8
H9: =sum(H4:H8)
B11: Year | C11: Capex (Year 1-3) | E11: Capex (Year 4-5) | G11: Working Capital (Year 1-3) | I11: Working Capital (Year 4-5) | K11: Total | N11: Retained Earnings | O11: Capital Funded | R11: Surplus Retained Earnings | S11: Fixed Deposits | T11: Cumulative Fixed Deposit | U11: Interest Income | V11: Free Cash Flow
C12: Own Funds (VNLS) | D12: Fund Raising | E12: Own Funds (VNLS) | F12: Debt | G12: Own Funds (VNLS) | H12: Fund Raising | I12: Own Funds (VNLS) | J12: Debt | K12: VNLS | L12: Fund Raising | M12: Debt | O12: Funding Required | P12: Surplus Capital | Q12: Total
C13: 0.15 | D13: 0.85 | E13: 0.25 | F13: 0.75 | I13: 0.1 | J13: 0.9 | S13: 0.25 | U13: 0.06
B14: 1 | C14: =$G$4*C13 | D14: =$G$4*D13 | E14: - | F14: - | G14: =if(O14>H14,0,H14-O14) | H14: =F4 | I14: - | J14: - | K14: =C14+G14 | L14: =D14+H14 | M14: - | N14: 0 | O14: 22 | Q14: =sum(O14:P14) | R14: 0 | S14: =R14*$S$13 | T14: =S14 | U14: =T14*$U$13 | V14: =R14-S14
B15: 2 | C15: =G5*$C$13 | D15: =G5*$D$13 | E15: - | F15: - | G15: =F5-H15 | H15: =F5 | I15: - | J15: - | K15: =C15+G15 | L15: =D15+H15 | M15: - | N15: ='P&L'!C79+'P&L'!C71 | O15: 60 | P15: =if(O14>H14,O14-H14," ") | Q15: =sum(O15:P15) | R15: =-K15+N15 | S15: =R15*$S$13 | T15: =T14+S15 | U15: =T15*$U$13 | V15: =R15-S15
B16: 3 | C16: =C13*G6 | D16: =D13*G6 | E16: - | F16: - | G16: =if(Q16>(H16+D16),0,(Q16-D16-H16)) | H16: =if((O16-D16)>F6,F6,(O16-D16)) | I16: - | J16: - | K16: =C16+G16 | L16: =D16+H16 | M16: - | N16: ='P&L'!D79+'P&L'!D71 | O16: 220 | P16: =Q15-H15-D15 | Q16: =sum(O16:P16) | R16: =-K16+N16 | S16: =R16*$S$13 | T16: =T15+S16 | U16: =T16*$U$13 | V16: =R16-S16
B17: 4 | C17: - | D17: =Q17 | E17: =G7*E13 | F17: =(G7-D17-E17) | G17: - | H17: - | I17: =F7*I13 | J17: =G7*J13 | K17: =E17+I17 | L17: - | M17: =F17+J17 | N17: ='P&L'!E71+'P&L'!E79 | O17: 0 | P17: =O16-H16-D16 | Q17: =sum(O17:P17) | R17: =-K17+N17 | S17: =R17*$S$13 | T17: =T16+S17 | U17: =T17*$U$13 | V17: =R17-S17
B18: 5 | C18: - | D18: - | E18: =E13*G8 | F18: =G8*F13 | G18: - | H18: - | I18: =F8*I13 | J18: =G8*J13 | K18: =E18+I18 | L18: - | M18: =F18+J18 | N18: ='P&L'!F71+'P&L'!F79 | O18: 0 | Q18: =sum(O18:P18) | R18: =-K18+N18 | S18: =R18*$S$13 | T18: =T17+S18 | U18: =T18*$U$13 | V18: =R18-S18
D19: * In the 4th year, the Surplus capital will be used | F19: * In the 4th year, only the remaining requirent is taken as debt (i.e. 52%) | K19: =sum(K14:K18) | L19: =sum(L14:L18) | M19: =sum(M14:M18) | N19: =sum(N14:N18) | O19: =sum(O14:O18) | R19: =sum(R14:R18) | S19: * Out of the free cash flow, 25% will be invested into Fixed Deposits | V19: =sum(V14:V18)
R20: * Retained Earnings - Capex and W.C. requirement from Own Funds

Sheet  Allocation
B2: Year | C2: Capex (in Cr) | D2: Working Capital (in Cr) | E2: Total (Capex & WC) | F2: Capex sourced by Equity | G2: W.C. sourced by Equity
B3: 1 | C3: ='Project Financing'!C14 | D3: ='Project Financing'!G14 | E3: =SUM(C3:D3) | F3: =IFERROR(C3*100%,0) | G3: =IFERROR(D3*100%,0)
B4: 2 | C4: ='Project Financing'!C15 | D4: ='Project Financing'!G15 | E4: =SUM(C4:D4) | F4: =IFERROR(C4*$K$4,0) | G4: =IFERROR(D4*$K$5,0)
B5: 3 | C5: ='Project Financing'!C16 | D5: ='Project Financing'!G16 | E5: =SUM(C5:D5) | F5: =IFERROR(C5*$K$4,0) | G5: =IFERROR(D5*$K$5,0)
B6: 4 | C6: ='Project Financing'!C17 | D6: ='Project Financing'!G17 | E6: =SUM(C6:D6) | F6: =IFERROR(C6*$K$4,0) | G6: =IFERROR(D6*$K$5,0)
B7: 5 | C7: ='Project Financing'!C18 | D7: ='Project Financing'!G18 | E7: =SUM(C7:D7) | F7: =IFERROR(C7*$K$4,0) | G7: =IFERROR(D7*$K$5,0)

Sheet Project NPV, PI & EVA
A1: NATAL CARE - NPV, PI & EVA Calculations
B3: Net Present Value (in Cr) | C3: =E23-E12 | G3: Economic Value Added (in Cr) | H3: =H6-('ROCE & RONW'!C8*H7) | I3: =I6-('ROCE & RONW'!D8*I7) | J3: =J6-('ROCE & RONW'!E8*J7) | K3: =K6-('ROCE & RONW'!F8*K7) | L3: =L6-('ROCE & RONW'!G8*L7)
B4: * Considering 7 years | G4: * NOPAT - (Capital Invested * WACC)
B5: Years (Start of the Year) | C5: Cash Outflow (in Cr) | D5: Df @ WACC
B6: 1 | C6: ='Project Financing'!H4 | D6: 1 | E6: =C6*D6 | G6: NOPAT (in Cr) | H6: =('P&L'!C72)*(1-0.25) | I6: =('P&L'!D72)*(1-0.25) | J6: =('P&L'!E72)*(1-0.25) | K6: =('P&L'!F72)*(1-0.25) | L6: =('P&L'!G72)*(1-0.25)
B7: 2 | C7: ='Project Financing'!H5 | D7: =1/(1+H7) | E7: =C7*D7 | G7: WACC | H7: ='ROCE & RONW'!C12 | I7: ='ROCE & RONW'!D12 | J7: ='ROCE & RONW'!E12 | K7: ='ROCE & RONW'!F12 | L7: ='ROCE & RONW'!G12
B8: 3 | C8: ='Project Financing'!H6 | D8: =1/((1+I7)^B17) | E8: =C8*D8 | G8: * (Equity/Total Capital)*Ke + (Debt/Total Capital)*Kd
B9: 4 | C9: ='Project Financing'!H7 | D9: =1/((1+J7)^B18) | E9: =C9*D9
B10: 5 | C10: ='Project Financing'!H8 | D10: =1/((1+K7)^B19) | E10: =C10*D10 | G10: Ke | H10: 0.108 | I10: =H10*1 | J10: Benchmark Reference (pg.3)
G11: Kd (Net of Tax) | H11: 0.12 | I11: =H11*(1-0.25)
B12: Present Value of Cash Outflows | E12: =SUM(E6:E10)
B15: Years | C15: Cash Inflows | D15: Df @ WACC
B16: 1 | C16: ='P&L'!C79+'P&L'!C71 | D16: =1/(1+H7) | E16: =C16*D16
B17: 2 | C17: ='P&L'!D79+'P&L'!D71 | D17: =1/((1+I7)^B17) | E17: =C17*D17
B18: 3 | C18: ='P&L'!E79+'P&L'!E71 | D18: =1/((1+J7)^B18) | E18: =C18*D18
B19: 4 | C19: ='P&L'!F79+'P&L'!F71 | D19: =1/((1+K7)^B19) | E19: =C19*D19
B20: 5 | C20: ='P&L'!G79+'P&L'!G71 | D20: =1/((1+L7)^B20) | E20: =C20*D20
B21: 6 | C21: ='P&L'!G79+'P&L'!G71 | D21: =1/((1+L7)^B21) | E21: =C21*D21
B22: 7 | C22: ='P&L'!G79+'P&L'!G71 | D22: =1/((1+L7)^B21) | E22: =C22*D22
B23: Present Value of Cash Inflows | E23: =SUM(E16:E22)
B27: PV of Future Cash Inflows (in Cr) | D27: =E23
B28: PV of Future Cash Outflows (in Cr) | D28: =E12
B30: Profitability Index (PI) | C30: =(D27+D28)/D28 | D30: * (NPV + Initial Investment) / Initial Investment

Sheet Debt Schedule
B2: Year | C2: Capex (in Cr) | D2: Working Capital (in Cr) | E2: Total (Capex & WC) | F2: Cumulative Debt (in Cr) | G2: Interest Expense (in Cr)
B3: FY 27-28 | C3: ='Project Financing'!F14 | D3: ='Project Financing'!J14 | E3: =SUM(C3:D3) | F3: =E3 | G3: =F3*12%
B4: FY 28-29 | C4: ='Project Financing'!F15 | D4: ='Project Financing'!J15 | E4: =SUM(C4:D4) | F4: =E4+F3 | G4: =F4*12%
B5: FY 29-30 | C5: ='Project Financing'!F16 | D5: ='Project Financing'!J16 | E5: =SUM(C5:D5) | F5: =F4+E5 | G5: =F5*12%
B6: FY 30-31 | C6: ='Project Financing'!F17 | D6: ='Project Financing'!J17 | E6: =SUM(C6:D6) | F6: =F5+E6 | G6: =F6*12%
B7: FY 31-32 | C7: ='Project Financing'!F18 | D7: ='Project Financing'!J18 | E7: =SUM(C7:D7) | F7: =F6+E7 | G7: =F7*12%

Sheet ROCE & RONW
A1: NATAL CARE - ROCE & ROE
G3: Rs in cr
C4: FY 27-28 | D4: FY 28-29 | E4: FY 29-30 | F4: FY 30-31 | G4: FY 31-32
B6: Equity | C6: ='Project Financing'!K14 | D6: =C6+'Project Financing'!K15+'Project Financing'!R15 | E6: =D6+'Project Financing'!K16+'Project Financing'!R16 | F6: =E6+'Project Financing'!K17+'Project Financing'!R17 | G6: =F6+'Project Financing'!K18+'Project Financing'!R18
B7: Debt | C7: ='Project Financing'!L14 | D7: =C7+'Project Financing'!L15 | E7: =D7+'Project Financing'!L16 | F7: =E7+'Project Financing'!N16 | G7: =F7+'Project Financing'!O16
B8: Total Capital Employed | C8: =SUM(C6:C7) | D8: =SUM(D6:D7) | E8: =SUM(E6:E7) | F8: =SUM(F6:F7) | G8: =SUM(G6:G7)
B10: EBIT | C10: ='P&L'!C72 | D10: ='P&L'!D72 | E10: ='P&L'!E72 | F10: ='P&L'!F72 | G10: ='P&L'!G72
B11: PAT | C11: ='P&L'!C79 | D11: ='P&L'!D79 | E11: ='P&L'!E79 | F11: ='P&L'!F79 | G11: ='P&L'!G79
B12: WACC % | C12: =(C6/C8*$C$16)+(C7/C8*$C$17) | D12: =(D6/D8*$C$16)+(D7/D8*$C$17) | E12: =(E6/E8*$C$16)+(E7/E8*$C$17) | F12: =(F6/F8*$C$16)+(F7/F8*$C$17) | G12: =(G6/G8*$C$16)+(G7/G8*$C$17)
B13: ROCE% | C13: =IFERROR(C10/C8,"-") | D13: =IFERROR(D10/D8,"-") | E13: =IFERROR(E10/E8,"-") | F13: =IFERROR(F10/F8,"-") | G13: =IFERROR(G10/G8,"-") | H13: * ROCE = (EBIT / Capital Employed) * 100
B14: ROE% | C14: =IFERROR(C11/C6,"-") | D14: =IFERROR(D11/D6,"-") | E14: =IFERROR(E11/E6,"-") | F14: =IFERROR(F11/F6,"-") | G14: =IFERROR(G11/G6,"-") | H14: * ROE= (PAT / Equity) * 100
B16: Ke | C16: ='Project NPV, PI & EVA'!I10
B17: Kd (12% Incl. tax) | C17: ='Project NPV, PI & EVA'!I11

Sheet IRR & Payback Period
A1: NATAL CARE - IRR & Payback Period
B3: Internal Rate of Return | C3: 0.90598
B5: Year (Start of the year) | C5: Cash Inflows | D5: Cash Outflows | E5: Net Cash flows | F5: Discouting Factor @ IRR | H5: Discounted Cash Flows
B6: 1 | D6: ='Project NPV, PI & EVA'!C6 | E6: =C6-D6 | F6: 1 | H6: =E6*F6
B7: 2 | C7: ='Project NPV, PI & EVA'!C16 | D7: ='Project NPV, PI & EVA'!C7 | E7: =C7-D7 | F7: =1/(1+C3) | H7: =E7*F7
B8: 3 | C8: ='Project NPV, PI & EVA'!C17 | D8: ='Project NPV, PI & EVA'!C8 | E8: =C8-D8 | F8: =F7/(1+$C$3) | H8: =E8*F8
B9: 4 | C9: ='Project NPV, PI & EVA'!C18 | D9: ='Project NPV, PI & EVA'!C9 | E9: =C9-D9 | F9: =F8/(1+$C$3) | H9: =E9*F9
B10: 5 | C10: ='Project NPV, PI & EVA'!C19 | D10: ='Project NPV, PI & EVA'!C10 | E10: =C10-D10 | F10: =F9/(1+$C$3) | H10: =E10*F10
B11: 6 | C11: ='Project NPV, PI & EVA'!C20 | D11: 0 | E11: =C11-D11 | F11: =F10/(1+$C$3) | H11: =E11*F11
B12: 7 | C12: ='Project NPV, PI & EVA'!C21 | D12: 0 | E12: =C12-D12 | F12: =F11/(1+$C$3) | H12: =E12*F12
B13: 8 | C13: ='Project NPV, PI & EVA'!C22 | D13: 0 | E13: =C13-D13 | F13: =F12/(1+$C$3) | H13: =E13*F13
F14: NPV | H14: =SUM(H6:H13)
B18: Payback Period (in years) | C18: =C20/C22
B20: Initial Cash Outflow | C20: ='Project Financing'!H4
B22: Annual Cash Inflows | C22: ='P&L'!C79+'P&L'!C71
B26: Discounted Payback Period (in years) | C26: =B31+((C28-F31)/(F32-F31))
B28: Initial Cash Outflow | C28: ='Project Financing'!H4
B30: Years | C30: Cash Inflows | D30: DF @WACC | E30: Discounted Cash Inflows | F30: Cumulative Discounted Cash Inflows
B31: 1 | C31: ='Project NPV, PI & EVA'!C16 | D31: ='Project NPV, PI & EVA'!D16 | E31: =D31*C31 | F31: =E31 | G31: =If(F31>$C$28,B31," ")
B32: 2 | C32: ='Project NPV, PI & EVA'!C17 | D32: ='Project NPV, PI & EVA'!D17 | E32: =D32*C32 | F32: =F31+E32 | G32: =If(F32>$C$28,B32," ")
B33: 3 | C33: ='Project NPV, PI & EVA'!C18 | D33: ='Project NPV, PI & EVA'!D18 | E33: =D33*C33 | F33: =F32+E33 | G33: =If(F33>$C$28,B33," ")
B34: 4 | C34: ='Project NPV, PI & EVA'!C19 | D34: ='Project NPV, PI & EVA'!D19 | E34: =D34*C34 | F34: =F33+E34 | G34: =If(F34>$C$28,B34," ")
B35: 5 | C35: ='Project NPV, PI & EVA'!C20 | D35: ='Project NPV, PI & EVA'!D20 | E35: =D35*C35 | F35: =F34+E35 | G35: =If(F35>$C$28,B35," ")
B36: 6 | C36: ='Project NPV, PI & EVA'!C21 | D36: ='Project NPV, PI & EVA'!D21 | E36: =D36*C36 | F36: =F35+E36 | G36: =If(F36>$C$28,B36," ")
B37: 7 | C37: ='Project NPV, PI & EVA'!C22 | D37: ='Project NPV, PI & EVA'!D22 | E37: =D37*C37 | F37: =F36+E37 | G37: =If(F37>$C$28,B37," ")
E38: =SUM(E31:E37) | G38: =If(F38>$C$28,B38," ")
