Workbook
Name Medak: #REF!

Sheet Index
B2: Bill Of Material (BOM)
B3: 1 | C3: Pregnancy Powder
B4: 2 | C4: Lactation Powder
B5: 3 | C5: Infant Formula Milk
B6: 4 | C6: Child Nutrition
B8: Profit & Loss Statement
B10: 22Cr Summary Sheet
B12: Year 1
B13: 1 | C13: 22Cr Capital Raised Working
B14: 2 | C14: Working Capital
B16: Year 2
B17: 1 | C17: 60Cr Capital Raised Working
B18: 2 | C18: Working Capital
B20: Year 3
B21: 1 | C21: Plant works @ 100% Efficiency
B22: 2 | C22: Working Capital

Sheet Infant Complementary BOM
B2: RAW MATERIAL COST
B4: Item No. | C4: Ingredient Name | D4: In Grams | F4: In Rupees
D5: Quantity Per 100 g | E5: Quantity per 400 gm | F5: Rate / Kg | G5: Rate / Gram | H5: Rate Per 400 g
B6: 1 | C6: Milk Solids | D6: 35 | E6: =D6*4 -> 140 | F6: 240 | G6: =F6/1000 -> 0.24 | H6: =E6*G6 -> 33.6
B7: 2 | C7: Maltodextrin | D7: 20 | E7: =D7*4 -> 80 | F7: 50 | G7: =F7/1000 -> 0.05 | H7: =E7*G7 -> 4
B8: 3 | C8: Sprouted Ragi Powder | D8: 13 | E8: =D8*4 -> 52 | F8: 50 | G8: =F8/1000 -> 0.05 | H8: =E8*G8 -> 2.6
B9: 4 | C9: Rice Powder | D9: 10 | E9: =D9*4 -> 40 | F9: 50 | G9: =F9/1000 -> 0.05 | H9: =E9*G9 -> 2
B10: 5 | C10: Apple Powder | D10: 8 | E10: =D10*4 -> 32 | F10: 170 | G10: =F10/1000 -> 0.17 | H10: =E10*G10 -> 5.44
B11: 6 | C11: Enzyme(Alpha Amylase) | D11: 0.5 | E11: =D11*4 -> 2 | F11: 1000 | G11: =F11/1000 -> 1 | H11: =E11*G11 -> 2
B12: 7 | C12: Fructooligosaccharides | D12: 7 | E12: =D12*4 -> 28 | F12: 170 | G12: =F12/1000 -> 0.17 | H12: =E12*G12 -> 4.76
B13: 8 | C13: Mineral premix(Calcium, Phosphorous, Sodium, Potassium, Chloride, Magnesium, Iron, Zinc, Copper, Manganese, Iodine, Selenium) | D13: 1.88 | E13: =D13*4 -> 7.52 | F13: 400 | G13: =F13/1000 -> 0.4 | H13: =E13*G13 -> 3.008
B14: 9 | C14: Vitamin premix(Vitamin A, D, E, K, C, B1, B2, B6, B12, B7,B5, B3) | D14: 0.05 | E14: =D14*4 -> 0.2 | F14: 500 | G14: =F14/1000 -> 0.5 | H14: =E14*G14 -> 0.1
B15: 10 | C15: Jaggery Powder | D15: 5 | E15: =D15*4 -> 20 | F15: 60 | G15: =F15/1000 -> 0.06 | H15: =E15*G15 -> 1.2
B16: RAW MATERIAL TOTAL COST | D16: =SUM(D6:D15) -> 100.43 | E16: =D16*4 -> 401.72 | H16: =SUM(H6:H14) -> 57.508
B18: OTHER COSTS
C20: Packaging | H20: 12
C21: Conversion | H21: 30
F23: TOTAL COST / BOX | H23: =H16+H20+H21 -> 99.508
F25: PRODUCTION COST / BATCH | H25: 20000000
F27: BOXES / BATCH | H27: =H25/H23 -> 200988.87
F29: BOXES / VARIANT | H29: =H27/3 -> 66996.288
F31: AS PER PROJETIONS SHEET
F32: Total Cost (Excl. GST) | H32: 111 | I32: VS | J32: =H23 -> 99.508
F33: GST 18% | H33: 16
F34: Total Cost (Incl. GST) | H34: 127

Sheet Total Production
A1: VALENCIA NUTRACARE LIFESCIENCES (Consumer Validation)
B3: EARLY STAGE FUND | C3: Natal Care | D3: Infant & Child Nutrition | E3: Total
B4: Funding (₹ Cr) | C4: 11 | D4: 11 | E4: =C4+D4 -> 22
B5: Production (₹ Cr) | C5: 8 | D5: 8 | E5: =C5+D5 -> 16 | F5: * 2 cycles of production
B6: Admin & Marketing Exp (₹ Cr) | C6: 3 | D6: 3 | E6: =C6+D6 -> 6
C8: Pregnancy Powder (Garbhika) | D8: Lactation Powder (Matrusneha) | E8: Infant Formula Milk Powder (Poshit) | F8: Child Nutrition Powder
B9: Cost/Box | C9: ='PP BOM'!H25 -> 178.594 | D9: ='LP BOM'!H28 -> 158.835 | E9: ='IFM BOM'!H30 -> 124.1836 | F9: ='CNP BOM'!H24 -> 121.88
B10: Production Cost/Batch | C10: ='PP BOM'!H27 -> 20000000 | D10: ='LP BOM'!H30 -> 20000000 | E10: ='IFM BOM'!H32 -> 20000000 | F10: ='CNP BOM'!H26 -> 20000000
B11: Boxes/Batch | C11: =Round(C10/C9,0) -> 111986 | D11: =Round(D10/D9,0) -> 125917 | E11: =Round(E10/E9,0) -> 161052 | F11: =Round(F10/F9,0) -> 164096
B13: TOTAL BOXES | C13: =C11+D11+E11+F11 -> 563051
B15: AVERAGE BOXES/VARIANT | C15: =average(C11:F11) -> 140762.75
B17: AVERAGE COST/BOX | C17: =average(C9:F9) -> 145.87315
B19: Products | C19: Selling Price (in ₹) | D19: Boxes/Batch | E19: Revenue / Batch (in ₹) | F19: COGS / Batch (in ₹) | G19: Gross Profit/ Batch (in ₹)
B20: Pregnancy Powder | C20: 280 | D20: =C11 -> 111986 | E20: =C20*D20 -> 31356080 | F20: =D20*C9 -> 20000028 | G20: =E20-F20 -> 11356052
B21: Lactation Powder | C21: 286 | D21: =D11 -> 125917 | E21: =C21*D21 -> 36012262 | F21: =D21*D9 -> 20000027 | G21: =E21-F21 -> 16012235
B22: Infant Formula Milk Powder | C22: 242 | D22: =E11 -> 161052 | E22: =C22*E11 -> 38974584 | F22: =D22*E9 -> 20000017 | G22: =E22-F22 -> 18974567
B23: Child Nutrition Powder | C23: 212 | D23: =F11 -> 164096 | E23: =C23*F11 -> 34788352 | F23: =D23*F9 -> 20000020 | G23: =E23-F23 -> 14788332
D24: TOTAL (in ₹) | E24: =SUM(E20:E23) -> 141131278 | F24: =SUM(F20:F23) -> 80000092 | G24: =SUM(G20:G23) -> 61131186
D25: TOTAL (₹ in Cr) | E25: =E24/10^7 -> 14.113128 | F25: =F24/10^7 -> 8.0000092 | G25: =G24/10^7 -> 6.1131186
B28: Amount in ₹ Cr
B29: Gross Profit | C29: =G25 -> 6.1131186
B30: Marketing Expense | C30: =#REF! -> #REF!
B31: EBITDA | C31: =C29-C30 -> #REF!
B33: Remaining Funds | C33: =(E5+E6)/2 -> 11 | D33: * 8cr for Production, 3cr for Marketing Expense
B34: Production Funds for Batch 2 | C34: =C31+(E5/2) -> #REF!
B36: Maketing Funds for Batch 2 | C36: =E6/2 -> 3
B38: TRIO FIT WORKING CAPACITY
C39: 1 day | D39: Working Efficiency | F39: Bulk density | G39: Manufacturing | H39: 1 day
B40: Blender | C40: 500l | D40: 0.7 | E40: =1200 -> 1200 | F40: 0.4 | G40: 400kg/5 hrs | H40: 800kg
B41: Blender 1 | C41: 1500 | D41: 0.7
B42: Blender 2 | C42: =300 -> 300 | D42: 0.7 | G42: 100kg/5hrs | H42: 200kg
C44: PP | D44: LP | E44: IFP | F44: CNP
B45: Kgs to be Manufactured | C45: =C11*0.5 -> 55993 | D45: =D11*0.5 -> 62958.5 | E45: =(E11*400)/1000 -> 64420.8 | F45: =(F11*400)/1000 -> 65638.4 | G45: * 1 batch capacity
B46: Tons to be Manufactured | C46: =C45/1000 -> 55.993 | D46: =D45/1000 -> 62.9585 | E46: =E45/1000 -> 64.4208 | F46: =F45/1000 -> 65.6384
C48: Total Production Capacity | D48: Days | E48: Months (25 days working)
C49: =2*300*1000 -> 600000 | D49: 300 | E49: =D49/25 -> 12
C50: =sum(C45:F45) -> 249010.7 | D50: =(C50*D49)/C49 -> 124.50535 | E50: =D50/25 -> 4.980214
C52: 1 DAY PRODUCTION CAPACITY (Rohan sir's factory)
C53: PP | D53: LP | E53: IFP | F53: CNP
B54: Boxes | C54: =C55*2 -> 795.56559 | D54: =D55*2 -> 894.53353 | E54: =(E55*1000)/400 -> 1430.1724 | F54: =(F55*1000)/400 -> 1457.2037 | G54: =SUM(C54:F54) -> 4577.4752
B55: Kgs | C55: =C56*$G$55 -> 397.78279 | D55: =D56*$G$55 -> 447.26677 | E55: =E56*$G$55 -> 572.06896 | F55: =F56*$G$55 -> 582.88148 | G55: =2*1000 -> 2000 | H55: * 300 kg per batch
B56: Percentage % | C56: =C11/sum($C$11:$F$11) -> 0.1988914 | D56: =D11/sum($C$11:$F$11) -> 0.22363338 | E56: =E11/sum($C$11:$F$11) -> 0.28603448 | F56: =F11/sum($C$11:$F$11) -> 0.29144074
B57: Days taken for 1 Batch | C57: =C11/C54 -> 140.76275 | D57: =D11/D54 -> 140.76275 | E57: =E11/E54 -> 112.6102 | F57: =F11/F54 -> 112.6102 | G57: =average(C57:F57) -> 126.68648 | H57: * Average Days Taken
B59: APPLICATION & SOURCES OF FUND
B60: Sources of Fund | C60: =C63 -> #REF!
B61: A. VNL | C61: =C60-C62 -> #REF!
B62: B. Capital Raise | C62: =E4 -> 22
B63: Application of Fund | C63: =sum(C64:C65) -> #REF!
B64: A. Production | C64: =('WC (Year 1)'!D9-#REF!)/10^7 -> #REF!
B65: B. Indirect Expense | C65: =#REF! -> #REF!
B89: Phase 1
B90: Phase 2

Sheet Year 2
B2: YEAR 2 FUNDING (in Cr) | C2: 60
C4: Pregnancy Powder (Garbhika) | D4: Lactation Powder (Matrusneha) | E4: Infant Formula Milk Powder (Poshit) | F4: Child Nutrition Powder
B5: Cost/Box | C5: ='PP BOM'!H32 -> #REF! | D5: ='LP BOM'!H35 -> #REF! | E5: ='IFM BOM'!H39 -> #REF! | F5: ='CNP BOM'!H31 -> #REF!
B6: Selling Price/Box | C6: ='Total Production'!C20 -> 280 | D6: ='Total Production'!C21 -> 286 | E6: ='Total Production'!C22 -> 242 | F6: ='Total Production'!C23 -> 212
B7: Profit/Box | C7: =C6-C5 -> #REF! | D7: =D6-D5 -> #REF! | E7: =E6-E5 -> #REF! | F7: =F6-F5 -> #REF!
B9: Taking into consideration the following information:
B10: Tons Manufactured / Day | C10: 40 | D10: * 2 tons a day at Rohan Sir's Factory (Natal Care only). Assuming another factory will have 2 tons too
B11: Kgs Manufactured / Day | C11: =C10*1000 -> 40000
B12: Boxes Manufactured / Day | C12: =((C11*1000*0.5)/500)+((C11*1000*0.5)/400) -> 90000
B14: Natal Care Boxes/Day | C14: =((C11*1000*0.5)/500)*C76 -> 0 | D14: * Natal Care Products are 500gms each
B15: Infant & Child Care Boxes/Day | C15: =((C11*1000*0.5)/400)*C76 -> 0 | D15: * Infant and Child Care Products are 400gms each
B17: Working Days/Month | C17: 25
B18: Working Months/Year | C18: 12
B19: Working Days/Year | C19: =C17*C18 -> 300
B21: PRODUCTION
B22: Products | C22: Boxes/Year | D22: Revenue/Year | E22: Revenue (in Cr) | F22: COGS (in Cr) | G22: Gross Profit (in Cr)
B23: Infant Formula Milk | C23: =($C$19*$C$15)/2 -> 0 | D23: =C23*E6 -> 0 | E23: =D23/10^7 -> 0 | F23: =(C23*E5)/10^7 -> #REF! | G23: =E23-F23 -> #REF!
B24: Child Nutrition Powder | C24: =($C$19*$C$15)/2 -> 0 | D24: =C24*F6 -> 0 | E24: =D24/10^7 -> 0 | F24: =(C24*F5)/10^7 -> #REF! | G24: =E24-F24 -> #REF!
B25: Pregnancy Powder | C25: =($C$19*$C$14)/2 -> 0 | D25: =C25*C6 -> 0 | E25: =D25/10^7 -> 0 | F25: =(C25*C5)/10^7 -> #REF! | G25: =E25-F25 -> #REF!
B26: Lactation Powder | C26: =($C$19*$C$14)/2 -> 0 | D26: =C26*D6 -> 0 | E26: =D26/10^7 -> 0 | F26: =(C26*D5)/10^7 -> #REF! | G26: =E26-F26 -> #REF!
C27: =sum(C23:C26) -> 0 | E27: =sum(E23:E26) -> 0 | F27: =sum(F23:F26) -> #REF! | G27: =sum(G23:G26) -> #REF!
B29: WORKING CAPITAL
C30: Year 1 | D30: Year 2 | E30: Fresh Capital Needed
B31: Working Capital (in Cr) | C31: ='Contract (1 yr)'!C30 -> 21.598213 | D31: ='WC (Year 3-5)'!D17/10^7 -> #REF! | E31: =D31-C31 -> #REF!
B32: Pregnancy Powder (in Cr) | C32: ='Contract (1 yr)'!C31 -> 5.7940809 | D32: ='WC (Year 3-5)'!D5/10^7 -> #REF! | E32: =D32-C32 -> #REF!
B33: Lactation Powder (in Cr) | C33: ='Contract (1 yr)'!C32 -> 5.3445637 | D33: ='WC (Year 3-5)'!D8/10^7 -> #REF! | E33: =D33-C33 -> #REF!
B34: Infant Formula Milk (in Cr) | C34: ='Contract (1 yr)'!C33 -> 5.2625385 | D34: ='WC (Year 3-5)'!D11/10^7 -> #REF! | E34: =D34-C34 -> #REF!
B35: Child Nutrition Powder (in Cr) | C35: ='Contract (1 yr)'!C34 -> 5.1970299 | D35: ='WC (Year 3-5)'!D14/10^7 -> #REF! | E35: =D35-C35 -> #REF!
B37: APPLICATION & SOURCES OF FUND
B38: Sources of Fund | C38: =C42 -> #REF!
B39: A. VNL | C39: =C38-C40-C41 -> #REF!
B40: B. Capital Raise | C40: =C2 -> 60
B41: C. Existing Working Capital | C41: =C31 -> 21.598213
B42: Application of Fund | C42: =sum(C43:C45) -> #REF!
B43: A. Production | C43: ='WC (Year 3-5)'!H17/10^7 -> 0
B44: B. Indirect Expense | C44: ='WC (Year 3-5)'!I17/10^7 -> 0
B45: C. Plant CAPEX | C45: =C64 -> #REF!
B47: CAPEX TABLE
B48: Cost of Project | C48: Cost (in Cr)
B49: Land and Plant Building | C49: =IFERROR(__xludf.DUMMYFUNCTION("importrange(""https://docs.google.com/spreadsheets/d/1bEcp3VCHzQgxan8VY9FCqLk1Yk8qAjekoqv5jLH-RCM/edit?gid=3774512#gid=3774512"",""Capex & Depreciation!C12:C26"")"),"#REF!") -> #REF!
B50: Utilities (Power, Tanks etc.)
B51: FBD (Fluid Bed Dryer)
B52: Precision Octagonal Blending
B53: Compressor Unit
B54: HVAC
B55: Vibro Sifter
B56: Multi-mill Crusher
B57: Vertical Form Filling Sachets
B58: Packaging Conveyor Unit
B59: Sanitization Machine
B60: Laboratories and Accessories
B61: Tray Dryer
... B63: Contingency Expenses
B64: Total | C64: =sum(C49:C63) -> #REF!
B66: WORKING EFFICIENCY
B67: Months | C67: Year 1
C68: Capacity/Month | D68: Capacity/Quarter
B69: April to June | C69: =IFERROR(__xludf.DUMMYFUNCTION("IMPORTRANGE(""https://docs.google.com/spreadsheets/d/1DXOBRjKEc9pOcmohKWx0l59g3hrSjk2ZicxFB9zphD4/edit?gid=1653862983#gid=1653862983"",""In-house Manufacturing!C96:D100"")"),"#REF!") -> #REF!
B70: January to March
B71: July to September
B72: October to December
B73: Average Working Capacity %
B75: Capacity Breakup | C75: Year 1 Plant | D75: * Divided in the ratio 3:1
B76: Our brand manufacturing | C76: =D73
B77: Contract manufacturing | C77: =D73-C76 -> 0
B79: INDIRECT EXPENSES
B80: Expense Bifurcation | D80: Expense % | E80: Total Expense
B81: Training & Community Engagement | D81: ='Contract (1 yr)'!D63 -> 0.01 | E81: =(D81*$E$27)*10^7 -> 0
B82: Monitoring & Evaluation | D82: 0.005 | E82: =(D82*$E$27)*10^7 -> 0
B83: Technology & Reporting | D83: 0.003 | E83: =(D83*$E$27)*10^7 -> 0
B84: Administrative Cost | D84: 0.017 | E84: =(D84*$E$27)*10^7 -> 0
B85: Logistics & Distribution Cost | D85: Rs. 8.5/ Box | E85: =8.5*C27 -> 0
B86: Communication & Impact Documentation | D86: ='Contract (1 yr)'!D68 -> 0.0065035685 | E86: =(D86*$E$27)*10^7 -> 0
B87: Contingency | D87: ='Contract (1 yr)'!D69 -> 0.1 | E87: =sum(E81:E86)*D87 -> 0
D88: TOTAL (in ₹) | E88: =sum(E81:E87) -> 0
D89: TOTAL (₹ in Cr) | E89: =E88/10^7 -> 0

Sheet Year 3
B2: YEAR 3 FUNDING (in Cr) | C2: 0
C4: Pregnancy Powder (Garbhika) | D4: Lactation Powder (Matrusneha) | E4: Infant Formula Milk Powder (Poshit) | F4: Child Nutrition Powder
B5: Cost/Box | C5: ='PP BOM'!H32 -> #REF! | D5: ='LP BOM'!H35 -> #REF! | E5: ='IFM BOM'!H39 -> #REF! | F5: ='CNP BOM'!H31 -> #REF!
B6: Selling Price/Box | C6: ='Total Production'!C20 -> 280 | D6: ='Total Production'!C21 -> 286 | E6: ='Total Production'!C22 -> 242 | F6: ='Total Production'!C23 -> 212
B7: Profit/Box | C7: =C6-C5 -> #REF! | D7: =D6-D5 -> #REF! | E7: =E6-E5 -> #REF! | F7: =F6-F5 -> #REF!
B9: Taking into consideration the following information:
B10: Tons Manufactured / Day | C10: 40 | D10: * 2 tons a day at Rohan Sir's Factory (Natal Care only). Assuming another factory will have 2 tons too
B11: Kgs Manufactured / Day | C11: =C10*1000 -> 40000
B12: Boxes Manufactured / Day | C12: =((C11*1000*0.5)/500)+((C11*1000*0.5)/400) -> 90000
B14: Natal Care Boxes/Day | C14: =((C11*1000*0.5)/500)*C75 -> 0 | D14: * Natal Care Products are 500gms each
B15: Infant & Child Care Boxes/Day | C15: =((C11*1000*0.5)/400)*C75 -> 0 | D15: * Infant and Child Care Products are 400gms each
B17: Working Days/Month | C17: 25
B18: Working Months/Year | C18: 12
B19: Working Days/Year | C19: =C17*C18 -> 300
B21: PRODUCTION
B22: Products | C22: Boxes/Year | D22: Revenue/Year | E22: Revenue (in Cr) | F22: COGS (in Cr) | G22: Gross Profit (in Cr)
B23: Infant Formula Milk | C23: =($C$19*$C$15)/2 -> 0 | D23: =C23*E6 -> 0 | E23: =D23/10^7 -> 0 | F23: =(C23*E5)/10^7 -> #REF! | G23: =E23-F23 -> #REF!
B24: Child Nutrition Powder | C24: =($C$19*$C$15)/2 -> 0 | D24: =C24*F6 -> 0 | E24: =D24/10^7 -> 0 | F24: =(C24*F5)/10^7 -> #REF! | G24: =E24-F24 -> #REF!
B25: Pregnancy Powder | C25: =($C$19*$C$14)/2 -> 0 | D25: =C25*C6 -> 0 | E25: =D25/10^7 -> 0 | F25: =(C25*C5)/10^7 -> #REF! | G25: =E25-F25 -> #REF!
B26: Lactation Powder | C26: =($C$19*$C$14)/2 -> 0 | D26: =C26*D6 -> 0 | E26: =D26/10^7 -> 0 | F26: =(C26*D5)/10^7 -> #REF! | G26: =E26-F26 -> #REF!
C27: =sum(C23:C26) -> 0 | E27: =sum(E23:E26) -> 0 | F27: =sum(F23:F26) -> #REF! | G27: =sum(G23:G26) -> #REF!
B29: WORKING CAPITAL
C30: Year 3 | D30: Year 2 | E30: Fresh Capital Needed
B31: Working Capital (in Cr) | C31: ='WC (Year 3)'!D9/10^7 -> #REF! | D31: ='Year 2'!D31 -> #REF! | E31: =C31-D31 -> #REF!
B32: Pregnancy Powder (in Cr) | C32: ='WC (Year 3)'!D5/10^7 -> #REF! | D32: ='WC (Year 3-5)'!D5/10^7 -> #REF! | E32: =C32-D32 -> #REF!
B33: Lactation Powder (in Cr) | C33: ='WC (Year 3)'!D6/10^7 -> #REF! | D33: ='WC (Year 3-5)'!D8/10^7 -> #REF! | E33: =C33-D33 -> #REF!
B34: Infant Formula Milk (in Cr) | C34: ='WC (Year 3)'!D7/10^7 -> #REF! | D34: ='WC (Year 3-5)'!D11/10^7 -> #REF! | E34: =C34-D34 -> #REF!
B35: Child Nutrition Powder (in Cr) | C35: ='WC (Year 3)'!D8/10^7 -> #REF! | D35: ='WC (Year 3-5)'!D14/10^7 -> #REF! | E35: =C35-D35 -> #REF!
B37: APPLICATION & SOURCES OF FUND
B38: Sources of Fund | C38: =C42 -> #REF!
B39: A. VNL Retained Earnings | C39: =C38-C40-C41 -> #REF! | D39: * 7.58% of Retained Earnings
B40: B. Capital Raise | C40: =C2 -> 0
B41: C. Existing Working Capital | C41: =D31 -> #REF!
B42: Application of Fund | C42: =sum(C43:C44) -> #REF!
B43: A. Production | C43: ='WC (Year 3)'!H9/10^7 -> #REF!
B44: B. Indirect Expense | C44: ='WC (Year 3)'!I9/10^7 -> 0
B46: CAPEX TABLE
B47: Cost of Project | C47: Cost (in Cr)
B48: Land and Plant Building | C48: =IFERROR(__xludf.DUMMYFUNCTION("importrange(""https://docs.google.com/spreadsheets/d/1bEcp3VCHzQgxan8VY9FCqLk1Yk8qAjekoqv5jLH-RCM/edit?gid=3774512#gid=3774512"",""Capex & Depreciation!C12:C26"")"),"#REF!") -> #REF!
B49: Utilities (Power, Tanks etc.)
B50: FBD (Fluid Bed Dryer)
B51: Precision Octagonal Blending
B52: Compressor Unit
B53: HVAC
B54: Vibro Sifter
B55: Multi-mill Crusher
B56: Vertical Form Filling Sachets
B57: Packaging Conveyor Unit
B58: Sanitization Machine
B59: Laboratories and Accessories
B60: Tray Dryer
... B62: Contingency Expenses
B63: Total | C63: =sum(C48:C62) -> #REF!
B65: WORKING EFFICIENCY
B66: Months | C66: Year 1 | E66: Year 2
C67: Capacity/Month | D67: Capacity/Quarter | E67: Capacity/Month | F67: Capacity/Quarter
B68: April to June | C68: =IFERROR(__xludf.DUMMYFUNCTION("IMPORTRANGE(""https://docs.google.com/spreadsheets/d/1DXOBRjKEc9pOcmohKWx0l59g3hrSjk2ZicxFB9zphD4/edit?gid=1653862983#gid=1653862983"",""In-house Manufacturing!C96:D100"")"),"#REF!") -> #REF! | E68: =IFERROR(__xludf.DUMMYFUNCTION("IMPORTRANGE(""https://docs.google.com/spreadsheets/d/1DXOBRjKEc9pOcmohKWx0l59g3hrSjk2ZicxFB9zphD4/edit?gid=1653862983#gid=1653862983"",""In-house Manufacturing!G96:H100"")"),"#REF!") -> #REF!
B69: January to March
B70: July to September
B71: October to December
B72: Average Working Capacity %
B74: Capacity Breakup | C74: Year 2 Plant
B75: Our brand manufacturing | C75: =F72
B76: Contract manufacturing | C76: =F72-C75 -> 0
B78: INDIRECT EXPENSES
B79: Expense Bifurcation | D79: Expense % | E79: Total Expense
B80: Training & Community Engagement | D80: 0.008 | E80: =(D80*$E$27)*10^7 -> 0
B81: Monitoring & Evaluation | D81: 0.003 | E81: =(D81*$E$27)*10^7 -> 0
B82: Technology & Reporting | D82: 0.0015 | E82: =(D82*$E$27)*10^7 -> 0
B83: Administrative Cost | D83: 0.015 | E83: =(D83*$E$27)*10^7 -> 0
B84: Logistics & Distribution Cost | D84: Rs. 7/ Box | E84: =7*C27 -> 0
B85: Communication & Impact Documentation | D85: ='Year 2'!D86 -> 0.0065035685 | E85: =(D85*$E$27)*10^7 -> 0
B86: Contingency | D86: 0.05 | E86: =(D86*$E$27)*10^7 -> 0
D87: TOTAL (in ₹) | E87: =sum(E80:E86) -> 0
D88: TOTAL (₹ in Cr) | E88: =E87/10^7 -> 0

Sheet WC (Year 3)
B2: TOTAL WORKING CAPITAL | G2: APPLICATION OF FUNDS
C4: Revenue | D4: Initial Working Capital | E4: W.C.Rotation | H4: Production | I4: Indirect Expense
B5: PP | C5: =D35 -> 0 | D5: =D36 -> #REF! | E5: =C5/D5 -> #REF! | G5: PP | H5: =(D13*D14)*2.5 -> #REF! | I5: =D16*2.5 -> 0
B6: LP | C6: =D64 -> 0 | D6: =D65 -> #REF! | E6: =C6/D6 -> #REF! | G6: LP | H6: =(D42*D43)*2.5 -> #REF! | I6: =D45*2.5 -> 0
B7: IFP | C7: =D93 -> 0 | D7: =D94 -> #REF! | E7: =C7/D7 -> #REF! | G7: IFP | H7: =(D71*D72)*2.5 -> #REF! | I7: =D74*2.5 -> 0
B8: CNP | C8: =D122 -> 0 | D8: =D123 -> #REF! | E8: =C8/D8 -> #REF! | G8: CNP | H8: =(D100*D101)*2.5 -> #REF! | I8: =D103*2.5 -> 0
D9: =sum(D5:D8) -> #REF! | H9: =sum(H5:H8) -> #REF! | I9: =sum(I5:I8) -> 0
H10: =H9+I9 -> #REF!
B11: PREGNANCY POWDER
B13: Monthly Boxes Produced (in Units) | D13: ='Year 3'!C25/12 -> 0
B14: Cost/Box (in ₹) | D14: ='Year 2'!C5 -> #REF!
B15: Revenue/Box (in ₹) | D15: ='Year 2'!C6 -> 280
B16: Monthly Indirect Expense (in ₹) | D16: =('Year 2'!$E$88/12)/4 -> 0
G17: * The working capital that we are investing in the first month is derived from the cash outflow that is required in the first month
B18: Month | C18: Cash Outflow | D18: Cash Inflow | E18: Difference (CO-CI) | G18: Opening W.C. | H18: Net Cash Flow | I18: Closing W.C.
B19: April | C19: =($D$13*$D$14)+$D$16 -> #REF! | D19: =$D$13*$D$15 -> 0 | E19: =D19-C19 -> #REF! | G19: =C19+D33 -> #REF! | H19: =E19 -> #REF! | I19: =G19+H19 -> #REF!
B20: May | C20: =($D$13*$D$14)+$D$16 -> #REF! | D20: =$D$13*$D$15 -> 0 | E20: =D20-C20 -> #REF! | G20: =I19 -> #REF! | H20: =E20 -> #REF! | I20: =G20+H20 -> #REF!
B21: June | C21: =($D$13*$D$14)+$D$16 -> #REF! | D21: =$D$13*$D$15 -> 0 | E21: =D21-C21 -> #REF! | G21: =I20 -> #REF! | H21: =E21 -> #REF! | I21: =G21+H21 -> #REF!
B22: July | C22: =($D$13*$D$14)+$D$16 -> #REF! | D22: =$D$13*$D$15 -> 0 | E22: =D22-C22 -> #REF! | G22: =I21 -> #REF! | H22: =E22 -> #REF! | I22: =G22+H22 -> #REF!
B23: August | C23: =($D$13*$D$14)+$D$16 -> #REF! | D23: =$D$13*$D$15 -> 0 | E23: =D23-C23 -> #REF! | G23: =I22 -> #REF! | H23: =E23 -> #REF! | I23: =G23+H23 -> #REF!
B24: September | C24: =($D$13*$D$14)+$D$16 -> #REF! | D24: =$D$13*$D$15 -> 0 | E24: =D24-C24 -> #REF! | G24: =I23 -> #REF! | H24: =E24 -> #REF! | I24: =G24+H24 -> #REF!
B25: October | C25: =($D$13*$D$14)+$D$16 -> #REF! | D25: =$D$13*$D$15 -> 0 | E25: =D25-C25 -> #REF! | G25: =I24 -> #REF! | H25: =E25 -> #REF! | I25: =G25+H25 -> #REF!
B26: November | C26: =($D$13*$D$14)+$D$16 -> #REF! | D26: =$D$13*$D$15 -> 0 | E26: =D26-C26 -> #REF! | G26: =I25 -> #REF! | H26: =E26 -> #REF! | I26: =G26+H26 -> #REF!
B27: December | C27: =($D$13*$D$14)+$D$16 -> #REF! | D27: =$D$13*$D$15 -> 0 | E27: =D27-C27 -> #REF! | G27: =I26 -> #REF! | H27: =E27 -> #REF! | I27: =G27+H27 -> #REF!
B28: January | C28: =($D$13*$D$14)+$D$16 -> #REF! | D28: =$D$13*$D$15 -> 0 | E28: =D28-C28 -> #REF! | G28: =I27 -> #REF! | H28: =E28 -> #REF! | I28: =G28+H28 -> #REF!
B29: February | C29: =($D$13*$D$14)+$D$16 -> #REF! | D29: =$D$13*$D$15 -> 0 | E29: =D29-C29 -> #REF! | G29: =I28 -> #REF! | H29: =E29 -> #REF! | I29: =G29+H29 -> #REF!
B30: March | C30: =($D$13*$D$14)+$D$16 -> #REF! | D30: =$D$13*$D$15 -> 0 | E30: =D30-C30 -> #REF! | G30: =I29 -> #REF! | H30: =E30 -> #REF! | I30: =G30+H30 -> #REF!
C31: =SUM(C19:C30) -> #REF! | D31: =SUM(D19:D30) -> 0 | E31: =D31-C31 -> #REF!
B33: Buffer Capital (Production Cost of 1.5 Months) | D33: =C19*1.5 -> #REF!
B35: Total Yearly Turnover | D35: =D31 -> 0
B36: Initial Working Capital | D36: =C19+D33 -> #REF! | E36: * Working Capital Required=Cash outflow for the first month + Contingency fund
B37: Working Capital Rotation | D37: =D35/D36 -> #REF!
B40: LACTATION POWDER
B42: Monthly Boxes Produced (in Units) | D42: ='Year 3'!C26/12 -> 0
B43: Cost/Box (in ₹) | D43: ='Year 2'!D5 -> #REF!
B44: Revenue/Box (in ₹) | D44: ='Year 2'!D6 -> 286
B45: Monthly Indirect Expense (in ₹) | D45: =('Year 2'!$E$88/12)/4 -> 0
G46: * The working capital that we are investing in the first month is derived from the cash outflow that is required in the first month
B47: Month | C47: Cash Outflow | D47: Cash Inflow | E47: Difference (CO-CI) | G47: Opening W.C. | H47: Net Cash Flow | I47: Closing W.C.
B48: April | C48: =($D$42*$D$43)+$D$45 -> #REF! | D48: =$D$42*$D$44 -> 0 | E48: =D48-C48 -> #REF! | G48: =C48+D62 -> #REF! | H48: =E48 -> #REF! | I48: =G48+H48 -> #REF!
B49: May | C49: =($D$42*$D$43)+$D$45 -> #REF! | D49: =$D$42*$D$44 -> 0 | E49: =D49-C49 -> #REF! | G49: =I48 -> #REF! | H49: =E49 -> #REF! | I49: =G49+H49 -> #REF!
B50: June | C50: =($D$42*$D$43)+$D$45 -> #REF! | D50: =$D$42*$D$44 -> 0 | E50: =D50-C50 -> #REF! | G50: =I49 -> #REF! | H50: =E50 -> #REF! | I50: =G50+H50 -> #REF!
B51: July | C51: =($D$42*$D$43)+$D$45 -> #REF! | D51: =$D$42*$D$44 -> 0 | E51: =D51-C51 -> #REF! | G51: =I50 -> #REF! | H51: =E51 -> #REF! | I51: =G51+H51 -> #REF!
B52: August | C52: =($D$42*$D$43)+$D$45 -> #REF! | D52: =$D$42*$D$44 -> 0 | E52: =D52-C52 -> #REF! | G52: =I51 -> #REF! | H52: =E52 -> #REF! | I52: =G52+H52 -> #REF!
B53: September | C53: =($D$42*$D$43)+$D$45 -> #REF! | D53: =$D$42*$D$44 -> 0 | E53: =D53-C53 -> #REF! | G53: =I52 -> #REF! | H53: =E53 -> #REF! | I53: =G53+H53 -> #REF!
B54: October | C54: =($D$42*$D$43)+$D$45 -> #REF! | D54: =$D$42*$D$44 -> 0 | E54: =D54-C54 -> #REF! | G54: =I53 -> #REF! | H54: =E54 -> #REF! | I54: =G54+H54 -> #REF!
B55: November | C55: =($D$42*$D$43)+$D$45 -> #REF! | D55: =$D$42*$D$44 -> 0 | E55: =D55-C55 -> #REF! | G55: =I54 -> #REF! | H55: =E55 -> #REF! | I55: =G55+H55 -> #REF!
B56: December | C56: =($D$42*$D$43)+$D$45 -> #REF! | D56: =$D$42*$D$44 -> 0 | E56: =D56-C56 -> #REF! | G56: =I55 -> #REF! | H56: =E56 -> #REF! | I56: =G56+H56 -> #REF!
B57: January | C57: =($D$42*$D$43)+$D$45 -> #REF! | D57: =$D$42*$D$44 -> 0 | E57: =D57-C57 -> #REF! | G57: =I56 -> #REF! | H57: =E57 -> #REF! | I57: =G57+H57 -> #REF!
B58: February | C58: =($D$42*$D$43)+$D$45 -> #REF! | D58: =$D$42*$D$44 -> 0 | E58: =D58-C58 -> #REF! | G58: =I57 -> #REF! | H58: =E58 -> #REF! | I58: =G58+H58 -> #REF!
B59: March | C59: =($D$42*$D$43)+$D$45 -> #REF! | D59: =$D$42*$D$44 -> 0 | E59: =D59-C59 -> #REF! | G59: =I58 -> #REF! | H59: =E59 -> #REF! | I59: =G59+H59 -> #REF!
C60: =SUM(C48:C59) -> #REF! | D60: =SUM(D48:D59) -> 0 | E60: =D60-C60 -> #REF!
B62: Buffer Capital (Production Cost of 1.5 Months) | D62: =C48*1.5 -> #REF!
B64: Total Yearly Turnover | D64: =D60 -> 0
B65: Initial Working Capital | D65: =C48+D62 -> #REF! | E65: * Working Capital Required=Cash outflow for the first month + Contingency fund
B66: Working Capital Rotation | D66: =D64/D65 -> #REF!
B69: INFANT POWDER
B71: Monthly Boxes Produced (in Units) | D71: ='Year 3'!C23/12 -> 0
B72: Cost/Box (in ₹) | D72: ='Year 2'!E5 -> #REF!
B73: Revenue/Box (in ₹) | D73: ='Year 2'!E6 -> 242
B74: Monthly Indirect Expense (in ₹) | D74: =('Year 2'!$E$88/12)/4 -> 0
G75: * The working capital that we are investing in the first month is derived from the cash outflow that is required in the first month
B76: Month | C76: Cash Outflow | D76: Cash Inflow | E76: Difference (CO-CI) | G76: Opening W.C. | H76: Net Cash Flow | I76: Closing W.C.
B77: April | C77: =($D$71*$D$72)+$D$74 -> #REF! | D77: =$D$71*$D$73 -> 0 | E77: =D77-C77 -> #REF! | G77: =C77+D91 -> #REF! | H77: =E77 -> #REF! | I77: =G77+H77 -> #REF!
B78: May | C78: =($D$71*$D$72)+$D$74 -> #REF! | D78: =$D$71*$D$73 -> 0 | E78: =D78-C78 -> #REF! | G78: =I77 -> #REF! | H78: =E78 -> #REF! | I78: =G78+H78 -> #REF!
B79: June | C79: =($D$71*$D$72)+$D$74 -> #REF! | D79: =$D$71*$D$73 -> 0 | E79: =D79-C79 -> #REF! | G79: =I78 -> #REF! | H79: =E79 -> #REF! | I79: =G79+H79 -> #REF!
B80: July | C80: =($D$71*$D$72)+$D$74 -> #REF! | D80: =$D$71*$D$73 -> 0 | E80: =D80-C80 -> #REF! | G80: =I79 -> #REF! | H80: =E80 -> #REF! | I80: =G80+H80 -> #REF!
B81: August | C81: =($D$71*$D$72)+$D$74 -> #REF! | D81: =$D$71*$D$73 -> 0 | E81: =D81-C81 -> #REF! | G81: =I80 -> #REF! | H81: =E81 -> #REF! | I81: =G81+H81 -> #REF!
B82: September | C82: =($D$71*$D$72)+$D$74 -> #REF! | D82: =$D$71*$D$73 -> 0 | E82: =D82-C82 -> #REF! | G82: =I81 -> #REF! | H82: =E82 -> #REF! | I82: =G82+H82 -> #REF!
B83: October | C83: =($D$71*$D$72)+$D$74 -> #REF! | D83: =$D$71*$D$73 -> 0 | E83: =D83-C83 -> #REF! | G83: =I82 -> #REF! | H83: =E83 -> #REF! | I83: =G83+H83 -> #REF!
B84: November | C84: =($D$71*$D$72)+$D$74 -> #REF! | D84: =$D$71*$D$73 -> 0 | E84: =D84-C84 -> #REF! | G84: =I83 -> #REF! | H84: =E84 -> #REF! | I84: =G84+H84 -> #REF!
B85: December | C85: =($D$71*$D$72)+$D$74 -> #REF! | D85: =$D$71*$D$73 -> 0 | E85: =D85-C85 -> #REF! | G85: =I84 -> #REF! | H85: =E85 -> #REF! | I85: =G85+H85 -> #REF!
B86: January | C86: =($D$71*$D$72)+$D$74 -> #REF! | D86: =$D$71*$D$73 -> 0 | E86: =D86-C86 -> #REF! | G86: =I85 -> #REF! | H86: =E86 -> #REF! | I86: =G86+H86 -> #REF!
B87: February | C87: =($D$71*$D$72)+$D$74 -> #REF! | D87: =$D$71*$D$73 -> 0 | E87: =D87-C87 -> #REF! | G87: =I86 -> #REF! | H87: =E87 -> #REF! | I87: =G87+H87 -> #REF!
B88: March | C88: =($D$71*$D$72)+$D$74 -> #REF! | D88: =$D$71*$D$73 -> 0 | E88: =D88-C88 -> #REF! | G88: =I87 -> #REF! | H88: =E88 -> #REF! | I88: =G88+H88 -> #REF!
C89: =SUM(C77:C88) -> #REF! | D89: =SUM(D77:D88) -> 0 | E89: =D89-C89 -> #REF!
B91: Buffer Capital (Production Cost of 1.5 Months) | D91: =C77*1.5 -> #REF!
B93: Total Yearly Turnover | D93: =D89 -> 0
B94: Initial Working Capital | D94: =C77+D91 -> #REF! | E94: * Working Capital Required=Cash outflow for the first month + Contingency fund
B95: Working Capital Rotation | D95: =D93/D94 -> #REF!
B98: CHILDREN POWDER
B100: Monthly Boxes Produced (in Units) | D100: ='Year 3'!C24/12 -> 0
B101: Cost/Box (in ₹) | D101: ='Year 2'!F5 -> #REF!
B102: Revenue/Box (in ₹) | D102: ='Year 2'!F6 -> 212
B103: Monthly Indirect Expense (in ₹) | D103: =('Year 2'!$E$88/12)/4 -> 0
G104: * The working capital that we are investing in the first month is derived from the cash outflow that is required in the first month
B105: Month | C105: Cash Outflow | D105: Cash Inflow | E105: Difference (CO-CI) | G105: Opening W.C. | H105: Net Cash Flow | I105: Closing W.C.
B106: April | C106: =($D$100*$D$101)+$D$103 -> #REF! | D106: =$D$100*$D$102 -> 0 | E106: =D106-C106 -> #REF! | G106: =C106+D120 -> #REF! | H106: =E106 -> #REF! | I106: =G106+H106 -> #REF!
B107: May | C107: =($D$100*$D$101)+$D$103 -> #REF! | D107: =$D$100*$D$102 -> 0 | E107: =D107-C107 -> #REF! | G107: =I106 -> #REF! | H107: =E107 -> #REF! | I107: =G107+H107 -> #REF!
B108: June | C108: =($D$100*$D$101)+$D$103 -> #REF! | D108: =$D$100*$D$102 -> 0 | E108: =D108-C108 -> #REF! | G108: =I107 -> #REF! | H108: =E108 -> #REF! | I108: =G108+H108 -> #REF!
B109: July | C109: =($D$100*$D$101)+$D$103 -> #REF! | D109: =$D$100*$D$102 -> 0 | E109: =D109-C109 -> #REF! | G109: =I108 -> #REF! | H109: =E109 -> #REF! | I109: =G109+H109 -> #REF!
B110: August | C110: =($D$100*$D$101)+$D$103 -> #REF! | D110: =$D$100*$D$102 -> 0 | E110: =D110-C110 -> #REF! | G110: =I109 -> #REF! | H110: =E110 -> #REF! | I110: =G110+H110 -> #REF!
B111: September | C111: =($D$100*$D$101)+$D$103 -> #REF! | D111: =$D$100*$D$102 -> 0 | E111: =D111-C111 -> #REF! | G111: =I110 -> #REF! | H111: =E111 -> #REF! | I111: =G111+H111 -> #REF!
B112: October | C112: =($D$100*$D$101)+$D$103 -> #REF! | D112: =$D$100*$D$102 -> 0 | E112: =D112-C112 -> #REF! | G112: =I111 -> #REF! | H112: =E112 -> #REF! | I112: =G112+H112 -> #REF!
B113: November | C113: =($D$100*$D$101)+$D$103 -> #REF! | D113: =$D$100*$D$102 -> 0 | E113: =D113-C113 -> #REF! | G113: =I112 -> #REF! | H113: =E113 -> #REF! | I113: =G113+H113 -> #REF!
B114: December | C114: =($D$100*$D$101)+$D$103 -> #REF! | D114: =$D$100*$D$102 -> 0 | E114: =D114-C114 -> #REF! | G114: =I113 -> #REF! | H114: =E114 -> #REF! | I114: =G114+H114 -> #REF!
B115: January | C115: =($D$100*$D$101)+$D$103 -> #REF! | D115: =$D$100*$D$102 -> 0 | E115: =D115-C115 -> #REF! | G115: =I114 -> #REF! | H115: =E115 -> #REF! | I115: =G115+H115 -> #REF!
B116: February | C116: =($D$100*$D$101)+$D$103 -> #REF! | D116: =$D$100*$D$102 -> 0 | E116: =D116-C116 -> #REF! | G116: =I115 -> #REF! | H116: =E116 -> #REF! | I116: =G116+H116 -> #REF!
B117: March | C117: =($D$100*$D$101)+$D$103 -> #REF! | D117: =$D$100*$D$102 -> 0 | E117: =D117-C117 -> #REF! | G117: =I116 -> #REF! | H117: =E117 -> #REF! | I117: =G117+H117 -> #REF!
C118: =SUM(C106:C117) -> #REF! | D118: =SUM(D106:D117) -> 0 | E118: =D118-C118 -> #REF!
...

Sheet PP BOM
B2: RAW MATERIAL COST
B4: Item No. | C4: Ingredient Name | D4: In Grams | F4: In Rupees
D5: Quantity Per 100 g | E5: Quantity per 500 gm | F5: Rate / Kg | G5: Rate / Gram | H5: Rate Per 500 g
B6: 1 | C6: Skimmed Milk Powder | D6: 35 | E6: =D6*5 -> 175 | F6: 320 | G6: =F6/1000 -> 0.32 | H6: =E6*G6 -> 56
B7: 2 | C7: Maltodextrin | D7: 23.84 | E7: =D7*5 -> 119.2 | F7: 70 | G7: =F7/1000 -> 0.07 | H7: =E7*G7 -> 8.344
B8: 3 | C8: Fructooligosaccharides | D8: 5 | E8: =D8*5 -> 25 | F8: 170 | G8: =F8/1000 -> 0.17 | H8: =E8*G8 -> 4.25
B9: 4 | C9: Rice Protein | D9: 7 | E9: =D9*5 -> 35 | F9: 270 | G9: =F9/1000 -> 0.27 | H9: =E9*G9 -> 9.45
B10: 5 | C10: Soy Protein | D10: 13 | E10: =D10*5 -> 65 | F10: 290 | G10: =F10/1000 -> 0.29 | H10: =E10*G10 -> 18.85
B11: 6 | C11: Shingada Flour | D11: 2 | E11: =D11*5 -> 10 | F11: 190 | G11: =F11/1000 -> 0.19 | H11: =E11*G11 -> 1.9
B12: 7 | C12: Cocoa Powder | D12: 8 | E12: =D12*5 -> 40 | F12: 600 | G12: =F12/1000 -> 0.6 | H12: =E12*G12 -> 24 | I12: 1 | J12: KESAR PISTA
B13: 8 | C13: Vitamin and Mineral Premix | D13: 3.5 | E13: =D13*5 -> 17.5 | F13: 850 | G13: =F13/1000 -> 0.85 | H13: =E13*G13 -> 14.875 | I13: 2 | J13: CHOCOLATE
B14: 9 | C14: Culture | D14: 0.1 | E14: =D14*5 -> 0.5 | F14: 480 | G14: =F14/1000 -> 0.48 | H14: =E14*G14 -> 0.24
B15: 10 | C15: Sucralose | D15: 0.06 | E15: =D15*5 -> 0.3 | F15: 1450 | G15: =F15/1000 -> 1.45 | H15: =E15*G15 -> 0.435
B16: 11 | C16: Nature Identical Flavour | D16: 2 | E16: =D16*5 -> 10 | F16: 700 | G16: =F16/1000 -> 0.7 | H16: =E16*G16 -> 7 | J16: KG | K16: BOXES | L16: COST
B17: 12 | C17: Multisense | D17: 0.5 | E17: =D17*5 -> 2.5 | F17: 2500 | G17: =F17/1000 -> 2.5 | H17: =E17*G17 -> 6.25 | J17: =(K17*500)/1000 -> 400 | K17: 800 | L17: =K17*H25 -> 142875.2 | M17: COGS_ Preg
D18: =SUM(D6:D17) -> 100 | E18: =SUM(E6:E17) -> 500 | H18: =SUM(H6:H17) -> 151.594 | J18: =(K18*500)/1000 -> 400 | K18: 800 | L18: =K18*'LP BOM'!H28 -> 127068 | M18: COGS_Lact
J19: =J17+J18 -> 800 | K19: =K17+K18 -> 1600 | L19: =L17+L18 -> 269943.2 | M19: TOTAL
B20: OTHER COSTS
C22: Packaging cost | H22: 20
C23: Conversion cost | H23: ='Contract (1 yr)'!C43 -> 7
F25: TOTAL COST / BOX | H25: =SUM(H18:H23) -> 178.594
F27: COST / BATCH | H27: 20000000
F29: BOXES / BATCH | H29: =H27/H25 -> 111985.85
F31: AS PER PROJETIONS SHEET
F32: Total Cost (Excl. GST) | H32: =IFERROR(__xludf.DUMMYFUNCTION("importrange(""https://docs.google.com/spreadsheets/d/1DXOBRjKEc9pOcmohKWx0l59g3hrSjk2ZicxFB9zphD4/edit?gid=1408855594#gid=1408855594"",""COGS Breakup!C70:C72"")"),"#REF!") -> #REF! | I32: VS | J32: =H25 -> 178.594
F33: GST 18%
F34: Total Cost (Incl. GST)
B37: Mawa Kulfi
B38: Item No. | C38: Ingredient Name | D38: In Grams | F38: In Rupees
D39: Quantity Per 100 g | E39: Quantity per 500 gm | F39: Rate / Kg | G39: Rate / Gram | H39: Rate Per 500 g
B40: 1 | C40: Skimmed Milk Powder | D40: 36 | E40: =D40*5 -> 180 | F40: 240 | G40: =F40/1000 -> 0.24 | H40: =E40*G40 -> 43.2
B41: 2 | C41: Maltodextrin | D41: 27.84 | E41: =D41*5 -> 139.2 | F41: 70 | G41: =F41/1000 -> 0.07 | H41: =E41*G41 -> 9.744
B42: 3 | C42: Fructooligosaccharides | D42: 5 | E42: =D42*5 -> 25 | F42: 170 | G42: =F42/1000 -> 0.17 | H42: =E42*G42 -> 4.25
B43: 4 | C43: Rice Protein | D43: 8 | E43: =D43*5 -> 40 | F43: 270 | G43: =F43/1000 -> 0.27 | H43: =E43*G43 -> 10.8
B44: 5 | C44: Soy Protein | D44: 15 | E44: =D44*5 -> 75 | F44: 290 | G44: =F44/1000 -> 0.29 | H44: =E44*G44 -> 21.75
B45: 6 | C45: Shingada Flour | D45: 2 | E45: =D45*5 -> 10 | F45: 190 | G45: =F45/1000 -> 0.19 | H45: =E45*G45 -> 1.9
B46: 7 | D46: 0 | E46: =D46*5 -> 0 | F46: 600 | G46: =F46/1000 -> 0.6 | H46: =E46*G46 -> 0
B47: 8 | C47: Vitamin and Mineral Premix | D47: 3.5 | E47: =D47*5 -> 17.5 | F47: 850 | G47: =F47/1000 -> 0.85 | H47: =E47*G47 -> 14.875
B48: 9 | C48: Culture | D48: 0.1 | E48: =D48*5 -> 0.5 | F48: 480 | G48: =F48/1000 -> 0.48 | H48: =E48*G48 -> 0.24
B49: 10 | C49: Sucralose | D49: 0.06 | E49: =D49*5 -> 0.3 | F49: 1300 | G49: =F49/1000 -> 1.3 | H49: =E49*G49 -> 0.39
B50: 11 | C50: Nature Identical Flavour | D50: 2 | E50: =D50*5 -> 10 | F50: 700 | G50: =F50/1000 -> 0.7 | H50: =E50*G50 -> 7
B51: 12 | C51: Multisense | D51: 0.5 | E51: =D51*5 -> 2.5 | G51: =F51/1000 -> 0 | H51: =E51*G51 -> 0
D52: =SUM(D40:D51) -> 100 | E52: =SUM(E40:E51) -> 500 | H52: =SUM(H40:H51) -> 114.149

Sheet LP BOM
B2: RAW MATERIAL COST
B4: Item No. | C4: Ingredient Name | D4: In Grams | F4: In Rupees
D5: Quantity Per 100 g | E5: Quantity per 500 gm | F5: Rate / Kg | G5: Rate / Gram | H5: Rate Per 500 g
B6: 1 | C6: Skimmed Milk Powder | D6: 35.5 | E6: =D6*5 -> 177.5 | F6: 320 | G6: =F6/1000 -> 0.32 | H6: =E6*G6 -> 56.8
B7: 2 | C7: Maltodextrin | D7: 24.85 | E7: =D7*5 -> 124.25 | F7: 70 | G7: =F7/1000 -> 0.07 | H7: =E7*G7 -> 8.6975
B8: 3 | C8: Fructooligosaccharides | D8: 5 | E8: =D8*5 -> 25 | F8: 170 | G8: =F8/1000 -> 0.17 | H8: =E8*G8 -> 4.25
B9: 4 | C9: Rice Protein | D9: 8 | E9: =D9*5 -> 40 | F9: 270 | G9: =F9/1000 -> 0.27 | H9: =E9*G9 -> 10.8 | I9: 1 | J9: MAWA KULFI
B10: 5 | C10: Soy Protein | D10: 15 | E10: =D10*5 -> 75 | F10: 290 | G10: =F10/1000 -> 0.29 | H10: =E10*G10 -> 21.75 | I10: 2 | J10: VANILA
B11: 6 | C11: Shingada Flour | D11: 2 | E11: =D11*5 -> 10 | F11: 180 | G11: =F11/1000 -> 0.18 | H11: =E11*G11 -> 1.8
B12: 7 | C12: Vitamin and Mineral premix | D12: 3.5 | E12: =D12*5 -> 17.5 | F12: 800 | G12: =F12/1000 -> 0.8 | H12: =E12*G12 -> 14
B13: 8 | C13: Culture | D13: 0.1 | E13: =D13*5 -> 0.5 | F13: 450 | G13: =F13/1000 -> 0.45 | H13: =E13*G13 -> 0.225
B14: 9 | C14: Sucralose | D14: 0.05 | E14: =D14*5 -> 0.25 | F14: 1450 | G14: =F14/1000 -> 1.45 | H14: =E14*G14 -> 0.3625
B15: 10 | C15: Nature Identical Flavour Cardamom | D15: 1.5 | E15: =D15*5 -> 7.5 | F15: 700 | G15: =F15/1000 -> 0.7 | H15: =E15*G15 -> 5.25
B16: 11 | C16: Shatavari | D16: 2 | E16: =D16*5 -> 10 | F16: 350 | G16: =F16/1000 -> 0.35 | H16: =E16*G16 -> 3.5
B17: 12 | C17: Ashwagandha | D17: 1 | E17: =D17*5 -> 5 | F17: 650 | G17: =F17/1000 -> 0.65 | H17: =E17*G17 -> 3.25
B18: 13 | C18: Moringa | D18: 0.5 | E18: =D18*5 -> 2.5 | F18: 180 | G18: =F18/1000 -> 0.18 | H18: =E18*G18 -> 0.45
B19: 14 | C19: Funnel | D19: 0.5 | E19: =D19*5 -> 2.5 | F19: 180 | G19: =F19/1000 -> 0.18 | H19: =E19*G19 -> 0.45
B20: 15 | C20: Cinnamon | D20: 0.5 | E20: =D20*5 -> 2.5 | F20: 100 | G20: =F20/1000 -> 0.1 | H20: =E20*G20 -> 0.25
D21: =SUM(D6:D20) -> 100 | E21: =SUM(E6:E20) -> 500 | H21: =SUM(H6:H20) -> 131.835
B23: OTHER COSTS
C25: Packaging cost | H25: 20
C26: Conversion cost | H26: ='Contract (1 yr)'!C43 -> 7
F28: TOTAL COST / BOX | H28: =sum(H21:H26) -> 158.835 | K28: =H28*800 -> 127068 | L28: - COST OF 400 Boxes
F30: PRODUCTION COST / BATCH | H30: 20000000
F32: BOXES / BATCH | H32: =H30/H28 -> 125916.83
F34: AS PER PROJETIONS SHEET
F35: Total Cost (Excl. GST) | H35: =IFERROR(__xludf.DUMMYFUNCTION("importrange(""https://docs.google.com/spreadsheets/d/1DXOBRjKEc9pOcmohKWx0l59g3hrSjk2ZicxFB9zphD4/edit?gid=1408855594#gid=1408855594"",""COGS Breakup!C103:C105"")"),"#REF!") -> #REF! | I35: VS | J35: =H28 -> 158.835
F36: GST 18%
F37: Total Cost (Incl. GST)
C39: Kesar
B40: Item No. | C40: Ingredient Name | D40: In Grams | F40: In Rupees
D41: Quantity Per 100 g | E41: Quantity per 500 gm | F41: Rate / Kg | G41: Rate / Gram | H41: Rate Per 500 g
B42: 1 | C42: Skimmed Milk Powder | D42: 35 | E42: =D42*5 -> 175 | F42: 240 | G42: =F42/1000 -> 0.24 | H42: =E42*G42 -> 42
B43: 2 | C43: Maltodextrin | D43: 25 | E43: =D43*5 -> 125 | F43: 50 | G43: =F43/1000 -> 0.05 | H43: =E43*G43 -> 6.25
B44: 3 | C44: Fructooligosaccharides | D44: 5 | E44: =D44*5 -> 25 | F44: 170 | G44: =F44/1000 -> 0.17 | H44: =E44*G44 -> 4.25
B45: 4 | C45: Rice Protein | D45: 8.35 | E45: =D45*5 -> 41.75 | F45: 270 | G45: =F45/1000 -> 0.27 | H45: =E45*G45 -> 11.2725
B46: 5 | C46: Soy Protein | D46: 15 | E46: =D46*5 -> 75 | F46: 290 | G46: =F46/1000 -> 0.29 | H46: =E46*G46 -> 21.75
B47: 6 | C47: Shingada Flour | D47: 2 | E47: =D47*5 -> 10 | F47: 180 | G47: =F47/1000 -> 0.18 | H47: =E47*G47 -> 1.8
B48: 7 | C48: Vitamin and Mineral premix | D48: 3.5 | E48: =D48*5 -> 17.5 | F48: 800 | G48: =F48/1000 -> 0.8 | H48: =E48*G48 -> 14
B49: 8 | C49: Culture | D49: 0.1 | E49: =D49*5 -> 0.5 | F49: 450 | G49: =F49/1000 -> 0.45 | H49: =E49*G49 -> 0.225
B50: 9 | C50: Sucralose | D50: 0.05 | E50: =D50*5 -> 0.25 | F50: 1300 | G50: =F50/1000 -> 1.3 | H50: =E50*G50 -> 0.325
B51: 10 | C51: Nature Identical Flavour kesar | D51: 2 | E51: =D51*5 -> 10 | F51: 700 | G51: =F51/1000 -> 0.7 | H51: =E51*G51 -> 7
B52: 11 | C52: Shatavari | D52: 2 | E52: =D52*5 -> 10 | F52: 350 | G52: =F52/1000 -> 0.35 | H52: =E52*G52 -> 3.5
B53: 12 | C53: Ashwagandha | D53: 1 | E53: =D53*5 -> 5 | F53: 190 | G53: =F53/1000 -> 0.19 | H53: =E53*G53 -> 0.95
... B55: 14 | C55: Cinnamon Powder | D55: 0.5 | E55: =D55*5 -> 2.5 | F55: 180 | G55: =F55/1000 -> 0.18 | H55: =E55*G55 -> 0.45
D56: 0 | E56: =D56*5 -> 0 | G56: =F56/1000 -> 0 | H56: =E56*G56 -> 0
D57: =SUM(D42:D56) -> 100 | E57: =SUM(E42:E56) -> 500 | H57: =SUM(H42:H56) -> 114.2225

Sheet IFM BOM
B2: RAW MATERIAL COST
B4: Item No. | C4: Ingredient Name | D4: In Grams | F4: In Rupees
D5: Quantity Per 100 g | E5: Quantity per 400 gm | F5: Rate / Kg | G5: Rate / Gram | H5: Rate Per 400 g
B6: 1 | C6: Skim Milk Powder | D6: 35 | E6: =D6*4 -> 140 | F6: 320 | G6: =F6/1000 -> 0.32 | H6: =E6*G6 -> 44.8
B7: 2 | C7: Demineralised Whey Powder | D7: 22 | E7: =D7*4 -> 88 | F7: 150 | G7: =F7/1000 -> 0.15 | H7: =E7*G7 -> 13.2
B8: 3 | C8: Lactose | D8: 13 | E8: =D8*4 -> 52 | F8: 200 | G8: =F8/1000 -> 0.2 | H8: =E8*G8 -> 10.4
B9: 4 | C9: Maltodextrin | D9: 8.05 | E9: =D9*4 -> 32.2 | F9: 70 | G9: =F9/1000 -> 0.07 | H9: =E9*G9 -> 2.254
B10: 5 | C10: High Oleic Sunflower Oil | D10: 6 | E10: =D10*4 -> 24 | F10: 350 | G10: =F10/1000 -> 0.35 | H10: =E10*G10 -> 8.4
B11: 6 | C11: Soya oil Powder | D11: 4 | E11: =D11*4 -> 16 | F11: 100 | G11: =F11/1000 -> 0.1 | H11: =E11*G11 -> 1.6
B12: 7 | C12: Coconut oil Powder | D12: 2 | E12: =D12*4 -> 8 | F12: 250 | G12: =F12/1000 -> 0.25 | H12: =E12*G12 -> 2
B13: 8 | C13: Milk fat powder | D13: 4 | E13: =D13*4 -> 16 | F13: 230 | G13: =F13/1000 -> 0.23 | H13: =E13*G13 -> 3.68
B14: 9 | C14: DHA oil Powder | D14: 0.2 | E14: =D14*4 -> 0.8 | F14: 400 | G14: =F14/1000 -> 0.4 | H14: =E14*G14 -> 0.32
B15: 10 | C15: ARA oil Powder | D15: 0.2 | E15: =D15*4 -> 0.8 | F15: 150 | G15: =F15/1000 -> 0.15 | H15: =E15*G15 -> 0.12
B16: 11 | C16: Fructooligosaccharides | D16: 2 | E16: =D16*4 -> 8 | F16: 170 | G16: =F16/1000 -> 0.17 | H16: =E16*G16 -> 1.36
B17: 12 | C17: Galactooligosaccharides | D17: 1.5 | E17: =D17*4 -> 6 | F17: 200 | G17: =F17/1000 -> 0.2 | H17: =E17*G17 -> 1.2
... B22: 17 | C22: L-Carnitine | D22: 0.05 | E22: =D22*4 -> 0.2 | F22: 2000 | G22: =F22/1000 -> 2 | H22: =E22*G22 -> 0.4
B23: RAW MATERIAL TOTAL COST | D23: =SUM(D6:D22) -> 100.008 | E23: =D23*5 -> 500.04 | H23: =SUM(H6:H22) -> 92.9836
B25: OTHER COSTS
C27: Packaging | H27: 20
C28: Conversion | H28: ='Contract (1 yr)'!C51 -> 11.2
F30: TOTAL COST / BOX | H30: =H23+H27+H28 -> 124.1836
F32: PRODUCTION COST / BATCH | H32: 20000000
F34: BOXES / BATCH | H34: =H32/H30 -> 161051.86
F36: BOXES / VARIANT | H36: =H34/3 -> 53683.954
F38: AS PER PROJETIONS SHEET
F39: Total Cost (Excl. GST) | H39: =IFERROR(__xludf.DUMMYFUNCTION("importrange(""https://docs.google.com/spreadsheets/d/1bEcp3VCHzQgxan8VY9FCqLk1Yk8qAjekoqv5jLH-RCM/edit?gid=1653862983#gid=1653862983"",""COGS Breakup!C69:C71"")"),"#REF!") -> #REF! | I39: VS | J39: =H30 -> 124.1836
F40: GST 18%
F41: Total Cost (Incl. GST)

Sheet CNP BOM
B2: RAW MATERIAL COST
B4: Item No. | C4: Ingredient Name | D4: In Grams | F4: In Rupees
D5: Quantity Per 100 g | E5: Quantity per 400 gm | F5: Rate / Kg | G5: Rate / Gram | H5: Rate Per 400 g
B6: 1 | C6: Skimmed Milk Powder | D6: 35 | E6: =D6*4 -> 140 | F6: 320 | G6: =F6/1000 -> 0.32 | H6: =E6*G6 -> 44.8
B7: 2 | C7: Maltodextrin | D7: 14 | E7: =D7*4 -> 56 | F7: 70 | G7: =F7/1000 -> 0.07 | H7: =E7*G7 -> 3.92
B8: 3 | C8: Nuts blend(Almond, Cashew, Walnut, Pista, Dates) | D8: 6 | E8: =D8*4 -> 24 | F8: 180 | G8: =F8/1000 -> 0.18 | H8: =E8*G8 -> 4.32
B9: 4 | C9: Cocoa powder | D9: 6 | E9: =D9*4 -> 24 | F9: 600 | G9: =F9/1000 -> 0.6 | H9: =E9*G9 -> 14.4 | I9: 1 | J9: VANILLA
B10: 5 | C10: Palmyra Jaggery | D10: 13 | E10: =D10*4 -> 52 | F10: 50 | G10: =F10/1000 -> 0.05 | H10: =E10*G10 -> 2.6 | I10: 2 | J10: CHOCOLATE
B11: 6 | C11: Fructooligosaccharides | D11: 2 | E11: =D11*4 -> 8 | F11: 170 | G11: =F11/1000 -> 0.17 | H11: =E11*G11 -> 1.36
B12: 7 | C12: Nature Identical Flavours | D12: 2 | E12: =D12*4 -> 8 | F12: 600 | G12: =F12/1000 -> 0.6 | H12: =E12*G12 -> 4.8
B13: 8 | C13: Vitamins | D13: 1 | E13: =D13*4 -> 4 | F13: 500 | G13: =F13/1000 -> 0.5 | H13: =E13*G13 -> 2
B14: 9 | C14: Minerals | D14: 1 | E14: =D14*4 -> 4 | F14: 400 | G14: =F14/1000 -> 0.4 | H14: =E14*G14 -> 1.6
B15: 10 | C15: Fruit Powder | D15: 12 | E15: =D15*4 -> 48 | F15: 200 | G15: =F15/1000 -> 0.2 | H15: =E15*G15 -> 9.6
B16: 11 | C16: Ragi Powder | D16: 8 | E16: =D16*4 -> 32 | F16: 40 | G16: =F16/1000 -> 0.04 | H16: =E16*G16 -> 1.28
D17: =SUM(D6:D16) -> 100 | E17: =D17*4 -> 400 | H17: =SUM(H6:H16) -> 90.68
B19: OTHER COSTS
C21: Packaging Cost | H21: 20
C22: Conversion cost | H22: ='Contract (1 yr)'!C51 -> 11.2
F24: TOTAL COST / BOX | H24: =sum(H17:H22) -> 121.88
F26: PRODUCTION COST / BATCH | H26: 20000000
F28: BOXES / BATCH | H28: =H26/H24 -> 164095.83
F30: AS PER PROJETIONS SHEET
F31: Total Cost (Excl. GST) | H31: =IFERROR(__xludf.DUMMYFUNCTION("importrange(""https://docs.google.com/spreadsheets/d/1bEcp3VCHzQgxan8VY9FCqLk1Yk8qAjekoqv5jLH-RCM/edit?gid=1653862983#gid=1653862983"",""COGS Breakup!C102:C104"")"),"#REF!") -> #REF! | I31: VS | J31: =H24 -> 121.88
F32: GST 18%
F33: Total Cost (Incl. GST)

Sheet Product Line
B2: * SKUs may vary from year to year due to addition of new flavours (Currently 1-2 flavours of each Variant)
B3: Years | C3: All Products | D3: Tier
B4: Year 1 | C4: 4
C5: Pregnancy Powder | D5: 3
C6: Lactation Powder | D6: 3
C7: Infant Powder | D7: 3
C8: Children Powder | D8: 3
B10: Year 2 | C10: =COUNTA(C11:C24) -> 14
C11: Pregnancy Powder- Trimester 1 | D11: 1
C12: Pregnancy Powder- Trimester 2 | D12: 1
C13: Pregnancy Powder- Trimester 3 | D13: 1
C14: Lactation Powder | D14: 1
C15: Infant Formula Powder- 0 to 6m | D15: 1
C16: Infant Formula Powder- 6 to 12m | D16: 1
C17: Infant Formula Powder- 12 to 24m | D17: 1
C18: Infant Complementary Food- 6 to 12m | D18: 1
C19: Infant Complementary Food- 12 to 24m | D19: 1
C20: Children Powder | D20: 1
C21: Pregnancy Powder | D21: 3
C22: Lactation Powder | D22: 3
... C24: Children Powder | D24: 3
B26: Year 3 | C26: =counta(C27:C50) -> 24
C27: Pregnancy Powder- Trimester 1 | D27: 1
C28: Pregnancy Powder- Trimester 2 | D28: 1
C29: Pregnancy Powder- Trimester 3 | D29: 1
C30: Lactation Powder | D30: 1
C31: Infant Formula Powder- 0 to 6m | D31: 1
C32: Infant Formula Powder- 6 to 12m | D32: 1
C33: Infant Formula Powder- 12 to 24m | D33: 1
C34: Infant Complementary Food- 6 to 12m | D34: 1
C35: Infant Complementary Food- 12 to 24m | D35: 1
C36: Children Powder | D36: 1
C37: Pregnancy Powder- Trimester 1 | D37: 2
C38: Pregnancy Powder- Trimester 2 | D38: 2
... C50: Children Powder | D50: 3
B52: Year 4 | C52: =counta(C53:C76) -> 24
C53: Pregnancy Powder- Trimester 1 | D53: 1
C54: Pregnancy Powder- Trimester 2 | D54: 1
C55: Pregnancy Powder- Trimester 3 | D55: 1
C56: Lactation Powder | D56: 1
C57: Infant Formula Powder- 0 to 6m | D57: 1
C58: Infant Formula Powder- 6 to 12m | D58: 1
C59: Infant Formula Powder- 12 to 24m | D59: 1
C60: Infant Complementary Food- 6 to 12m | D60: 1
C61: Infant Complementary Food- 12 to 24m | D61: 1
C62: Children Powder | D62: 1
C63: Pregnancy Powder- Trimester 1 | D63: 2
C64: Pregnancy Powder- Trimester 2 | D64: 2
... C76: Children Powder | D76: 3
B78: Year 5 | C78: =counta(C79:C102) -> 24
C79: Pregnancy Powder- Trimester 1 | D79: 1
C80: Pregnancy Powder- Trimester 2 | D80: 1
C81: Pregnancy Powder- Trimester 3 | D81: 1
C82: Lactation Powder | D82: 1
C83: Infant Formula Powder- 0 to 6m | D83: 1
C84: Infant Formula Powder- 6 to 12m | D84: 1
C85: Infant Formula Powder- 12 to 24m | D85: 1
C86: Infant Complementary Food- 6 to 12m | D86: 1
C87: Infant Complementary Food- 12 to 24m | D87: 1
C88: Children Powder | D88: 1
C89: Pregnancy Powder- Trimester 1 | D89: 2
C90: Pregnancy Powder- Trimester 2 | D90: 2
... C102: Children Powder | D102: 3
B105: Pregnancy Powder (GREESHMA)
B106: Tier 1 | C106: Wonder Womb
B107: Tier 2 | C107: Matrunayana
B108: Tier 3 | C108: Garbhika
B110: Lactation Powder
B111: Tier 1 | C111: Lacto Love
B112: Tier 2 | C112: Milknest
B113: Tier 3 | C113: Matrusneha
B115: Infant Nutrition
B116: Tier 1 | C116: Alpha Baby
B117: Tier 2 | C117: Healthy Cubs
B118: Tier 3 | C118: Poshit
B120: Child Nutrition
B121: Tier 1 | C121: Little Vita GOLD
B122: Tier 2 | C122: Little Vita PRO
B123: Tier 3 | C123: Little Vita CHINDI

Sheet Strategy
H5: Years | I5: 1 | J5: 2 | K5: 3 | L5: 4 | M5: 5
H6: Tiers Targetted | I6: Tier 3 | J6: Tier 1 & 3 | K6: All Tiers | L6: All Tiers | M6: All Tiers
H7: Investor Capital Deployed (in Cr) | I7: 22 | J7: 60 | K7: 220 | L7: 0 | M7: 0
H8: Products (SKUs) | I8: ='Product Line'!C4 -> 4 | J8: ='Product Line'!C10 -> 14 | K8: ='Product Line'!C26 -> 24 | L8: =K8 -> 24 | M8: =L8 -> 24
H9: Manufacturing | I9: Contract Manufacturing | J9: In-house & Third Party Manufacturing | K9: In-house & Third Party Manufacturing | L9: In-house & Third Party Manufacturing | M9: In-house & Third Party Manufacturing
H10: Plants Set up | I10: ='In-house (2-5yrs)'!C3 -> 0 | J10: ='In-house (2-5yrs)'!C4 -> 1 | K10: ='In-house (2-5yrs)'!C5 -> 2 | L10: ='In-house (2-5yrs)'!C6 -> 3 | M10: ='In-house (2-5yrs)'!C7 -> 3
H11: Total Plants | I11: =I10 -> 0 | J11: =J10+I11 -> 1 | K11: =K10+J11 -> 3 | L11: =L10+K11 -> 6 | M11: =M10+L11 -> 9

Sheet P&L
G2: Rs. in cr
B3: YEARS | C3: 1 | D3: 2 | E3: 3 | F3: 4 | G3: 5
B5: REVENUE
B6: Revenue from Operation | C6: ='Contract (1 yr)'!E27 -> 88.413 | D6: ='In-house (2-5yrs)'!F4+'Third Party (2-5yrs)'!R4 -> #REF! | E6: ='In-house (2-5yrs)'!F5+'Third Party (2-5yrs)'!R5 -> #REF! | F6: ='In-house (2-5yrs)'!F6+'Third Party (2-5yrs)'!R6 -> #REF! | G6: ='In-house (2-5yrs)'!F7+'Third Party (2-5yrs)'!R7 -> #REF!
B7: Pregnancy Powder- Trimester 1- Tier 1 | D7: =('In-house (2-5yrs)'!$C$20/3)/10^7 -> #REF! | E7: =('In-house (2-5yrs)'!$C$21/10^7)/3 -> #REF! | F7: =('In-house (2-5yrs)'!$C$22/10^7)/3 -> #REF! | G7: ='In-house (2-5yrs)'!$C$23/10^7/3 -> #REF!
B8: Pregnancy Powder- Trimester 2- Tier 1 | D8: =('In-house (2-5yrs)'!$C$20/3)/10^7 -> #REF! | E8: =('In-house (2-5yrs)'!$C$21/10^7)/3 -> #REF! | F8: =('In-house (2-5yrs)'!$C$22/10^7)/3 -> #REF! | G8: ='In-house (2-5yrs)'!$C$23/10^7/3 -> #REF!
B9: Pregnancy Powder- Trimester 3- Tier 1 | D9: =('In-house (2-5yrs)'!$C$20/3)/10^7 -> #REF! | E9: =('In-house (2-5yrs)'!$C$21/10^7)/3 -> #REF! | F9: =('In-house (2-5yrs)'!$C$22/10^7)/3 -> #REF! | G9: ='In-house (2-5yrs)'!$C$23/10^7/3 -> #REF!
B10: Lactation Powder- Tier 1 | D10: ='In-house (2-5yrs)'!F20/10^7 -> 0 | E10: ='In-house (2-5yrs)'!F21/10^7 -> 0 | F10: ='In-house (2-5yrs)'!F22/10^7 -> 0 | G10: ='In-house (2-5yrs)'!F23/10^7 -> 0
B11: Infant Formula Powder- 0 to 6m- Tier 1 | D11: =('In-house (2-5yrs)'!$D$97*'In-house (2-5yrs)'!$I$12)/10^7/5 -> #REF! | E11: =('In-house (2-5yrs)'!$I$21/10^7)/5 -> #REF! | F11: =('In-house (2-5yrs)'!$I$22/10^7)/5 -> #REF! | G11: ='In-house (2-5yrs)'!$I$23/10^7/5 -> #REF!
B12: Infant Formula Powder- 6 to 12m- Tier 1 | D12: =('In-house (2-5yrs)'!$D$97*'In-house (2-5yrs)'!$I$12)/10^7/5 -> #REF! | E12: =('In-house (2-5yrs)'!$I$21/10^7)/5 -> #REF! | F12: =('In-house (2-5yrs)'!$I$22/10^7)/5 -> #REF! | G12: ='In-house (2-5yrs)'!$I$23/10^7/5 -> #REF!
B13: Infant Formula Powder- 12 to 24m- Tier 1 | D13: =('In-house (2-5yrs)'!$D$97*'In-house (2-5yrs)'!$I$12)/10^7/5 -> #REF! | E13: =('In-house (2-5yrs)'!$I$21/10^7)/5 -> #REF! | F13: =('In-house (2-5yrs)'!$I$22/10^7)/5 -> #REF! | G13: ='In-house (2-5yrs)'!$I$23/10^7/5 -> #REF!
B14: Infant Complementary Food- 6 to 12m- Tier 1 | D14: =('In-house (2-5yrs)'!$D$97*'In-house (2-5yrs)'!$I$12)/10^7/5 -> #REF! | E14: =('In-house (2-5yrs)'!$I$21/10^7)/5 -> #REF! | F14: =('In-house (2-5yrs)'!$I$22/10^7)/5 -> #REF! | G14: ='In-house (2-5yrs)'!$I$23/10^7/5 -> #REF!
B15: Infant Complementary Food- 12 to 24m- Tier 1 | D15: =('In-house (2-5yrs)'!$D$97*'In-house (2-5yrs)'!$I$12)/10^7/5 -> #REF! | E15: =('In-house (2-5yrs)'!$I$21/10^7)/5 -> #REF! | F15: =('In-house (2-5yrs)'!$I$22/10^7)/5 -> #REF! | G15: ='In-house (2-5yrs)'!$I$23/10^7/5 -> #REF!
B16: Children Powder- Tier 1 | D16: =('In-house (2-5yrs)'!L12*'In-house (2-5yrs)'!D100)/10^7 -> 0 | E16: ='In-house (2-5yrs)'!L21/10^7 -> 0 | F16: ='In-house (2-5yrs)'!L22/10^7 -> 0 | G16: ='In-house (2-5yrs)'!L23/10^7 -> 0
B17: Pregnancy Powder- Trimester 1- Tier 2 | E17: =('In-house (2-5yrs)'!$D$21/10^7)/3 -> 0 | F17: ='In-house (2-5yrs)'!$D$22/10^7/3 -> 0 | G17: ='In-house (2-5yrs)'!$D$23/10^7/3 -> 0
B18: Pregnancy Powder- Trimester 2- Tier 2 | E18: =('In-house (2-5yrs)'!$D$21/10^7)/3 -> 0 | F18: ='In-house (2-5yrs)'!$D$22/10^7/3 -> 0 | G18: ='In-house (2-5yrs)'!$D$23/10^7/3 -> 0
B19: Pregnancy Powder- Trimester 3- Tier 2 | E19: =('In-house (2-5yrs)'!$D$21/10^7)/3 -> 0 | F19: ='In-house (2-5yrs)'!$D$22/10^7/3 -> 0 | G19: ='In-house (2-5yrs)'!$D$23/10^7/3 -> 0
B20: Lactation Powder- Tier 2 | E20: ='In-house (2-5yrs)'!G21/10^7 -> 0 | F20: ='In-house (2-5yrs)'!G22/10^7 -> 0 | G20: ='In-house (2-5yrs)'!G23/10^7 -> 0
B21: Infant Formula Powder- 0 to 6m- Tier 2 | E21: =('In-house (2-5yrs)'!$J$21/10^7)/5 -> 0 | F21: ='In-house (2-5yrs)'!$J$22/10^7/5 -> 0 | G21: ='In-house (2-5yrs)'!$J$23/10^7/5 -> 0
B22: Infant Formula Powder- 6 to 12m- Tier 2 | E22: =('In-house (2-5yrs)'!$J$21/10^7)/5 -> 0 | F22: ='In-house (2-5yrs)'!$J$22/10^7/5 -> 0 | G22: ='In-house (2-5yrs)'!$J$23/10^7/5 -> 0
B23: Infant Formula Powder- 12 to 24m- Tier 2 | E23: =('In-house (2-5yrs)'!$J$21/10^7)/5 -> 0 | F23: ='In-house (2-5yrs)'!$J$22/10^7/5 -> 0 | G23: ='In-house (2-5yrs)'!$J$23/10^7/5 -> 0
B24: Infant Complementary Food- 6 to 12m- Tier 2 | E24: =('In-house (2-5yrs)'!$J$21/10^7)/5 -> 0 | F24: ='In-house (2-5yrs)'!$J$22/10^7/5 -> 0 | G24: ='In-house (2-5yrs)'!$J$23/10^7/5 -> 0
B25: Infant Complementary Food- 12 to 24m- Tier 2 | E25: =('In-house (2-5yrs)'!$J$21/10^7)/5 -> 0 | F25: ='In-house (2-5yrs)'!$J$22/10^7/5 -> 0 | G25: ='In-house (2-5yrs)'!$J$23/10^7/5 -> 0
B26: Children Powder- Tier 2 | E26: ='In-house (2-5yrs)'!M21/10^7 -> 0 | F26: ='In-house (2-5yrs)'!M22/10^7 -> 0 | G26: ='In-house (2-5yrs)'!M23/10^7 -> 0
B27: Pregnancy Powder- Tier 3 | C27: ='Contract (1 yr)'!E25 -> 21.84 | D27: =('In-house (2-5yrs)'!E12*'In-house (2-5yrs)'!D93)/10^7 -> 0 | E27: ='In-house (2-5yrs)'!E21/10^7 -> 0 | F27: ='In-house (2-5yrs)'!E22/10^7 -> 0 | G27: ='In-house (2-5yrs)'!E23/10^7 -> 0
B28: Lactation Powder- Tier 3 | C28: ='Contract (1 yr)'!E26 -> 22.308 | D28: =('In-house (2-5yrs)'!D96*'In-house (2-5yrs)'!H12)/10^7 -> 0 | E28: ='In-house (2-5yrs)'!H21/10^7 -> 0 | F28: ='In-house (2-5yrs)'!H22/10^7 -> 0 | G28: ='In-house (2-5yrs)'!H23/10^7 -> 0
B29: Infant Powder- Tier 3 | C29: ='Contract (1 yr)'!E23 -> 23.595 | D29: =('In-house (2-5yrs)'!K12*'In-house (2-5yrs)'!D99)/10^7 -> 0 | E29: ='In-house (2-5yrs)'!K21/10^7 -> 0 | F29: ='In-house (2-5yrs)'!K22/10^7 -> 0 | G29: ='In-house (2-5yrs)'!K23/10^7 -> 0
B30: Children Powder- Tier 3 | C30: ='Contract (1 yr)'!E24 -> 20.67 | D30: =('In-house (2-5yrs)'!D102*'In-house (2-5yrs)'!N12)/10^7 -> 0 | E30: ='In-house (2-5yrs)'!N21/10^7 -> 0 | F30: ='In-house (2-5yrs)'!N22/10^7 -> 0 | G30: ='In-house (2-5yrs)'!N23/10^7 -> 0
B31: Contract Manufacturing | D31: ='Third Party (2-5yrs)'!R4 -> #REF! | E31: ='Third Party (2-5yrs)'!R5 -> #REF! | F31: ='Third Party (2-5yrs)'!R6 -> #REF! | G31: ='Third Party (2-5yrs)'!R7 -> #REF!
B32: Other income | C32: ='Project Financing'!U14 -> 0 | D32: ='Project Financing'!U15 -> #REF! | E32: ='Project Financing'!U16 -> #REF! | F32: ='Project Financing'!U17 -> #REF! | G32: ='Project Financing'!U18 -> #REF!
B33: Total Revenue | C33: =C6+C32 -> 88.413 | D33: =D6+D32 -> #REF! | E33: =E6+E32 -> #REF! | F33: =F6+F32 -> #REF! | G33: =G6+G32 -> #REF!
B34: Revenue Growth % | D34: =(D33-C33)/C33 -> #REF! | E34: =(E33-D33)/D33 -> #REF! | F34: =(F33-E33)/E33 -> #REF! | G34: =(G33-F33)/F33 -> #REF!
B36: COGS | C36: ='Contract (1 yr)'!F27 -> 50.310663 | D36: ='In-house (2-5yrs)'!G4 -> 0 | E36: ='In-house (2-5yrs)'!G5 -> 0 | F36: ='In-house (2-5yrs)'!G6 -> 0 | G36: ='In-house (2-5yrs)'!G7 -> 0
B37: Gross Profit Margin % | C37: =C36/C33 -> 0.56904146 | D37: =D36/D33 -> #REF! | E37: =E36/E33 -> #REF! | F37: =F36/F33 -> #REF! | G37: =G36/G33 -> #REF!
B39: INDIRECT EXPENSES
B40: Marketing & Advertising | C40: =sum('Indirect Expenses'!C56:E56) -> 6.18891 | D40: =sum('Indirect Expenses'!F56:H56) -> #REF! | E40: =sum('Indirect Expenses'!I56:K56) -> #REF! | F40: =sum('Indirect Expenses'!L56:N56) -> #REF! | G40: =sum('Indirect Expenses'!O56:Q56) -> #REF! | H40: * Includes Consumer digital ads, Influencer & KOL marketing, Sampling & trial programs, GTM marketing, Branding, Events, etc
B41: Tier 1 | C41: ='Indirect Expenses'!C56 -> 0 | D41: ='Indirect Expenses'!F56 -> #REF! | E41: ='Indirect Expenses'!I56 -> #REF! | F41: ='Indirect Expenses'!L56 -> #REF! | G41: ='Indirect Expenses'!O56 -> #REF!
B42: Tier 2 | C42: ='Indirect Expenses'!D56 -> 0 | D42: ='Indirect Expenses'!G56 -> 0 | E42: ='Indirect Expenses'!J56 -> 0 | F42: ='Indirect Expenses'!M56 -> 0 | G42: ='Indirect Expenses'!P56 -> 0
B43: Tier 3 | C43: ='Indirect Expenses'!E56 -> 6.18891 | D43: ='Indirect Expenses'!H56 -> 0 | E43: ='Indirect Expenses'!K56 -> 0 | F43: ='Indirect Expenses'!N56 -> 0 | G43: ='Indirect Expenses'!Q56 -> 0
B44: HCP Detailing & Medical Engagement | C44: =sum('Indirect Expenses'!C57:E57) -> 1.76826 | D44: =sum('Indirect Expenses'!F57:H57) -> #REF! | E44: =sum('Indirect Expenses'!I57:K57) -> #REF! | F44: =sum('Indirect Expenses'!L57:N57) -> #REF! | G44: =sum('Indirect Expenses'!O57:Q57) -> #REF! | H44: * OBGYN, Gynecologist, Pediatrician detailing, Hospital & Nursing home tie-ups, Lactation Consultant & Dietitian programs, Medical conference sponsorships
B45: Tier 1 | C45: ='Indirect Expenses'!C57 -> 0 | D45: ='Indirect Expenses'!F57 -> #REF! | E45: ='Indirect Expenses'!I57 -> #REF! | F45: ='Indirect Expenses'!L57 -> #REF! | G45: ='Indirect Expenses'!O57 -> #REF!
B46: Tier 2 | C46: ='Indirect Expenses'!D57 -> 0 | D46: ='Indirect Expenses'!G57 -> 0 | E46: ='Indirect Expenses'!J57 -> 0 | F46: ='Indirect Expenses'!M57 -> 0 | G46: ='Indirect Expenses'!P57 -> 0
B47: Tier 3 | C47: ='Indirect Expenses'!E57 -> 1.76826 | D47: ='Indirect Expenses'!H57 -> 0 | E47: ='Indirect Expenses'!K57 -> 0 | F47: ='Indirect Expenses'!N57 -> 0 | G47: ='Indirect Expenses'!Q57 -> 0
B48: Distribution & Logistics | C48: =sum('Indirect Expenses'!C58:E58) -> 3.159 | D48: =sum('Indirect Expenses'!F58:H58) -> 23.554615 | E48: =sum('Indirect Expenses'!I58:K58) -> 74.996187 | F48: =sum('Indirect Expenses'!L58:N58) -> 138.88183 | G48: =sum('Indirect Expenses'!O58:Q58) -> 240.65565 | H48: * Rs. 9 per box for Year 1 & 2. Rs. 8.5 from Year 3 to 5. Includes Outbound freight, Warehousing, Cold chain storage, Channel commission
B49: Tier 1 | C49: ='Indirect Expenses'!C58 -> 0 | D49: ='Indirect Expenses'!F58 -> 1.0708663 | E49: ='Indirect Expenses'!I58 -> 3.2125989 | F49: ='Indirect Expenses'!L58 -> 5.9492571 | G49: ='Indirect Expenses'!O58 -> 17.280841
B50: Tier 2 | C50: ='Indirect Expenses'!D58 -> 0 | D50: ='Indirect Expenses'!G58 -> 0 | E50: ='Indirect Expenses'!J58 -> 4.3323429 | F50: ='Indirect Expenses'!M58 -> 8.0228571 | G50: ='Indirect Expenses'!P58 -> 20.515657
B51: Tier 3 | C51: ='Indirect Expenses'!E58 -> 3.159 | D51: ='Indirect Expenses'!H58 -> 22.483749 | E51: ='Indirect Expenses'!K58 -> 67.451246 | F51: ='Indirect Expenses'!N58 -> 124.90971 | G51: ='Indirect Expenses'!Q58 -> 202.85915
B52: R&D / Regulatory / Compliance | C52: =sum('Indirect Expenses'!C59:E59) -> 3.53652 | D52: =sum('Indirect Expenses'!F59:H59) -> #REF! | E52: =sum('Indirect Expenses'!I59:K59) -> #REF! | F52: =sum('Indirect Expenses'!L59:N59) -> #REF! | G52: =sum('Indirect Expenses'!O59:Q59) -> #REF! | H52: * Product development, Clinical & nutritional testing, FSSAI approval (per SKU), IMS Act compliance monitoring, Stability & shelf-life studies
B53: Tier 1 | C53: ='Indirect Expenses'!C59 -> 0 | D53: ='Indirect Expenses'!F59 -> #REF! | E53: ='Indirect Expenses'!I59 -> #REF! | F53: ='Indirect Expenses'!L59 -> #REF! | G53: ='Indirect Expenses'!O59 -> #REF!
B54: Tier 2 | C54: ='Indirect Expenses'!D59 -> 0 | D54: ='Indirect Expenses'!G59 -> 0 | E54: ='Indirect Expenses'!J59 -> 0 | F54: ='Indirect Expenses'!M59 -> 0 | G54: ='Indirect Expenses'!P59 -> 0
B55: Tier 3 | C55: ='Indirect Expenses'!E59 -> 3.53652 | D55: ='Indirect Expenses'!H59 -> 0 | E55: ='Indirect Expenses'!K59 -> 0 | F55: ='Indirect Expenses'!N59 -> 0 | G55: ='Indirect Expenses'!Q59 -> 0
B56: G&A / Operations Overheads | C56: =sum('Indirect Expenses'!C60:E60) -> 2.65239 | D56: =sum('Indirect Expenses'!F60:H60) -> #REF! | E56: =sum('Indirect Expenses'!I60:K60) -> #REF! | F56: =sum('Indirect Expenses'!L60:N60) -> #REF! | G56: =sum('Indirect Expenses'!O60:Q60) -> #REF! | H56: * Rent & utilities, IT infrastructure, ERP & CRM, Legal, audit & insurance, Office supplies & misc admin
B57: Tier 1 | C57: ='Indirect Expenses'!C60 -> 0 | D57: ='Indirect Expenses'!F60 -> #REF! | E57: ='Indirect Expenses'!I60 -> #REF! | F57: ='Indirect Expenses'!L60 -> #REF! | G57: ='Indirect Expenses'!O60 -> #REF!
B58: Tier 2 | C58: ='Indirect Expenses'!D60 -> 0 | D58: ='Indirect Expenses'!G60 -> 0 | E58: ='Indirect Expenses'!J60 -> 0 | F58: ='Indirect Expenses'!M60 -> 0 | G58: ='Indirect Expenses'!P60 -> 0
B59: Tier 3 | C59: ='Indirect Expenses'!E60 -> 2.65239 | D59: ='Indirect Expenses'!H60 -> 0 | E59: ='Indirect Expenses'!K60 -> 0 | F59: ='Indirect Expenses'!N60 -> 0 | G59: ='Indirect Expenses'!Q60 -> 0
B60: Employee Cost | C60: =sum('Indirect Expenses'!C61:E61) -> 5.30478 | D60: =sum('Indirect Expenses'!F61:H61) -> #REF! | E60: =sum('Indirect Expenses'!I61:K61) -> #REF! | F60: =sum('Indirect Expenses'!L61:N61) -> #REF! | G60: =sum('Indirect Expenses'!O61:Q61) -> #REF! | H60: * Core team salaries, PF / ESI / statutory, HCP field force, Recruitment, training & contract staff
B61: Tier 1 | C61: ='Indirect Expenses'!C61 -> 0 | D61: ='Indirect Expenses'!F61 -> #REF! | E61: ='Indirect Expenses'!I61 -> #REF! | F61: ='Indirect Expenses'!L61 -> #REF! | G61: ='Indirect Expenses'!O61 -> #REF!
B62: Tier 2 | C62: ='Indirect Expenses'!D61 -> 0 | D62: ='Indirect Expenses'!G61 -> 0 | E62: ='Indirect Expenses'!J61 -> 0 | F62: ='Indirect Expenses'!M61 -> 0 | G62: ='Indirect Expenses'!P61 -> 0
B63: Tier 3 | C63: ='Indirect Expenses'!E61 -> 5.30478 | D63: ='Indirect Expenses'!H61 -> 0 | E63: ='Indirect Expenses'!K61 -> 0 | F63: ='Indirect Expenses'!N61 -> 0 | G63: ='Indirect Expenses'!Q61 -> 0
B64: Contingency Fund | C64: =sum(C40:C60)*5% -> 1.995747 | D64: =sum(D40:D60)*5% -> #REF! | E64: =sum(E40:E60)*5% -> #REF! | F64: =sum(F40:F60)*5% -> #REF! | G64: =sum(G40:G60)*5% -> #REF! | H64: * 5% Contingency Fund
B66: Total Expenses | C66: =sum(C40,C44,C48,C52,C56,C60,C64,C36) -> 74.91627 | D66: =sum(D40,D44,D48,D52,D56,D60,D64,D36) -> #REF! | E66: =sum(E40,E44,E48,E52,E56,E60,E64,E36) -> #REF! | F66: =sum(F40,F44,F48,F52,F56,F60,F64,F36) -> #REF! | G66: =sum(G40,G44,G48,G52,G56,G60,G64,G36) -> #REF!
B68: EBIDTA | C68: =C33-C66 -> 13.49673 | D68: =D33-D66 -> #REF! | E68: =E33-E66 -> #REF! | F68: =F33-F66 -> #REF! | G68: =G33-G66 -> #REF!
B69: EBIDTA Margin% | C69: =C68/C33 -> 0.15265549 | D69: =D68/D33 -> #REF! | E69: =E68/E33 -> #REF! | F69: =F68/F33 -> #REF! | G69: =G68/G33 -> #REF!
B71: Depreciation and Amortisation | C71: ='Capex & Depreciation'!E39 -> 0 | D71: ='Capex & Depreciation'!E40 -> 0.56739 | E71: ='Capex & Depreciation'!E41 -> 1.70217 | F71: ='Capex & Depreciation'!E42 -> 3.40434 | G71: ='Capex & Depreciation'!E43 -> 5.10651
B72: EBIT | C72: =C68-C71 -> 13.49673 | D72: =D68-D71 -> #REF! | E72: =E68-E71 -> #REF! | F72: =F68-F71 -> #REF! | G72: =G68-G71 -> #REF!
B74: Financial Costs | C74: ='Debt Schedule'!G3 -> 0 | D74: ='Debt Schedule'!G4 -> 0 | E74: ='Debt Schedule'!G5 -> 0 | F74: ='Debt Schedule'!G6 -> #REF! | G74: ='Debt Schedule'!G7 -> #REF!
B75: EBT/PBT | C75: =C72-C74 -> 13.49673 | D75: =D72-D74 -> #REF! | E75: =E72-E74 -> #REF! | F75: =F72-F74 -> #REF! | G75: =G72-G74 -> #REF!
B77: Tax | C77: =IF(C75>0, C75*0.25,0) -> 3.3741825 | D77: =IF(D75>0, D75*0.25,0) -> #REF! | E77: =IF(E75>0, E75*0.25,0) -> #REF! | F77: =IF(F75>0, F75*0.25,0) -> #REF! | G77: =IF(G75>0, G75*0.25,0) -> #REF!
B79: PAT/EAT | C79: =C75-C77 -> 10.122547 | D79: =D75-D77 -> #REF! | E79: =E75-E77 -> #REF! | F79: =F75-F77 -> #REF! | G79: =G75-G77 -> #REF!
B80: Net Profit Margin% | C80: =C79/C33 -> 0.11449162 | D80: =D79/D33 -> #REF! | E80: =E79/E33 -> #REF! | F80: =F79/F33 -> #REF! | G80: =G79/G33 -> #REF!

Sheet Competitor Brands
B2: Expense Head | C2: Remarks | D2: HealthKart | E2: Kapiva | F2: OZiva | G2: Wellbeing Nutrition | H2: Early Stage Guide
B4: Marketing & brand
B5: Advertising & Promotions | C5: Digital, influencer, trade mktg | D5: 0.2 | E5: 0.55 | F5: 0.47 | G5: ~38% | H5: 30 – 50%
B6: Brand building & design | C6: Identity, packaging, PR | D6: ~3% | E6: ~5% | F6: ~4% | G6: ~5% | H6: 5 – 10%
B7: Doctor detailing & KOL | C7: Esp. critical for pregnancy/infant | D7: N/A | E7: N/A | F7: N/A | G7: N/A | H7: 3 – 6%
B9: Human resources
B10: Employee benefits | C10: Salaries, PF, ESOP | D10: 0.088 | E10: 0.17 | F10: 0.089 | G10: ~15% | H10: 15 – 25%
B12: Sales & distribution
B13: Channel commissions | C13: Amazon, Flipkart, 1mg, pharmacy | D13: 0.062 | E13: ~8% | F13: ~10% | G13: ~10% | H13: 8 – 12%
B14: Logistics & fulfilment | C14: Freight, 3PL, returns | D14: ~4% | E14: ~6% | F14: ~6% | G14: ~7% | H14: 5 – 8%
B16: Overheads & compliance
B17: Legal, regulatory & FSSAI | D17: ~1% | E17: ~2% | F17: ~2% | G17: ~2% | H17: 2 – 4%
B18: IT, SaaS & tech infra | D18: ~1% | E18: ~2% | F18: ~2% | G18: ~2% | H18: 2 – 4%
B19: Rent, utilities & admin | D19: ~2% | E19: ~3% | F19: ~3% | G19: ~4% | H19: 3 – 6%
B21: R&D & product
B22: R&D, testing & FSSAI dossiers | C22: 1.5-2x higher for infant formula | D22: ~1% | E22: ~1% | F22: ~3% | G22: ~4% | H22: 2 – 5%
B24: Profitability summary
B25: Gross margin | D25: ~51% | E25: ~72% | F25: ~73% | G25: ~70% | H25: 45 – 65%
B26: EBITDA margin | D26: =+6% -> 0.06 | E26: -0.21 | F26: -0.012 | G26: ~-5% | H26: -30 to -50%
B27: ₹ spent to earn ₹1 | D27: ₹0.97 | E27: ₹1.22 | F27: ₹1.04 | G27: ~₹1.10 | H27: ₹1.40–1.80

Sheet Revenue Breakup
C2: 1 | E2: 2 | G2: 3 | I2: 4 | K2: 5
B3: Revenue from Operation | C3: ='P&L'!C6 -> 88.413 | D3: =C3/$C$3 -> 1 | E3: ='P&L'!D6 -> #REF! | F3: =E3/$E$3 -> #REF! | G3: ='P&L'!E6 -> #REF! | H3: =G3/$G$3 -> #REF! | I3: ='P&L'!F6 -> #REF! | J3: =I3/$I$3 -> #REF! | K3: ='P&L'!G6 -> #REF! | L3: =K3/$K$3 -> #REF!
B4: Pregnancy Powder- Trimester 1- Tier 1 | C4: ='P&L'!C7 | D4: =C4/$C$3 -> 0 | E4: ='P&L'!D7 -> #REF! | F4: =E4/$E$3 -> #REF! | G4: ='P&L'!E7 -> #REF! | H4: =G4/$G$3 -> #REF! | I4: ='P&L'!F7 -> #REF! | J4: =I4/$I$3 -> #REF! | K4: ='P&L'!G7 -> #REF! | L4: =K4/$K$3 -> #REF!
B5: Pregnancy Powder- Trimester 2- Tier 1 | C5: ='P&L'!C8 | D5: =C5/$C$3 -> 0 | E5: ='P&L'!D8 -> #REF! | F5: =E5/$E$3 -> #REF! | G5: ='P&L'!E8 -> #REF! | H5: =G5/$G$3 -> #REF! | I5: ='P&L'!F8 -> #REF! | J5: =I5/$I$3 -> #REF! | K5: ='P&L'!G8 -> #REF! | L5: =K5/$K$3 -> #REF!
B6: Pregnancy Powder- Trimester 3- Tier 1 | C6: ='P&L'!C9 | D6: =C6/$C$3 -> 0 | E6: ='P&L'!D9 -> #REF! | F6: =E6/$E$3 -> #REF! | G6: ='P&L'!E9 -> #REF! | H6: =G6/$G$3 -> #REF! | I6: ='P&L'!F9 -> #REF! | J6: =I6/$I$3 -> #REF! | K6: ='P&L'!G9 -> #REF! | L6: =K6/$K$3 -> #REF!
B7: Lactation Powder- Tier 1 | C7: ='P&L'!C10 | D7: =C7/$C$3 -> 0 | E7: ='P&L'!D10 -> 0 | F7: =E7/$E$3 -> #REF! | G7: ='P&L'!E10 -> 0 | H7: =G7/$G$3 -> #REF! | I7: ='P&L'!F10 -> 0 | J7: =I7/$I$3 -> #REF! | K7: ='P&L'!G10 -> 0 | L7: =K7/$K$3 -> #REF!
B8: Infant Formula Powder- 0 to 6m- Tier 1 | C8: ='P&L'!C11 | D8: =C8/$C$3 -> 0 | E8: ='P&L'!D11 -> #REF! | F8: =E8/$E$3 -> #REF! | G8: ='P&L'!E11 -> #REF! | H8: =G8/$G$3 -> #REF! | I8: ='P&L'!F11 -> #REF! | J8: =I8/$I$3 -> #REF! | K8: ='P&L'!G11 -> #REF! | L8: =K8/$K$3 -> #REF!
B9: Infant Formula Powder- 6 to 12m- Tier 1 | C9: ='P&L'!C12 | D9: =C9/$C$3 -> 0 | E9: ='P&L'!D12 -> #REF! | F9: =E9/$E$3 -> #REF! | G9: ='P&L'!E12 -> #REF! | H9: =G9/$G$3 -> #REF! | I9: ='P&L'!F12 -> #REF! | J9: =I9/$I$3 -> #REF! | K9: ='P&L'!G12 -> #REF! | L9: =K9/$K$3 -> #REF!
B10: Infant Formula Powder- 12 to 24m- Tier 1 | C10: ='P&L'!C13 | D10: =C10/$C$3 -> 0 | E10: ='P&L'!D13 -> #REF! | F10: =E10/$E$3 -> #REF! | G10: ='P&L'!E13 -> #REF! | H10: =G10/$G$3 -> #REF! | I10: ='P&L'!F13 -> #REF! | J10: =I10/$I$3 -> #REF! | K10: ='P&L'!G13 -> #REF! | L10: =K10/$K$3 -> #REF!
B11: Infant Complementary Food- 6 to 12m- Tier 1 | C11: ='P&L'!C14 | D11: =C11/$C$3 -> 0 | E11: ='P&L'!D14 -> #REF! | F11: =E11/$E$3 -> #REF! | G11: ='P&L'!E14 -> #REF! | H11: =G11/$G$3 -> #REF! | I11: ='P&L'!F14 -> #REF! | J11: =I11/$I$3 -> #REF! | K11: ='P&L'!G14 -> #REF! | L11: =K11/$K$3 -> #REF!
B12: Infant Complementary Food- 12 to 24m- Tier 1 | C12: ='P&L'!C15 | D12: =C12/$C$3 -> 0 | E12: ='P&L'!D15 -> #REF! | F12: =E12/$E$3 -> #REF! | G12: ='P&L'!E15 -> #REF! | H12: =G12/$G$3 -> #REF! | I12: ='P&L'!F15 -> #REF! | J12: =I12/$I$3 -> #REF! | K12: ='P&L'!G15 -> #REF! | L12: =K12/$K$3 -> #REF!
B13: Children Powder- Tier 1 | C13: ='P&L'!C16 | D13: =C13/$C$3 -> 0 | E13: ='P&L'!D16 -> 0 | F13: =E13/$E$3 -> #REF! | G13: ='P&L'!E16 -> 0 | H13: =G13/$G$3 -> #REF! | I13: ='P&L'!F16 -> 0 | J13: =I13/$I$3 -> #REF! | K13: ='P&L'!G16 -> 0 | L13: =K13/$K$3 -> #REF!
B14: Pregnancy Powder- Trimester 1- Tier 2 | C14: ='P&L'!C17 | D14: =C14/$C$3 -> 0 | E14: ='P&L'!D17 | F14: =E14/$E$3 -> #REF! | G14: ='P&L'!E17 -> 0 | H14: =G14/$G$3 -> #REF! | I14: ='P&L'!F17 -> 0 | J14: =I14/$I$3 -> #REF! | K14: ='P&L'!G17 -> 0 | L14: =K14/$K$3 -> #REF!
... B28: Contract Manufacturing | C28: ='P&L'!C31 | D28: =C28/$C$3 -> 0 | E28: ='P&L'!D31 -> #REF! | F28: =E28/$E$3 -> #REF! | G28: ='P&L'!E31 -> #REF! | H28: =G28/$G$3 -> #REF! | I28: ='P&L'!F31 -> #REF! | J28: =I28/$I$3 -> #REF! | K28: ='P&L'!G31 -> #REF! | L28: =K28/$K$3 -> #REF!
C30: 1 | E30: 2 | G30: 3 | I30: 4 | K30: 5
B31: Tier 1 | C31: =sum(C4:C13) -> 0 | D31: =sum(D4:D13) -> 0 | E31: =sum(E4:E13) -> #REF! | F31: =sum(F4:F13) -> #REF! | G31: =sum(G4:G13) -> #REF! | H31: =sum(H4:H13) -> #REF! | I31: =sum(I4:I13) -> #REF! | J31: =sum(J4:J13) -> #REF! | ... L31: =sum(L4:L13) -> #REF!
B32: Tier 2 | C32: =sum(C14:C23) -> 0 | D32: =sum(D14:D23) -> 0 | E32: =sum(E14:E23) -> 0 | F32: =sum(F14:F23) -> #REF! | G32: =sum(G14:G23) -> 0 | H32: =sum(H14:H23) -> #REF! | I32: =sum(I14:I23) -> 0 | J32: =sum(J14:J23) -> #REF! | ... L32: =sum(L14:L23) -> #REF!
B33: Tier 3 | C33: =sum(C24:C27) -> 88.413 | D33: =sum(D24:D27) -> 1 | E33: =sum(E24:E27) -> 0 | F33: =sum(F24:F27) -> #REF! | G33: =sum(G24:G27) -> 0 | H33: =sum(H24:H27) -> #REF! | I33: =sum(I24:I27) -> 0 | J33: =sum(J24:J27) -> #REF! | ... L33: =sum(L24:L27) -> #REF!
C35: 1 | D35: 2 | E35: 3 | F35: 4 | G35: 5
B36: Pregnancy Powder | C36: =sum($D$4:$D$6,$D$14:$D$16,$D$24) -> 0.2470225 | D36: =sum(F4:F6,F14:F16,F24) -> #REF! | E36: =sum(H4:H6,H14:H16,H24) -> #REF! | F36: =sum(J4:J6,J14:J16,J24) -> #REF! | G36: =sum(L4:L6,L14:L16,L24) -> #REF!
B37: Lactation Powder | C37: =sum($D$7,$D$17,$D$25) -> 0.25231584 | D37: =sum(F7,F17,F25) -> #REF! | E37: =sum(H7,H17,H25) -> #REF! | F37: =sum(J7,J17,J25) -> #REF! | G37: =sum(L7,L17,L25) -> #REF!
B38: Infant Powder | C38: =sum($D$8:$D$12,$D$18:$D$22,$D$26) -> 0.26687252 | D38: =sum(F8:F12,F18:F22,F26) -> #REF! | E38: =sum(H8:H12,H18:H22,H26) -> #REF! | F38: =sum(J8:J12,J18:J22,J26) -> #REF! | G38: =sum(L8:L12,L18:L22,L26) -> #REF!
B39: Children Powder | C39: =$D$13+$D$23+$D$27 -> 0.23378915 | D39: =F13+F23+F27 -> #REF! | E39: =H13+H23+H27 -> #REF! | F39: =J13+J23+J27 -> #REF! | G39: =L13+L23+L27 -> #REF!
B40: Total | C40: =sum(C36:C39) -> 1 | D40: =sum(D36:D39) -> #REF! | E40: =sum(E36:E39) -> #REF! | F40: =sum(F36:F39) -> #REF! | G40: =sum(G36:G39) -> #REF!
B41: Average | C41: =average(C36:C39) -> 0.25 | D41: =average(D36:D39) -> #REF! | E41: =average(E36:E39) -> #REF! | F41: =average(F36:F39) -> #REF! | G41: =average(G36:G39) -> #REF!
C43: 1 | D43: 2 | E43: 3 | F43: 4 | G43: 5
B44: Pregnancy Powder | C44: =VALUE(SUBSTITUTE(C36, "%", "")) -> 24.7 | D44: =VALUE(SUBSTITUTE(D36, "%", "")) -> #REF! | E44: =VALUE(SUBSTITUTE(E36, "%", "")) -> #REF! | F44: =VALUE(SUBSTITUTE(F36, "%", "")) -> #REF! | G44: =VALUE(SUBSTITUTE(G36, "%", "")) -> #REF!
B45: Lactation Powder | C45: =VALUE(SUBSTITUTE(C37, "%", "")) -> 25.2 | D45: =VALUE(SUBSTITUTE(D37, "%", "")) -> #REF! | E45: =VALUE(SUBSTITUTE(E37, "%", "")) -> #REF! | F45: =VALUE(SUBSTITUTE(F37, "%", "")) -> #REF! | G45: =VALUE(SUBSTITUTE(G37, "%", "")) -> #REF!
B46: Infant Powder | C46: =VALUE(SUBSTITUTE(C38, "%", "")) -> 26.7 | D46: =VALUE(SUBSTITUTE(D38, "%", "")) -> #REF! | E46: =VALUE(SUBSTITUTE(E38, "%", "")) -> #REF! | F46: =VALUE(SUBSTITUTE(F38, "%", "")) -> #REF! | G46: =VALUE(SUBSTITUTE(G38, "%", "")) -> #REF!
B47: Children Powder | C47: =VALUE(SUBSTITUTE(C39, "%", "")) -> 23.4 | D47: =VALUE(SUBSTITUTE(D39, "%", "")) -> #REF! | E47: =VALUE(SUBSTITUTE(E39, "%", "")) -> #REF! | F47: =VALUE(SUBSTITUTE(F39, "%", "")) -> #REF! | G47: =VALUE(SUBSTITUTE(G39, "%", "")) -> #REF!
C48: =sum(C44:C47) -> 100 | D48: =sum(D44:D47) -> #REF! | E48: =sum(E44:E47) -> #REF! | F48: =sum(F44:F47) -> #REF! | G48: =sum(G44:G47) -> #REF!

Sheet Indirect Expenses
B2: INDIRECT EXPENSE % BREAKUP TIER WISE & PRODUCT WISE
B3: Cost Head | C3: Remark | D3: Year 1 | G3: Year 2 | J3: Year 3 | M3: Year 4 | P3: Year 5
D4: Tier 1 (Metro) | E4: Tier 2 (Mid Cities) | F4: Tier 3 (Small Towns) | G4: Tier 1 (Metro) | H4: Tier 2 (Mid Cities) | I4: Tier 3 (Small Towns) | J4: Tier 1 (Metro) | K4: Tier 2 (Mid Cities) | L4: Tier 3 (Small Towns) | M4: Tier 1 (Metro) | N4: Tier 2 (Mid Cities) | O4: Tier 3 (Small Towns) | P4: Tier 1 (Metro) | Q4: Tier 2 (Mid Cities) | R4: Tier 3 (Small Towns)
B5: Marketing & Advertising (in %) | C5: * IMS Act prohibits infant formula consumer ads. Tier 1 budget shifts entirely to HCP detailing. 3 brand budgets from Y3. | D5: =VALUE(SUBSTITUTE('IE Biffurcation'!N13, "%", "")) -> 0 | E5: =VALUE(SUBSTITUTE('IE Biffurcation'!I13, "%", "")) -> 0 | F5: =VALUE(SUBSTITUTE('IE Biffurcation'!D13, "%", "")) -> 7 | G5: =VALUE(SUBSTITUTE('IE Biffurcation'!O13, "%", "")) -> 5 | H5: =VALUE(SUBSTITUTE('IE Biffurcation'!J13, "%", "")) -> 0 | I5: =VALUE(SUBSTITUTE('IE Biffurcation'!E13, "%", "")) -> 4 | J5: =VALUE(SUBSTITUTE('IE Biffurcation'!P13, "%", "")) -> 5 | K5: =VALUE(SUBSTITUTE('IE Biffurcation'!K13, "%", "")) -> 7 | L5: =VALUE(SUBSTITUTE('IE Biffurcation'!F13, "%", "")) -> 8 | M5: =VALUE(SUBSTITUTE('IE Biffurcation'!Q13, "%", "")) -> 6 | N5: =VALUE(SUBSTITUTE('IE Biffurcation'!L13, "%", "")) -> 6 | O5: =VALUE(SUBSTITUTE('IE Biffurcation'!G13, "%", "")) -> 5 | P5: =VALUE(SUBSTITUTE('IE Biffurcation'!R13, "%", "")) -> 3 | Q5: =VALUE(SUBSTITUTE('IE Biffurcation'!M13, "%", "")) -> 5 | R5: =VALUE(SUBSTITUTE('IE Biffurcation'!H13, "%", "")) -> 5
B6: Pregnancy Powder | D6: =D5 -> 0 | E6: =E5 -> 0 | F6: =$F$5*'Revenue Breakup'!C36 -> 1.7291575 | G6: =$G$5*('Revenue Breakup'!D36/'Revenue Breakup'!$D$40) -> #REF! | H6: =H5 -> 0 | I6: =$I$5*('Revenue Breakup'!D36/'Revenue Breakup'!$D$40) -> #REF! | J6: =$J$5*('Revenue Breakup'!E36/'Revenue Breakup'!$E$40) -> #REF! | K6: =$K$5*('Revenue Breakup'!E36/'Revenue Breakup'!$E$40) -> #REF! | L6: =$L$5*('Revenue Breakup'!E36/'Revenue Breakup'!$E$40) -> #REF! | M6: =$M$5*('Revenue Breakup'!F36/'Revenue Breakup'!$F$40) -> #REF! | N6: =$N$5*('Revenue Breakup'!F36/'Revenue Breakup'!$F$40) -> #REF! | O6: =$O$5*('Revenue Breakup'!F36/'Revenue Breakup'!$F$40) -> #REF! | P6: =$P$5*('Revenue Breakup'!G36/'Revenue Breakup'!$G$40) -> #REF! | Q6: =$Q$5*('Revenue Breakup'!G36/'Revenue Breakup'!$G$40) -> #REF! | R6: =$R$5*('Revenue Breakup'!G36/'Revenue Breakup'!$G$40) -> #REF!
B7: Lactation Powder | D7: =D6 -> 0 | E7: =E6 -> 0 | F7: =$F$5*'Revenue Breakup'!C37 -> 1.7662109 | G7: =$G$5*('Revenue Breakup'!D37/'Revenue Breakup'!$D$40) -> #REF! | H7: =H6 -> 0 | I7: =$I$5*('Revenue Breakup'!D37/'Revenue Breakup'!$D$40) -> #REF! | J7: =$J$5*('Revenue Breakup'!E37/'Revenue Breakup'!$E$40) -> #REF! | K7: =$K$5*('Revenue Breakup'!E37/'Revenue Breakup'!$E$40) -> #REF! | L7: =$L$5*('Revenue Breakup'!E37/'Revenue Breakup'!$E$40) -> #REF! | M7: =$M$5*('Revenue Breakup'!F37/'Revenue Breakup'!$F$40) -> #REF! | N7: =$N$5*('Revenue Breakup'!F37/'Revenue Breakup'!$F$40) -> #REF! | O7: =$O$5*('Revenue Breakup'!F37/'Revenue Breakup'!$F$40) -> #REF! | P7: =$P$5*('Revenue Breakup'!G37/'Revenue Breakup'!$G$40) -> #REF! | Q7: =$Q$5*('Revenue Breakup'!G37/'Revenue Breakup'!$G$40) -> #REF! | R7: =$R$5*('Revenue Breakup'!G37/'Revenue Breakup'!$G$40) -> #REF!
B8: Infant Powder | D8: =D7 -> 0 | E8: =E7 -> 0 | F8: =$F$5*'Revenue Breakup'!C38 -> 1.8681076 | G8: =$G$5*('Revenue Breakup'!D38/'Revenue Breakup'!$D$40) -> #REF! | H8: =H7 -> 0 | I8: =$I$5*('Revenue Breakup'!D38/'Revenue Breakup'!$D$40) -> #REF! | J8: =$J$5*('Revenue Breakup'!E38/'Revenue Breakup'!$E$40) -> #REF! | K8: =$K$5*('Revenue Breakup'!E38/'Revenue Breakup'!$E$40) -> #REF! | L8: =$L$5*('Revenue Breakup'!E38/'Revenue Breakup'!$E$40) -> #REF! | M8: =$M$5*('Revenue Breakup'!F38/'Revenue Breakup'!$F$40) -> #REF! | N8: =$N$5*('Revenue Breakup'!F38/'Revenue Breakup'!$F$40) -> #REF! | O8: =$O$5*('Revenue Breakup'!F38/'Revenue Breakup'!$F$40) -> #REF! | P8: =$P$5*('Revenue Breakup'!G38/'Revenue Breakup'!$G$40) -> #REF! | Q8: =$Q$5*('Revenue Breakup'!G38/'Revenue Breakup'!$G$40) -> #REF! | R8: =$R$5*('Revenue Breakup'!G38/'Revenue Breakup'!$G$40) -> #REF!
B9: Children Powder | D9: =D8 -> 0 | E9: =E8 -> 0 | F9: =$F$5*'Revenue Breakup'!C39 -> 1.636524 | G9: =$G$5*('Revenue Breakup'!D39/'Revenue Breakup'!$D$40) -> #REF! | H9: =H8 -> 0 | I9: =$I$5*('Revenue Breakup'!D39/'Revenue Breakup'!$D$40) -> #REF! | J9: =$J$5*('Revenue Breakup'!E39/'Revenue Breakup'!$E$40) -> #REF! | K9: =$K$5*('Revenue Breakup'!E39/'Revenue Breakup'!$E$40) -> #REF! | L9: =$L$5*('Revenue Breakup'!E39/'Revenue Breakup'!$E$40) -> #REF! | M9: =$M$5*('Revenue Breakup'!F39/'Revenue Breakup'!$F$40) -> #REF! | N9: =$N$5*('Revenue Breakup'!F39/'Revenue Breakup'!$F$40) -> #REF! | O9: =$O$5*('Revenue Breakup'!F39/'Revenue Breakup'!$F$40) -> #REF! | P9: =$P$5*('Revenue Breakup'!G39/'Revenue Breakup'!$G$40) -> #REF! | Q9: =$Q$5*('Revenue Breakup'!G39/'Revenue Breakup'!$G$40) -> #REF! | R9: =$R$5*('Revenue Breakup'!G39/'Revenue Breakup'!$G$40) -> #REF!
B10: HCP Detailing & Medical Engagement (in %) | C10: * OBGYNs, pediatricians, hospitals drive prescription/recommendation. Mandatory for infant formula category growth. | D10: =VALUE(SUBSTITUTE('IE Biffurcation'!N20, "%", "")) -> 0 | E10: =VALUE(SUBSTITUTE('IE Biffurcation'!I20, "%", "")) -> 0 | F10: =VALUE(SUBSTITUTE('IE Biffurcation'!D20, "%", "")) -> 2 | G10: =VALUE(SUBSTITUTE('IE Biffurcation'!O20, "%", "")) -> 3 | H10: =VALUE(SUBSTITUTE('IE Biffurcation'!J20, "%", "")) -> 0 | I10: =VALUE(SUBSTITUTE('IE Biffurcation'!E20, "%", "")) -> 2 | J10: =VALUE(SUBSTITUTE('IE Biffurcation'!P20, "%", "")) -> 5 | K10: =VALUE(SUBSTITUTE('IE Biffurcation'!K20, "%", "")) -> 3 | L10: =VALUE(SUBSTITUTE('IE Biffurcation'!F20, "%", "")) -> 2 | M10: =VALUE(SUBSTITUTE('IE Biffurcation'!Q20, "%", "")) -> 5 | N10: =VALUE(SUBSTITUTE('IE Biffurcation'!L20, "%", "")) -> 4 | O10: =VALUE(SUBSTITUTE('IE Biffurcation'!G20, "%", "")) -> 4 | P10: =VALUE(SUBSTITUTE('IE Biffurcation'!R20, "%", "")) -> 6 | Q10: =VALUE(SUBSTITUTE('IE Biffurcation'!M20, "%", "")) -> 5 | R10: =VALUE(SUBSTITUTE('IE Biffurcation'!H20, "%", "")) -> 4
B11: Pregnancy Powder | D11: =D10 -> 0 | E11: =E10 -> 0 | F11: =$F$10*'Revenue Breakup'!C36 -> 0.49404499 | G11: =$G$10*('Revenue Breakup'!D36/'Revenue Breakup'!$D$40) -> #REF! | H11: =H10 -> 0 | I11: =$I$10*('Revenue Breakup'!D36/'Revenue Breakup'!$D$40) -> #REF! | J11: =$J$10*('Revenue Breakup'!E36/'Revenue Breakup'!$E$40) -> #REF! | K11: =$K$10*('Revenue Breakup'!E36/'Revenue Breakup'!$E$40) -> #REF! | L11: =$L$10*('Revenue Breakup'!E36/'Revenue Breakup'!$E$40) -> #REF! | M11: =$M$10*('Revenue Breakup'!F36/'Revenue Breakup'!$F$40) -> #REF! | N11: =$N$10*('Revenue Breakup'!F36/'Revenue Breakup'!$F$40) -> #REF! | O11: =$O$10*('Revenue Breakup'!F36/'Revenue Breakup'!$F$40) -> #REF! | P11: =$P$10*('Revenue Breakup'!G36/'Revenue Breakup'!$G$40) -> #REF! | Q11: =$Q$10*('Revenue Breakup'!G36/'Revenue Breakup'!$G$40) -> #REF! | R11: =$R$10*('Revenue Breakup'!G36/'Revenue Breakup'!$G$40) -> #REF!
B12: Lactation Powder | D12: =D11 -> 0 | E12: =E11 -> 0 | F12: =$F$10*'Revenue Breakup'!C37 -> 0.50463167 | G12: =$G$10*('Revenue Breakup'!D37/'Revenue Breakup'!$D$40) -> #REF! | H12: =H11 -> 0 | I12: =$I$10*('Revenue Breakup'!D37/'Revenue Breakup'!$D$40) -> #REF! | J12: =$J$10*('Revenue Breakup'!E37/'Revenue Breakup'!$E$40) -> #REF! | K12: =$K$10*('Revenue Breakup'!E37/'Revenue Breakup'!$E$40) -> #REF! | L12: =$L$10*('Revenue Breakup'!E37/'Revenue Breakup'!$E$40) -> #REF! | M12: =$M$10*('Revenue Breakup'!F37/'Revenue Breakup'!$F$40) -> #REF! | N12: =$N$10*('Revenue Breakup'!F37/'Revenue Breakup'!$F$40) -> #REF! | O12: =$O$10*('Revenue Breakup'!F37/'Revenue Breakup'!$F$40) -> #REF! | P12: =$P$10*('Revenue Breakup'!G37/'Revenue Breakup'!$G$40) -> #REF! | Q12: =$Q$10*('Revenue Breakup'!G37/'Revenue Breakup'!$G$40) -> #REF! | R12: =$R$10*('Revenue Breakup'!G37/'Revenue Breakup'!$G$40) -> #REF!
B13: Infant Powder | D13: =D12 -> 0 | E13: =E12 -> 0 | F13: =$F$10*'Revenue Breakup'!C38 -> 0.53374504 | G13: =$G$10*('Revenue Breakup'!D38/'Revenue Breakup'!$D$40) -> #REF! | H13: =H12 -> 0 | I13: =$I$10*('Revenue Breakup'!D38/'Revenue Breakup'!$D$40) -> #REF! | J13: =$J$10*('Revenue Breakup'!E38/'Revenue Breakup'!$E$40) -> #REF! | K13: =$K$10*('Revenue Breakup'!E38/'Revenue Breakup'!$E$40) -> #REF! | L13: =$L$10*('Revenue Breakup'!E38/'Revenue Breakup'!$E$40) -> #REF! | M13: =$M$10*('Revenue Breakup'!F38/'Revenue Breakup'!$F$40) -> #REF! | N13: =$N$10*('Revenue Breakup'!F38/'Revenue Breakup'!$F$40) -> #REF! | O13: =$O$10*('Revenue Breakup'!F38/'Revenue Breakup'!$F$40) -> #REF! | P13: =$P$10*('Revenue Breakup'!G38/'Revenue Breakup'!$G$40) -> #REF! | Q13: =$Q$10*('Revenue Breakup'!G38/'Revenue Breakup'!$G$40) -> #REF! | R13: =$R$10*('Revenue Breakup'!G38/'Revenue Breakup'!$G$40) -> #REF!
B14: Children Powder | D14: =D13 -> 0 | E14: =E13 -> 0 | F14: =$F$10*'Revenue Breakup'!C39 -> 0.4675783 | G14: =$G$10*('Revenue Breakup'!D39/'Revenue Breakup'!$D$40) -> #REF! | H14: =H13 -> 0 | I14: =$I$10*('Revenue Breakup'!D39/'Revenue Breakup'!$D$40) -> #REF! | J14: =$J$10*('Revenue Breakup'!E39/'Revenue Breakup'!$E$40) -> #REF! | K14: =$K$10*('Revenue Breakup'!E39/'Revenue Breakup'!$E$40) -> #REF! | L14: =$L$10*('Revenue Breakup'!E39/'Revenue Breakup'!$E$40) -> #REF! | M14: =$M$10*('Revenue Breakup'!F39/'Revenue Breakup'!$F$40) -> #REF! | N14: =$N$10*('Revenue Breakup'!F39/'Revenue Breakup'!$F$40) -> #REF! | O14: =$O$10*('Revenue Breakup'!F39/'Revenue Breakup'!$F$40) -> #REF! | P14: =$P$10*('Revenue Breakup'!G39/'Revenue Breakup'!$G$40) -> #REF! | Q14: =$Q$10*('Revenue Breakup'!G39/'Revenue Breakup'!$G$40) -> #REF! | R14: =$R$10*('Revenue Breakup'!G39/'Revenue Breakup'!$G$40) -> #REF!
B15: Distribution & Logistics (in Cr) | C15: * Rs. 9 per box in Year 1 and Year 2. Rs. 8.5 per box Year 3 onwards | D15: =sum(D17:D20) -> 0 | E15: =sum(E17:E20) -> 0 | F15: =sum(F17:F20) -> 3.159 | G15: =sum(G17:G20) -> 1.0708663 | H15: =sum(H17:H20) -> 0 | I15: =sum(I17:I20) -> 22.483749 | J15: =sum(J17:J20) -> 3.2125989 | K15: =sum(K17:K20) -> 4.3323429 | ... R15: =sum(R17:R20) -> 194.85915
B16: Cost per Box (in ₹) | D16: 9 | E16: =D16 -> 9 | F16: =E16 -> 9 | G16: 9 | H16: =G16 -> 9 | I16: =H16 -> 9 | J16: 9 | K16: 9 | L16: 9 | M16: 8 | N16: 8 | O16: 8 | P16: 8 | Q16: 8 | R16: 8
B17: Pregnancy Powder | D17: =D16*'In-house (2-5yrs)'!C11 -> 0 | E17: =E16*'In-house (2-5yrs)'!D11 -> 0 | F17: =($F$16*'Contract (1 yr)'!C25)/10^7 -> 0.702 | G17: =($G$16*'In-house (2-5yrs)'!C12)/10^7 -> 0.248832 | H17: =($H$16*'In-house (2-5yrs)'!D12)/10^7 -> 0 | I17: =($I$16*'In-house (2-5yrs)'!E12)/10^7 -> 4.9855269 | J17: =($J$16*'In-house (2-5yrs)'!C13)/10^7 -> 0.746496 | K17: =($K$16*'In-house (2-5yrs)'!D13)/10^7 -> 0.97311086 | L17: =($L$16*'In-house (2-5yrs)'!E13)/10^7 -> 14.956581 | M17: =($M$16*'In-house (2-5yrs)'!C14)/10^7 -> 1.3824 | N17: =($N$16*'In-house (2-5yrs)'!D14)/10^7 -> 1.8020571 | O17: =($O$16*'In-house (2-5yrs)'!E14)/10^7 -> 27.697371 | P17: =($P$16*'In-house (2-5yrs)'!C15)/10^7 -> 2.156544 | Q17: =($Q$16*'In-house (2-5yrs)'!D15)/10^7 -> 2.8112091 | R17: =($R$16*'In-house (2-5yrs)'!E15)/10^7 -> 43.207899
B18: Lactation Powder | D18: ='In-house (2-5yrs)'!F11*D16 -> 0 | E18: =E16*'In-house (2-5yrs)'!D11 -> 0 | F18: =($F$16*'Contract (1 yr)'!C26)/10^7 -> 0.702 | G18: =($G$16*'In-house (2-5yrs)'!F12)/10^7 -> 0.28882286 | H18: =($H$16*'In-house (2-5yrs)'!G12)/10^7 -> 0 | I18: =($I$16*'In-house (2-5yrs)'!H12)/10^7 -> 4.8966583 | J18: =($J$16*'In-house (2-5yrs)'!F13)/10^7 -> 0.86646857 | K18: =($K$16*'In-house (2-5yrs)'!G13)/10^7 -> 1.1064137 | L18: =($L$16*'In-house (2-5yrs)'!H13)/10^7 -> 14.689975 | M18: =($M$16*'In-house (2-5yrs)'!F14)/10^7 -> 1.6045714 | N18: =($N$16*'In-house (2-5yrs)'!G14)/10^7 -> 2.0489143 | O18: =($O$16*'In-house (2-5yrs)'!H14)/10^7 -> 27.203657 | P18: =($P$16*'In-house (2-5yrs)'!F15)/10^7 -> 2.5031314 | Q18: =($Q$16*'In-house (2-5yrs)'!G15)/10^7 -> 3.1963063 | R18: =($R$16*'In-house (2-5yrs)'!H15)/10^7 -> 42.437705
B19: Infant Powder | D19: ='In-house (2-5yrs)'!I11*D16 -> 0 | E19: ='In-house (2-5yrs)'!J11*E16 -> 0 | F19: =($F$16*'Contract (1 yr)'!C23)/10^7 -> 0.8775 | G19: =($G$16*'In-house (2-5yrs)'!I12)/10^7 -> 0.22217143 | H19: =($H$16*'In-house (2-5yrs)'!J12)/10^7 -> 0 | I19: =($I$16*'In-house (2-5yrs)'!K12)/10^7 -> 6.37632 | J19: =($J$16*'In-house (2-5yrs)'!I13)/10^7 -> 0.66651429 | K19: =($K$16*'In-house (2-5yrs)'!J13)/10^7 -> 1.0397623 | L19: =($L$16*'In-house (2-5yrs)'!K13)/10^7 -> 19.12896 | M19: =($M$16*'In-house (2-5yrs)'!I14)/10^7 -> 1.2342857 | N19: =($N$16*'In-house (2-5yrs)'!J14)/10^7 -> 1.9254857 | O19: =($O$16*'In-house (2-5yrs)'!K14)/10^7 -> 35.424 | P19: =($P$16*'In-house (2-5yrs)'!I15)/10^7 -> 1.9254857 | Q19: =($Q$16*'In-house (2-5yrs)'!J15)/10^7 -> 3.0037577 | R19: =($R$16*'In-house (2-5yrs)'!K15)/10^7 -> 55.26144
B20: Children Powder | D20: =D16*'In-house (2-5yrs)'!L11 -> 0 | E20: =E16*'In-house (2-5yrs)'!M11 -> 0 | F20: =($F$16*'Contract (1 yr)'!C24)/10^7 -> 0.8775 | G20: =($G$16*'In-house (2-5yrs)'!L12)/10^7 -> 0.31104 | H20: =($H$16*'In-house (2-5yrs)'!M12)/10^7 -> 0 | I20: =($I$16*'In-house (2-5yrs)'!N12)/10^7 -> 6.2252434 | J20: =($J$16*'In-house (2-5yrs)'!L13)/10^7 -> 0.93312 | K20: =($K$16*'In-house (2-5yrs)'!M13)/10^7 -> 1.213056 | L20: =($L$16*'In-house (2-5yrs)'!N13)/10^7 -> 18.67573 | M20: =($M$16*'In-house (2-5yrs)'!L14)/10^7 -> 1.728 | N20: =($N$16*'In-house (2-5yrs)'!M14)/10^7 -> 2.2464 | O20: =($O$16*'In-house (2-5yrs)'!N14)/10^7 -> 34.584686 | P20: =($P$16*'In-house (2-5yrs)'!L15)/10^7 -> 2.69568 | Q20: =($Q$16*'In-house (2-5yrs)'!M15)/10^7 -> 3.504384 | R20: =($R$16*'In-house (2-5yrs)'!N15)/10^7 -> 53.95211
B21: R&D / Regulatory / Compliance (in %) | C21: * Infant formula under FSS Act strictest category. Each stage/ trimester/ flavour variant = separate FSSAI testing + label approval. | D21: ='IE Biffurcation'!N27 -> - | E21: ='IE Biffurcation'!I27 -> - | F21: =VALUE(SUBSTITUTE('IE Biffurcation'!D27, "%", "")) -> 4 | G21: =VALUE(SUBSTITUTE('IE Biffurcation'!E27, "%", "")) -> 4 | H21: ='IE Biffurcation'!J27 -> - | I21: =VALUE(SUBSTITUTE('IE Biffurcation'!O27, "%", "")) -> 4 | J21: =VALUE(SUBSTITUTE('IE Biffurcation'!F27, "%", "")) -> 4 | K21: =VALUE(SUBSTITUTE('IE Biffurcation'!K27, "%", "")) -> 3 | L21: =VALUE(SUBSTITUTE('IE Biffurcation'!P27, "%", "")) -> 2 | M21: =VALUE(SUBSTITUTE('IE Biffurcation'!G27, "%", "")) -> 3 | N21: =VALUE(SUBSTITUTE('IE Biffurcation'!L27, "%", "")) -> 3 | O21: =VALUE(SUBSTITUTE('IE Biffurcation'!Q27, "%", "")) -> 3 | P21: =VALUE(SUBSTITUTE('IE Biffurcation'!H27, "%", "")) -> 3 | Q21: =VALUE(SUBSTITUTE('IE Biffurcation'!M27, "%", "")) -> 3 | R21: =VALUE(SUBSTITUTE('IE Biffurcation'!R27, "%", "")) -> 1
B22: Pregnancy Powder | D22: =D21 -> - | E22: =E21 -> - | F22: =$F$21*'Revenue Breakup'!C36 -> 0.98808999 | G22: =$G$21*('Revenue Breakup'!D36/'Revenue Breakup'!$D$40) -> #REF! | H22: =H21 -> - | I22: =$I$21*('Revenue Breakup'!D36/'Revenue Breakup'!$D$40) -> #REF! | J22: =$J$21*('Revenue Breakup'!E36/'Revenue Breakup'!$E$40) -> #REF! | K22: =$K$21*('Revenue Breakup'!E36/'Revenue Breakup'!$E$40) -> #REF! | L22: =$L$21*('Revenue Breakup'!E36/'Revenue Breakup'!$E$40) -> #REF! | M22: =$M$21*('Revenue Breakup'!F36/'Revenue Breakup'!$F$40) -> #REF! | N22: =$N$21*('Revenue Breakup'!F36/'Revenue Breakup'!$F$40) -> #REF! | O22: =$O$21*('Revenue Breakup'!F36/'Revenue Breakup'!$F$40) -> #REF! | P22: =$P$21*('Revenue Breakup'!G36/'Revenue Breakup'!$G$40) -> #REF! | Q22: =$Q$21*('Revenue Breakup'!G36/'Revenue Breakup'!$G$40) -> #REF! | R22: =$R$21*('Revenue Breakup'!G36/'Revenue Breakup'!$G$40) -> #REF!
B23: Lactation Powder | D23: =D22 -> - | E23: =E22 -> - | F23: =$F$21*'Revenue Breakup'!C37 -> 1.0092633 | G23: =$G$21*('Revenue Breakup'!D37/'Revenue Breakup'!$D$40) -> #REF! | H23: =H22 -> - | I23: =$I$21*('Revenue Breakup'!D37/'Revenue Breakup'!$D$40) -> #REF! | J23: =$J$21*('Revenue Breakup'!E37/'Revenue Breakup'!$E$40) -> #REF! | K23: =$K$21*('Revenue Breakup'!E37/'Revenue Breakup'!$E$40) -> #REF! | L23: =$L$21*('Revenue Breakup'!E37/'Revenue Breakup'!$E$40) -> #REF! | M23: =$M$21*('Revenue Breakup'!F37/'Revenue Breakup'!$F$40) -> #REF! | N23: =$N$21*('Revenue Breakup'!F37/'Revenue Breakup'!$F$40) -> #REF! | O23: =$O$21*('Revenue Breakup'!F37/'Revenue Breakup'!$F$40) -> #REF! | P23: =$P$21*('Revenue Breakup'!G37/'Revenue Breakup'!$G$40) -> #REF! | Q23: =$Q$21*('Revenue Breakup'!G37/'Revenue Breakup'!$G$40) -> #REF! | R23: =$R$21*('Revenue Breakup'!G37/'Revenue Breakup'!$G$40) -> #REF!
B24: Infant Powder | D24: =D23 -> - | E24: =E23 -> - | F24: =$F$21*'Revenue Breakup'!C38 -> 1.0674901 | G24: =$G$21*('Revenue Breakup'!D38/'Revenue Breakup'!$D$40) -> #REF! | H24: =H23 -> - | I24: =$I$21*('Revenue Breakup'!D38/'Revenue Breakup'!$D$40) -> #REF! | J24: =$J$21*('Revenue Breakup'!E38/'Revenue Breakup'!$E$40) -> #REF! | K24: =$K$21*('Revenue Breakup'!E38/'Revenue Breakup'!$E$40) -> #REF! | L24: =$L$21*('Revenue Breakup'!E38/'Revenue Breakup'!$E$40) -> #REF! | M24: =$M$21*('Revenue Breakup'!F38/'Revenue Breakup'!$F$40) -> #REF! | N24: =$N$21*('Revenue Breakup'!F38/'Revenue Breakup'!$F$40) -> #REF! | O24: =$O$21*('Revenue Breakup'!F38/'Revenue Breakup'!$F$40) -> #REF! | P24: =$P$21*('Revenue Breakup'!G38/'Revenue Breakup'!$G$40) -> #REF! | Q24: =$Q$21*('Revenue Breakup'!G38/'Revenue Breakup'!$G$40) -> #REF! | R24: =$R$21*('Revenue Breakup'!G38/'Revenue Breakup'!$G$40) -> #REF!
B25: Children Powder | D25: =D24 -> - | E25: =E24 -> - | F25: =$F$21*'Revenue Breakup'!C39 -> 0.93515659 | G25: =$G$21*('Revenue Breakup'!D39/'Revenue Breakup'!$D$40) -> #REF! | H25: =H24 -> - | I25: =$I$21*('Revenue Breakup'!D39/'Revenue Breakup'!$D$40) -> #REF! | J25: =$J$21*('Revenue Breakup'!E39/'Revenue Breakup'!$E$40) -> #REF! | K25: =$K$21*('Revenue Breakup'!E39/'Revenue Breakup'!$E$40) -> #REF! | L25: =$L$21*('Revenue Breakup'!E39/'Revenue Breakup'!$E$40) -> #REF! | M25: =$M$21*('Revenue Breakup'!F39/'Revenue Breakup'!$F$40) -> #REF! | N25: =$N$21*('Revenue Breakup'!F39/'Revenue Breakup'!$F$40) -> #REF! | O25: =$O$21*('Revenue Breakup'!F39/'Revenue Breakup'!$F$40) -> #REF! | P25: =$P$21*('Revenue Breakup'!G39/'Revenue Breakup'!$G$40) -> #REF! | Q25: =$Q$21*('Revenue Breakup'!G39/'Revenue Breakup'!$G$40) -> #REF! | R25: =$R$21*('Revenue Breakup'!G39/'Revenue Breakup'!$G$40) -> #REF!
B26: G&A / Operations Overheads (in %) | D26: ='IE Biffurcation'!N33 -> - | E26: ='IE Biffurcation'!I33 -> - | F26: =VALUE(SUBSTITUTE('IE Biffurcation'!D33, "%", "")) -> 3 | G26: =VALUE(SUBSTITUTE('IE Biffurcation'!E33, "%", "")) -> 3 | H26: ='IE Biffurcation'!J33 -> - | I26: =VALUE(SUBSTITUTE('IE Biffurcation'!O33, "%", "")) -> 3 | J26: =VALUE(SUBSTITUTE('IE Biffurcation'!F33, "%", "")) -> 3 | K26: =VALUE(SUBSTITUTE('IE Biffurcation'!K33, "%", "")) -> 3 | L26: =VALUE(SUBSTITUTE('IE Biffurcation'!P33, "%", "")) -> 3 | M26: =VALUE(SUBSTITUTE('IE Biffurcation'!G33, "%", "")) -> 3 | N26: =VALUE(SUBSTITUTE('IE Biffurcation'!L33, "%", "")) -> 3 | O26: =VALUE(SUBSTITUTE('IE Biffurcation'!Q33, "%", "")) -> 3 | P26: =VALUE(SUBSTITUTE('IE Biffurcation'!H33, "%", "")) -> 3 | Q26: =VALUE(SUBSTITUTE('IE Biffurcation'!M33, "%", "")) -> 3 | R26: =VALUE(SUBSTITUTE('IE Biffurcation'!R33, "%", "")) -> 3
B27: Pregnancy Powder | D27: =D26 -> - | E27: =E26 -> - | F27: =$F$26*('Revenue Breakup'!C36) -> 0.74106749 | G27: =$G$26*('Revenue Breakup'!D36/'Revenue Breakup'!$D$40) -> #REF! | H27: =H26 -> - | I27: =$I$26*('Revenue Breakup'!D36/'Revenue Breakup'!$D$40) -> #REF! | J27: =$J$26*('Revenue Breakup'!E36/'Revenue Breakup'!$E$40) -> #REF! | K27: =$K$26*('Revenue Breakup'!E36/'Revenue Breakup'!$E$40) -> #REF! | L27: =$K$26*('Revenue Breakup'!E36/'Revenue Breakup'!$E$40) -> #REF! | M27: =$M$26*('Revenue Breakup'!F36/'Revenue Breakup'!$F$40) -> #REF! | N27: =$N$26*('Revenue Breakup'!F36/'Revenue Breakup'!$F$40) -> #REF! | O27: =$O$26*('Revenue Breakup'!F36/'Revenue Breakup'!$F$40) -> #REF! | P27: =$P$26*('Revenue Breakup'!G36/'Revenue Breakup'!$G$40) -> #REF! | Q27: =$Q$26*('Revenue Breakup'!G36/'Revenue Breakup'!$G$40) -> #REF! | R27: =$R$26*('Revenue Breakup'!G36/'Revenue Breakup'!$G$40) -> #REF!
B28: Lactation Powder | D28: =D27 -> - | E28: =E27 -> - | F28: =$F$26*('Revenue Breakup'!C37) -> 0.75694751 | G28: =$G$26*('Revenue Breakup'!D37/'Revenue Breakup'!$D$40) -> #REF! | H28: =H27 -> - | I28: =$I$26*('Revenue Breakup'!D37/'Revenue Breakup'!$D$40) -> #REF! | J28: =$J$26*('Revenue Breakup'!E37/'Revenue Breakup'!$E$40) -> #REF! | K28: =$K$26*('Revenue Breakup'!E37/'Revenue Breakup'!$E$40) -> #REF! | L28: =$K$26*('Revenue Breakup'!E37/'Revenue Breakup'!$E$40) -> #REF! | M28: =$M$26*('Revenue Breakup'!F37/'Revenue Breakup'!$F$40) -> #REF! | N28: =$N$26*('Revenue Breakup'!F37/'Revenue Breakup'!$F$40) -> #REF! | O28: =$O$26*('Revenue Breakup'!F37/'Revenue Breakup'!$F$40) -> #REF! | P28: =$P$26*('Revenue Breakup'!G37/'Revenue Breakup'!$G$40) -> #REF! | Q28: =$Q$26*('Revenue Breakup'!G37/'Revenue Breakup'!$G$40) -> #REF! | R28: =$R$26*('Revenue Breakup'!G37/'Revenue Breakup'!$G$40) -> #REF!
B29: Infant Powder | D29: =D28 -> - | E29: =E28 -> - | F29: =$F$26*('Revenue Breakup'!C38) -> 0.80061756 | G29: =$G$26*('Revenue Breakup'!D38/'Revenue Breakup'!$D$40) -> #REF! | H29: =H28 -> - | I29: =$I$26*('Revenue Breakup'!D38/'Revenue Breakup'!$D$40) -> #REF! | J29: =$J$26*('Revenue Breakup'!E38/'Revenue Breakup'!$E$40) -> #REF! | K29: =$K$26*('Revenue Breakup'!E38/'Revenue Breakup'!$E$40) -> #REF! | L29: =$K$26*('Revenue Breakup'!E38/'Revenue Breakup'!$E$40) -> #REF! | M29: =$M$26*('Revenue Breakup'!F38/'Revenue Breakup'!$F$40) -> #REF! | N29: =$N$26*('Revenue Breakup'!F38/'Revenue Breakup'!$F$40) -> #REF! | O29: =$O$26*('Revenue Breakup'!F38/'Revenue Breakup'!$F$40) -> #REF! | P29: =$P$26*('Revenue Breakup'!G38/'Revenue Breakup'!$G$40) -> #REF! | Q29: =$Q$26*('Revenue Breakup'!G38/'Revenue Breakup'!$G$40) -> #REF! | R29: =$R$26*('Revenue Breakup'!G38/'Revenue Breakup'!$G$40) -> #REF!
B30: Children Powder | D30: =D29 -> - | E30: =E29 -> - | F30: =$F$26*('Revenue Breakup'!C39) -> 0.70136745 | G30: =$G$26*('Revenue Breakup'!D39/'Revenue Breakup'!$D$40) -> #REF! | H30: =H29 -> - | I30: =$I$26*('Revenue Breakup'!D39/'Revenue Breakup'!$D$40) -> #REF! | J30: =$J$26*('Revenue Breakup'!E39/'Revenue Breakup'!$E$40) -> #REF! | K30: =$K$26*('Revenue Breakup'!E39/'Revenue Breakup'!$E$40) -> #REF! | L30: =$K$26*('Revenue Breakup'!E39/'Revenue Breakup'!$E$40) -> #REF! | M30: =$M$26*('Revenue Breakup'!F39/'Revenue Breakup'!$F$40) -> #REF! | N30: =$N$26*('Revenue Breakup'!F39/'Revenue Breakup'!$F$40) -> #REF! | O30: =$O$26*('Revenue Breakup'!F39/'Revenue Breakup'!$F$40) -> #REF! | P30: =$P$26*('Revenue Breakup'!G39/'Revenue Breakup'!$G$40) -> #REF! | Q30: =$Q$26*('Revenue Breakup'!G39/'Revenue Breakup'!$G$40) -> #REF! | R30: =$R$26*('Revenue Breakup'!G39/'Revenue Breakup'!$G$40) -> #REF!
B31: Employee Cost (in %) | C31: * QA/QC teams per plant, regulatory staff per brand, HCP field force are unavoidable. Costs higher in early years. | D31: ='IE Biffurcation'!N40 -> - | E31: ='IE Biffurcation'!I40 -> - | F31: =VALUE(SUBSTITUTE('IE Biffurcation'!D40, "%", "")) -> 6 | G31: =VALUE(SUBSTITUTE('IE Biffurcation'!O40, "%", "")) -> 9 | H31: ='IE Biffurcation'!J40 -> - | I31: =VALUE(SUBSTITUTE('IE Biffurcation'!E40, "%", "")) -> 6 | J31: =VALUE(SUBSTITUTE('IE Biffurcation'!P40, "%", "")) -> 6 | K31: =VALUE(SUBSTITUTE('IE Biffurcation'!K40, "%", "")) -> 6 | L31: =VALUE(SUBSTITUTE('IE Biffurcation'!P40, "%", "")) -> 6 | M31: =VALUE(SUBSTITUTE('IE Biffurcation'!G40, "%", "")) -> 5 | N31: =VALUE(SUBSTITUTE('IE Biffurcation'!L40, "%", "")) -> 5 | O31: =VALUE(SUBSTITUTE('IE Biffurcation'!Q40, "%", "")) -> 5 | P31: =VALUE(SUBSTITUTE('IE Biffurcation'!R40, "%", "")) -> 4 | Q31: =VALUE(SUBSTITUTE('IE Biffurcation'!M40, "%", "")) -> 5 | R31: =VALUE(SUBSTITUTE('IE Biffurcation'!H40, "%", "")) -> 5
B32: Pregnancy Powder | D32: =D31 -> - | E32: =E31 -> - | F32: =$F$31*('Revenue Breakup'!C36) -> 1.482135 | G32: =$G$31*('Revenue Breakup'!D36/'Revenue Breakup'!$D$40) -> #REF! | H32: =H31 -> - | I32: =$I$31*('Revenue Breakup'!D36/'Revenue Breakup'!$D$40) -> #REF! | J32: =$J$31*('Revenue Breakup'!E36/'Revenue Breakup'!$E$40) -> #REF! | K32: =$K$31*('Revenue Breakup'!E36/'Revenue Breakup'!$E$40) -> #REF! | L32: =$K$31*('Revenue Breakup'!E36/'Revenue Breakup'!$E$40) -> #REF! | M32: =$M$31*('Revenue Breakup'!F36/'Revenue Breakup'!$F$40) -> #REF! | N32: =$N$31*('Revenue Breakup'!F36/'Revenue Breakup'!$F$40) -> #REF! | O32: =$O$31*('Revenue Breakup'!F36/'Revenue Breakup'!$F$40) -> #REF! | P32: =$P$31*('Revenue Breakup'!G36/'Revenue Breakup'!$G$40) -> #REF! | Q32: =$Q$31*('Revenue Breakup'!G36/'Revenue Breakup'!$G$40) -> #REF! | R32: =$R$31*('Revenue Breakup'!G36/'Revenue Breakup'!$G$40) -> #REF!
B33: Lactation Powder | D33: =D32 -> - | E33: =E32 -> - | F33: =$F$31*('Revenue Breakup'!C37) -> 1.513895 | G33: =$G$31*('Revenue Breakup'!D37/'Revenue Breakup'!$D$40) -> #REF! | H33: =H32 -> - | I33: =$I$31*('Revenue Breakup'!D37/'Revenue Breakup'!$D$40) -> #REF! | J33: =$J$31*('Revenue Breakup'!E37/'Revenue Breakup'!$E$40) -> #REF! | K33: =$K$31*('Revenue Breakup'!E37/'Revenue Breakup'!$E$40) -> #REF! | L33: =$K$31*('Revenue Breakup'!E37/'Revenue Breakup'!$E$40) -> #REF! | M33: =$M$31*('Revenue Breakup'!F37/'Revenue Breakup'!$F$40) -> #REF! | N33: =$N$31*('Revenue Breakup'!F37/'Revenue Breakup'!$F$40) -> #REF! | O33: =$O$31*('Revenue Breakup'!F37/'Revenue Breakup'!$F$40) -> #REF! | P33: =$P$31*('Revenue Breakup'!G37/'Revenue Breakup'!$G$40) -> #REF! | Q33: =$Q$31*('Revenue Breakup'!G37/'Revenue Breakup'!$G$40) -> #REF! | R33: =$R$31*('Revenue Breakup'!G37/'Revenue Breakup'!$G$40) -> #REF!
B34: Infant Powder | D34: =D33 -> - | E34: =E33 -> - | F34: =$F$31*('Revenue Breakup'!C38) -> 1.6012351 | G34: =$G$31*('Revenue Breakup'!D38/'Revenue Breakup'!$D$40) -> #REF! | H34: =H33 -> - | I34: =$I$31*('Revenue Breakup'!D38/'Revenue Breakup'!$D$40) -> #REF! | J34: =$J$31*('Revenue Breakup'!E38/'Revenue Breakup'!$E$40) -> #REF! | K34: =$K$31*('Revenue Breakup'!E38/'Revenue Breakup'!$E$40) -> #REF! | L34: =$K$31*('Revenue Breakup'!E38/'Revenue Breakup'!$E$40) -> #REF! | M34: =$M$31*('Revenue Breakup'!F38/'Revenue Breakup'!$F$40) -> #REF! | N34: =$N$31*('Revenue Breakup'!F38/'Revenue Breakup'!$F$40) -> #REF! | O34: =$O$31*('Revenue Breakup'!F38/'Revenue Breakup'!$F$40) -> #REF! | P34: =$P$31*('Revenue Breakup'!G38/'Revenue Breakup'!$G$40) -> #REF! | Q34: =$Q$31*('Revenue Breakup'!G38/'Revenue Breakup'!$G$40) -> #REF! | R34: =$R$31*('Revenue Breakup'!G38/'Revenue Breakup'!$G$40) -> #REF!
B35: Children Powder | D35: =D34 -> - | E35: =E34 -> - | F35: =$F$31*('Revenue Breakup'!C39) -> 1.4027349 | G35: =$G$31*('Revenue Breakup'!D39/'Revenue Breakup'!$D$40) -> #REF! | H35: =H34 -> - | I35: =$I$31*('Revenue Breakup'!D39/'Revenue Breakup'!$D$40) -> #REF! | J35: =$J$31*('Revenue Breakup'!E39/'Revenue Breakup'!$E$40) -> #REF! | K35: =$K$31*('Revenue Breakup'!E39/'Revenue Breakup'!$E$40) -> #REF! | L35: =$K$31*('Revenue Breakup'!E39/'Revenue Breakup'!$E$40) -> #REF! | M35: =$M$31*('Revenue Breakup'!F39/'Revenue Breakup'!$F$40) -> #REF! | N35: =$N$31*('Revenue Breakup'!F39/'Revenue Breakup'!$F$40) -> #REF! | O35: =$O$31*('Revenue Breakup'!F39/'Revenue Breakup'!$F$40) -> #REF! | P35: =$P$31*('Revenue Breakup'!G39/'Revenue Breakup'!$G$40) -> #REF! | Q35: =$Q$31*('Revenue Breakup'!G39/'Revenue Breakup'!$G$40) -> #REF! | R35: =$R$31*('Revenue Breakup'!G39/'Revenue Breakup'!$G$40) -> #REF!
B37: INDIRECT EXPENSE % BREAKUP TIER WISE
B38: Cost Head | C38: Year 1 | F38: Year 2 | I38: Year 3 | L38: Year 4 | O38: Year 5
C39: Tier 1 (Metro) | D39: Tier 2 (Mid Cities) | E39: Tier 3 (Small Towns) | F39: Tier 1 (Metro) | G39: Tier 2 (Mid Cities) | H39: Tier 3 (Small Towns) | I39: Tier 1 (Metro) | J39: Tier 2 (Mid Cities) | K39: Tier 3 (Small Towns) | L39: Tier 1 (Metro) | M39: Tier 2 (Mid Cities) | N39: Tier 3 (Small Towns) | O39: Tier 1 (Metro) | P39: Tier 2 (Mid Cities) | Q39: Tier 3 (Small Towns)
B40: Marketing & Advertising | C40: =D5 -> 0 | D40: =E5 -> 0 | E40: =F5 -> 7 | F40: =G5 -> 5 | G40: =H5 -> 0 | H40: =I5 -> 4 | I40: =J5 -> 5 | J40: =K5 -> 7 | ... Q40: =R5 -> 5 | X40: 5
B41: HCP Detailing & Medical Engagement | C41: =D10 -> 0 | D41: =E10 -> 0 | E41: =F10 -> 2 | F41: =G10 -> 3 | G41: =H10 -> 0 | H41: =I10 -> 2 | I41: =J10 -> 5 | J41: =K10 -> 3 | ... Q41: =R10 -> 4
B42: R&D / Regulatory / Compliance | C42: =D12 -> 0 | D42: =E12 -> 0 | E42: =F21 -> 4 | F42: =G21 -> 4 | G42: =H21 -> - | H42: =I21 -> 4 | I42: =J21 -> 4 | J42: =K21 -> 3 | K42: =L21 -> 2 | L42: =M21 -> 3 | ... Q42: =R21 -> 1
B43: G&A / Operations Overheads | C43: =D13 -> 0 | D43: =E13 -> 0 | E43: =F26 -> 3 | F43: =G26 -> 3 | G43: =H26 -> - | H43: =I26 -> 3 | I43: =J26 -> 3 | J43: =K26 -> 3 | K43: =L26 -> 3 | L43: =M26 -> 3 | ... Q43: =R26 -> 3
B44: Employee Cost | C44: =D14 -> 0 | D44: =E14 -> 0 | E44: =F31 -> 6 | F44: =G31 -> 9 | G44: =H31 -> - | H44: =I31 -> 6 | I44: =J31 -> 6 | J44: =K31 -> 6 | K44: =L31 -> 6 | L44: =M31 -> 5 | ... Q44: =R31 -> 5
B46: REVENUE BREAKUP TIER WISE
B47: REVENUE BREAKUP | C47: 1 | D47: 2 | E47: 3 | F47: 4 | G47: 5
B48: Tier 1 | C48: ='Revenue Breakup'!C31 -> 0 | D48: ='Revenue Breakup'!E31 -> #REF! | E48: ='Revenue Breakup'!G31 -> #REF! | F48: ='Revenue Breakup'!I31 -> #REF! | G48: ='Revenue Breakup'!K31 -> #REF!
B49: Tier 2 | C49: ='Revenue Breakup'!C32 -> 0 | D49: ='Revenue Breakup'!E32 -> 0 | E49: ='Revenue Breakup'!G32 -> 0 | F49: ='Revenue Breakup'!I32 -> 0 | G49: ='Revenue Breakup'!K32 -> 0
B50: Tier 3 | C50: ='Revenue Breakup'!C33 -> 88.413 | D50: ='Revenue Breakup'!E33 -> 0 | E50: ='Revenue Breakup'!G33 -> 0 | F50: ='Revenue Breakup'!I33 -> 0 | G50: ='Revenue Breakup'!K33 -> 0
B52: INDIRECT EXPENSE BREAKUP TIER WISE
B53: Cost Head | C53: Year 1 | F53: Year 2 | I53: Year 3 | L53: Year 4 | O53: Year 5
C54: Tier 1 (Metro) | D54: Tier 2 (Mid Cities) | E54: Tier 3 (Small Towns) | F54: Tier 1 (Metro) | G54: Tier 2 (Mid Cities) | H54: Tier 3 (Small Towns) | I54: Tier 1 (Metro) | J54: Tier 2 (Mid Cities) | K54: Tier 3 (Small Towns) | L54: Tier 1 (Metro) | M54: Tier 2 (Mid Cities) | N54: Tier 3 (Small Towns) | O54: Tier 1 (Metro) | P54: Tier 2 (Mid Cities) | Q54: Tier 3 (Small Towns)
B55: Revenue | C55: =C48 -> 0 | D55: =C49 -> 0 | E55: =C50 -> 88.413 | F55: =D48 -> #REF! | G55: =D49 -> 0 | H55: =D50 -> 0 | I55: =E48 -> #REF! | J55: =E49 -> 0 | K55: =E50 -> 0 | L55: =F48 -> #REF! | M55: =F49 -> 0 | N55: =F50 -> 0 | O55: =G48 -> #REF! | P55: =G49 -> 0 | Q55: =G50 -> 0
B56: Marketing & Advertising | C56: 0 | D56: 0 | E56: =$E$55*(E40/100) -> 6.18891 | F56: =$F$55*(F40/100) -> #REF! | G56: 0 | H56: =$H$55*(H40/100) -> 0 | I56: =$I$55*(I40/100) -> #REF! | J56: =$J$55*(J40/100) -> 0 | K56: =$K$55*(K40/100) -> 0 | L56: =$L$55*(L40/100) -> #REF! | M56: =$M$55*(M40/100) -> 0 | N56: =$N$55*(N40/100) -> 0 | O56: =$O$55*(O40/100) -> #REF! | P56: =$P$55*(P40/100) -> 0 | Q56: =$Q$55*(Q40/100) -> 0
B57: HCP Detailing & Medical Engagement | C57: 0 | D57: 0 | E57: =$E$55*(E41/100) -> 1.76826 | F57: =$F$55*(F41/100) -> #REF! | G57: 0 | H57: =$H$55*(H41/100) -> 0 | I57: =$I$55*(I41/100) -> #REF! | J57: =$J$55*(J41/100) -> 0 | K57: =$K$55*(K41/100) -> 0 | L57: =$L$55*(L41/100) -> #REF! | M57: =$M$55*(M41/100) -> 0 | N57: =$N$55*(N41/100) -> 0 | O57: =$O$55*(O41/100) -> #REF! | P57: =$P$55*(P41/100) -> 0 | Q57: =$Q$55*(Q41/100) -> 0
B58: Distribution & Logistics | C58: 0 | D58: 0 | E58: =sum(F17:F20) -> 3.159 | F58: =sum(G17:G20) -> 1.0708663 | G58: 0 | H58: =sum(I17:I20) -> 22.483749 | I58: =sum(J17:J20) -> 3.2125989 | J58: =sum(K17:K20) -> 4.3323429 | K58: =sum(L17:L20) -> 67.451246 | L58: =sum(M17:M20) -> 5.9492571 | M58: =sum(N17:N20) -> 8.0228571 | N58: =sum(O17:O20) -> 124.90971 | O58: =sum(P16:P20) -> 17.280841 | P58: =sum(Q16:Q20) -> 20.515657 | Q58: =sum(R16:R20) -> 202.85915
B59: R&D / Regulatory / Compliance | C59: 0 | D59: 0 | E59: =$E$55*(E42/100) -> 3.53652 | F59: =$F$55*(F42/100) -> #REF! | G59: 0 | H59: =$H$55*(H42/100) -> 0 | I59: =$I$55*(I42/100) -> #REF! | J59: =$J$55*(J42/100) -> 0 | K59: =$K$55*(K42/100) -> 0 | L59: =$L$55*(L42/100) -> #REF! | M59: =$M$55*(M42/100) -> 0 | N59: =$N$55*(N42/100) -> 0 | O59: =$O$55*(O42/100) -> #REF! | P59: =$P$55*(P42/100) -> 0 | Q59: =$Q$55*(Q42/100) -> 0
B60: G&A / Operations Overheads | C60: 0 | D60: 0 | E60: =$E$55*(E43/100) -> 2.65239 | F60: =$F$55*(F43/100) -> #REF! | G60: 0 | H60: =$H$55*(H43/100) -> 0 | I60: =$I$55*(I43/100) -> #REF! | J60: =$J$55*(J43/100) -> 0 | K60: =$K$55*(K43/100) -> 0 | L60: =$L$55*(L43/100) -> #REF! | M60: =$M$55*(M43/100) -> 0 | N60: =$N$55*(N43/100) -> 0 | O60: =$O$55*(O43/100) -> #REF! | P60: =$P$55*(P43/100) -> 0 | Q60: =$Q$55*(Q43/100) -> 0
B61: Employee Cost | C61: 0 | D61: 0 | E61: =$E$55*(E44/100) -> 5.30478 | F61: =$F$55*(F44/100) -> #REF! | G61: 0 | H61: =$H$55*(H44/100) -> 0 | I61: =$I$55*(I44/100) -> #REF! | J61: =$J$55*(J44/100) -> 0 | K61: =$K$55*(K44/100) -> 0 | L61: =$L$55*(L44/100) -> #REF! | M61: =$M$55*(M44/100) -> 0 | N61: =$N$55*(N44/100) -> 0 | O61: =$O$55*(O44/100) -> #REF! | P61: =$P$55*(P44/100) -> 0 | Q61: =$Q$55*(Q44/100) -> 0
B62: Contingency Fund | C62: =sum(C56:C61)*5% -> 0 | D62: =sum(D56:D61)*5% -> 0 | E62: =sum(E56:E61)*5% -> 1.130493 | F62: =sum(F56:F61)*5% -> #REF! | G62: =sum(G56:G61)*5% -> 0 | H62: =sum(H56:H61)*5% -> 1.1241874 | I62: =sum(I56:I61)*5% -> #REF! | J62: =sum(J56:J61)*5% -> 0.21661714 | ... Q62: =sum(Q56:Q61)*5% -> 10.142958
B63: Sub-Total | C63: =sum(C56:C62) -> 0 | D63: =sum(D56:D62) -> 0 | E63: =sum(E56:E62) -> 23.740353 | F63: =sum(F56:F62) -> #REF! | G63: =sum(G56:G62) -> 0 | H63: =sum(H56:H62) -> 23.607936 | I63: =sum(I56:I62) -> #REF! | J63: =sum(J56:J62) -> 4.54896 | ... Q63: =sum(Q56:Q62) -> 213.00211
B64: Total | C64: =sum(C63:E63) -> 23.740353 | F64: =sum(F63:H63) -> #REF! | I64: =sum(I63:K63) -> #REF! | L64: =sum(L63:N63) -> #REF! | O64: =sum(O63:Q63) -> #REF!
B66: INDIRECT EXPENSE BREAKUP TIER WISE & PRODUCT WISE
B67: Cost Head | C67: Remark | D67: Year 1 | G67: Year 2 | J67: Year 3 | M67: Year 4 | P67: Year 5
D68: Tier 1 (Metro) | E68: Tier 2 (Mid Cities) | F68: Tier 3 (Small Towns) | G68: Tier 1 (Metro) | H68: Tier 2 (Mid Cities) | I68: Tier 3 (Small Towns) | J68: Tier 1 (Metro) | K68: Tier 2 (Mid Cities) | L68: Tier 3 (Small Towns) | M68: Tier 1 (Metro) | N68: Tier 2 (Mid Cities) | O68: Tier 3 (Small Towns) | P68: Tier 1 (Metro) | Q68: Tier 2 (Mid Cities) | R68: Tier 3 (Small Towns)
B69: Marketing & Advertising | C69: * IMS Act prohibits infant formula consumer ads. Tier 1 budget shifts entirely to HCP detailing. 3 brand budgets from Y3. | D69: =IFERROR(D5*$C$55,0) -> 0 | E69: =IFERROr(0,$D$55*E5) -> 0 | F69: =iferror($E$55*F5%,0) -> 6.18891 | G69: =iferror($F$55*G5%,0) -> 0 | H69: =iferror($G$55*H5%,0) -> 0 | I69: =iferror($H$55*I5%,0) -> 0 | J69: =iferror($I$55*J5%,0) -> 0 | K69: =iferror($J$55*K5%,0) -> 0 | L69: =iferror($K$55*L5%,0) -> 0 | M69: =iferror($L$55*M5%,0) -> 0 | N69: =iferror($M$55*N5%,0) -> 0 | O69: =iferror($N$55*O5%,0) -> 0 | P69: =iferror($O$55*P5%,0) -> 0 | Q69: =iferror($P$55*Q5%,0) -> 0 | R69: =iferror($Q$55*R5%,0) -> 0
B70: Pregnancy Powder | D70: =IFERROR(D6*$C$55,0) -> 0 | E70: =IFERROr(0,$D$55*E6) -> 0 | F70: =iferror($E$55*F6%,0) -> 1.5288 | G70: =iferror($F$55*G6%,0) -> 0 | H70: =iferror($G$55*H6%,0) -> 0 | I70: =iferror($H$55*I6%,0) -> 0 | J70: =iferror($I$55*J6%,0) -> 0 | K70: =iferror($J$55*K6%,0) -> 0 | L70: =iferror($K$55*L6%,0) -> 0 | M70: =iferror($L$55*M6%,0) -> 0 | N70: =iferror($M$55*N6%,0) -> 0 | O70: =iferror($N$55*O6%,0) -> 0 | P70: =iferror($O$55*P6%,0) -> 0 | Q70: =iferror($P$55*Q6%,0) -> 0 | R70: =iferror($Q$55*R6%,0) -> 0
B71: Lactation Powder | D71: =IFERROR(D7*$C$55,0) -> 0 | E71: =IFERROr(0,$D$55*E7) -> 0 | F71: =iferror($E$55*F7%,0) -> 1.56156 | G71: =iferror($F$55*G7%,0) -> 0 | H71: =iferror($G$55*H7%,0) -> 0 | I71: =iferror($H$55*I7%,0) -> 0 | J71: =iferror($I$55*J7%,0) -> 0 | K71: =iferror($J$55*K7%,0) -> 0 | L71: =iferror($K$55*L7%,0) -> 0 | M71: =iferror($L$55*M7%,0) -> 0 | N71: =iferror($M$55*N7%,0) -> 0 | O71: =iferror($N$55*O7%,0) -> 0 | P71: =iferror($O$55*P7%,0) -> 0 | Q71: =iferror($P$55*Q7%,0) -> 0 | R71: =iferror($Q$55*R7%,0) -> 0
B72: Infant Powder | D72: =IFERROR(D8*$C$55,0) -> 0 | E72: =IFERROr(0,$D$55*E8) -> 0 | F72: =iferror($E$55*F8%,0) -> 1.65165 | G72: =iferror($F$55*G8%,0) -> 0 | H72: =iferror($G$55*H8%,0) -> 0 | I72: =iferror($H$55*I8%,0) -> 0 | J72: =iferror($I$55*J8%,0) -> 0 | K72: =iferror($J$55*K8%,0) -> 0 | L72: =iferror($K$55*L8%,0) -> 0 | M72: =iferror($L$55*M8%,0) -> 0 | N72: =iferror($M$55*N8%,0) -> 0 | O72: =iferror($N$55*O8%,0) -> 0 | P72: =iferror($O$55*P8%,0) -> 0 | Q72: =iferror($P$55*Q8%,0) -> 0 | R72: =iferror($Q$55*R8%,0) -> 0
B73: Children Powder | D73: =IFERROR(D9*$C$55,0) -> 0 | E73: =IFERROr(0,$D$55*E9) -> 0 | F73: =iferror($E$55*F9%,0) -> 1.4469 | G73: =iferror($F$55*G9%,0) -> 0 | H73: =iferror($G$55*H9%,0) -> 0 | I73: =iferror($H$55*I9%,0) -> 0 | J73: =iferror($I$55*J9%,0) -> 0 | K73: =iferror($J$55*K9%,0) -> 0 | L73: =iferror($K$55*L9%,0) -> 0 | M73: =iferror($L$55*M9%,0) -> 0 | N73: =iferror($M$55*N9%,0) -> 0 | O73: =iferror($N$55*O9%,0) -> 0 | P73: =iferror($O$55*P9%,0) -> 0 | Q73: =iferror($P$55*Q9%,0) -> 0 | R73: =iferror($Q$55*R9%,0) -> 0
B74: HCP Detailing & Medical Engagement | C74: * OBGYNs, pediatricians, hospitals drive prescription/recommendation. Mandatory for infant formula category growth. | D74: =IFERROR(0 ,D10*$C$55) -> 0 | E74: =IFERROr($D$55*E10,0) -> 0 | F74: =iferror($E$55*F10%,0) -> 1.76826 | G74: =iferror($F$55*G10%,0) -> 0 | H74: =iferror($G$55*H10%,0) -> 0 | I74: =iferror($H$55*I10%,0) -> 0 | J74: =iferror($I$55*J10%,0) -> 0 | K74: =iferror($J$55*K10%,0) -> 0 | L74: =iferror($K$55*L10%,0) -> 0 | M74: =iferror($L$55*M10%,0) -> 0 | N74: =iferror($M$55*N10%,0) -> 0 | O74: =iferror($N$55*O10%,0) -> 0 | P74: =iferror($O$55*P10%,0) -> 0 | Q74: =iferror($P$55*Q10%,0) -> 0 | R74: =iferror($Q$55*R10%,0) -> 0
B75: Pregnancy Powder | D75: =IFERROR(0 ,D11*$C$55) -> 0 | E75: =IFERROr($D$55*E11,0) -> 0 | F75: =iferror($E$55*F11%,0) -> 0.4368 | G75: =iferror($F$55*G11%,0) -> 0 | H75: =iferror($G$55*H11%,0) -> 0 | I75: =iferror($H$55*I11%,0) -> 0 | J75: =iferror($I$55*J11%,0) -> 0 | K75: =iferror($J$55*K11%,0) -> 0 | L75: =iferror($K$55*L11%,0) -> 0 | M75: =iferror($L$55*M11%,0) -> 0 | N75: =iferror($M$55*N11%,0) -> 0 | O75: =iferror($N$55*O11%,0) -> 0 | P75: =iferror($O$55*P11%,0) -> 0 | Q75: =iferror($P$55*Q11%,0) -> 0 | R75: =iferror($Q$55*R11%,0) -> 0
B76: Lactation Powder | D76: =IFERROR(0 ,D12*$C$55) -> 0 | E76: =IFERROr($D$55*E12,0) -> 0 | F76: =iferror($E$55*F12%,0) -> 0.44616 | G76: =iferror($F$55*G12%,0) -> 0 | H76: =iferror($G$55*H12%,0) -> 0 | I76: =iferror($H$55*I12%,0) -> 0 | J76: =iferror($I$55*J12%,0) -> 0 | K76: =iferror($J$55*K12%,0) -> 0 | L76: =iferror($K$55*L12%,0) -> 0 | M76: =iferror($L$55*M12%,0) -> 0 | N76: =iferror($M$55*N12%,0) -> 0 | O76: =iferror($N$55*O12%,0) -> 0 | P76: =iferror($O$55*P12%,0) -> 0 | Q76: =iferror($P$55*Q12%,0) -> 0 | R76: =iferror($Q$55*R12%,0) -> 0
B77: Infant Powder | D77: =IFERROR(0 ,D13*$C$55) -> 0 | E77: =IFERROr($D$55*E13,0) -> 0 | F77: =iferror($E$55*F13%,0) -> 0.4719 | G77: =iferror($F$55*G13%,0) -> 0 | H77: =iferror($G$55*H13%,0) -> 0 | I77: =iferror($H$55*I13%,0) -> 0 | J77: =iferror($I$55*J13%,0) -> 0 | K77: =iferror($J$55*K13%,0) -> 0 | L77: =iferror($K$55*L13%,0) -> 0 | M77: =iferror($L$55*M13%,0) -> 0 | N77: =iferror($M$55*N13%,0) -> 0 | O77: =iferror($N$55*O13%,0) -> 0 | P77: =iferror($O$55*P13%,0) -> 0 | Q77: =iferror($P$55*Q13%,0) -> 0 | R77: =iferror($Q$55*R13%,0) -> 0
B78: Children Powder | D78: =IFERROR(0 ,D14*$C$55) -> 0 | E78: =IFERROr($D$55*E14,0) -> 0 | F78: =iferror($E$55*F14%,0) -> 0.4134 | G78: =iferror($F$55*G14%,0) -> 0 | H78: =iferror($G$55*H14%,0) -> 0 | I78: =iferror($H$55*I14%,0) -> 0 | J78: =iferror($I$55*J14%,0) -> 0 | K78: =iferror($J$55*K14%,0) -> 0 | L78: =iferror($K$55*L14%,0) -> 0 | M78: =iferror($L$55*M14%,0) -> 0 | N78: =iferror($M$55*N14%,0) -> 0 | O78: =iferror($N$55*O14%,0) -> 0 | P78: =iferror($O$55*P14%,0) -> 0 | Q78: =iferror($P$55*Q14%,0) -> 0 | R78: =iferror($Q$55*R14%,0) -> 0
B79: Distribution & Logistics (in Cr) | C79: * Rs. 9 per box in Year 1 and Year 2. Rs. 8.5 per box Year 3 onwards | D79: =IFERROR(0 ,D15*$C$55) -> 0 | E79: =IFERROr(0,$D$55*E15) -> 0 | F79: =sum(F80:F83) -> 3.159 | G79: =sum(G80:G83) -> 1.0708663 | H79: =sum(H80:H83) -> 0 | I79: =sum(I80:I83) -> 22.483749 | J79: =sum(J80:J83) -> 3.2125989 | K79: =sum(K80:K83) -> 4.3323429 | L79: =sum(L80:L83) -> 67.451246 | M79: =sum(M80:M83) -> 5.9492571 | ... R79: =sum(R80:R83) -> 194.85915
B80: Pregnancy Powder | D80: =IFERROR(0 ,D17*$C$55) -> 0 | E80: =IFERROr(0,$D$55*E17) -> 0 | F80: =F17 -> 0.702 | G80: =G17 -> 0.248832 | H80: =H17 -> 0 | I80: =I17 -> 4.9855269 | J80: =J17 -> 0.746496 | K80: =K17 -> 0.97311086 | L80: =L17 -> 14.956581 | M80: =M17 -> 1.3824 | ... R80: =R17 -> 43.207899
B81: Lactation Powder | D81: =IFERROR(0 ,D18*$C$55) -> 0 | E81: =IFERROr(0,$D$55*E18) -> 0 | F81: =F18 -> 0.702 | G81: =G18 -> 0.28882286 | H81: =H18 -> 0 | I81: =I18 -> 4.8966583 | J81: =J18 -> 0.86646857 | K81: =K18 -> 1.1064137 | L81: =L18 -> 14.689975 | M81: =M18 -> 1.6045714 | ... R81: =R18 -> 42.437705
B82: Infant Powder | D82: =IFERROR(0 ,D19*$C$55) -> 0 | E82: =IFERROr(0,$D$55*E19) -> 0 | F82: =F19 -> 0.8775 | G82: =G19 -> 0.22217143 | H82: =H19 -> 0 | I82: =I19 -> 6.37632 | J82: =J19 -> 0.66651429 | K82: =K19 -> 1.0397623 | L82: =L19 -> 19.12896 | M82: =M19 -> 1.2342857 | ... R82: =R19 -> 55.26144
B83: Children Powder | D83: =IFERROR(0 ,D20*$C$55) -> 0 | E83: =IFERROr(0,$D$55*E20) -> 0 | F83: =F20 -> 0.8775 | G83: =G20 -> 0.31104 | H83: =H20 -> 0 | I83: =I20 -> 6.2252434 | J83: =J20 -> 0.93312 | K83: =K20 -> 1.213056 | L83: =L20 -> 18.67573 | M83: =M20 -> 1.728 | ... R83: =R20 -> 53.95211
B84: R&D / Regulatory / Compliance | C84: * Infant formula under FSS Act strictest category. Each stage/ trimester/ flavour variant = separate FSSAI testing + label approval. | D84: =IFERROR(0 ,D21*$C$55) -> 0 | E84: =IFERROr(0,$D$55*E21) -> 0 | F84: =iferror($E$55*F21%,0) -> 3.53652 | G84: =iferror($F$55*G21%,0) -> 0 | H84: =iferror($G$55*H21%,0) -> 0 | I84: =iferror($H$55*I21%,0) -> 0 | J84: =iferror($I$55*J21%,0) -> 0 | K84: =iferror($J$55*K21%,0) -> 0 | L84: =iferror($K$55*L21%,0) -> 0 | M84: =iferror($L$55*M21%,0) -> 0 | N84: =iferror($M$55*N21%,0) -> 0 | O84: =iferror($N$55*O21%,0) -> 0 | P84: =iferror($O$55*P21%,0) -> 0 | Q84: =iferror($P$55*Q21%,0) -> 0 | R84: =iferror($Q$55*R21%,0) -> 0
B85: Pregnancy Powder | D85: =IFERROR(0 ,D22*$C$55) -> 0 | E85: =IFERROr(0,$D$55*E22) -> 0 | F85: =iferror($E$55*F22%,0) -> 0.8736 | G85: =iferror($F$55*G22%,0) -> 0 | H85: =iferror($G$55*H22%,0) -> 0 | I85: =iferror($H$55*I22%,0) -> 0 | J85: =iferror($I$55*J22%,0) -> 0 | K85: =iferror($J$55*K22%,0) -> 0 | L85: =iferror($K$55*L22%,0) -> 0 | M85: =iferror($L$55*M22%,0) -> 0 | N85: =iferror($M$55*N22%,0) -> 0 | O85: =iferror($N$55*O22%,0) -> 0 | P85: =iferror($O$55*P22%,0) -> 0 | Q85: =iferror($P$55*Q22%,0) -> 0 | R85: =iferror($Q$55*R22%,0) -> 0
B86: Lactation Powder | D86: =IFERROR(0 ,D23*$C$55) -> 0 | E86: =IFERROr(0,$D$55*E23) -> 0 | F86: =iferror($E$55*F23%,0) -> 0.89232 | G86: =iferror($F$55*G23%,0) -> 0 | H86: =iferror($G$55*H23%,0) -> 0 | I86: =iferror($H$55*I23%,0) -> 0 | J86: =iferror($I$55*J23%,0) -> 0 | K86: =iferror($J$55*K23%,0) -> 0 | L86: =iferror($K$55*L23%,0) -> 0 | M86: =iferror($L$55*M23%,0) -> 0 | N86: =iferror($M$55*N23%,0) -> 0 | O86: =iferror($N$55*O23%,0) -> 0 | P86: =iferror($O$55*P23%,0) -> 0 | Q86: =iferror($P$55*Q23%,0) -> 0 | R86: =iferror($Q$55*R23%,0) -> 0
B87: Infant Powder | D87: =IFERROR(0 ,D24*$C$55) -> 0 | E87: =IFERROr(0,$D$55*E24) -> 0 | F87: =iferror($E$55*F24%,0) -> 0.9438 | G87: =iferror($F$55*G24%,0) -> 0 | H87: =iferror($G$55*H24%,0) -> 0 | I87: =iferror($H$55*I24%,0) -> 0 | J87: =iferror($I$55*J24%,0) -> 0 | K87: =iferror($J$55*K24%,0) -> 0 | L87: =iferror($K$55*L24%,0) -> 0 | M87: =iferror($L$55*M24%,0) -> 0 | N87: =iferror($M$55*N24%,0) -> 0 | O87: =iferror($N$55*O24%,0) -> 0 | P87: =iferror($O$55*P24%,0) -> 0 | Q87: =iferror($P$55*Q24%,0) -> 0 | R87: =iferror($Q$55*R24%,0) -> 0
B88: Children Powder | D88: =IFERROR(0 ,D25*$C$55) -> 0 | E88: =IFERROr(0,$D$55*E25) -> 0 | F88: =iferror($E$55*F25%,0) -> 0.8268 | G88: =iferror($F$55*G25%,0) -> 0 | H88: =iferror($G$55*H25%,0) -> 0 | I88: =iferror($H$55*I25%,0) -> 0 | J88: =iferror($I$55*J25%,0) -> 0 | K88: =iferror($J$55*K25%,0) -> 0 | L88: =iferror($K$55*L25%,0) -> 0 | M88: =iferror($L$55*M25%,0) -> 0 | N88: =iferror($M$55*N25%,0) -> 0 | O88: =iferror($N$55*O25%,0) -> 0 | P88: =iferror($O$55*P25%,0) -> 0 | Q88: =iferror($P$55*Q25%,0) -> 0 | R88: =iferror($Q$55*R25%,0) -> 0
B89: G&A / Operations Overheads | D89: =IFERROR(0 ,D26*$C$55) -> 0 | E89: =IFERROr(0,$D$55*E26) -> 0 | F89: =iferror($E$55*F26%,0) -> 2.65239 | G89: =iferror($F$55*G26%,0) -> 0 | H89: =iferror($G$55*H26%,0) -> 0 | I89: =iferror($H$55*I26%,0) -> 0 | J89: =iferror($I$55*J26%,0) -> 0 | K89: =iferror($J$55*K26%,0) -> 0 | L89: =iferror($K$55*L26%,0) -> 0 | M89: =iferror($L$55*M26%,0) -> 0 | N89: =iferror($M$55*N26%,0) -> 0 | O89: =iferror($N$55*O26%,0) -> 0 | P89: =iferror($O$55*P26%,0) -> 0 | Q89: =iferror($P$55*Q26%,0) -> 0 | R89: =iferror($Q$55*R26%,0) -> 0
B90: Pregnancy Powder | D90: =IFERROR(0 ,D27*$C$55) -> 0 | E90: =IFERROr(0,$D$55*E27) -> 0 | F90: =iferror($E$55*F27%,0) -> 0.6552 | G90: =iferror($F$55*G27%,0) -> 0 | H90: =iferror($G$55*H27%,0) -> 0 | I90: =iferror($H$55*I27%,0) -> 0 | J90: =iferror($I$55*J27%,0) -> 0 | K90: =iferror($J$55*K27%,0) -> 0 | L90: =iferror($K$55*L27%,0) -> 0 | M90: =iferror($L$55*M27%,0) -> 0 | N90: =iferror($M$55*N27%,0) -> 0 | O90: =iferror($N$55*O27%,0) -> 0 | P90: =iferror($O$55*P27%,0) -> 0 | Q90: =iferror($P$55*Q27%,0) -> 0 | R90: =iferror($Q$55*R27%,0) -> 0
B91: Lactation Powder | D91: =IFERROR(0 ,D28*$C$55) -> 0 | E91: =IFERROr(0,$D$55*E28) -> 0 | F91: =iferror($E$55*F28%,0) -> 0.66924 | G91: =iferror($F$55*G28%,0) -> 0 | H91: =iferror($G$55*H28%,0) -> 0 | I91: =iferror($H$55*I28%,0) -> 0 | J91: =iferror($I$55*J28%,0) -> 0 | K91: =iferror($J$55*K28%,0) -> 0 | L91: =iferror($K$55*L28%,0) -> 0 | M91: =iferror($L$55*M28%,0) -> 0 | N91: =iferror($M$55*N28%,0) -> 0 | O91: =iferror($N$55*O28%,0) -> 0 | P91: =iferror($O$55*P28%,0) -> 0 | Q91: =iferror($P$55*Q28%,0) -> 0 | R91: =iferror($Q$55*R28%,0) -> 0
B92: Infant Powder | D92: =IFERROR(0 ,D29*$C$55) -> 0 | E92: =IFERROr(0,$D$55*E29) -> 0 | F92: =iferror($E$55*F29%,0) -> 0.70785 | G92: =iferror($F$55*G29%,0) -> 0 | H92: =iferror($G$55*H29%,0) -> 0 | I92: =iferror($H$55*I29%,0) -> 0 | J92: =iferror($I$55*J29%,0) -> 0 | K92: =iferror($J$55*K29%,0) -> 0 | L92: =iferror($K$55*L29%,0) -> 0 | M92: =iferror($L$55*M29%,0) -> 0 | N92: =iferror($M$55*N29%,0) -> 0 | O92: =iferror($N$55*O29%,0) -> 0 | P92: =iferror($O$55*P29%,0) -> 0 | Q92: =iferror($P$55*Q29%,0) -> 0 | R92: =iferror($Q$55*R29%,0) -> 0
B93: Children Powder | D93: =IFERROR(0 ,D30*$C$55) -> 0 | E93: =IFERROr(0,$D$55*E30) -> 0 | F93: =iferror($E$55*F30%,0) -> 0.6201 | G93: =iferror($F$55*G30%,0) -> 0 | H93: =iferror($G$55*H30%,0) -> 0 | I93: =iferror($H$55*I30%,0) -> 0 | J93: =iferror($I$55*J30%,0) -> 0 | K93: =iferror($J$55*K30%,0) -> 0 | L93: =iferror($K$55*L30%,0) -> 0 | M93: =iferror($L$55*M30%,0) -> 0 | N93: =iferror($M$55*N30%,0) -> 0 | O93: =iferror($N$55*O30%,0) -> 0 | P93: =iferror($O$55*P30%,0) -> 0 | Q93: =iferror($P$55*Q30%,0) -> 0 | R93: =iferror($Q$55*R30%,0) -> 0
B94: Employee Cost | C94: * QA/QC teams per plant, regulatory staff per brand, HCP field force are unavoidable. Costs higher in early years. | D94: =IFERROR(0 ,D31*$C$55) -> 0 | E94: =IFERROr(0,$D$55*E31) -> 0 | F94: =iferror($E$55*F31%,0) -> 5.30478 | G94: =iferror($F$55*G31%,0) -> 0 | H94: =iferror($G$55*H31%,0) -> 0 | I94: =iferror($H$55*I31%,0) -> 0 | J94: =iferror($I$55*J31%,0) -> 0 | K94: =iferror($J$55*K31%,0) -> 0 | L94: =iferror($K$55*L31%,0) -> 0 | M94: =iferror($L$55*M31%,0) -> 0 | N94: =iferror($M$55*N31%,0) -> 0 | O94: =iferror($N$55*O31%,0) -> 0 | P94: =iferror($O$55*P31%,0) -> 0 | Q94: =iferror($P$55*Q31%,0) -> 0 | R94: =iferror($Q$55*R31%,0) -> 0
B95: Pregnancy Powder | D95: =IFERROR(0 ,D32*$C$55) -> 0 | E95: =IFERROr(0,$D$55*E32) -> 0 | F95: =iferror($E$55*F32%,0) -> 1.3104 | G95: =iferror($F$55*G32%,0) -> 0 | H95: =iferror($G$55*H32%,0) -> 0 | I95: =iferror($H$55*I32%,0) -> 0 | J95: =iferror($I$55*J32%,0) -> 0 | K95: =iferror($J$55*K32%,0) -> 0 | L95: =iferror($K$55*L32%,0) -> 0 | M95: =iferror($L$55*M32%,0) -> 0 | N95: =iferror($M$55*N32%,0) -> 0 | O95: =iferror($N$55*O32%,0) -> 0 | P95: =iferror($O$55*P32%,0) -> 0 | Q95: =iferror($P$55*Q32%,0) -> 0 | R95: =iferror($Q$55*R32%,0) -> 0
B96: Lactation Powder | D96: =IFERROR(0 ,D33*$C$55) -> 0 | E96: =IFERROr(0,$D$55*E33) -> 0 | F96: =iferror($E$55*F33%,0) -> 1.33848 | G96: =iferror($F$55*G33%,0) -> 0 | H96: =iferror($G$55*H33%,0) -> 0 | I96: =iferror($H$55*I33%,0) -> 0 | J96: =iferror($I$55*J33%,0) -> 0 | K96: =iferror($J$55*K33%,0) -> 0 | L96: =iferror($K$55*L33%,0) -> 0 | M96: =iferror($L$55*M33%,0) -> 0 | N96: =iferror($M$55*N33%,0) -> 0 | O96: =iferror($N$55*O33%,0) -> 0 | P96: =iferror($O$55*P33%,0) -> 0 | Q96: =iferror($P$55*Q33%,0) -> 0 | R96: =iferror($Q$55*R33%,0) -> 0
B97: Infant Powder | D97: =IFERROR(0 ,D34*$C$55) -> 0 | E97: =IFERROr(0,$D$55*E34) -> 0 | F97: =iferror($E$55*F34%,0) -> 1.4157 | G97: =iferror($F$55*G34%,0) -> 0 | H97: =iferror($G$55*H34%,0) -> 0 | I97: =iferror($H$55*I34%,0) -> 0 | J97: =iferror($I$55*J34%,0) -> 0 | K97: =iferror($J$55*K34%,0) -> 0 | L97: =iferror($K$55*L34%,0) -> 0 | M97: =iferror($L$55*M34%,0) -> 0 | N97: =iferror($M$55*N34%,0) -> 0 | O97: =iferror($N$55*O34%,0) -> 0 | P97: =iferror($O$55*P34%,0) -> 0 | Q97: =iferror($P$55*Q34%,0) -> 0 | R97: =iferror($Q$55*R34%,0) -> 0
B98: Children Powder | D98: =IFERROR(0 ,D35*$C$55) -> 0 | E98: =IFERROr(0,$D$55*E35) -> 0 | F98: =iferror($E$55*F35%,0) -> 1.2402 | G98: =iferror($F$55*G35%,0) -> 0 | H98: =iferror($G$55*H35%,0) -> 0 | I98: =iferror($H$55*I35%,0) -> 0 | J98: =iferror($I$55*J35%,0) -> 0 | K98: =iferror($J$55*K35%,0) -> 0 | L98: =iferror($K$55*L35%,0) -> 0 | M98: =iferror($L$55*M35%,0) -> 0 | N98: =iferror($M$55*N35%,0) -> 0 | O98: =iferror($N$55*O35%,0) -> 0 | P98: =iferror($O$55*P35%,0) -> 0 | Q98: =iferror($P$55*Q35%,0) -> 0 | R98: =iferror($Q$55*R35%,0) -> 0
B99: Employee Cost | D99: =sum(D100:D103) -> 0 | E99: =sum(E100:E103) -> 0 | F99: =sum(F100:F103) -> 1.130493 | G99: =sum(G100:G103) -> 0.053543314 | H99: =sum(H100:H103) -> 0 | I99: =sum(I100:I103) -> 1.1241874 | J99: =sum(J100:J103) -> 0.16062994 | K99: =sum(K100:K103) -> 0.21661714 | ... R99: =sum(R100:R103) -> 9.7429577
B100: Pregnancy Powder | D100: =sum(D70,D75,D80,D85,D90,D95)*5% -> 0 | E100: =sum(E70,E75,E80,E85,E90,E95)*5% -> 0 | F100: =sum(F70,F75,F80,F85,F90,F95)*5% -> 0.27534 | G100: =sum(G70,G75,G80,G85,G90,G95)*5% -> 0.0124416 | H100: =sum(H70,H75,H80,H85,H90,H95)*5% -> 0 | I100: =sum(I70,I75,I80,I85,I90,I95)*5% -> 0.24927634 | J100: =sum(J70,J75,J80,J85,J90,J95)*5% -> 0.0373248 | K100: =sum(K70,K75,K80,K85,K90,K95)*5% -> 0.048655543 | ... R100: =sum(R70,R75,R80,R85,R90,R95)*5% -> 2.160395
B101: Lactation Powder | D101: =sum(D71,D76,D81,D86,D91,D96)*5% -> 0 | E101: =sum(E71,E76,E81,E86,E91,E96)*5% -> 0 | F101: =sum(F71,F76,F81,F86,F91,F96)*5% -> 0.280488 | G101: =sum(G71,G76,G81,G86,G91,G96)*5% -> 0.014441143 | H101: =sum(H71,H76,H81,H86,H91,H96)*5% -> 0 | I101: =sum(I71,I76,I81,I86,I91,I96)*5% -> 0.24483291 | J101: =sum(J71,J76,J81,J86,J91,J96)*5% -> 0.043323429 | K101: =sum(K71,K76,K81,K86,K91,K96)*5% -> 0.055320686 | ... R101: =sum(R71,R76,R81,R86,R91,R96)*5% -> 2.1218853
B102: Infant Powder | D102: =sum(D72,D77,D82,D87,D92,D97)*5% -> 0 | E102: =sum(E72,E77,E82,E87,E92,E97)*5% -> 0 | F102: =sum(F72,F77,F82,F87,F92,F97)*5% -> 0.30342 | G102: =sum(G72,G77,G82,G87,G92,G97)*5% -> 0.011108571 | H102: =sum(H72,H77,H82,H87,H92,H97)*5% -> 0 | I102: =sum(I72,I77,I82,I87,I92,I97)*5% -> 0.318816 | J102: =sum(J72,J77,J82,J87,J92,J97)*5% -> 0.033325714 | K102: =sum(K72,K77,K82,K87,K92,K97)*5% -> 0.051988114 | ... R102: =sum(R72,R77,R82,R87,R92,R97)*5% -> 2.763072
B103: Children Powder | D103: =sum(D73,D78,D83,D88,D93,D98)*5% -> 0 | E103: =sum(E73,E78,E83,E88,E93,E98)*5% -> 0 | F103: =sum(F73,F78,F83,F88,F93,F98)*5% -> 0.271245 | G103: =sum(G73,G78,G83,G88,G93,G98)*5% -> 0.015552 | H103: =sum(H73,H78,H83,H88,H93,H98)*5% -> 0 | I103: =sum(I73,I78,I83,I88,I93,I98)*5% -> 0.31126217 | J103: =sum(J73,J78,J83,J88,J93,J98)*5% -> 0.046656 | K103: =sum(K73,K78,K83,K88,K93,K98)*5% -> 0.0606528 | ... R103: =sum(R73,R78,R83,R88,R93,R98)*5% -> 2.6976055
B105: INDIRECT EXPENSE PER PRODUCT
B106: Products | C106: Year 1 | F106: Year 2 | I106: Year 3 | L106: Year 4 | O106: Year 5
...

Sheet Contract (1 yr)
B2: YEAR 1 FUNDING (in Cr) | C2: ='Total Production'!E4 -> 22
C4: Pregnancy Powder (Garbhika) | D4: Lactation Powder (Matrusneha) | E4: Infant Formula Milk Powder (Poshit) | F4: Child Nutrition Powder
B5: Cost/Box | C5: ='Total Production'!C9 -> 178.594 | D5: ='Total Production'!D9 -> 158.835 | E5: ='Total Production'!E9 -> 124.1836 | F5: ='Total Production'!F9 -> 121.88
B6: Selling Price/Box | C6: ='Total Production'!C20 -> 280 | D6: ='Total Production'!C21 -> 286 | E6: ='Total Production'!C22 -> 242 | F6: ='Total Production'!C23 -> 212
B7: Profit/Box | C7: =C6-C5 -> 101.406 | D7: =D6-D5 -> 127.165 | E7: =E6-E5 -> 117.8164 | F7: =F6-F5 -> 90.12
B9: Taking into consideration the following information:
B10: Tons Manufactured / Day | C10: 5 | D10: * 2 tons a day at Rohan Sir's Factory (Natal Care only). Assuming another factory will have 4 tons too
B11: Kgs Manufactured / Day | C11: =C10*1000 -> 5000
B12: Boxes Manufactured / Day | C12: =((C11*1000*0.5)/500)+((C11*1000*0.5)/400) -> 11250
B14: Natal Care Boxes/Day | C14: =(C11*1000*0.5)/500 -> 5000 | D14: * Natal Care Products are 500gms each
B15: Infant & Child Care Boxes/Day | C15: =(C11*1000*0.5)/400 -> 6250 | D15: * Infant and Child Care Products are 400gms each
B17: Working Days/Month | C17: 26
B18: Working Months/Year | C18: 12
B19: Working Days/Year | C19: =C17*C18 -> 312
B21: PRODUCTION
B22: Products | C22: Boxes/Year | D22: Revenue/Year | E22: Revenue (in Cr) | F22: COGS (in Cr) | G22: Gross Profit (in Cr)
B23: Infant Formula Milk | C23: =($C$19*$C$15)/2 -> 975000 | D23: =C23*E6 -> 235950000 | E23: =D23/10^7 -> 23.595 | F23: =(C23*E5)/10^7 -> 12.107901 | G23: =E23-F23 -> 11.487099
B24: Child Nutrition Powder | C24: =($C$19*$C$15)/2 -> 975000 | D24: =C24*F6 -> 206700000 | E24: =D24/10^7 -> 20.67 | F24: =(C24*F5)/10^7 -> 11.8833 | G24: =E24-F24 -> 8.7867
B25: Pregnancy Powder | C25: =($C$19*$C$14)/2 -> 780000 | D25: =C25*C6 -> 218400000 | E25: =D25/10^7 -> 21.84 | F25: =(C25*C5)/10^7 -> 13.930332 | G25: =E25-F25 -> 7.909668
B26: Lactation Powder | C26: =($C$19*$C$14)/2 -> 780000 | D26: =C26*D6 -> 223080000 | E26: =D26/10^7 -> 22.308 | F26: =(C26*D5)/10^7 -> 12.38913 | G26: =E26-F26 -> 9.91887
C27: =sum(C23:C26) -> 3510000 | E27: =sum(E23:E26) -> 88.413 | F27: =sum(F23:F26) -> 50.310663 | G27: =sum(G23:G26) -> 38.102337
B29: WORKING CAPITAL
B30: Working Capital (in Cr) | C30: ='WC (Year 1)'!D9/10^7 -> 21.598213
B31: Pregnancy Powder (in Cr) | C31: ='WC (Year 1)'!D5/10^7 -> 5.7940809
B32: Lactation Powder (in Cr) | C32: ='WC (Year 1)'!D6/10^7 -> 5.3445637 | D32: =D94
B33: Infant Formula Milk (in Cr) | C33: ='WC (Year 1)'!D7/10^7 -> 5.2625385 | D33: =D124
B34: Child Nutrition Powder (in Cr) | C34: ='WC (Year 1)'!D8/10^7 -> 5.1970299 | D34: =D154
B36: CONVERSION CHARGES
B37: Rohan Sir's Factory
B39: Conversion Charges/Day | C39: 35000
B41: Natal Care Boxes/Day | C41: =C14 -> 5000
B43: Conversion Charge/Box | C43: =C39/C41 -> 7
B45: Other Person's Factory
B47: Conversion Charges/Day | C47: =C39*2 -> 70000
B49: Infant & Child Care Boxes/Day | C49: =C15 -> 6250
B51: Conversion Charge/Box | C51: =C47/C49 -> 11.2
B53: APPLICATION & SOURCES OF FUND
B54: Sources of Fund | C54: =C57 -> 21.598213
B55: A. VNL | C55: =C54-C56 -> -0.401787
B56: B. Capital Raise | C56: =C2 -> 22
B57: Application of Fund | C57: =sum(C58:C59) -> 21.598213
B58: A. Production | C58: ='WC (Year 1)'!H9/10^7 -> 14.673943
B59: B. Indirect Expense | C59: ='WC (Year 1)'!I9/10^7 -> 6.9242696
B61: INDIRECT EXPENSE BREAKUP
B62: Expenses | D62: % of Revenue | E62: Total Expense
B63: Training & Community Engagement | D63: 0.01 | E63: =(D63*$E$27)*10^7 -> 8841300
B64: Monitoring & Evaluation | D64: 0.008 | E64: =(D64*$E$27)*10^7 -> 7073040
B65: Technology & Reporting | D65: 0.0065 | E65: =(D65*$E$27)*10^7 -> 5746845
B66: Administrative Cost | D66: 0.015 | E66: =(D66*$E$27)*10^7 -> 13261950
B67: Logistics & Distribution Cost | D67: Rs. 9/ Box | E67: =9*C27 -> 31590000
B68: Communication & Impact Documentation | D68: 0.0065035685 | E68: =(D68*$E$27)*10^7 -> 5750000
B69: Contingency | D69: 0.1 | E69: =sum(E63:E68)*D69 -> 7226313.5
D70: TOTAL (in ₹) | E70: =sum(E63:E69) -> 79489448
D71: TOTAL (₹ in Cr) | E71: =E70/10^7 -> 7.9489449

Sheet In-house (2-5yrs)
B2: Year | C2: New Plants Added | D2: Total Plants | E2: Working Capacity | F2: Gross Revenue (Rs. Cr) | G2: COGS | H2: Gross Profit
B3: 1 | C3: 0 | D3: =C3 -> 0 | E3: =D121 -> 0 | F3: =(($C11*$D$91)+($D$92*$D11)+($E11*$D$93)+($F11*$D$94)+($D$95*$G11)+($H11*$D$96)+($I11*$D$97)+($D$98*$J11)+($K11*$D$99)+($D$100*$L11)+($M11*$D$101)+($D$102*$N11))/10000000 -> #REF! | G3: =(($C11*$E$91)+($E$92*$D11)+($E11*$E$93)+($F11*$E$94)+($E$95*$G11)+($H11*$E$96)+($I11*$E$97)+($E$98*$J11)+($K11*$E$99)+($E$100*$L11)+($M11*$E$101)+($E$102*$N11))/10000000 -> 0 | H3: =F3-G3 -> #REF!
B4: 2 | C4: 1 | D4: =D3+C4 -> 1 | E4: =D125 -> 1.0285714 | F4: =(($C12*$D$91)+($D$92*$D12)+($E12*$D$93)+($F12*$D$94)+($D$95*$G12)+($H12*$D$96)+($I12*$D$97)+($D$98*$J12)+($K12*$D$99)+($D$100*$L12)+($M12*$D$101)+($D$102*$N12))/10000000 -> #REF! | G4: =(($C12*$E$91)+($E$92*$D12)+($E12*$E$93)+($F12*$E$94)+($E$95*$G12)+($H12*$E$96)+($I12*$E$97)+($E$98*$J12)+($K12*$E$99)+($E$100*$L12)+($M12*$E$101)+($E$102*$N12))/10000000 -> 0 | H4: =F4-G4 -> #REF!
B5: 3 | C5: 2 | D5: =D4+C5 -> 3 | E5: =D129 -> 1.0285714 | F5: =(($C13*$D$91)+($D$92*$D13)+($E13*$D$93)+($F13*$D$94)+($D$95*$G13)+($H13*$D$96)+($I13*$D$97)+($D$98*$J13)+($K13*$D$99)+($D$100*$L13)+($M13*$D$101)+($D$102*$N13))/10000000 -> #REF! | G5: =(($C13*$E$91)+($E$92*$D13)+($E13*$E$93)+($F13*$E$94)+($E$95*$G13)+($H13*$E$96)+($I13*$E$97)+($E$98*$J13)+($K13*$E$99)+($E$100*$L13)+($M13*$E$101)+($E$102*$N13))/10000000 -> 0 | H5: =F5-G5 -> #REF!
B6: 4 | C6: 3 | D6: =D5+C6 -> 6 | E6: =D133 -> 1.0714286 | F6: =(($C14*$D$91)+($D$92*$D14)+($E14*$D$93)+($F14*$D$94)+($D$95*$G14)+($H14*$D$96)+($I14*$D$97)+($D$98*$J14)+($K14*$D$99)+($D$100*$L14)+($M14*$D$101)+($D$102*$N14))/10000000 -> #REF! | G6: =(($C14*$E$91)+($E$92*$D14)+($E14*$E$93)+($F14*$E$94)+($E$95*$G14)+($H14*$E$96)+($I14*$E$97)+($E$98*$J14)+($K14*$E$99)+($E$100*$L14)+($M14*$E$101)+($E$102*$N14))/10000000 -> 0 | H6: =F6-G6 -> #REF!
B7: 5 | C7: 3 | D7: =D6+C7 -> 9 | E7: =D137 -> 1.1142857 | F7: =(($C15*$D$91)+($D$92*$D15)+($E15*$D$93)+($F15*$D$94)+($D$95*$G15)+($H15*$D$96)+($I15*$D$97)+($D$98*$J15)+($K15*$D$99)+($D$100*$L15)+($M15*$D$101)+($D$102*$N15))/10000000 -> #REF! | G7: =(($C15*$E$91)+($E$92*$D15)+($E15*$E$93)+($F15*$E$94)+($E$95*$G15)+($H15*$E$96)+($I15*$E$97)+($E$98*$J15)+($K15*$E$99)+($E$100*$L15)+($M15*$E$101)+($E$102*$N15))/10000000 -> 0 | H7: =F7-G7 -> #REF!
B9: BOXES MANUFACTURED
B10: Year | C10: Total PP - Tier 1 | D10: Total PP - Tier 2 | E10: Total PP - Tier 3 | F10: Total LP - Tier 1 | G10: Total LP - Tier 2 | H10: Total LP - Tier 3 | I10: Total IFP - Tier 1 | J10: Total IFP - Tier 2 | K10: Total IFP - Tier 3 | L10: Total CP - Tier 1 | M10: Total CP - Tier 2 | N10: Total CP - Tier 3
B11: 1 | C11: =sum(E121:E124) -> 0 | D11: =sum(F121:F124) -> 0 | E11: =sum(G121:G124) -> 0 | F11: =sum(H121:H124) -> 0 | G11: =sum(I121:I124) -> 0 | H11: =sum(J121:J124) -> 0 | I11: =sum(K121:K124) -> 0 | J11: =sum(L121:L124) -> 0 | ... N11: =sum(P121:P124) -> 0
B12: 2 | C12: =sum(E125:E128) -> 276480 | D12: =sum(F125:F128) -> 0 | E12: =sum(G125:G128) -> 5539474.3 | F12: =sum(H125:H128) -> 320914.29 | G12: =sum(I125:I128) -> 0 | H12: =sum(J125:J128) -> 5440731.4 | I12: =sum(K125:K128) -> 246857.14 | J12: =sum(L125:L128) -> 0 | ... N12: =sum(P125:P128) -> 6916937.1
B13: 3 | C13: =sum(E129:E132) -> 829440 | D13: =sum(F129:F132) -> 1081234.3 | E13: =sum(G129:G132) -> 16618423 | F13: =sum(H129:H132) -> 962742.86 | G13: =sum(I129:I132) -> 1229348.6 | H13: =sum(J129:J132) -> 16322194 | I13: =sum(K129:K132) -> 740571.43 | J13: =sum(L129:L132) -> 1155291.4 | ... N13: =sum(P129:P132) -> 20750811
B14: 4 | C14: =sum(E133:E136) -> 1728000 | D14: =sum(F133:F136) -> 2252571.4 | E14: =sum(G133:G136) -> 34621714 | F14: =sum(H133:H136) -> 2005714.3 | G14: =sum(I133:I136) -> 2561142.9 | H14: =sum(J133:J136) -> 34004571 | I14: =sum(K133:K136) -> 1542857.1 | J14: =sum(L133:L136) -> 2406857.1 | ... N14: =sum(P133:P136) -> 43230857
B15: 5 | C15: =sum(E137:E140) -> 2695680 | D15: =sum(F137:F140) -> 3514011.4 | E15: =sum(G137:G140) -> 54009874 | F15: =sum(H137:H140) -> 3128914.3 | G15: =sum(I137:I140) -> 3995382.9 | H15: =sum(J137:J140) -> 53047131 | I15: =sum(K137:K140) -> 2406857.1 | J15: =sum(L137:L140) -> 3754697.1 | ... N15: =sum(P137:P140) -> 67440137
B17: REVENUE TABLE
B18: Year | C18: Total PP - Tier 1 | D18: Total PP - Tier 2 | E18: Total PP - Tier 3 | F18: Total LP - Tier 1 | G18: Total LP - Tier 2 | H18: Total LP - Tier 3 | I18: Total IFP - Tier 1 | J18: Total IFP - Tier 2 | K18: Total IFP - Tier 3 | L18: Total CP - Tier 1 | M18: Total CP - Tier 2 | N18: Total CP - Tier 3
B19: 1 | C19: =C11*$D$91 -> #REF! | D19: =D11*$D$92 -> 0 | E19: =$D$93*E11 -> 0 | F19: =F11*$D$94 -> 0 | G19: =G11*$D$95 -> 0 | H19: =H11*$D$96 -> 0 | I19: =I11*$D$97 -> #REF! | J19: =J11*$D$98 -> 0 | K19: =K11*$D$99 -> 0 | L19: =L11*$D$100 -> 0 | M19: =M11*$D$101 -> 0 | N19: =N11*$D$102 -> 0
B20: 2 | C20: =C12*$D$91 -> #REF! | D20: =D12*$D$92 -> 0 | E20: =$D$93*E12 -> 0 | F20: =F12*$D$94 -> 0 | G20: =G12*$D$95 -> 0 | H20: =H12*$D$96 -> 0 | I20: =I12*$D$97 -> #REF! | J20: =J12*$D$98 -> 0 | K20: =K12*$D$99 -> 0 | L20: =L12*$D$100 -> 0 | M20: =M12*$D$101 -> 0 | N20: =N12*$D$102 -> 0
B21: 3 | C21: =C13*$D$91 -> #REF! | D21: =D13*$D$92 -> 0 | E21: =$D$93*E13 -> 0 | F21: =F13*$D$94 -> 0 | G21: =G13*$D$95 -> 0 | H21: =H13*$D$96 -> 0 | I21: =I13*$D$97 -> #REF! | J21: =J13*$D$98 -> 0 | K21: =K13*$D$99 -> 0 | L21: =L13*$D$100 -> 0 | M21: =M13*$D$101 -> 0 | N21: =N13*$D$102 -> 0
B22: 4 | C22: =C14*$D$91 -> #REF! | D22: =D14*$D$92 -> 0 | E22: =$D$93*E14 -> 0 | F22: =F14*$D$94 -> 0 | G22: =G14*$D$95 -> 0 | H22: =H14*$D$96 -> 0 | I22: =I14*$D$97 -> #REF! | J22: =J14*$D$98 -> 0 | K22: =K14*$D$99 -> 0 | L22: =L14*$D$100 -> 0 | M22: =M14*$D$101 -> 0 | N22: =N14*$D$102 -> 0
B23: 5 | C23: =C15*$D$91 -> #REF! | D23: =D15*$D$92 -> 0 | E23: =$D$93*E15 -> 0 | F23: =F15*$D$94 -> 0 | G23: =G15*$D$95 -> 0 | H23: =H15*$D$96 -> 0 | I23: =I15*$D$97 -> #REF! | J23: =J15*$D$98 -> 0 | K23: =K15*$D$99 -> 0 | L23: =L15*$D$100 -> 0 | M23: =M15*$D$101 -> 0 | N23: =N15*$D$102 -> 0
B25: Working Days/Month | C25: 25 | D25: * Taking the number of working months/day into consideration
B26: Working Months/Year | C26: 7
B27: Working Hours/Day | C27: 16
B28: Minutes/Year | C28: =C27*C26*C25 -> 2800
B30: Kgs/Day Manufactured | C30: 40000 | D30: * As per engineers' recommendations
B31: Natal Boxes/Day Manufactured | C31: =((C30*1000)/2)/500 -> 40000
B32: Infant Boxes/Day Manufactured | C32: =((C30*1000)/2)/400 -> 50000
B33: Natal Boxes/Hour Manufactured | C33: =C31/C27 -> 2500
B34: Infant Boxes/Hour Manufactured | C34: =C32/C27 -> 3125
B36: SAM of 3rd Year | C36: Tier 1 | D36: Tier 2 | E36: Tier 3
B37: Pregnancy Powder | C37: 0.0447 | D37: 0.058 | E37: 0.8973
B38: Lactation Powder | C38: 0.0518 | D38: 0.0667 | E38: 0.8815
B39: Infant Nutrition Powder | C39: 0.032 | D39: 0.05 | E39: 0.918
B40: Child Nutrition Powder | C40: 0.045 | D40: 0.058 | E40: 0.897
C42: Year 2 | D42: Year 3-5
B43: Pregnancy Powder- Tier 1 | C43: =Round($C$37*$D$46,0) -> 56 | D43: =Round($C$37*$D$46,0) -> 56
B44: Pregnancy Powder- Tier 2 | C44: 0 | D44: =Round($D$37*$D$46,0) -> 73
B45: Pregnancy Powder- Tier 3 | C45: =Round($E$37*$D$46,0) -> 1122 | D45: =Round($E$37*$D$46,0) -> 1122
B46: Total BPH for Pregnancy Powder | C46: =sum(C43:C45) -> 1178 | D46: =$C$33/2 -> 1250
B48: Lactation Powder- Tier 1 | C48: =Round($C$38*$D$51,0) -> 65 | D48: =Round($C$38*$D$51,0) -> 65
B49: Lactation Powder- Tier 2 | C49: 0 | D49: =Round($D$38*$D$51,0) -> 83
B50: Lactation Powder- Tier 3 | C50: =Round($E$38*$D$51,0) -> 1102 | D50: =Round($E$38*$D$51,0) -> 1102
B51: Total BPH for Lactation Powder | C51: =sum(C48:C50) -> 1167 | D51: =$C$33/2 -> 1250
B53: Infant Powder- Tier 1 | C53: =ROUND($D$56*$C$39,0) -> 50 | D53: =ROUND($D$56*$C$39,0) -> 50
B54: Infant Powder- Tier 2 | C54: 0 | D54: =ROUND($D$56*$D$39,0) -> 78
B55: Infant Powder- Tier 3 | C55: =ROUND($D$56*$E$39,0) -> 1435 | D55: =ROUND($D$56*$E$39,0) -> 1435
B56: Total BPH for Infant Powder | C56: =sum(C53:C55) -> 1485 | D56: =Round($C$34/2,0) -> 1563
B58: Children Powder- Tier 1 | C58: =Round($D$61*$C$40,0) -> 70 | D58: =Round($D$61*$C$40,0) -> 70
B59: Children Powder- Tier 2 | C59: 0 | D59: =Round($D$61*$D$40,0) -> 91
B60: Children Powder- Tier 3 | C60: =Round($D$61*$E$40,0) -> 1401 | D60: =Round($D$61*$E$40,0) -> 1401
B61: Total BPH for Children Powder | C61: =sum(C58:C60) -> 1471 | D61: =$C$34-D56 -> 1562
B63: Total BPH per Plant | C63: =C46+C51+C56+C61 -> 5301 | D63: =$C$34+C33 -> 5625
B65: Boxes/Year/Plant
C66: Year 1 | D66: Year 2 | E66: Year 3 | F66: Year 4 | G66: Year 5
B67: Boxes/Year (@ Working Capacity) | C67: =($C$28*$D$63*$E3) -> 0 | D67: =($C$28*$C$63*$E4) -> 15266880 | E67: =($C$28*$D$63*$E5) -> 16200000 | F67: =($C$28*$D$63*$E6) -> 16875000 | G67: =($C$28*$D$63*$E7) -> 17550000
B69: Total Pregnancy Powder Boxes | C69: =SUM(C70:C72) -> 0 | D69: =SUM(D70:D72) -> 3392640 | E69: =SUM(E70:E72) -> 3602880 | F69: =SUM(F70:F72) -> 3753000 | G69: =SUM(G70:G72) -> 3903120
B70: Total PP (Tier 1) | C70: =($C$28*$D43*$E$3) -> 0 | D70: =($C$28*$C43*$E$4) -> 161280 | E70: =($C$28*$D43*$E$5) -> 161280 | F70: =($C$28*$D43*$E$6) -> 168000 | G70: =($C$28*$D43*$E$7) -> 174720
B71: Total PP (Tier 2) | C71: =($C$28*$D44*$E$3) -> 0 | D71: =($C$28*$C44*$E$4) -> 0 | E71: =($C$28*$D44*$E$5) -> 210240 | F71: =($C$28*$D44*$E$6) -> 219000 | G71: =($C$28*$D44*$E$7) -> 227760
B72: Total PP (Tier 3) | C72: =($C$28*$D45*$E$3) -> 0 | D72: =($C$28*$C45*$E$4) -> 3231360 | E72: =($C$28*$D45*$E$5) -> 3231360 | F72: =($C$28*$D45*$E$6) -> 3366000 | G72: =($C$28*$D45*$E$7) -> 3500640
B74: Total Lactation Powder Boxes | C74: =SUM(C75:C77) -> 0 | D74: =SUM(D75:D77) -> 3360960 | E74: =SUM(E75:E77) -> 3600000 | F74: =SUM(F75:F77) -> 3750000 | G74: =SUM(G75:G77) -> 3900000
B75: Total LP (Tier 1) | C75: =($C$28*$D48*$E$3) -> 0 | D75: =($C$28*$C48*$E$4) -> 187200 | E75: =($C$28*$D48*$E$5) -> 187200 | F75: =($C$28*$D48*$E$6) -> 195000 | G75: =($C$28*$D48*$E$7) -> 202800
B76: Total LP (Tier 2) | C76: =($C$28*$D49*$E$3) -> 0 | D76: =($C$28*$C49*$E$4) -> 0 | E76: =($C$28*$D49*$E$5) -> 239040 | F76: =($C$28*$D49*$E$6) -> 249000 | G76: =($C$28*$D49*$E$7) -> 258960
B77: Total LP (Tier 3) | C77: =($C$28*$D50*$E$3) -> 0 | D77: =($C$28*$C50*$E$4) -> 3173760 | E77: =($C$28*$D50*$E$5) -> 3173760 | F77: =($C$28*$D50*$E$6) -> 3306000 | G77: =($C$28*$D50*$E$7) -> 3438240
B79: Total Infant Powder Boxes | C79: =SUM(C80:C82) -> 0 | D79: =SUM(D80:D82) -> 4276800 | E79: =SUM(E80:E82) -> 4501440 | F79: =SUM(F80:F82) -> 4689000 | G79: =SUM(G80:G82) -> 4876560
B80: Total IFP (Tier 1) | C80: =($C$28*$D53*$E$3) -> 0 | D80: =($C$28*$C53*$E$4) -> 144000 | E80: =($C$28*$D53*$E$5) -> 144000 | F80: =($C$28*$D53*$E$6) -> 150000 | G80: =($C$28*$D53*$E$7) -> 156000
B81: Total IFP (Tier 2) | C81: =($C$28*$D54*$E$3) -> 0 | D81: =($C$28*$C54*$E$4) -> 0 | E81: =($C$28*$D54*$E$5) -> 224640 | F81: =($C$28*$D54*$E$6) -> 234000 | G81: =($C$28*$D54*$E$7) -> 243360
B82: Total IFP (Tier 3) | C82: =($C$28*$D55*$E$3) -> 0 | D82: =($C$28*$C55*$E$4) -> 4132800 | E82: =($C$28*$D55*$E$5) -> 4132800 | F82: =($C$28*$D55*$E$6) -> 4305000 | G82: =($C$28*$D55*$E$7) -> 4477200
B84: Total Child Powder Boxes | C84: =SUM(C85:C87) -> 0 | D84: =SUM(D85:D87) -> 4236480 | E84: =SUM(E85:E87) -> 4498560 | F84: =SUM(F85:F87) -> 4686000 | G84: =SUM(G85:G87) -> 4873440
B85: Total CP (Tier 1) | C85: =($C$28*$D58*$E$3) -> 0 | D85: =($C$28*$C58*$E$4) -> 201600 | E85: =($C$28*$D58*$E$5) -> 201600 | F85: =($C$28*$D58*$E$6) -> 210000 | G85: =($C$28*$D58*$E$7) -> 218400
B86: Total CP (Tier 2) | C86: =($C$28*$D59*$E$3) -> 0 | D86: =($C$28*$C59*$E$4) -> 0 | E86: =($C$28*$D59*$E$5) -> 262080 | F86: =($C$28*$D59*$E$6) -> 273000 | G86: =($C$28*$D59*$E$7) -> 283920
B87: Total CP (Tier 3) | C87: =($C$28*$D60*$E$3) -> 0 | D87: =($C$28*$C60*$E$4) -> 4034880 | E87: =($C$28*$D60*$E$5) -> 4034880 | F87: =($C$28*$D60*$E$6) -> 4203000 | G87: =($C$28*$D60*$E$7) -> 4371120
B89: Exclusive of GST
B90: Products | C90: MRP | D90: Sale Price/Box | E90: Cost/Box | F90: Profit/Box
B91: Pregnancy Powder- Tier 1 (18%) | C91: 1120 | D91: =IFERROR(__xludf.DUMMYFUNCTION("importrange(""https://docs.google.com/spreadsheets/d/1DXOBRjKEc9pOcmohKWx0l59g3hrSjk2ZicxFB9zphD4/edit?gid=1653862983#gid=1653862983"",""In-house Manufacturing!D85:E90"")"),"#REF!") -> #REF! | F91: =D91-E91 -> #REF!
B92: Pregnancy Powder- Tier 2 (18%) | C92: 750 | F92: =D92-E92 -> 0
B93: Pregnancy Powder- Tier 3 (18%) | C93: 500 | F93: =D93-E93 -> 0
B94: Lactation Powder- Tier 1 (18%) | C94: 1300 | F94: =D94-E94 -> 0
B95: Lactation Powder- Tier 2 (18%) | C95: 800 | F95: =D95-E95 -> 0
B96: Lactation Powder- Tier 3 (18%) | C96: 650 | F96: =D96-E96 -> 0
B97: Infant Powder- Tier 1 (18%) | C97: 1200 | D97: =IFERROR(__xludf.DUMMYFUNCTION("importrange(""https://docs.google.com/spreadsheets/d/1bEcp3VCHzQgxan8VY9FCqLk1Yk8qAjekoqv5jLH-RCM/edit?gid=1653862983#gid=1653862983"",""In-house Manufacturing!D101:E106"")"),"#REF!") -> #REF! | F97: =D97-E97 -> #REF!
B98: Infant Powder- Tier 2 (18%) | C98: 800 | F98: =D98-E98 -> 0
B99: Infant Powder- Tier 3 (18%) | C99: 550 | F99: =D99-E99 -> 0
B100: Children Powder- Tier 1 (18%) | C100: 1050 | F100: =D100-E100 -> 0
B101: Children Powder- Tier 2 (18%) | C101: 700 | F101: =D101-E101 -> 0
B102: Children Powder- Tier 3 (18%) | C102: 480 | F102: =D102-E102 -> 0
B104: Working Capacity Calculations for Boxes (Quarterly)
B105: Months | C105: Year 1 | E105: Year 2 | G105: Year 3 | I105: Year 4 | K105: Year 5
C106: Capacity/Month | D106: Capacity/Quarter | E106: Capacity/Month | F106: Capacity/Quarter | G106: Capacity/Month | H106: Capacity/Quarter | I106: Capacity/Month | J106: Capacity/Quarter | K106: Capacity/Month | L106: Capacity/Quarter
B107: April to June | C107: 0.8 | D107: =C107*3 -> 2.4 | E107: 0.8 | F107: =E107*3 -> 2.4 | G107: 1 | H107: =G107*3 -> 3 | I107: 1 | J107: =I107*3 -> 3 | K107: 1 | L107: =K107*3 -> 3
B108: January to March | C108: 0.8 | D108: =C108*3 -> 2.4 | E108: 0.8 | F108: =E108*3 -> 2.4 | G108: 1 | H108: =G108*3 -> 3 | I108: 1 | J108: =I108*3 -> 3 | K108: 1 | L108: =K108*3 -> 3
B109: July to September | C109: 0.8 | D109: =C109*3 -> 2.4 | E109: 0.8 | F109: =E109*3 -> 2.4 | G109: 1 | H109: =G109*3 -> 3 | I109: 1 | J109: =I109*3 -> 3 | K109: 1 | L109: =K109*3 -> 3
B110: October to December | C110: 0.8 | D110: =C110*3 -> 2.4 | E110: 0.8 | F110: =E110*3 -> 2.4 | G110: 1 | H110: =G110*3 -> 3 | I110: 1 | J110: =I110*3 -> 3 | K110: 1 | L110: =K110*3 -> 3
B111: Average Working Capacity % | D111: =SUM(D107:D110)/C26 -> 1.3714286 | F111: =SUM(F107:F110)/C26 -> 1.3714286 | H111: =SUM(H107:H110)/C26 -> 1.7142857 | J111: =SUM(J107:J110)/C26 -> 1.7142857 | L111: =SUM(L107:L110)/C26 -> 1.7142857
B113: Capacity Breakup for Boxes
C114: Year 1 Capacity | D114: Year 2 Capacity | E114: Year 3 Capacity | F114: Year 4 Capacity | G114: Year 5 Capacity
B115: Our brand manufacturing | C115: =D111*75% -> 1.0285714 | D115: =F111*75% -> 1.0285714 | E115: =H111*75% -> 1.2857143 | F115: =J111*75% -> 1.2857143 | G115: =L111*75% -> 1.2857143
B116: Contract manufacturing | C116: =D111-C115 -> 0.34285714 | D116: =F111-D115 -> 0.34285714 | E116: =H111-E115 -> 0.42857143 | F116: =J111-F115 -> 0.42857143 | G116: =L111-G115 -> 0.42857143
B119: Quaterly Revenue Table | E119: *Multiplying by 3 considering no. of months
B120: Years | C120: Months | D120: Working Capacity (Monthly) | E120: Total PP - Tier 1 | F120: Total PP - Tier 2 | G120: Total PP - Tier 3 | H120: Total LP - Tier 1 | I120: Total LP - Tier 2 | J120: Total LP - Tier 3 | K120: Total IFP - Tier 1 | L120: Total IFP - Tier 2 | M120: Total IFP - Tier 3 | N120: Total CP - Tier 1 | O120: Total CP - Tier 2 | P120: Total CP - Tier 3 | Q120: Gross Revenue
B121: 1 | C121: April to June | D121: =IFERROR(0,($C$115*$C$3)/$D$3) -> 0 | E121: =(($C$25*$C$27)*$D$43*3*D121*$D$3) -> 0 | F121: =(($C$25*$C$27)*$D$44*3*D121*$D$3) -> 0 | G121: =(($C$25*$C$27)*$D$45*3*$D121*$D$3) -> 0 | H121: =(($C$25*$C$27)*$D$48*3*$D121*$D$3) -> 0 | I121: =(($C$25*$C$27)*$D$49*3*$D121*$D$3) -> 0 | J121: =(($C$25*$C$27)*$D$50*3*$D121*$D$3) -> 0 | K121: =(($C$25*$C$27)*$D$53*3*$D121*$D$3) -> 0 | L121: =(($C$25*$C$27)*$D$54*3*$D121*$D$3) -> 0 | M121: =(($C$25*$C$27)*$D$55*3*$D121*$D$3) -> 0 | N121: =(($C$25*$C$27)*$D$58*3*$D121*$D$3) -> 0 | O121: =(($C$25*$C$27)*$D$59*3*$D121*$D$3) -> 0 | P121: =(($C$25*$C$27)*$D$60*3*$D121*$D$3) -> 0 | Q121: =(E121*$D$91)+(F121*$D$92)+($D$93*G121)+(H121*$D$94)+(I121*$D$95)+(J121*$D$96)+(K121*$D$97)+($D$98*L121)+(M121*$D$99)+($D$100*N121)+(O121*$D$101)+($D$102*P121) -> #REF!
...

Sheet Third Party (2-5yrs)
B2: Year | C2: New Plants Added | D2: Total Plants | E2: Working Capacity | F2: Total PP - Tier 1 | G2: Total PP - Tier 2 | H2: Total PP - Tier 3 | I2: Total LP - Tier 1 | J2: Total LP - Tier 2 | K2: Total LP - Tier 3 | L2: Total IFP - Tier 1 | M2: Total IFP - Tier 2 | N2: Total IFP - Tier 3 | O2: Total CP - Tier 1 | P2: Total CP - Tier 2 | Q2: Total CP - Tier 3 | R2: Gross Revenue (Rs. in Cr)
B3: 1 | C3: ='In-house (2-5yrs)'!C3 -> 0 | D3: =C3 -> 0 | E3: =IFERROR(((C3*C87)/D3),0) -> 0 | F3: =D3*$C$42 -> 0 | G3: =$C$43*D3 -> 0 | H3: =$C$44*D3 -> 0 | I3: =D3*$C$47 -> 0 | J3: =D3*$C$48 -> 0 | K3: =D3*$C$49 -> 0 | L3: =E3*$C$52 -> 0 | M3: =D3*$C$53 -> 0 | N3: =$D3*$C$54 -> 0 | O3: =$D3*$C$57 -> 0 | P3: =$D3*$C$58 -> 0 | Q3: =$D3*$C$59 -> 0 | R3: =((F3*$C$63)+(G3*$C$64)+($C$65*H3)+($C$66*I3)+(J3*$C$67)+($C$68*K3))/10000000 -> #REF!
B4: 2 | C4: ='In-house (2-5yrs)'!C4 -> 1 | D4: =D3+C4 -> 1 | E4: =IFERROR((((C4*D87)+(C3*C87))/D4),0) -> 0.34285714 | F4: =D4*D42 -> 53760 | G4: =D43*D4 -> 0 | H4: =D44*D4 -> 1077120 | I4: =D4*D47 -> 62400 | J4: =D4*D48 -> 0 | K4: =D4*$D$49 -> 1057920 | L4: =E4*$D$52 -> 16457.143 | M4: =D4*$D$53 -> 0 | N4: =D4*$D$54 -> 1377600 | O4: =$D4*$D$57 -> 67200 | P4: =$D4*$D$58 -> 0 | Q4: =$D4*$D$59 -> 1344960 | R4: =((F4*$C$63)+(G4*$C$64)+($C$65*H4)+($C$66*I4)+(J4*$C$67)+($C$68*K4)+($C$69*L4)+(M4*$C$70)+($C$71*N4)+(O4*$C$72)+($C$73*P4)+(Q4*$C$74))/10000000 -> #REF!
B5: 3 | C5: ='In-house (2-5yrs)'!C5 -> 2 | D5: =D4+C5 -> 3 | E5: =IFERROR(((C5*C87)+(D87*C4)+(C3*E87))/D5,0) -> 0.34285714 | F5: =D5*E42 -> 161280 | G5: =D5*E43 -> 210240 | H5: =E44*D5 -> 3231360 | I5: =D5*E47 -> 187200 | J5: =D5*E48 -> 239040 | K5: =D5*$E$49 -> 3173760 | L5: =E5*$E$52 -> 16457.143 | M5: =D5*$E$53 -> 224640 | N5: =D5*$E$54 -> 4132800 | O5: =$D5*$E$57 -> 201600 | P5: =$D5*$E$58 -> 262080 | Q5: =$D5*$E$59 -> 4034880 | R5: =((F5*$C$63)+(G5*$C$64)+($C$65*H5)+($C$66*I5)+(J5*$C$67)+($C$68*K5)+($C$69*L5)+(M5*$C$70)+($C$71*N5)+(O5*$C$72)+($C$73*P5)+(Q5*$C$74))/10000000 -> #REF!
B6: 4 | C6: ='In-house (2-5yrs)'!C6 -> 3 | D6: =D5+C6 -> 6 | E6: =iferror(((C6*C87)+(C5*D87)+(C4*E87)+(C3*F87))/D6,0) -> 0.35714286 | F6: =D6*F42 -> 336000 | G6: =F43*D6 -> 438000 | H6: =F44*D6 -> 6732000 | I6: =D6*F47 -> 390000 | J6: =D6*F48 -> 498000 | K6: =D6*$F$49 -> 6612000 | L6: =E6*$F$52 -> 17857.143 | M6: =D6*$F$53 -> 468000 | N6: =D6*$F$54 -> 8610000 | O6: =$D6*$F$57 -> 420000 | P6: =$D6*$F$58 -> 546000 | Q6: =$D6*$F$59 -> 8406000 | R6: =((F6*$C$63)+(G6*$C$64)+($C$65*H6)+($C$66*I6)+(J6*$C$67)+($C$68*K6)+($C$69*L6)+(M6*$C$70)+($C$71*N6)+(O6*$C$72)+($C$73*P6)+(Q6*$C$74))/10000000 -> #REF!
B7: 5 | C7: ='In-house (2-5yrs)'!C7 -> 3 | D7: =D6+C7 -> 9 | E7: =iferror(((C7*C87)+(C6*D87)+(C5*E87)+(C4*F87)+(G87*C3))/D7,0) -> 0.37142857 | F7: =D7*G42 -> 524160 | G7: =G43*D7 -> 683280 | H7: =G44*D7 -> 10501920 | I7: =D7*G47 -> 608400 | J7: =D7*G48 -> 776880 | K7: =D7*$G$49 -> 10314720 | L7: =E7*$G$52 -> 19314.286 | M7: =D7*$G$53 -> 730080 | N7: =D7*$G$54 -> 13431600 | O7: =$D7*$G$57 -> 655200 | P7: =$D7*$G$58 -> 851760 | Q7: =$D7*$G$59 -> 13113360 | R7: =((F7*$C$63)+(G7*$C$64)+($C$65*H7)+($C$66*I7)+(J7*$C$67)+($C$68*K7)+($C$69*L7)+(M7*$C$70)+($C$71*N7)+(O7*$C$72)+($C$73*P7)+(Q7*$C$74))/10000000 -> #REF!
B9: Working Days/Month | C9: ='In-house (2-5yrs)'!C25 -> 25
B10: Working Months/Year | C10: ='In-house (2-5yrs)'!C26 -> 7
B11: Working Hours/Day | C11: ='In-house (2-5yrs)'!C27 -> 16
B12: Minutes/Year | C12: =C11*C10*C9 -> 2800
C14: Year 2 | D14: Year 3-5
B15: Pregnancy Powder- Tier 1 | C15: ='In-house (2-5yrs)'!C43 -> 56 | D15: ='In-house (2-5yrs)'!D43 -> 56
B16: Pregnancy Powder- Tier 2 | C16: ='In-house (2-5yrs)'!C44 -> 0 | D16: ='In-house (2-5yrs)'!D44 -> 73
B17: Pregnancy Powder- Tier 3 | C17: ='In-house (2-5yrs)'!C45 -> 1122 | D17: ='In-house (2-5yrs)'!D45 -> 1122
B18: Total BPH for Pregnancy Powder | C18: ='In-house (2-5yrs)'!C46 -> 1178 | D18: ='In-house (2-5yrs)'!D46 -> 1250
C19: ='In-house (2-5yrs)'!C47 | D19: ='In-house (2-5yrs)'!D47
B20: Lactation Powder- Tier 1 | C20: ='In-house (2-5yrs)'!C48 -> 65 | D20: ='In-house (2-5yrs)'!D48 -> 65
B21: Lactation Powder- Tier 2 | C21: ='In-house (2-5yrs)'!C49 -> 0 | D21: ='In-house (2-5yrs)'!D49 -> 83
B22: Lactation Powder- Tier 3 | C22: ='In-house (2-5yrs)'!C50 -> 1102 | D22: ='In-house (2-5yrs)'!D50 -> 1102
B23: Total BPH for Lactation Powder | C23: ='In-house (2-5yrs)'!C51 -> 1167 | D23: ='In-house (2-5yrs)'!D51 -> 1250
B25: Infant Powder- Tier 1 | C25: ='In-house (2-5yrs)'!C53 -> 50 | D25: ='In-house (2-5yrs)'!D53 -> 50
B26: Infant Powder- Tier 2 | C26: ='In-house (2-5yrs)'!C54 -> 0 | D26: ='In-house (2-5yrs)'!D54 -> 78
B27: Infant Powder- Tier 3 | C27: ='In-house (2-5yrs)'!C55 -> 1435 | D27: ='In-house (2-5yrs)'!D55 -> 1435
B28: Total BPH for Infant Powder | C28: ='In-house (2-5yrs)'!C56 -> 1485 | D28: ='In-house (2-5yrs)'!D56 -> 1563
B30: Children Powder- Tier 1 | C30: ='In-house (2-5yrs)'!C58 -> 70 | D30: ='In-house (2-5yrs)'!D58 -> 70
B31: Children Powder- Tier 2 | C31: ='In-house (2-5yrs)'!C59 -> 0 | D31: ='In-house (2-5yrs)'!D59 -> 91
B32: Children Powder- Tier 3 | C32: ='In-house (2-5yrs)'!C60 -> 1401 | D32: ='In-house (2-5yrs)'!D60 -> 1401
B33: Total BPH for Children Powder | C33: ='In-house (2-5yrs)'!C61 -> 1471 | D33: ='In-house (2-5yrs)'!D61 -> 1562
B35: Total BPH per Plant | C35: =sum(C18,C23,C28,C33) -> 5301 | D35: =sum(D18,D23,D28,D33) -> 5625
B37: Boxes/Year/Plant
C38: Year 1 | D38: Year 2 | E38: Year 3 | F38: Year 4 | G38: Year 5
B39: Boxes/Year (@ Working Capacity) | C39: =(C12*D35*E3) -> 0 | D39: =$D$35*$C$12*E4 -> 5400000 | E39: =$D$35*$C$12*E5 -> 5400000 | F39: =$D$35*$C$12*E6 -> 5625000 | G39: =$D$35*$C$12*E7 -> 5850000
B41: Total Pregnancy Powder Boxes | C41: =C42+C43+C44 -> 0 | D41: =D42+D43+D44 -> 1130880 | E41: =E42+E43+E44 -> 1200960 | F41: =F42+F43+F44 -> 1251000 | G41: =G42+G43+G44 -> 1301040
B42: Total PP (Tier 1) | C42: =($C$12*$D15*$E$3) -> 0 | D42: =($C$12*$C15*$E$4) -> 53760 | E42: =($C$12*$D15*$E$5) -> 53760 | F42: =($C$12*$D15*$E$6) -> 56000 | G42: =($C$12*$D15*$E$7) -> 58240
B43: Total PP (Tier 2) | C43: =($C$12*$D16*$E$3) -> 0 | D43: =($C$12*$C16*$E$4) -> 0 | E43: =($C$12*$D16*$E$5) -> 70080 | F43: =($C$12*$D16*$E$6) -> 73000 | G43: =($C$12*$D16*$E$7) -> 75920
B44: Total PP (Tier 3) | C44: =($C$12*$D17*$E$3) -> 0 | D44: =($C$12*$C17*$E$4) -> 1077120 | E44: =($C$12*$D17*$E$5) -> 1077120 | F44: =($C$12*$D17*$E$6) -> 1122000 | G44: =($C$12*$D17*$E$7) -> 1166880
B46: Total Lactation Powder Boxes | C46: =C47+C48+C49 -> 0 | D46: =D47+D48+D49 -> 1120320 | E46: =E47+E48+E49 -> 1200000 | F46: =F47+F48+F49 -> 1250000 | G46: =G47+G48+G49 -> 1300000
B47: Total LP (Tier 1) | C47: =($C$12*$D20*$E$3) -> 0 | D47: =($C$12*$C20*$E$4) -> 62400 | E47: =($C$12*$D20*$E$5) -> 62400 | F47: =($C$12*$D20*$E$6) -> 65000 | G47: =($C$12*$D20*$E$7) -> 67600
B48: Total LP (Tier 2) | C48: =($C$12*$D21*$E$3) -> 0 | D48: =($C$12*$C21*$E$4) -> 0 | E48: =($C$12*$D21*$E$5) -> 79680 | F48: =($C$12*$D21*$E$6) -> 83000 | G48: =($C$12*$D21*$E$7) -> 86320
B49: Total LP (Tier 3) | C49: =($C$12*$D22*$E$3) -> 0 | D49: =($C$12*$C22*$E$4) -> 1057920 | E49: =($C$12*$D22*$E$5) -> 1057920 | F49: =($C$12*$D22*$E$6) -> 1102000 | G49: =($C$12*$D22*$E$7) -> 1146080
B51: Total Infant Powder Boxes | C51: =SUM(C52:C54) -> 0 | D51: =SUM(D52:D54) -> 1425600 | E51: =SUM(E52:E54) -> 1500480 | F51: =SUM(F52:F54) -> 1563000 | G51: =SUM(G52:G54) -> 1625520
B52: Total IFP (Tier 1) | C52: =($C$12*$D25*$E$3) -> 0 | D52: =($C$12*$C25*$E$4) -> 48000 | E52: =($C$12*$D25*$E$5) -> 48000 | F52: =($C$12*$D25*$E$6) -> 50000 | G52: =($C$12*$D25*$E$7) -> 52000
B53: Total IFP (Tier 2) | C53: =($C$12*$D26*$E$3) -> 0 | D53: =($C$12*$C26*$E$4) -> 0 | E53: =($C$12*$D26*$E$5) -> 74880 | F53: =($C$12*$D26*$E$6) -> 78000 | G53: =($C$12*$D26*$E$7) -> 81120
B54: Total IFP (Tier 3) | C54: =($C$12*$D27*$E$3) -> 0 | D54: =($C$12*$C27*$E$4) -> 1377600 | E54: =($C$12*$D27*$E$5) -> 1377600 | F54: =($C$12*$D27*$E$6) -> 1435000 | G54: =($C$12*$D27*$E$7) -> 1492400
B56: Total Child Powder Boxes | C56: =SUM(C57:C59) -> 0 | D56: =SUM(D57:D59) -> 1412160 | E56: =SUM(E57:E59) -> 1499520 | F56: =SUM(F57:F59) -> 1562000 | G56: =SUM(G57:G59) -> 1624480
B57: Total CP (Tier 1) | C57: =($C$12*$D30*$E$3) -> 0 | D57: =($C$12*$C30*$E$4) -> 67200 | E57: =($C$12*$D30*$E$5) -> 67200 | F57: =($C$12*$D30*$E$6) -> 70000 | G57: =($C$12*$D30*$E$7) -> 72800
B58: Total CP (Tier 2) | C58: =($C$12*$D31*$E$3) -> 0 | D58: =($C$12*$C31*$E$4) -> 0 | E58: =($C$12*$D31*$E$5) -> 87360 | F58: =($C$12*$D31*$E$6) -> 91000 | G58: =($C$12*$D31*$E$7) -> 94640
B59: Total CP (Tier 3) | C59: =($C$12*$D32*$E$3) -> 0 | D59: =($C$12*$C32*$E$4) -> 1344960 | E59: =($C$12*$D32*$E$5) -> 1344960 | F59: =($C$12*$D32*$E$6) -> 1401000 | G59: =($C$12*$D32*$E$7) -> 1457040
B61: Exclusive of GST
B62: Products | C62: Sale Price/Box | D62: Cost/Box | E62: Profit/Box
B63: Pregnancy Powder- Tier 1 (18%) | C63: =IFERROR(__xludf.DUMMYFUNCTION("importrange(""https://docs.google.com/spreadsheets/d/1DXOBRjKEc9pOcmohKWx0l59g3hrSjk2ZicxFB9zphD4/edit?gid=1653862983#gid=1653862983"",""Third Party Manufacturing!C45:D50"")"),"#REF!") -> #REF! | E63: =C63-D63 -> #REF! | F63: * Our only cost is processing charges
B64: Pregnancy Powder- Tier 2 (18%) | E64: =C64-D64 -> 0
B65: Pregnancy Powder- Tier 3 (18%) | E65: =C65-D65 -> 0
B66: Lactation Powder- Tier 1 (18%) | E66: =C66-D66 -> 0
B67: Lactation Powder- Tier 2 (18%) | E67: =C67-D67 -> 0
B68: Lactation Powder- Tier 3 (18%) | E68: =C68-D68 -> 0
B69: Infant Powder- Tier 1 (18%) | C69: =IFERROR(__xludf.DUMMYFUNCTION("importrange(""https://docs.google.com/spreadsheets/d/1bEcp3VCHzQgxan8VY9FCqLk1Yk8qAjekoqv5jLH-RCM/edit?gid=1063770156#gid=1063770156"",""Third Party Manufacturing!C45:D50"")"),"#REF!") -> #REF! | E69: =C69-D69 -> #REF!
B70: Infant Powder- Tier 2 (18%) | E70: =C70-D70 -> 0
B71: Infant Powder- Tier 3 (18%) | E71: =C71-D71 -> 0
B72: Children Powder- Tier 1 (18%) | E72: =C72-D72 -> 0
B73: Children Powder- Tier 2 (18%) | E73: =C73-D73 -> 0
B74: Children Powder- Tier 3 (18%) | E74: =C74-D74 -> 0
B76: Working Capacity Calculations (Quarterly)
C77: Year 1 | E77: Year 2 | G77: Year 3 | I77: Year 4 | K77: Year 5
C78: Capacity/Month | D78: Capacity/Quarter | E78: Capacity/Month | F78: Capacity/Quarter | G78: Capacity/Month | H78: Capacity/Quarter | I78: Capacity/Month | J78: Capacity/Quarter | K78: Capacity/Month | L78: Capacity/Quarter
B79: April to June | C79: ='In-house (2-5yrs)'!C107 -> 0.8 | D79: ='In-house (2-5yrs)'!D107 -> 2.4 | E79: ='In-house (2-5yrs)'!E107 -> 0.8 | F79: ='In-house (2-5yrs)'!F107 -> 2.4 | G79: ='In-house (2-5yrs)'!G107 -> 1 | H79: ='In-house (2-5yrs)'!H107 -> 3 | I79: ='In-house (2-5yrs)'!I107 -> 1 | J79: ='In-house (2-5yrs)'!J107 -> 3 | ... L79: ='In-house (2-5yrs)'!L107 -> 3
B80: January to March | C80: ='In-house (2-5yrs)'!C108 -> 0.8 | D80: ='In-house (2-5yrs)'!D108 -> 2.4 | E80: ='In-house (2-5yrs)'!E108 -> 0.8 | F80: ='In-house (2-5yrs)'!F108 -> 2.4 | G80: ='In-house (2-5yrs)'!G108 -> 1 | H80: ='In-house (2-5yrs)'!H108 -> 3 | I80: ='In-house (2-5yrs)'!I108 -> 1 | J80: ='In-house (2-5yrs)'!J108 -> 3 | ... L80: ='In-house (2-5yrs)'!L108 -> 3
B81: July to September | C81: ='In-house (2-5yrs)'!C109 -> 0.8 | D81: ='In-house (2-5yrs)'!D109 -> 2.4 | E81: ='In-house (2-5yrs)'!E109 -> 0.8 | F81: ='In-house (2-5yrs)'!F109 -> 2.4 | G81: ='In-house (2-5yrs)'!G109 -> 1 | H81: ='In-house (2-5yrs)'!H109 -> 3 | I81: ='In-house (2-5yrs)'!I109 -> 1 | J81: ='In-house (2-5yrs)'!J109 -> 3 | ... L81: ='In-house (2-5yrs)'!L109 -> 3
B82: October to December | C82: ='In-house (2-5yrs)'!C110 -> 0.8 | D82: ='In-house (2-5yrs)'!D110 -> 2.4 | E82: ='In-house (2-5yrs)'!E110 -> 0.8 | F82: ='In-house (2-5yrs)'!F110 -> 2.4 | G82: ='In-house (2-5yrs)'!G110 -> 1 | H82: ='In-house (2-5yrs)'!H110 -> 3 | I82: ='In-house (2-5yrs)'!I110 -> 1 | J82: ='In-house (2-5yrs)'!J110 -> 3 | ... L82: ='In-house (2-5yrs)'!L110 -> 3
B83: Average Working Capacity % | D83: =SUM(D79:D82)/C10 -> 1.3714286 | F83: =SUM(F79:F82)/C10 -> 1.3714286 | H83: =SUM(H79:H82)/C10 -> 1.7142857 | J83: =SUM(J79:J82)/C10 -> 1.7142857 | L83: =SUM(L79:L82)/C10 -> 1.7142857
B85: Capacity Breakup for Boxes | C85: Year 1 Capacity | D85: Year 2 Capacity | E85: Year 3 Capacity | F85: Year 4 Capacity | G85: Year 5 Capacity
B86: Our brand manufacturing | C86: ='In-house (2-5yrs)'!C115 -> 1.0285714 | D86: ='In-house (2-5yrs)'!D115 -> 1.0285714 | E86: ='In-house (2-5yrs)'!E115 -> 1.2857143 | F86: ='In-house (2-5yrs)'!F115 -> 1.2857143 | G86: ='In-house (2-5yrs)'!G115 -> 1.2857143
B87: Contract manufacturing | C87: ='In-house (2-5yrs)'!C116 -> 0.34285714 | D87: ='In-house (2-5yrs)'!D116 -> 0.34285714 | E87: ='In-house (2-5yrs)'!E116 -> 0.42857143 | F87: ='In-house (2-5yrs)'!F116 -> 0.42857143 | G87: ='In-house (2-5yrs)'!G116 -> 0.42857143

Sheet IE Biffurcation
B2: Expense Head / Line Item | C2: Notes | D2: TIER 3 — VALUE (Small Towns / Mass) | I2: TIER 2 — MID (Mid Cities) | N2: TIER 1 — PREMIUM (Metro / Institutional)
D3: Year 1 | E3: Year 2 | F3: Year 3 | G3: Year 4 | H3: Year 5 | I3: Year 1 | J3: Year 2 | K3: Year 3 | L3: Year 4 | M3: Year 5 | N3: Year 1 | O3: Year 2 | P3: Year 3 | Q3: Year 4 | R3: Year 5
B4: A. MARKETING & ADVERTISING (% of tier net revenue)
B5: Consumer digital ads (Meta/Google/Programmatic) | C5: T3 high – volume push. T1 ZERO for infant formula (IMS Act) | D5: 0.03 | E5: 0.02 | F5: 0.01 | G5: 0.01 | H5: 0.01 | I5: - | J5: - | K5: 0.02 | L5: 0.02 | M5: 0.01 | N5: - | O5: 0.01 | P5: - | Q5: 0.01 | R5: -
B6: Influencer & KOL marketing | C6: Mommy bloggers, nutritionists | D6: 0.01 | E6: - | F6: 0.01 | G6: 0.01 | H6: 0.01 | I6: - | J6: - | K6: 0.01 | L6: 0.01 | M6: 0.01 | N6: - | O6: - | P6: - | Q6: 0.01 | R6: -
B7: Sampling & trial programs | C7: Higher in Y1-Y2 for trial generation | D7: 0.01 | E7: - | F7: 0.01 | G7: - | H7: - | I7: - | J7: - | K7: 0.01 | L7: - | M7: - | N7: - | O7: - | P7: 0.01 | Q7: - | R7: -
B8: Trade marketing (shelf / pharmacy / MT visibility) | C8: Grows as offline scale builds | D8: 0.01 | E8: 0.01 | F8: 0.01 | G8: 0.01 | H8: 0.01 | I8: - | J8: - | K8: 0.01 | L8: 0.01 | M8: 0.01 | N8: - | O8: 0.01 | P8: 0.01 | Q8: 0.01 | R8: 0.01
B9: Brand identity & design (per tier brand) | C9: T1 higher – premium packaging investment | D9: 0.01 | E9: 0.01 | F9: 0.01 | G9: - | H9: - | I9: - | J9: - | K9: 0.01 | L9: - | M9: - | N9: - | O9: 0.02 | P9: - | Q9: 0.01 | R9: -
B10: Events, baby expos, hospital tie-ups | D10: - | E10: - | F10: 0.01 | G10: - | H10: - | I10: - | J10: - | K10: - | L10: - | M10: - | N10: - | O10: - | P10: 0.01 | Q10: - | R10: -
B11: Loyalty & referral programs | C11: Grows with repeat purchase base | D11: - | E11: - | F11: 0.01 | G11: 0.01 | H11: 0.01 | I11: - | J11: - | K11: 0.01 | L11: 0.01 | M11: 0.01 | N11: - | O11: - | P11: 0.01 | Q11: 0.01 | R11: 0.01
B12: PR & communications | D12: - | E12: - | F12: 0.01 | G12: 0.01 | H12: 0.01 | I12: - | J12: - | K12: - | L12: 0.01 | M12: 0.01 | N12: - | O12: 0.01 | P12: 0.01 | Q12: 0.01 | R12: 0.01
B13: TOTAL Marketing & Advertising | C13: Target: Lean digital + HCP-led growth. | D13: =sum(D5:D12) -> 0.07 | E13: =sum(E5:E12) -> 0.04 | F13: =sum(F5:F12) -> 0.08 | G13: =sum(G5:G12) -> 0.05 | H13: =sum(H5:H12) -> 0.05 | I13: =sum(I5:I12) -> 0 | J13: =sum(J5:J12) -> 0 | K13: =sum(K5:K12) -> 0.07 | ... R13: =sum(R5:R12) -> 0.03
B14: B. HCP DETAILING & MEDICAL ENGAGEMENT (critical for maternal+infant category)
B15: OBGYN / gynecologist detailing | C15: T1 highest – drives Tier 1 infant formula prescriptions | D15: 0.01 | E15: 0.01 | F15: 0.01 | G15: 0.01 | H15: 0.01 | I15: - | J15: - | K15: 0.01 | L15: 0.01 | M15: 0.01 | N15: - | O15: 0.01 | P15: 0.01 | Q15: 0.01 | R15: 0.02
B16: Pediatrician detailing | C16: IMS Act: mandatory for infant formula growth | D16: 0.01 | E16: 0.01 | F16: 0.01 | G16: 0.01 | H16: 0.01 | I16: - | J16: - | K16: 0.01 | L16: 0.01 | M16: 0.01 | N16: - | O16: 0.01 | P16: 0.01 | Q16: 0.01 | R16: 0.01
B17: Hospital & nursing home tie-ups | C17: Formulary listing in private hospitals – T1 focus | D17: - | E17: - | F17: - | G17: 0.01 | H17: 0.01 | I17: - | J17: - | K17: 0.01 | L17: 0.01 | M17: 0.01 | N17: - | O17: 0.01 | P17: 0.01 | Q17: 0.01 | R17: 0.01
B18: Lactation consultant & dietitian programs | D18: - | E18: - | F18: - | G18: 0.01 | H18: 0.01 | I18: - | J18: - | K18: - | L18: 0.01 | M18: 0.01 | N18: - | O18: - | P18: 0.01 | Q18: 0.01 | R18: 0.01
B19: CME / medical conference sponsorships | D19: - | E19: - | F19: - | G19: - | H19: - | I19: - | J19: - | K19: - | L19: - | M19: 0.01 | N19: - | O19: - | P19: 0.01 | Q19: 0.01 | R19: 0.01
B20: TOTAL HCP Detailing | C20: Benchmark: Infant formula has ZERO consumer advertising — budget shifts to HCP detailing | D20: =sum(D15:D19) -> 0.02 | E20: =sum(E15:E19) -> 0.02 | F20: =sum(F15:F19) -> 0.02 | G20: =sum(G15:G19) -> 0.04 | H20: =sum(H15:H19) -> 0.04 | I20: =sum(I15:I19) -> 0 | J20: =sum(J15:J19) -> 0 | K20: =sum(K15:K19) -> 0.03 | ... R20: =sum(R15:R19) -> 0.06
B21: C. R&D / REGULATORY / COMPLIANCE (% of tier net revenue)
B22: Flavour & variant development | C22: Each new flavour triggers fresh lab trials | D22: 0.01 | E22: 0.01 | F22: 0.01 | G22: - | H22: - | I22: - | J22: - | K22: 0.01 | L22: - | M22: - | N22: - | O22: 0.01 | P22: 0.01 | Q22: - | R22: -
B23: Clinical & nutritional testing (per formulation) | C23: Trimester & stage-specific = multiply by variant count | D23: 0.01 | E23: 0.01 | F23: 0.01 | G23: 0.01 | H23: 0.01 | I23: - | J23: - | K23: 0.01 | L23: 0.01 | M23: 0.01 | N23: - | O23: 0.01 | P23: - | Q23: 0.01 | R23: -
B24: FSSAI dossier prep & label approval (per SKU) | C24: Infant formula = strictest FSSAI category | D24: 0.01 | E24: 0.01 | F24: 0.01 | G24: 0.01 | H24: 0.01 | I24: - | J24: - | K24: 0.01 | L24: 0.01 | M24: 0.01 | N24: - | O24: 0.01 | P24: - | Q24: 0.01 | R24: -
B25: IMS Act compliance monitoring | C25: IMS Act: ongoing monitoring for infant formula labeling/ads | D25: - | E25: - | F25: 0.01 | G25: 0.01 | H25: 0.01 | I25: - | J25: - | K25: - | L25: 0.01 | M25: 0.01 | N25: - | O25: - | P25: 0.01 | Q25: 0.01 | R25: 0.01
B26: Stability & shelf-life studies | D26: 0.01 | E26: 0.01 | F26: - | G26: - | H26: - | I26: - | J26: - | K26: - | L26: - | M26: - | N26: - | O26: 0.01 | P26: - | Q26: - | R26: -
B27: TOTAL R&D / Regulatory / Compliance | C27: Target: 3-5% across all years. FSSAI & IMS Act key drivers. | D27: 0.04 | E27: 0.04 | F27: 0.04 | G27: 0.03 | H27: 0.03 | I27: - | J27: - | K27: 0.03 | L27: 0.03 | M27: 0.03 | N27: - | O27: 0.04 | P27: 0.02 | Q27: 0.03 | R27: 0.01
B28: D. G&A / OPERATIONS OVERHEADS (% of tier net revenue)
B29: Rent & utilities (office + warehouse) | C29: T1 metro higher rent base | D29: 0.01 | E29: 0.01 | F29: 0.01 | G29: 0.01 | H29: 0.01 | I29: - | J29: - | K29: 0.01 | L29: 0.01 | M29: 0.01 | N29: - | O29: 0.01 | P29: 0.01 | Q29: 0.01 | R29: 0.01
B30: IT infrastructure, ERP & CRM | D30: 0.01 | E30: 0.01 | F30: 0.01 | G30: 0.01 | H30: 0.01 | I30: - | J30: - | K30: 0.01 | L30: 0.01 | M30: 0.01 | N30: - | O30: 0.01 | P30: 0.01 | Q30: 0.01 | R30: 0.01
B31: Legal, audit & insurance | D31: 0.01 | E31: 0.01 | F31: 0.01 | G31: 0.01 | H31: 0.01 | I31: - | J31: - | K31: 0.01 | L31: 0.01 | M31: 0.01 | N31: - | O31: 0.01 | P31: 0.01 | Q31: 0.01 | R31: 0.01
B32: Office supplies & misc admin | D32: - | E32: - | F32: - | G32: - | H32: - | I32: - | J32: - | K32: - | L32: - | M32: - | N32: - | O32: - | P32: - | Q32: - | R32: -
B33: TOTAL G&A / Overheads | C33: Target: 3% lean ops. Scales with headcount. | D33: 0.03 | E33: 0.03 | F33: 0.03 | G33: 0.03 | H33: 0.03 | I33: - | J33: - | K33: 0.03 | L33: 0.03 | M33: 0.03 | N33: - | O33: 0.03 | P33: 0.03 | Q33: 0.03 | R33: 0.03
B34: E. HUMAN RESOURCES (% of tier net revenue)
B35: Core team salaries | C35: Fixed cost – high as % when revenue small | D35: 0.04 | E35: 0.03 | F35: 0.03 | G35: 0.03 | H35: 0.03 | I35: - | J35: - | K35: 0.03 | L35: 0.03 | M35: 0.03 | N35: - | O35: 0.05 | P35: 0.04 | Q35: 0.03 | R35: 0.03
B36: PF / ESI / statutory (13% of salaries) | D36: 0.01 | E36: 0.01 | F36: 0.01 | G36: - | H36: - | I36: - | J36: - | K36: 0.01 | L36: - | M36: - | N36: - | O36: 0.01 | P36: 0.01 | Q36: - | R36: -
B37: QA/QC plant staff (Own plant from Y2) | C37: Per plant headcount fixed cost | D37: - | E37: 0.01 | F37: 0.01 | G37: 0.01 | H37: 0.01 | I37: - | J37: - | K37: 0.01 | L37: 0.01 | M37: 0.01 | N37: - | O37: 0.01 | P37: - | Q37: 0.01 | R37: -
B38: HCP field force (detailing reps) | C38: T1 highest field force – hospital + clinic coverage | D38: - | E38: - | F38: 0.01 | G38: 0.01 | H38: 0.01 | I38: - | J38: - | K38: 0.01 | L38: 0.01 | M38: 0.01 | N38: - | O38: 0.01 | P38: 0.01 | Q38: 0.01 | R38: 0.01
B39: Recruitment, training & contract staff | D39: 0.01 | E39: 0.01 | F39: - | G39: - | H39: - | I39: - | J39: - | K39: - | L39: - | M39: - | N39: - | O39: 0.01 | P39: - | Q39: - | R39: -
B40: TOTAL Human Resources | C40: Target: 6-8% Y1-Y2 lean team; 6-8% Y3+ as % reduces with revenue scale. | D40: 0.06 | E40: 0.06 | F40: 0.06 | G40: 0.05 | H40: 0.05 | I40: - | J40: - | K40: 0.06 | L40: 0.05 | M40: 0.05 | N40: - | O40: 0.09 | P40: 0.06 | Q40: 0.05 | R40: 0.04

Sheet WC (Year 1)
B2: TOTAL WORKING CAPITAL | G2: APPLICATION OF FUNDS
C4: Revenue | D4: Initial Working Capital | E4: W.C.Rotation | H4: Production | I4: Indirect Expense
B5: PP | C5: =D35 -> 218400000 | D5: =D36 -> 57940809 | E5: =C5/D5 -> 3.769364 | G5: PP | H5: =(D13*D14)*3.5 -> 40630135 | I5: =D16*3.5 -> 17310674
B6: LP | C6: =D64 -> 223080000 | D6: =D65 -> 53445637 | E6: =C6/D6 -> 4.173961 | G6: LP | H6: =(D42*D43)*3.5 -> 36134962 | I6: =D45*3.5 -> 17310674
B7: IFP | C7: =D93 -> 235950000 | D7: =D94 -> 52625385 | E7: =C7/D7 -> 4.4835776 | G7: IFP | H7: =(D71*D72)*3.5 -> 35314711 | I7: =D74*3.5 -> 17310674
B8: CNP | C8: =D122 -> 206700000 | D8: =D123 -> 51970299 | E8: =C8/D8 -> 3.9772717 | G8: CNP | H8: =(D100*D101)*3.5 -> 34659625 | I8: =D103*3.5 -> 17310674
D9: =sum(D5:D8) -> 215982130 | H9: =sum(H5:H8) -> 1.4673943e+08 | I9: =sum(I5:I8) -> 69242696
H10: =H9+I9 -> 215982130
B11: PREGNANCY POWDER
B13: Monthly Boxes Produced (in Units) | D13: ='Contract (1 yr)'!C25/12 -> 65000
B14: Cost/Box (in ₹) | D14: ='Total Production'!C9 -> 178.594
B15: Revenue/Box (in ₹) | D15: ='Total Production'!C20 -> 280
B16: Monthly Indirect Expense (in ₹) | D16: =(('Indirect Expenses'!E63/12)/4)*10^7 -> 4945906.9
G17: * The working capital that we are investing in the first month is derived from the cash outflow that is required in the first month
B18: Month | C18: Cash Outflow | D18: Cash Inflow | E18: Difference (CO-CI) | G18: Opening W.C. | H18: Net Cash Flow | I18: Closing W.C.
B19: April | C19: =($D$13*$D$14)+$D$16 -> 16554517 | D19: =$D$13*$D$15 -> 18200000 | E19: =D19-C19 -> 1645483.1 | G19: =C19+D33 -> 57940809 | H19: =E19 -> 1645483.1 | I19: =G19+H19 -> 59586292
B20: May | C20: =($D$13*$D$14)+$D$16 -> 16554517 | D20: =$D$13*$D$15 -> 18200000 | E20: =D20-C20 -> 1645483.1 | G20: =I19 -> 59586292 | H20: =E20 -> 1645483.1 | I20: =G20+H20 -> 61231775
B21: June | C21: =($D$13*$D$14)+$D$16 -> 16554517 | D21: =$D$13*$D$15 -> 18200000 | E21: =D21-C21 -> 1645483.1 | G21: =I20 -> 61231775 | H21: =E21 -> 1645483.1 | I21: =G21+H21 -> 62877258
B22: July | C22: =($D$13*$D$14)+$D$16 -> 16554517 | D22: =$D$13*$D$15 -> 18200000 | E22: =D22-C22 -> 1645483.1 | G22: =I21 -> 62877258 | H22: =E22 -> 1645483.1 | I22: =G22+H22 -> 64522742
B23: August | C23: =($D$13*$D$14)+$D$16 -> 16554517 | D23: =$D$13*$D$15 -> 18200000 | E23: =D23-C23 -> 1645483.1 | G23: =I22 -> 64522742 | H23: =E23 -> 1645483.1 | I23: =G23+H23 -> 66168225
B24: September | C24: =($D$13*$D$14)+$D$16 -> 16554517 | D24: =$D$13*$D$15 -> 18200000 | E24: =D24-C24 -> 1645483.1 | G24: =I23 -> 66168225 | H24: =E24 -> 1645483.1 | I24: =G24+H24 -> 67813708
B25: October | C25: =($D$13*$D$14)+$D$16 -> 16554517 | D25: =$D$13*$D$15 -> 18200000 | E25: =D25-C25 -> 1645483.1 | G25: =I24 -> 67813708 | H25: =E25 -> 1645483.1 | I25: =G25+H25 -> 69459191
B26: November | C26: =($D$13*$D$14)+$D$16 -> 16554517 | D26: =$D$13*$D$15 -> 18200000 | E26: =D26-C26 -> 1645483.1 | G26: =I25 -> 69459191 | H26: =E26 -> 1645483.1 | I26: =G26+H26 -> 71104674
B27: December | C27: =($D$13*$D$14)+$D$16 -> 16554517 | D27: =$D$13*$D$15 -> 18200000 | E27: =D27-C27 -> 1645483.1 | G27: =I26 -> 71104674 | H27: =E27 -> 1645483.1 | I27: =G27+H27 -> 72750157
B28: January | C28: =($D$13*$D$14)+$D$16 -> 16554517 | D28: =$D$13*$D$15 -> 18200000 | E28: =D28-C28 -> 1645483.1 | G28: =I27 -> 72750157 | H28: =E28 -> 1645483.1 | I28: =G28+H28 -> 74395640
B29: February | C29: =($D$13*$D$14)+$D$16 -> 16554517 | D29: =$D$13*$D$15 -> 18200000 | E29: =D29-C29 -> 1645483.1 | G29: =I28 -> 74395640 | H29: =E29 -> 1645483.1 | I29: =G29+H29 -> 76041123
B30: March | C30: =($D$13*$D$14)+$D$16 -> 16554517 | D30: =$D$13*$D$15 -> 18200000 | E30: =D30-C30 -> 1645483.1 | G30: =I29 -> 76041123 | H30: =E30 -> 1645483.1 | I30: =G30+H30 -> 77686607
C31: =SUM(C19:C30) -> 1.986542e+08 | D31: =SUM(D19:D30) -> 218400000 | E31: =D31-C31 -> 19745798
B33: Buffer Capital (Production Cost of 2.5 Months) | D33: =C19*2.5 -> 41386292
B35: Total Yearly Turnover | D35: =D31 -> 218400000
B36: Initial Working Capital | D36: =C19+D33 -> 57940809 | E36: * Working Capital Required=Cash outflow for the first month + Contingency fund
B37: Working Capital Rotation | D37: =D35/D36 -> 3.769364
B40: LACTATION POWDER
B42: Monthly Boxes Produced (in Units) | D42: ='Contract (1 yr)'!C26/12 -> 65000
B43: Cost/Box (in ₹) | D43: ='Total Production'!D9 -> 158.835
B44: Revenue/Box (in ₹) | D44: ='Total Production'!C21 -> 286
B45: Monthly Indirect Expense (in ₹) | D45: =D16 -> 4945906.9
G46: * The working capital that we are investing in the first month is derived from the cash outflow that is required in the first month
B47: Month | C47: Cash Outflow | D47: Cash Inflow | E47: Difference (CO-CI) | G47: Opening W.C. | H47: Net Cash Flow | I47: Closing W.C.
B48: April | C48: =($D$42*$D$43)+$D$45 -> 15270182 | D48: =$D$42*$D$44 -> 18590000 | E48: =D48-C48 -> 3319818.1 | G48: =C48+D62 -> 53445637 | H48: =E48 -> 3319818.1 | I48: =G48+H48 -> 56765455
B49: May | C49: =($D$42*$D$43)+$D$45 -> 15270182 | D49: =$D$42*$D$44 -> 18590000 | E49: =D49-C49 -> 3319818.1 | G49: =I48 -> 56765455 | H49: =E49 -> 3319818.1 | I49: =G49+H49 -> 60085273
B50: June | C50: =($D$42*$D$43)+$D$45 -> 15270182 | D50: =$D$42*$D$44 -> 18590000 | E50: =D50-C50 -> 3319818.1 | G50: =I49 -> 60085273 | H50: =E50 -> 3319818.1 | I50: =G50+H50 -> 63405091
B51: July | C51: =($D$42*$D$43)+$D$45 -> 15270182 | D51: =$D$42*$D$44 -> 18590000 | E51: =D51-C51 -> 3319818.1 | G51: =I50 -> 63405091 | H51: =E51 -> 3319818.1 | I51: =G51+H51 -> 66724909
B52: August | C52: =($D$42*$D$43)+$D$45 -> 15270182 | D52: =$D$42*$D$44 -> 18590000 | E52: =D52-C52 -> 3319818.1 | G52: =I51 -> 66724909 | H52: =E52 -> 3319818.1 | I52: =G52+H52 -> 70044727
B53: September | C53: =($D$42*$D$43)+$D$45 -> 15270182 | D53: =$D$42*$D$44 -> 18590000 | E53: =D53-C53 -> 3319818.1 | G53: =I52 -> 70044727 | H53: =E53 -> 3319818.1 | I53: =G53+H53 -> 73364545
B54: October | C54: =($D$42*$D$43)+$D$45 -> 15270182 | D54: =$D$42*$D$44 -> 18590000 | E54: =D54-C54 -> 3319818.1 | G54: =I53 -> 73364545 | H54: =E54 -> 3319818.1 | I54: =G54+H54 -> 76684363
B55: November | C55: =($D$42*$D$43)+$D$45 -> 15270182 | D55: =$D$42*$D$44 -> 18590000 | E55: =D55-C55 -> 3319818.1 | G55: =I54 -> 76684363 | H55: =E55 -> 3319818.1 | I55: =G55+H55 -> 80004182
B56: December | C56: =($D$42*$D$43)+$D$45 -> 15270182 | D56: =$D$42*$D$44 -> 18590000 | E56: =D56-C56 -> 3319818.1 | G56: =I55 -> 80004182 | H56: =E56 -> 3319818.1 | I56: =G56+H56 -> 83324000
B57: January | C57: =($D$42*$D$43)+$D$45 -> 15270182 | D57: =$D$42*$D$44 -> 18590000 | E57: =D57-C57 -> 3319818.1 | G57: =I56 -> 83324000 | H57: =E57 -> 3319818.1 | I57: =G57+H57 -> 86643818
B58: February | C58: =($D$42*$D$43)+$D$45 -> 15270182 | D58: =$D$42*$D$44 -> 18590000 | E58: =D58-C58 -> 3319818.1 | G58: =I57 -> 86643818 | H58: =E58 -> 3319818.1 | I58: =G58+H58 -> 89963636
B59: March | C59: =($D$42*$D$43)+$D$45 -> 15270182 | D59: =$D$42*$D$44 -> 18590000 | E59: =D59-C59 -> 3319818.1 | G59: =I58 -> 89963636 | H59: =E59 -> 3319818.1 | I59: =G59+H59 -> 93283454
C60: =SUM(C48:C59) -> 1.8324218e+08 | D60: =SUM(D48:D59) -> 223080000 | E60: =D60-C60 -> 39837818
B62: Buffer Capital (Production Cost of 2.5 Months) | D62: =C48*2.5 -> 38175455
B64: Total Yearly Turnover | D64: =D60 -> 223080000
B65: Initial Working Capital | D65: =C48+D62 -> 53445637 | E65: * Working Capital Required=Cash outflow for the first month + Contingency fund
B66: Working Capital Rotation | D66: =D64/D65 -> 4.173961
B69: INFANT POWDER
B71: Monthly Boxes Produced (in Units) | D71: ='Contract (1 yr)'!C23/12 -> 81250
B72: Cost/Box (in ₹) | D72: ='Total Production'!E9 -> 124.1836
B73: Revenue/Box (in ₹) | D73: ='Total Production'!C22 -> 242
B74: Monthly Indirect Expense (in ₹) | D74: =D45 -> 4945906.9
G75: * The working capital that we are investing in the first month is derived from the cash outflow that is required in the first month
B76: Month | C76: Cash Outflow | D76: Cash Inflow | E76: Difference (CO-CI) | G76: Opening W.C. | H76: Net Cash Flow | I76: Closing W.C.
B77: April | C77: =($D$71*$D$72)+$D$74 -> 15035824 | D77: =$D$71*$D$73 -> 19662500 | E77: =D77-C77 -> 4626675.6 | G77: =C77+D91 -> 52625385 | H77: =E77 -> 4626675.6 | I77: =G77+H77 -> 57252061
B78: May | C78: =($D$71*$D$72)+$D$74 -> 15035824 | D78: =$D$71*$D$73 -> 19662500 | E78: =D78-C78 -> 4626675.6 | G78: =I77 -> 57252061 | H78: =E78 -> 4626675.6 | I78: =G78+H78 -> 61878737
B79: June | C79: =($D$71*$D$72)+$D$74 -> 15035824 | D79: =$D$71*$D$73 -> 19662500 | E79: =D79-C79 -> 4626675.6 | G79: =I78 -> 61878737 | H79: =E79 -> 4626675.6 | I79: =G79+H79 -> 66505412
B80: July | C80: =($D$71*$D$72)+$D$74 -> 15035824 | D80: =$D$71*$D$73 -> 19662500 | E80: =D80-C80 -> 4626675.6 | G80: =I79 -> 66505412 | H80: =E80 -> 4626675.6 | I80: =G80+H80 -> 71132088
B81: August | C81: =($D$71*$D$72)+$D$74 -> 15035824 | D81: =$D$71*$D$73 -> 19662500 | E81: =D81-C81 -> 4626675.6 | G81: =I80 -> 71132088 | H81: =E81 -> 4626675.6 | I81: =G81+H81 -> 75758763
B82: September | C82: =($D$71*$D$72)+$D$74 -> 15035824 | D82: =$D$71*$D$73 -> 19662500 | E82: =D82-C82 -> 4626675.6 | G82: =I81 -> 75758763 | H82: =E82 -> 4626675.6 | I82: =G82+H82 -> 80385439
B83: October | C83: =($D$71*$D$72)+$D$74 -> 15035824 | D83: =$D$71*$D$73 -> 19662500 | E83: =D83-C83 -> 4626675.6 | G83: =I82 -> 80385439 | H83: =E83 -> 4626675.6 | I83: =G83+H83 -> 85012115
B84: November | C84: =($D$71*$D$72)+$D$74 -> 15035824 | D84: =$D$71*$D$73 -> 19662500 | E84: =D84-C84 -> 4626675.6 | G84: =I83 -> 85012115 | H84: =E84 -> 4626675.6 | I84: =G84+H84 -> 89638790
B85: December | C85: =($D$71*$D$72)+$D$74 -> 15035824 | D85: =$D$71*$D$73 -> 19662500 | E85: =D85-C85 -> 4626675.6 | G85: =I84 -> 89638790 | H85: =E85 -> 4626675.6 | I85: =G85+H85 -> 94265466
B86: January | C86: =($D$71*$D$72)+$D$74 -> 15035824 | D86: =$D$71*$D$73 -> 19662500 | E86: =D86-C86 -> 4626675.6 | G86: =I85 -> 94265466 | H86: =E86 -> 4626675.6 | I86: =G86+H86 -> 98892142
B87: February | C87: =($D$71*$D$72)+$D$74 -> 15035824 | D87: =$D$71*$D$73 -> 19662500 | E87: =D87-C87 -> 4626675.6 | G87: =I86 -> 98892142 | H87: =E87 -> 4626675.6 | I87: =G87+H87 -> 1.0351882e+08
B88: March | C88: =($D$71*$D$72)+$D$74 -> 15035824 | D88: =$D$71*$D$73 -> 19662500 | E88: =D88-C88 -> 4626675.6 | G88: =I87 -> 1.0351882e+08 | H88: =E88 -> 4626675.6 | I88: =G88+H88 -> 1.0814549e+08
C89: =SUM(C77:C88) -> 1.8042989e+08 | D89: =SUM(D77:D88) -> 235950000 | E89: =D89-C89 -> 55520108
B91: Buffer Capital (Production Cost of 2.5 Months) | D91: =C77*2.5 -> 37589561
B93: Total Yearly Turnover | D93: =D89 -> 235950000
B94: Initial Working Capital | D94: =C77+D91 -> 52625385 | E94: * Working Capital Required=Cash outflow for the first month + Contingency fund
B95: Working Capital Rotation | D95: =D93/D94 -> 4.4835776
B98: CHILDREN POWDER
B100: Monthly Boxes Produced (in Units) | D100: ='Contract (1 yr)'!C24/12 -> 81250
B101: Cost/Box (in ₹) | D101: ='Total Production'!F9 -> 121.88
B102: Revenue/Box (in ₹) | D102: ='Total Production'!C23 -> 212
B103: Monthly Indirect Expense (in ₹) | D103: =D74 -> 4945906.9
G104: * The working capital that we are investing in the first month is derived from the cash outflow that is required in the first month
B105: Month | C105: Cash Outflow | D105: Cash Inflow | E105: Difference (CO-CI) | G105: Opening W.C. | H105: Net Cash Flow | I105: Closing W.C.
B106: April | C106: =($D$100*$D$101)+$D$103 -> 14848657 | D106: =$D$100*$D$102 -> 17225000 | E106: =D106-C106 -> 2376343.1 | G106: =C106+D120 -> 51970299 | H106: =E106 -> 2376343.1 | I106: =G106+H106 -> 54346642
B107: May | C107: =($D$100*$D$101)+$D$103 -> 14848657 | D107: =$D$100*$D$102 -> 17225000 | E107: =D107-C107 -> 2376343.1 | G107: =I106 -> 54346642 | H107: =E107 -> 2376343.1 | I107: =G107+H107 -> 56722985
B108: June | C108: =($D$100*$D$101)+$D$103 -> 14848657 | D108: =$D$100*$D$102 -> 17225000 | E108: =D108-C108 -> 2376343.1 | G108: =I107 -> 56722985 | H108: =E108 -> 2376343.1 | I108: =G108+H108 -> 59099328
B109: July | C109: =($D$100*$D$101)+$D$103 -> 14848657 | D109: =$D$100*$D$102 -> 17225000 | E109: =D109-C109 -> 2376343.1 | G109: =I108 -> 59099328 | H109: =E109 -> 2376343.1 | I109: =G109+H109 -> 61475672
B110: August | C110: =($D$100*$D$101)+$D$103 -> 14848657 | D110: =$D$100*$D$102 -> 17225000 | E110: =D110-C110 -> 2376343.1 | G110: =I109 -> 61475672 | H110: =E110 -> 2376343.1 | I110: =G110+H110 -> 63852015
B111: September | C111: =($D$100*$D$101)+$D$103 -> 14848657 | D111: =$D$100*$D$102 -> 17225000 | E111: =D111-C111 -> 2376343.1 | G111: =I110 -> 63852015 | H111: =E111 -> 2376343.1 | I111: =G111+H111 -> 66228358
B112: October | C112: =($D$100*$D$101)+$D$103 -> 14848657 | D112: =$D$100*$D$102 -> 17225000 | E112: =D112-C112 -> 2376343.1 | G112: =I111 -> 66228358 | H112: =E112 -> 2376343.1 | I112: =G112+H112 -> 68604701
B113: November | C113: =($D$100*$D$101)+$D$103 -> 14848657 | D113: =$D$100*$D$102 -> 17225000 | E113: =D113-C113 -> 2376343.1 | G113: =I112 -> 68604701 | H113: =E113 -> 2376343.1 | I113: =G113+H113 -> 70981044
B114: December | C114: =($D$100*$D$101)+$D$103 -> 14848657 | D114: =$D$100*$D$102 -> 17225000 | E114: =D114-C114 -> 2376343.1 | G114: =I113 -> 70981044 | H114: =E114 -> 2376343.1 | I114: =G114+H114 -> 73357387
B115: January | C115: =($D$100*$D$101)+$D$103 -> 14848657 | D115: =$D$100*$D$102 -> 17225000 | E115: =D115-C115 -> 2376343.1 | G115: =I114 -> 73357387 | H115: =E115 -> 2376343.1 | I115: =G115+H115 -> 75733730
B116: February | C116: =($D$100*$D$101)+$D$103 -> 14848657 | D116: =$D$100*$D$102 -> 17225000 | E116: =D116-C116 -> 2376343.1 | G116: =I115 -> 75733730 | H116: =E116 -> 2376343.1 | I116: =G116+H116 -> 78110073
B117: March | C117: =($D$100*$D$101)+$D$103 -> 14848657 | D117: =$D$100*$D$102 -> 17225000 | E117: =D117-C117 -> 2376343.1 | G117: =I116 -> 78110073 | H117: =E117 -> 2376343.1 | I117: =G117+H117 -> 80486417
C118: =SUM(C106:C117) -> 1.7818388e+08 | D118: =SUM(D106:D117) -> 206700000 | E118: =D118-C118 -> 28516118
...

Sheet WC (Year 2)
B2: TOTAL WORKING CAPITAL
C4: Revenue | D4: Initial Working Capital | E4: W.C.Rotation
B5: PP (Tier 1) | C5: =D42 -> #REF! | D5: =D43 -> #REF! | E5: =C5/D5 -> #REF!
B6: PP (Tier 3) | C6: =D73 -> 0 | D6: =D74 -> 12910590 | E6: =C6/D6 -> 0
B7: LP (Tier 1) | C7: =D104 -> 0 | D7: =D105 -> #REF! | E7: =C7/D7 -> #REF!
B8: LP (Tier 3) | C8: =D135 -> 0 | D8: =D136 -> 12910590 | E8: =C8/D8 -> 0
B9: INP (Tier 1) | C9: =D166 -> #REF! | D9: =D167 -> #REF! | E9: =C9/D9 -> #REF!
B10: INP (Tier 3) | C10: =D197 -> 0 | D10: =D198 -> 12910590 | E10: =C10/D10 -> 0
B11: CNP (Tier 1) | C11: =D228 -> 0 | D11: =D229 -> #REF! | E11: =C11/D11 -> #REF!
B12: CNP (Tier 3) | C12: =D259 -> 0 | D12: =D260 -> 12910590 | E12: =C12/D12 -> 0
D13: =sum(D5:D12) -> #REF!
B15: PREGNANCY POWDER: TIER 1
B17: Monthly Inhouse Boxes Produced (in Units) | D17: ='In-house (2-5yrs)'!D70/12 -> 13440
B18: Monthly Contract Boxes Produced (in Units) | D18: ='Third Party (2-5yrs)'!D42/12 -> 4480
B19: Cost/Box for Inhouse Mfg (in ₹) | D19: ='In-house (2-5yrs)'!E91
B20: Cost/Box for Contractual Mfg (in ₹) | D20: ='Third Party (2-5yrs)'!D63
B21: Revenue/Box for Inhouse Mfg (in ₹) | D21: ='In-house (2-5yrs)'!D91 -> #REF!
B22: Revenue/Box for Contractual Mfg (in ₹) | D22: ='Third Party (2-5yrs)'!C63 -> #REF!
B23: Monthly Indirect Expense (in ₹) | D23: =((('Indirect Expenses'!$F$63/12)/4)*105%)*10^7 -> #REF!
G24: * The working capital that we are investing in the first month is derived from the cash outflow that is required in the first month
B25: Month | C25: Cash Outflow | D25: Cash Inflow | E25: Difference (CO-CI) | G25: Opening W.C. | H25: Net Cash Flow | I25: Closing W.C.
B26: April | C26: =(D$17*D$19)+($D$18*$D$20)+D$23 -> #REF! | D26: =($D$17*$D$21)+($D$18*$D$22) -> #REF! | E26: =D26-C26 -> #REF! | G26: =C26+D40 -> #REF! | H26: =E26 -> #REF! | I26: =G26+H26 -> #REF!
B27: May | C27: =(D$17*D$19)+($D$18*$D$20)+D$23 -> #REF! | D27: =($D$17*$D$21)+($D$18*$D$22) -> #REF! | E27: =D27-C27 -> #REF! | G27: =I26 -> #REF! | H27: =E27 -> #REF! | I27: =G27+H27 -> #REF!
B28: June | C28: =(D$17*D$19)+($D$18*$D$20)+D$23 -> #REF! | D28: =($D$17*$D$21)+($D$18*$D$22) -> #REF! | E28: =D28-C28 -> #REF! | G28: =I27 -> #REF! | H28: =E28 -> #REF! | I28: =G28+H28 -> #REF!
B29: July | C29: =(D$17*D$19)+($D$18*$D$20)+D$23 -> #REF! | D29: =($D$17*$D$21)+($D$18*$D$22) -> #REF! | E29: =D29-C29 -> #REF! | G29: =I28 -> #REF! | H29: =E29 -> #REF! | I29: =G29+H29 -> #REF!
B30: August | C30: =(D$17*D$19)+($D$18*$D$20)+D$23 -> #REF! | D30: =($D$17*$D$21)+($D$18*$D$22) -> #REF! | E30: =D30-C30 -> #REF! | G30: =I29 -> #REF! | H30: =E30 -> #REF! | I30: =G30+H30 -> #REF!
B31: September | C31: =(D$17*D$19)+($D$18*$D$20)+D$23 -> #REF! | D31: =($D$17*$D$21)+($D$18*$D$22) -> #REF! | E31: =D31-C31 -> #REF! | G31: =I30 -> #REF! | H31: =E31 -> #REF! | I31: =G31+H31 -> #REF!
B32: October | C32: =(D$17*D$19)+($D$18*$D$20)+D$23 -> #REF! | D32: =($D$17*$D$21)+($D$18*$D$22) -> #REF! | E32: =D32-C32 -> #REF! | G32: =I31 -> #REF! | H32: =E32 -> #REF! | I32: =G32+H32 -> #REF!
B33: November | C33: =(D$17*D$19)+($D$18*$D$20)+D$23 -> #REF! | D33: =($D$17*$D$21)+($D$18*$D$22) -> #REF! | E33: =D33-C33 -> #REF! | G33: =I32 -> #REF! | H33: =E33 -> #REF! | I33: =G33+H33 -> #REF!
B34: December | C34: =(D$17*D$19)+($D$18*$D$20)+D$23 -> #REF! | D34: =($D$17*$D$21)+($D$18*$D$22) -> #REF! | E34: =D34-C34 -> #REF! | G34: =I33 -> #REF! | H34: =E34 -> #REF! | I34: =G34+H34 -> #REF!
B35: January | C35: =(D$17*D$19)+($D$18*$D$20)+D$23 -> #REF! | D35: =($D$17*$D$21)+($D$18*$D$22) -> #REF! | E35: =D35-C35 -> #REF! | G35: =I34 -> #REF! | H35: =E35 -> #REF! | I35: =G35+H35 -> #REF!
B36: February | C36: =(D$17*D$19)+($D$18*$D$20)+D$23 -> #REF! | D36: =($D$17*$D$21)+($D$18*$D$22) -> #REF! | E36: =D36-C36 -> #REF! | G36: =I35 -> #REF! | H36: =E36 -> #REF! | I36: =G36+H36 -> #REF!
B37: March | C37: =(D$17*D$19)+($D$18*$D$20)+D$23 -> #REF! | D37: =($D$17*$D$21)+($D$18*$D$22) -> #REF! | E37: =D37-C37 -> #REF! | G37: =I36 -> #REF! | H37: =E37 -> #REF! | I37: =G37+H37 -> #REF!
C38: =SUM(C26:C37) -> #REF! | D38: =SUM(D26:D37) -> #REF! | E38: =D38-C38 -> #REF!
B40: Buffer Capital (Production Cost of 1.5 Month) | D40: =C26*1.5 -> #REF!
B42: Total Yearly Turnover | D42: =D38 -> #REF!
B43: Initial Working Capital | D43: =C26+D40 -> #REF! | E43: * Working Capital Required=Cash outflow for the first month + Contingency fund
B44: Working Capital Rotation | D44: =D42/D43 -> #REF!
B46: PREGNANCY POWDER: TIER 3
B48: Monthly Inhouse Boxes Produced (in Units) | D48: ='In-house (2-5yrs)'!D72/12 -> 269280
B49: Monthly Contract Boxes Produced (in Units) | D49: ='Third Party (2-5yrs)'!D44/12 -> 89760
B50: Cost/Box for Inhouse Mfg (in ₹) | D50: ='In-house (2-5yrs)'!E93
B51: Cost/Box for Contractual Mfg (in ₹) | D51: ='Third Party (2-5yrs)'!D65
B52: Revenue/Box for Inhouse Mfg (in ₹) | D52: ='In-house (2-5yrs)'!D93
B53: Revenue/Box for Contractual Mfg (in ₹) | D53: ='Third Party (2-5yrs)'!C65
B54: Monthly Indirect Expense (in ₹) | D54: =((('Indirect Expenses'!H63/12)/4)*105%)*10^7 -> 5164236
G55: * The working capital that we are investing in the first month is derived from the cash outflow that is required in the first month
B56: Month | C56: Cash Outflow | D56: Cash Inflow | E56: Difference (CO-CI) | G56: Opening W.C. | H56: Net Cash Flow | I56: Closing W.C.
B57: April | C57: =($D$48*$D$50)+$D$54+($D$49*$D$51) -> 5164236 | D57: =($D$48*$D$52)+($D$49*$D$53) -> 0 | E57: =D57-C57 -> -5164236 | G57: =C57+D71 -> 12910590 | H57: =E57 -> -5164236 | I57: =G57+H57 -> 7746354
B58: May | C58: =($D$48*$D$50)+$D$54+($D$49*$D$51) -> 5164236 | D58: =($D$48*$D$52)+($D$49*$D$53) -> 0 | E58: =D58-C58 -> -5164236 | G58: =I57 -> 7746354 | H58: =E58 -> -5164236 | I58: =G58+H58 -> 2582118
B59: June | C59: =($D$48*$D$50)+$D$54+($D$49*$D$51) -> 5164236 | D59: =($D$48*$D$52)+($D$49*$D$53) -> 0 | E59: =D59-C59 -> -5164236 | G59: =I58 -> 2582118 | H59: =E59 -> -5164236 | I59: =G59+H59 -> -2582118
B60: July | C60: =($D$48*$D$50)+$D$54+($D$49*$D$51) -> 5164236 | D60: =($D$48*$D$52)+($D$49*$D$53) -> 0 | E60: =D60-C60 -> -5164236 | G60: =I59 -> -2582118 | H60: =E60 -> -5164236 | I60: =G60+H60 -> -7746354
B61: August | C61: =($D$48*$D$50)+$D$54+($D$49*$D$51) -> 5164236 | D61: =($D$48*$D$52)+($D$49*$D$53) -> 0 | E61: =D61-C61 -> -5164236 | G61: =I60 -> -7746354 | H61: =E61 -> -5164236 | I61: =G61+H61 -> -12910590
B62: September | C62: =($D$48*$D$50)+$D$54+($D$49*$D$51) -> 5164236 | D62: =($D$48*$D$52)+($D$49*$D$53) -> 0 | E62: =D62-C62 -> -5164236 | G62: =I61 -> -12910590 | H62: =E62 -> -5164236 | I62: =G62+H62 -> -18074826
B63: October | C63: =($D$48*$D$50)+$D$54+($D$49*$D$51) -> 5164236 | D63: =($D$48*$D$52)+($D$49*$D$53) -> 0 | E63: =D63-C63 -> -5164236 | G63: =I62 -> -18074826 | H63: =E63 -> -5164236 | I63: =G63+H63 -> -23239062
B64: November | C64: =($D$48*$D$50)+$D$54+($D$49*$D$51) -> 5164236 | D64: =($D$48*$D$52)+($D$49*$D$53) -> 0 | E64: =D64-C64 -> -5164236 | G64: =I63 -> -23239062 | H64: =E64 -> -5164236 | I64: =G64+H64 -> -28403298
B65: December | C65: =($D$48*$D$50)+$D$54+($D$49*$D$51) -> 5164236 | D65: =($D$48*$D$52)+($D$49*$D$53) -> 0 | E65: =D65-C65 -> -5164236 | G65: =I64 -> -28403298 | H65: =E65 -> -5164236 | I65: =G65+H65 -> -33567534
B66: January | C66: =($D$48*$D$50)+$D$54+($D$49*$D$51) -> 5164236 | D66: =($D$48*$D$52)+($D$49*$D$53) -> 0 | E66: =D66-C66 -> -5164236 | G66: =I65 -> -33567534 | H66: =E66 -> -5164236 | I66: =G66+H66 -> -38731770
B67: February | C67: =($D$48*$D$50)+$D$54+($D$49*$D$51) -> 5164236 | D67: =($D$48*$D$52)+($D$49*$D$53) -> 0 | E67: =D67-C67 -> -5164236 | G67: =I66 -> -38731770 | H67: =E67 -> -5164236 | I67: =G67+H67 -> -43896006
B68: March | C68: =($D$48*$D$50)+$D$54+($D$49*$D$51) -> 5164236 | D68: =($D$48*$D$52)+($D$49*$D$53) -> 0 | E68: =D68-C68 -> -5164236 | G68: =I67 -> -43896006 | H68: =E68 -> -5164236 | I68: =G68+H68 -> -49060242
C69: =SUM(C57:C68) -> 61970832 | D69: =SUM(D57:D68) -> 0 | E69: =D69-C69 -> -61970832
B71: Buffer Capital (Production Cost of 1.5 Month) | D71: =C57*1.5 -> 7746354
B73: Total Yearly Turnover | D73: =D69 -> 0
B74: Initial Working Capital | D74: =C57+D71 -> 12910590 | E74: * Working Capital Required=Cash outflow for the first month + Contingency fund
B75: Working Capital Rotation | D75: =D73/D74 -> 0
B77: LACTATION POWDER: TIER 1
B79: Monthly Inhouse Boxes Produced (in Units) | D79: ='In-house (2-5yrs)'!D75/12 -> 15600
B80: Monthly Contract Boxes Produced (in Units) | D80: ='Third Party (2-5yrs)'!D47/12 -> 5200
B81: Cost/Box for Inhouse Mfg (in ₹) | D81: ='In-house (2-5yrs)'!E94
B82: Cost/Box for Contractual Mfg (in ₹) | D82: ='Third Party (2-5yrs)'!D66
B83: Revenue/Box for Inhouse Mfg (in ₹) | D83: ='In-house (2-5yrs)'!D94
B84: Revenue/Box for Contractual Mfg (in ₹) | D84: ='Third Party (2-5yrs)'!C66
B85: Monthly Indirect Expense (in ₹) | D85: =D23 -> #REF!
G86: * The working capital that we are investing in the first month is derived from the cash outflow that is required in the first month
B87: Month | C87: Cash Outflow | D87: Cash Inflow | E87: Difference (CO-CI) | G87: Opening W.C. | H87: Net Cash Flow | I87: Closing W.C.
B88: April | C88: =($D$79*$D$81)+$D$85+($D$80*$D$82) -> #REF! | D88: =($D$79*$D$83)+($D$80*$D$84) -> 0 | E88: =D88-C88 -> #REF! | G88: =C88+D102 -> #REF! | H88: =E88 -> #REF! | I88: =G88+H88 -> #REF!
B89: May | C89: =($D$79*$D$81)+$D$85+($D$80*$D$82) -> #REF! | D89: =($D$79*$D$83)+($D$80*$D$84) -> 0 | E89: =D89-C89 -> #REF! | G89: =I88 -> #REF! | H89: =E89 -> #REF! | I89: =G89+H89 -> #REF!
B90: June | C90: =($D$79*$D$81)+$D$85+($D$80*$D$82) -> #REF! | D90: =($D$79*$D$83)+($D$80*$D$84) -> 0 | E90: =D90-C90 -> #REF! | G90: =I89 -> #REF! | H90: =E90 -> #REF! | I90: =G90+H90 -> #REF!
B91: July | C91: =($D$79*$D$81)+$D$85+($D$80*$D$82) -> #REF! | D91: =($D$79*$D$83)+($D$80*$D$84) -> 0 | E91: =D91-C91 -> #REF! | G91: =I90 -> #REF! | H91: =E91 -> #REF! | I91: =G91+H91 -> #REF!
B92: August | C92: =($D$79*$D$81)+$D$85+($D$80*$D$82) -> #REF! | D92: =($D$79*$D$83)+($D$80*$D$84) -> 0 | E92: =D92-C92 -> #REF! | G92: =I91 -> #REF! | H92: =E92 -> #REF! | I92: =G92+H92 -> #REF!
B93: September | C93: =($D$79*$D$81)+$D$85+($D$80*$D$82) -> #REF! | D93: =($D$79*$D$83)+($D$80*$D$84) -> 0 | E93: =D93-C93 -> #REF! | G93: =I92 -> #REF! | H93: =E93 -> #REF! | I93: =G93+H93 -> #REF!
B94: October | C94: =($D$79*$D$81)+$D$85+($D$80*$D$82) -> #REF! | D94: =($D$79*$D$83)+($D$80*$D$84) -> 0 | E94: =D94-C94 -> #REF! | G94: =I93 -> #REF! | H94: =E94 -> #REF! | I94: =G94+H94 -> #REF!
B95: November | C95: =($D$79*$D$81)+$D$85+($D$80*$D$82) -> #REF! | D95: =($D$79*$D$83)+($D$80*$D$84) -> 0 | E95: =D95-C95 -> #REF! | G95: =I94 -> #REF! | H95: =E95 -> #REF! | I95: =G95+H95 -> #REF!
B96: December | C96: =($D$79*$D$81)+$D$85+($D$80*$D$82) -> #REF! | D96: =($D$79*$D$83)+($D$80*$D$84) -> 0 | E96: =D96-C96 -> #REF! | G96: =I95 -> #REF! | H96: =E96 -> #REF! | I96: =G96+H96 -> #REF!
B97: January | C97: =($D$79*$D$81)+$D$85+($D$80*$D$82) -> #REF! | D97: =($D$79*$D$83)+($D$80*$D$84) -> 0 | E97: =D97-C97 -> #REF! | G97: =I96 -> #REF! | H97: =E97 -> #REF! | I97: =G97+H97 -> #REF!
B98: February | C98: =($D$79*$D$81)+$D$85+($D$80*$D$82) -> #REF! | D98: =($D$79*$D$83)+($D$80*$D$84) -> 0 | E98: =D98-C98 -> #REF! | G98: =I97 -> #REF! | H98: =E98 -> #REF! | I98: =G98+H98 -> #REF!
B99: March | C99: =($D$79*$D$81)+$D$85+($D$80*$D$82) -> #REF! | D99: =($D$79*$D$83)+($D$80*$D$84) -> 0 | E99: =D99-C99 -> #REF! | G99: =I98 -> #REF! | H99: =E99 -> #REF! | I99: =G99+H99 -> #REF!
C100: =SUM(C88:C99) -> #REF! | D100: =SUM(D88:D99) -> 0 | E100: =D100-C100 -> #REF!
B102: Buffer Capital (Production Cost of 1.5 Month) | D102: =C88*1.5 -> #REF!
B104: Total Yearly Turnover | D104: =D100 -> 0
B105: Initial Working Capital | D105: =C88+D102 -> #REF! | E105: * Working Capital Required=Cash outflow for the first month + Contingency fund
B106: Working Capital Rotation | D106: =D104/D105 -> #REF!
B108: LACTATION POWDER: TIER 3
B110: Monthly Inhouse Boxes Produced (in Units) | D110: ='In-house (2-5yrs)'!D77/12 -> 264480
B111: Monthly Contract Boxes Produced (in Units) | D111: ='Third Party (2-5yrs)'!D49/12 -> 88160
B112: Cost/Box for Inhouse Mfg (in ₹) | D112: ='In-house (2-5yrs)'!E99
B113: Cost/Box for Contractual Mfg (in ₹) | D113: ='Third Party (2-5yrs)'!D68
B114: Revenue/Box for Inhouse Mfg (in ₹) | D114: ='In-house (2-5yrs)'!D99
B115: Revenue/Box for Contractual Mfg (in ₹) | D115: ='Third Party (2-5yrs)'!C68
B116: Monthly Indirect Expense (in ₹) | D116: =D54 -> 5164236
...

Sheet WC (Year 3-5)
B2: TOTAL WORKING CAPITAL
C4: Revenue | D4: Initial Working Capital | E4: W.C.Rotation
B5: PP (Tier 1) | C5: =D46 -> #REF! | D5: =D47 -> #REF! | E5: =C5/D5 -> #REF!
B6: PP (Tier 2) | C6: =D77 -> 0 | D6: =D78 -> 995085 | E6: =C6/D6 -> 0
B7: PP (Tier 3) | C7: =D108 -> 0 | D7: =D109 -> 15492708 | E7: =C7/D7 -> 0
B8: LP (Tier 1) | C8: =D139 -> 0 | D8: =D140 -> #REF! | E8: =C8/D8 -> #REF!
B9: LP (Tier 2) | C9: =D170 -> 0 | D9: =D171 -> 995085 | E9: =C9/D9 -> 0
B10: LP (Tier 3) | C10: =D201 -> 0 | D10: =D202 -> 15492708 | E10: =C10/D10 -> 0
B11: INP (Tier 1) | C11: =D232 -> #REF! | D11: =D233 -> #REF! | E11: =C11/D11 -> #REF!
B12: INP (Tier 2) | C12: =D263 -> 0 | D12: =D264 -> 995085 | E12: =C12/D12 -> 0
B13: INP (Tier 3) | C13: =D294 -> 0 | D13: =D295 -> 15492708 | E13: =C13/D13 -> 0
B14: CNP (Tier 1) | C14: =D325 -> 0 | D14: =D326 -> #REF! | E14: =C14/D14 -> #REF!
B15: CNP (Tier 2) | C15: =D356 -> 0 | D15: =D357 -> 995085 | E15: =C15/D15 -> 0
B16: CNP (Tier 3) | C16: =D387 -> 0 | D16: =D388 -> 15492708 | E16: =C16/D16 -> 0
D17: =sum(D5:D16) -> #REF!
B19: PREGNANCY POWDER: TIER 1
B21: Monthly Inhouse Boxes Produced (in Units) | D21: ='In-house (2-5yrs)'!E70/12 -> 13440
B22: Monthly Contract Boxes Produced (in Units) | D22: ='Third Party (2-5yrs)'!E42/12 -> 4480
B23: Cost/Box for Inhouse Mfg (in ₹) | D23: ='In-house (2-5yrs)'!E91
B24: Cost/Box for Contractual Mfg (in ₹) | D24: ='Third Party (2-5yrs)'!D63
B25: Revenue/Box for Inhouse Mfg (in ₹) | D25: ='In-house (2-5yrs)'!D91 -> #REF!
B26: Revenue/Box for Contractual Mfg (in ₹) | D26: ='Third Party (2-5yrs)'!C63 -> #REF!
B27: Monthly Indirect Expense (in ₹) | D27: =((('Indirect Expenses'!I63/4)/12/'In-house (2-5yrs)'!$D$5)*105%)*10^7 -> #REF!
G28: * The working capital that we are investing in the first month is derived from the cash outflow that is required in the first month
B29: Month | C29: Cash Outflow | D29: Cash Inflow | E29: Difference (CO-CI) | G29: Opening W.C. | H29: Net Cash Flow | I29: Closing W.C.
B30: April | C30: =($D$21*$D$23)+$D$27+($D$22*$D$24) -> #REF! | D30: =($D$21*$D$25)+($D$22*$D$26) -> #REF! | E30: =D30-C30 -> #REF! | G30: =C30+D44 -> #REF! | H30: =E30 -> #REF! | I30: =G30+H30 -> #REF!
B31: May | C31: =($D$21*$D$23)+$D$27+($D$22*$D$24) -> #REF! | D31: =($D$21*$D$25)+($D$22*$D$26) -> #REF! | E31: =D31-C31 -> #REF! | G31: =I30 -> #REF! | H31: =E31 -> #REF! | I31: =G31+H31 -> #REF!
B32: June | C32: =($D$21*$D$23)+$D$27+($D$22*$D$24) -> #REF! | D32: =($D$21*$D$25)+($D$22*$D$26) -> #REF! | E32: =D32-C32 -> #REF! | G32: =I31 -> #REF! | H32: =E32 -> #REF! | I32: =G32+H32 -> #REF!
B33: July | C33: =($D$21*$D$23)+$D$27+($D$22*$D$24) -> #REF! | D33: =($D$21*$D$25)+($D$22*$D$26) -> #REF! | E33: =D33-C33 -> #REF! | G33: =I32 -> #REF! | H33: =E33 -> #REF! | I33: =G33+H33 -> #REF!
B34: August | C34: =($D$21*$D$23)+$D$27+($D$22*$D$24) -> #REF! | D34: =($D$21*$D$25)+($D$22*$D$26) -> #REF! | E34: =D34-C34 -> #REF! | G34: =I33 -> #REF! | H34: =E34 -> #REF! | I34: =G34+H34 -> #REF!
B35: September | C35: =($D$21*$D$23)+$D$27+($D$22*$D$24) -> #REF! | D35: =($D$21*$D$25)+($D$22*$D$26) -> #REF! | E35: =D35-C35 -> #REF! | G35: =I34 -> #REF! | H35: =E35 -> #REF! | I35: =G35+H35 -> #REF!
B36: October | C36: =($D$21*$D$23)+$D$27+($D$22*$D$24) -> #REF! | D36: =($D$21*$D$25)+($D$22*$D$26) -> #REF! | E36: =D36-C36 -> #REF! | G36: =I35 -> #REF! | H36: =E36 -> #REF! | I36: =G36+H36 -> #REF!
B37: November | C37: =($D$21*$D$23)+$D$27+($D$22*$D$24) -> #REF! | D37: =($D$21*$D$25)+($D$22*$D$26) -> #REF! | E37: =D37-C37 -> #REF! | G37: =I36 -> #REF! | H37: =E37 -> #REF! | I37: =G37+H37 -> #REF!
B38: December | C38: =($D$21*$D$23)+$D$27+($D$22*$D$24) -> #REF! | D38: =($D$21*$D$25)+($D$22*$D$26) -> #REF! | E38: =D38-C38 -> #REF! | G38: =I37 -> #REF! | H38: =E38 -> #REF! | I38: =G38+H38 -> #REF!
B39: January | C39: =($D$21*$D$23)+$D$27+($D$22*$D$24) -> #REF! | D39: =($D$21*$D$25)+($D$22*$D$26) -> #REF! | E39: =D39-C39 -> #REF! | G39: =I38 -> #REF! | H39: =E39 -> #REF! | I39: =G39+H39 -> #REF!
B40: February | C40: =($D$21*$D$23)+$D$27+($D$22*$D$24) -> #REF! | D40: =($D$21*$D$25)+($D$22*$D$26) -> #REF! | E40: =D40-C40 -> #REF! | G40: =I39 -> #REF! | H40: =E40 -> #REF! | I40: =G40+H40 -> #REF!
B41: March | C41: =($D$21*$D$23)+$D$27+($D$22*$D$24) -> #REF! | D41: =($D$21*$D$25)+($D$22*$D$26) -> #REF! | E41: =D41-C41 -> #REF! | G41: =I40 -> #REF! | H41: =E41 -> #REF! | I41: =G41+H41 -> #REF!
C42: =SUM(C30:C41) -> #REF! | D42: =SUM(D30:D41) -> #REF! | E42: =D42-C42 -> #REF!
B44: Buffer Capital (Production Cost of 2 Month) | D44: =C30*2 -> #REF!
B46: Total Yearly Turnover | D46: =D42 -> #REF!
B47: Initial Working Capital | D47: =C30+D44 -> #REF! | E47: * Working Capital Required=Cash outflow for the first month + Contingency fund
B48: Working Capital Rotation | D48: =D46/D47 -> #REF!
B50: PREGNANCY POWDER: TIER 2
B52: Monthly Inhouse Boxes Produced (in Units) | D52: ='In-house (2-5yrs)'!E71/12 -> 17520
B53: Monthly Contract Boxes Produced (in Units) | D53: ='Third Party (2-5yrs)'!E43/12 -> 5840
B54: Cost/Box for Inhouse Mfg (in ₹) | D54: ='In-house (2-5yrs)'!E92
B55: Cost/Box for Contractual Mfg (in ₹) | D55: ='Third Party (2-5yrs)'!D64
B56: Revenue/Box for Inhouse Mfg (in ₹) | D56: ='In-house (2-5yrs)'!D92
B57: Revenue/Box for Contractual Mfg (in ₹) | D57: ='Third Party (2-5yrs)'!C64
B58: Monthly Indirect Expense (in ₹) | D58: =((('Indirect Expenses'!J63/4)/12/'In-house (2-5yrs)'!$D$5)*105%)*10^7 -> 331695
G59: * The working capital that we are investing in the first month is derived from the cash outflow that is required in the first month
B60: Month | C60: Cash Outflow | D60: Cash Inflow | E60: Difference (CO-CI) | G60: Opening W.C. | H60: Net Cash Flow | I60: Closing W.C.
B61: April | C61: =($D$52*$D$54)+$D$58+($D$53*$D$55) -> 331695 | D61: =($D$52*$D$56)+($D$53*$D$57) -> 0 | E61: =D61-C61 -> -331695 | G61: =C61+D75 -> 995085 | H61: =E61 -> -331695 | I61: =G61+H61 -> 663390
B62: May | C62: =($D$52*$D$54)+$D$58+($D$53*$D$55) -> 331695 | D62: =($D$52*$D$56)+($D$53*$D$57) -> 0 | E62: =D62-C62 -> -331695 | G62: =I61 -> 663390 | H62: =E62 -> -331695 | I62: =G62+H62 -> 331695
B63: June | C63: =($D$52*$D$54)+$D$58+($D$53*$D$55) -> 331695 | D63: =($D$52*$D$56)+($D$53*$D$57) -> 0 | E63: =D63-C63 -> -331695 | G63: =I62 -> 331695 | H63: =E63 -> -331695 | I63: =G63+H63 -> 0
